================================================================================
Timestamp: 2026-05-05T05:52:07.973503+00:00
Session: ../../../../../../../../.pi/agent/sessions/--home-vjovanov-c-forge-forge8-graalvm-reachability-metadata-forge-local_repositories-forge_worktrees-4490-2eb21853--/2026-05-05T05-51-11-813Z_019df6b0-bfc5-7029-84b2-889dc76a0676.jsonl
Persistent instructions: configured (2998 chars)
Event Trace:
[send] prompt
  Role: You are an expert JVM test engineer specializing in high-coverage integration testing for external libraries.
  
  Task:
  Improve test coverage for the active dynamic-access class in `com.squareup.moshi:moshi:1.15.2`.
  
  Source Context:
  Coordinate: com.squareup.moshi:moshi:1.15.2
  Repository URL: https://github.com/square/moshi
  Main sources:
  - URL: https://repo.maven.apache.org/maven2/com/squareup/moshi/moshi/1.15.2/moshi-1.15.2-sources.jar
  - Local path: local_repositories/source_context/com.squareup.moshi/moshi/1.15.2/main
  - Files available: 34
  
  Active class:
  - Class: com.squareup.moshi.RecordJsonAdapter$1
  - Source file: /home/vjovanov/c/forge/forge8/graalvm-reachability-metadata/forge/local_repositories/source_context/com.squareup.moshi/moshi/1.15.2/main/extracted/main/com/squareup/moshi/RecordJsonAdapter.java
  
  Progress since the previous dynamic-access report:
  - Attempts used for this class so far: 0
  - Newly covered call sites: none
  - Remaining uncovered call sites after the last report: 3
  
  Remaining uncovered dynamic-access call sites for this class:
  - [reflection] java.lang.Class#getRecordComponents() <- com.squareup.moshi.RecordJsonAdapter$1.create(RecordJsonAdapter.java:59) (line 59)
  - [reflection] java.lang.invoke.MethodHandles.Lookup#findConstructor(java.lang.Class, java.lang.invoke.MethodType) <- com.squareup.moshi.RecordJsonAdapter$1.create(RecordJsonAdapter.java:83) (line 83)
  - [reflection] java.lang.invoke.MethodHandles.Lookup#unreflect(java.lang.reflect.Method) <- com.squareup.moshi.RecordJsonAdapter$1.createComponentBinding(RecordJsonAdapter.java:106) (line 106)
  
  Rules:
  - Add or refine tests so execution reaches the remaining uncovered call sites for the active class.
  - Focus on the active class only.
[recv] prompt success
[recv] {"type": "agent_start"}
[recv] {"type": "turn_start"}
[recv] {"type": "message_start", "message": {"role": "user", "content": [{"type": "text", "text": "Role: You are an expert JVM test engineer specializing in high-coverage integration testing for external libraries.\n\nTask:\nImprove test coverage for the active dynamic-access class in `com.squareup.moshi:moshi:1.15.2`.\n\nSource Context:\nCoordinate: com.squareup.moshi:moshi:1.15.2\nRepository URL: https://github.com/square/moshi\nMain sources:\n- URL: https://repo.maven.apache.org/maven2/com/squareup/moshi/moshi/1.15.2/moshi-1.15.2-sources.jar\n- Local path: local_repositories/source_context/com.squareup.moshi/moshi/1.15.2/main\n- Files available: 34\n\nActive class:\n- Class: com.squareup.moshi.RecordJsonAdapter$1\n- Source file: /home/vjovanov/c/forge/forge8/graalvm-reachability-metadata/forge/local_repositories/source_context/com.squareup.moshi/moshi/1.15.2/main/extracted/main/com/squareup/moshi/RecordJsonAdapter.java\n\nProgress since the previous dynamic-access report:\n- Attempts used for this class so far: 0\n- Newly covered call sites: none\n- Remaining uncovered call sites after the last report: 3\n\nRemaining uncovered dynamic-access call sites for this class:\n- [reflection] java.lang.Class#getRecordComponents() <- com.squareup.moshi.RecordJsonAdapter$1.create(RecordJsonAdapter.java:59) (line 59)\n- [reflection] java.lang.invoke.MethodHandles.Lookup#findConstructor(java.lang.Class, java.lang.invoke.MethodType) <- com.squareup.moshi.RecordJsonAdapter$1.create(RecordJsonAdapter.java:83) (line 83)\n- [reflection] java.lang.invoke.MethodHandles.Lookup#unreflect(java.lang.reflect.Method) <- com.squareup.moshi.RecordJsonAdapter$1.createComponentBinding(RecordJsonAdapter.java:106) (line 106)\n\nRules:\n- Add or refine tests so execution reaches the remaining uncovered call sites for the active class.\n- Focus on the active class only.\n"}], "timestamp": 1777960271915}}
[recv] {"type": "message_end", "message": {"role": "user", "content": [{"type": "text", "text": "Role: You are an expert JVM test engineer specializing in high-coverage integration testing for external libraries.\n\nTask:\nImprove test coverage for the active dynamic-access class in `com.squareup.moshi:moshi:1.15.2`.\n\nSource Context:\nCoordinate: com.squareup.moshi:moshi:1.15.2\nRepository URL: https://github.com/square/moshi\nMain sources:\n- URL: https://repo.maven.apache.org/maven2/com/squareup/moshi/moshi/1.15.2/moshi-1.15.2-sources.jar\n- Local path: local_repositories/source_context/com.squareup.moshi/moshi/1.15.2/main\n- Files available: 34\n\nActive class:\n- Class: com.squareup.moshi.RecordJsonAdapter$1\n- Source file: /home/vjovanov/c/forge/forge8/graalvm-reachability-metadata/forge/local_repositories/source_context/com.squareup.moshi/moshi/1.15.2/main/extracted/main/com/squareup/moshi/RecordJsonAdapter.java\n\nProgress since the previous dynamic-access report:\n- Attempts used for this class so far: 0\n- Newly covered call sites: none\n- Remaining uncovered call sites after the last report: 3\n\nRemaining uncovered dynamic-access call sites for this class:\n- [reflection] java.lang.Class#getRecordComponents() <- com.squareup.moshi.RecordJsonAdapter$1.create(RecordJsonAdapter.java:59) (line 59)\n- [reflection] java.lang.invoke.MethodHandles.Lookup#findConstructor(java.lang.Class, java.lang.invoke.MethodType) <- com.squareup.moshi.RecordJsonAdapter$1.create(RecordJsonAdapter.java:83) (line 83)\n- [reflection] java.lang.invoke.MethodHandles.Lookup#unreflect(java.lang.reflect.Method) <- com.squareup.moshi.RecordJsonAdapter$1.createComponentBinding(RecordJsonAdapter.java:106) (line 106)\n\nRules:\n- Add or refine tests so execution reaches the remaining uncovered call sites for the active class.\n- Focus on the active class only.\n"}], "timestamp": 1777960271915}}
[recv] {"type": "message_start", "message": {"role": "assistant", "content": [], "api": "openai-responses", "provider": "OCA", "model": "gpt-5.5", "usage": {"input": 0, "output": 0, "cacheRead": 0, "cacheWrite": 0, "totalTokens": 0, "cost": {"input": 0, "output": 0, "cacheRead": 0, "cacheWrite": 0, "total": 0}}, "stopReason": "stop", "timestamp": 1777960272002}}
[assistant-event] thinking_start
[thinking] **Modifying tests**
[thinking] 
[thinking] I think it's time to modify the tests! I'll need to take a closer look at the repository to understand what changes are needed. There might be areas that need improvement or updating to match current conditions. This process could involve inspecting specific files or sections to ensure everything aligns correctly. It’s a bit overwhelming, but I’m ready to dive in and get it done!
[thinking] 
[assistant-event] thinking_end
[tool-call] start id=unknown
[tool-call] delta {"command": "pwd && ls"}
[tool-call] end id=call_cXRGjBTm7CjHjmF1jdtjFtm9|fc_0d8c31fa336f7f3d0169f985547fd481a28514edd391686c77 name=bash args={"command": "pwd && ls"}
[recv] {"type": "message_end", "message": {"role": "assistant", "content": [{"type": "thinking", "thinking": "**Modifying tests**\n\nI think it's time to modify the tests! I'll need to take a closer look at the repository to understand what changes are needed. There might be areas that need improvement or updating to match current conditions. This process could involve inspecting specific files or sections to ensure everything aligns correctly. It’s a bit overwhelming, but I’m ready to dive in and get it done!", "thinkingSignature": "{\"id\":\"rs_0d8c31fa336f7f3d0169f98551d5fc81a29e524e6a62e023bf\",\"type\":\"reasoning\",\"encrypted_content\":\"gAAAAABp-YVUNn422qGEtWwwequISj-Qs5cle9BW_cdoB0BH94cXbNHZD-AGJNTeTfJVbJFIJ68o9Ps4QQ_tyZaVrIZSIAWcZpoy1c4Tligrugc18QOm4KR9Dl0HQFqa55xtSHGJ87VuOGXsq6LkpQSi3iBZ04yrrwON-yb6oOod0bcEu51-4rbZA7b-AcR0tVfqe-vru9OeBWmk0UqkNJzChKcfQqmt3V-2Ev1DoW13haZyGlUs4COkxkFLj83zXIejknsv3FSUeORqbdLSxXDKLPFOcKv6vfpqiX5bTY1PHBvlR4m7votjvUUiFUZj7YAbYHsVfyBNUjTCBy1R04FvGQa3TPQtFKMOXc8BIwPOCudzBJvPn-WLjedYVZb2GHGI7LwOSn9S7QCFFX_ofwl1CrBdGY0c0PSg2mvxxzaKgPm3Kswkoh250WrhdNd_sd9I3NX4lduOZgqiWMib6WmTfel6mcyHoHmbP68jm0glWQxIDfPDdY2h-aw-0wfMeoORba01wD_g9AMzkYG6h5ytfENA5QwfxddR1q3e3K25JvWmxaxomdmJ0Mf9TAp6wxCDuMjsw6cg0229tabp7_5et_CQD7K4dvG6t_qBY4MIBJB3obhSA3i99rLHW07TFcAhNQWQiImh2HJ5kQ-s6Xu6kmIz8BijD2LuYMYnU2M0pntICkjaSaibs0eHAbra-AZ1HIuH5gLJCcU34iIYcV-IrJxS1heX7wHxKX0fZpDN7QIZHEcgSvhGjlNhqaIu6J3_hnErexYTGDkm0ps_MIj2ecjccH84FVL9ttJFklz18nw013pzUqI0dQkwkeJZ201jjGipbZCyTDyxJd80LNYjNfXkjquB1anOH8udiV42p-NmUxicVpGLqX3Ky2oRPNngFK82iKsk1Y5G9xrgwotK6cJNMn4T0Oq-yx9GCh922UPk3pJ8aIxNeS_T4sQw41h0d_GAZ8qVrf2tUtyQ6OVwPjL4kV-wg0SQuZ3X21CUNeZ-DcZ_rPQ=\",\"summary\":[{\"type\":\"summary_text\",\"text\":\"**Modifying tests**\\n\\nI think it's time to modify the tests! I'll need to take a closer look at the repository to understand what changes are needed. There might be areas that need improvement or updating to match current conditions. This process could involve inspecting specific files or sections to ensure everything aligns correctly. It’s a bit overwhelming, but I’m ready to dive in and get it done!\"}]}"}, {"type": "toolCall", "id": "call_cXRGjBTm7CjHjmF1jdtjFtm9|fc_0d8c31fa336f7f3d0169f985547fd481a28514edd391686c77", "name": "bash", "arguments": {"command": "pwd && ls"}}], "api": "openai-responses", "provider": "OCA", "model": "gpt-5.5", "usage": {"input": 7424, "output": 36, "cacheRead": 0, "cacheWrite": 0, "totalTokens": 7460, "cost": {"input": 0, "output": 0, "cacheRead": 0, "cacheWrite": 0, "total": 0}}, "stopReason": "toolUse", "timestamp": 1777960272002, "responseId": "resp_0d8c31fa336f7f3d0169f98550a6e881a2b0a9f330006e534d"}}
[tool-exec] start id=call_cXRGjBTm7CjHjmF1jdtjFtm9|fc_0d8c31fa336f7f3d0169f985547fd481a28514edd391686c77 name=bash args={"command": "pwd && ls"}
[tool-exec] update id=call_cXRGjBTm7CjHjmF1jdtjFtm9|fc_0d8c31fa336f7f3d0169f985547fd481a28514edd391686c77 name=bash
[tool-exec] update id=call_cXRGjBTm7CjHjmF1jdtjFtm9|fc_0d8c31fa336f7f3d0169f985547fd481a28514edd391686c77 name=bash
  /home/vjovanov/c/forge/forge8/graalvm-reachability-metadata/forge/local_repositories/forge_worktrees/4490-2eb21853
  AGENTS.md
  build
  build.gradle
  build_spec.yaml
  check-library-support.sh
  ci.json
  CLAUDE.md
  COVERAGE.md
  docs
  forge
  gradle
  gradle.properties
  gradlew
  gradlew.bat
  LICENSE
  metadata
  README.md
  settings.gradle
  skills
  stats
  tests
[tool-exec] end id=call_cXRGjBTm7CjHjmF1jdtjFtm9|fc_0d8c31fa336f7f3d0169f985547fd481a28514edd391686c77 name=bash status=success
  /home/vjovanov/c/forge/forge8/graalvm-reachability-metadata/forge/local_repositories/forge_worktrees/4490-2eb21853
  AGENTS.md
  build
  build.gradle
  build_spec.yaml
  check-library-support.sh
  ci.json
  CLAUDE.md
  COVERAGE.md
  docs
  forge
  gradle
  gradle.properties
  gradlew
  gradlew.bat
  LICENSE
  metadata
  README.md
  settings.gradle
  skills
  stats
  tests
[recv] {"type": "message_start", "message": {"role": "toolResult", "toolCallId": "call_cXRGjBTm7CjHjmF1jdtjFtm9|fc_0d8c31fa336f7f3d0169f985547fd481a28514edd391686c77", "toolName": "bash", "content": [{"type": "text", "text": "/home/vjovanov/c/forge/forge8/graalvm-reachability-metadata/forge/local_repositories/forge_worktrees/4490-2eb21853\nAGENTS.md\nbuild\nbuild.gradle\nbuild_spec.yaml\ncheck-library-support.sh\nci.json\nCLAUDE.md\nCOVERAGE.md\ndocs\nforge\ngradle\ngradle.properties\ngradlew\ngradlew.bat\nLICENSE\nmetadata\nREADME.md\nsettings.gradle\nskills\nstats\ntests\n"}], "isError": false, "timestamp": 1777960276770}}
[recv] {"type": "message_end", "message": {"role": "toolResult", "toolCallId": "call_cXRGjBTm7CjHjmF1jdtjFtm9|fc_0d8c31fa336f7f3d0169f985547fd481a28514edd391686c77", "toolName": "bash", "content": [{"type": "text", "text": "/home/vjovanov/c/forge/forge8/graalvm-reachability-metadata/forge/local_repositories/forge_worktrees/4490-2eb21853\nAGENTS.md\nbuild\nbuild.gradle\nbuild_spec.yaml\ncheck-library-support.sh\nci.json\nCLAUDE.md\nCOVERAGE.md\ndocs\nforge\ngradle\ngradle.properties\ngradlew\ngradlew.bat\nLICENSE\nmetadata\nREADME.md\nsettings.gradle\nskills\nstats\ntests\n"}], "isError": false, "timestamp": 1777960276770}}
[recv] {"type": "turn_end", "message": {"role": "assistant", "content": [{"type": "thinking", "thinking": "**Modifying tests**\n\nI think it's time to modify the tests! I'll need to take a closer look at the repository to understand what changes are needed. There might be areas that need improvement or updating to match current conditions. This process could involve inspecting specific files or sections to ensure everything aligns correctly. It’s a bit overwhelming, but I’m ready to dive in and get it done!", "thinkingSignature": "{\"id\":\"rs_0d8c31fa336f7f3d0169f98551d5fc81a29e524e6a62e023bf\",\"type\":\"reasoning\",\"encrypted_content\":\"gAAAAABp-YVUNn422qGEtWwwequISj-Qs5cle9BW_cdoB0BH94cXbNHZD-AGJNTeTfJVbJFIJ68o9Ps4QQ_tyZaVrIZSIAWcZpoy1c4Tligrugc18QOm4KR9Dl0HQFqa55xtSHGJ87VuOGXsq6LkpQSi3iBZ04yrrwON-yb6oOod0bcEu51-4rbZA7b-AcR0tVfqe-vru9OeBWmk0UqkNJzChKcfQqmt3V-2Ev1DoW13haZyGlUs4COkxkFLj83zXIejknsv3FSUeORqbdLSxXDKLPFOcKv6vfpqiX5bTY1PHBvlR4m7votjvUUiFUZj7YAbYHsVfyBNUjTCBy1R04FvGQa3TPQtFKMOXc8BIwPOCudzBJvPn-WLjedYVZb2GHGI7LwOSn9S7QCFFX_ofwl1CrBdGY0c0PSg2mvxxzaKgPm3Kswkoh250WrhdNd_sd9I3NX4lduOZgqiWMib6WmTfel6mcyHoHmbP68jm0glWQxIDfPDdY2h-aw-0wfMeoORba01wD_g9AMzkYG6h5ytfENA5QwfxddR1q3e3K25JvWmxaxomdmJ0Mf9TAp6wxCDuMjsw6cg0229tabp7_5et_CQD7K4dvG6t_qBY4MIBJB3obhSA3i99rLHW07TFcAhNQWQiImh2HJ5kQ-s6Xu6kmIz8BijD2LuYMYnU2M0pntICkjaSaibs0eHAbra-AZ1HIuH5gLJCcU34iIYcV-IrJxS1heX7wHxKX0fZpDN7QIZHEcgSvhGjlNhqaIu6J3_hnErexYTGDkm0ps_MIj2ecjccH84FVL9ttJFklz18nw013pzUqI0dQkwkeJZ201jjGipbZCyTDyxJd80LNYjNfXkjquB1anOH8udiV42p-NmUxicVpGLqX3Ky2oRPNngFK82iKsk1Y5G9xrgwotK6cJNMn4T0Oq-yx9GCh922UPk3pJ8aIxNeS_T4sQw41h0d_GAZ8qVrf2tUtyQ6OVwPjL4kV-wg0SQuZ3X21CUNeZ-DcZ_rPQ=\",\"summary\":[{\"type\":\"summary_text\",\"text\":\"**Modifying tests**\\n\\nI think it's time to modify the tests! I'll need to take a closer look at the repository to understand what changes are needed. There might be areas that need improvement or updating to match current conditions. This process could involve inspecting specific files or sections to ensure everything aligns correctly. It’s a bit overwhelming, but I’m ready to dive in and get it done!\"}]}"}, {"type": "toolCall", "id": "call_cXRGjBTm7CjHjmF1jdtjFtm9|fc_0d8c31fa336f7f3d0169f985547fd481a28514edd391686c77", "name": "bash", "arguments": {"command": "pwd && ls"}}], "api": "openai-responses", "provider": "OCA", "model": "gpt-5.5", "usage": {"input": 7424, "output": 36, "cacheRead": 0, "cacheWrite": 0, "totalTokens": 7460, "cost": {"input": 0, "output": 0, "cacheRead": 0, "cacheWrite": 0, "total": 0}}, "stopReason": "toolUse", "timestamp": 1777960272002, "responseId": "resp_0d8c31fa336f7f3d0169f98550a6e881a2b0a9f330006e534d"}, "toolResults": [{"role": "toolResult", "toolCallId": "call_cXRGjBTm7CjHjmF1jdtjFtm9|fc_0d8c31fa336f7f3d0169f985547fd481a28514edd391686c77", "toolName": "bash", "content": [{"type": "text", "text": "/home/vjovanov/c/forge/forge8/graalvm-reachability-metadata/forge/local_repositories/forge_worktrees/4490-2eb21853\nAGENTS.md\nbuild\nbuild.gradle\nbuild_spec.yaml\ncheck-library-support.sh\nci.json\nCLAUDE.md\nCOVERAGE.md\ndocs\nforge\ngradle\ngradle.properties\ngradlew\ngradlew.bat\nLICENSE\nmetadata\nREADME.md\nsettings.gradle\nskills\nstats\ntests\n"}], "isError": false, "timestamp": 1777960276770}]}
[recv] {"type": "turn_start"}
[recv] {"type": "message_start", "message": {"role": "assistant", "content": [], "api": "openai-responses", "provider": "OCA", "model": "gpt-5.5", "usage": {"input": 0, "output": 0, "cacheRead": 0, "cacheWrite": 0, "totalTokens": 0, "cost": {"input": 0, "output": 0, "cacheRead": 0, "cacheWrite": 0, "total": 0}}, "stopReason": "stop", "timestamp": 1777960276774}}
[assistant-event] thinking_start
[thinking] **Searching for moshi tests**
[thinking] 
[thinking] I need to find tests related to Moshi. It seems like I should look into various sources or maybe even code repositories to locate what I'm looking for. I'm thinking checking documentation or GitHub could be good places to start. Moshi testing could involve looking at certain libraries or frameworks that utilize it. I wonder what kinds of tests are most common and how I can best find them. Let's go ahead and search!
[thinking] 
[assistant-event] thinking_end
[tool-call] start id=unknown
[tool-call] delta {"command":"find tests -path '*moshi*' -maxdepth 8 -type f | head -50"}
[tool-call] end id=call_57OkPY9O60M16UkztmxRK9bX|fc_0d8c31fa336f7f3d0169f98557920481a2b89955e9c6381e9f name=bash args={"command": "find tests -path '*moshi*' -maxdepth 8 -type f | head -50"}
[recv] {"type": "message_end", "message": {"role": "assistant", "content": [{"type": "thinking", "thinking": "**Searching for moshi tests**\n\nI need to find tests related to Moshi. It seems like I should look into various sources or maybe even code repositories to locate what I'm looking for. I'm thinking checking documentation or GitHub could be good places to start. Moshi testing could involve looking at certain libraries or frameworks that utilize it. I wonder what kinds of tests are most common and how I can best find them. Let's go ahead and search!", "thinkingSignature": "{\"id\":\"rs_0d8c31fa336f7f3d0169f98555aaa881a280c895b9309b78bc\",\"type\":\"reasoning\",\"encrypted_content\":\"gAAAAABp-YVXYsSBJ3rZvM-zAKpPYMoMh2XkTbyNMrRaZU1aSjWm9D2kbugDPuLNoDu9d9g9keqKTD5T-MldfehAFJ4xkZ4Uy7e1gKO-03T8Ph2K2f9MQ4mqARz3AB2UFed4jM2-yPg5KAJioYMiHK94z7_Dbx_7x_zq6b4e1V30a3qdVr0XVteT_LISmXgNNAsuqr_DcuYBQU1JSqdNBJnzqLwI9I_6QcxE0D2leEV9WsOaJLKtxVLySFL1hnlFUsEZ8VXBqkwF4zu-JCqWaTioPs3mRW0ijF2bSa3FDgmNLdyfSLGZVRUMCMHqVf9f45vyIOYd57i6DKtCQ2BBiDDRwF5bDd1fz8PlOzqitGNyQSfNadmGCgMTNvS6Y9hgUXFFHltI0koX8zMHbJ2G6T-djofLD4jm7P__MommamTAua5ojgYA5YUTlz77khOXV5z7dmeXQo7_sKe2W6CB-W4bgZvjLIvyCdRFYOnN4G5ze7zAcBkVhWpMtno37eB8doFeW8Svk_a5F24s5KpfzocWjgh6qjQ_fVXvOWVtBkgdT6yYmLkWXxBQEVP5SrBe1bbFnBkGC1MPivAjFL7DG_wTMhDArFmglPHljupih-gG-OchPeh-2ywxTk563LIAL0zJpOzTjJlsB9j1bQG1GCM8z1F8NnWNdENGLrwAye6QsmI2ul2EoEjE1aEpf5px2Kj9J0CkYSi8TA4aBLR0frZfDQ-rmbJ0WOkupOPV9F2ym8esyIYTnbGR0byJ51sa-Y2XpseltqRfV9e1LPs-TFRUvKmTCbxIZsGdlpOO6Y4jNKwt0zToTmV_GU4knnh63q2Om34vAlL8WWQ3Yh_W_NGfo4bzIhBpvpsBmKTK4mmAeD3JhiELUY1ErmShOERCXlKKDgRZq659vd-RifAnySHrkrGT9Np_psoNbl6cbZnRuvovOhy_XyAR0dGOVmpVyVz0BMfIt6KokYi_csaT8Lz6dQKfhGmhTQ==\",\"summary\":[{\"type\":\"summary_text\",\"text\":\"**Searching for moshi tests**\\n\\nI need to find tests related to Moshi. It seems like I should look into various sources or maybe even code repositories to locate what I'm looking for. I'm thinking checking documentation or GitHub could be good places to start. Moshi testing could involve looking at certain libraries or frameworks that utilize it. I wonder what kinds of tests are most common and how I can best find them. Let's go ahead and search!\"}]}"}, {"type": "toolCall", "id": "call_57OkPY9O60M16UkztmxRK9bX|fc_0d8c31fa336f7f3d0169f98557920481a2b89955e9c6381e9f", "name": "bash", "arguments": {"command": "find tests -path '*moshi*' -maxdepth 8 -type f | head -50"}}], "api": "openai-responses", "provider": "OCA", "model": "gpt-5.5", "usage": {"input": 405, "output": 50, "cacheRead": 7168, "cacheWrite": 0, "totalTokens": 7623, "cost": {"input": 0, "output": 0, "cacheRead": 0, "cacheWrite": 0, "total": 0}}, "stopReason": "toolUse", "timestamp": 1777960276774, "responseId": "resp_0d8c31fa336f7f3d0169f98555041081a29ae70c63d85a2b57"}}
[tool-exec] start id=call_57OkPY9O60M16UkztmxRK9bX|fc_0d8c31fa336f7f3d0169f98557920481a2b89955e9c6381e9f name=bash args={"command": "find tests -path '*moshi*' -maxdepth 8 -type f | head -50"}
[tool-exec] update id=call_57OkPY9O60M16UkztmxRK9bX|fc_0d8c31fa336f7f3d0169f98557920481a2b89955e9c6381e9f name=bash
[tool-exec] update id=call_57OkPY9O60M16UkztmxRK9bX|fc_0d8c31fa336f7f3d0169f98557920481a2b89955e9c6381e9f name=bash
  tests/src/com.squareup.moshi/moshi/1.15.2/test-results-native/test/TEST-junit-jupiter.xml
  tests/src/com.squareup.moshi/moshi/1.15.2/test-results-native/test/TEST-junit-vintage.xml
  tests/src/com.squareup.moshi/moshi/1.15.2/user-code-filter.json
  tests/src/com.squareup.moshi/moshi/1.15.2/gradle.properties
  tests/src/com.squareup.moshi/moshi/1.15.2/.gitignore
  tests/src/com.squareup.moshi/moshi/1.15.2/settings.gradle
  tests/src/com.squareup.moshi/moshi/1.15.2/.gradle/9.1.0/executionHistory/executionHistory.bin
  tests/src/com.squareup.moshi/moshi/1.15.2/.gradle/9.1.0/executionHistory/executionHistory.lock
  tests/src/com.squareup.moshi/moshi/1.15.2/.gradle/9.1.0/fileHashes/resourceHashesCache.bin
  tests/src/com.squareup.moshi/moshi/1.15.2/.gradle/9.1.0/fileHashes/fileHashes.bin
  tests/src/com.squareup.moshi/moshi/1.15.2/.gradle/9.1.0/fileHashes/fileHashes.lock
  tests/src/com.squareup.moshi/moshi/1.15.2/.gradle/9.1.0/fileChanges/last-build.bin
  tests/src/com.squareup.moshi/moshi/1.15.2/.gradle/9.1.0/expanded/expanded.lock
  tests/src/com.squareup.moshi/moshi/1.15.2/.gradle/9.1.0/checksums/md5-checksums.bin
  tests/src/com.squareup.moshi/moshi/1.15.2/.gradle/9.1.0/checksums/checksums.lock
  tests/src/com.squareup.moshi/moshi/1.15.2/.gradle/9.1.0/checksums/sha1-checksums.bin
  tests/src/com.squareup.moshi/moshi/1.15.2/.gradle/9.1.0/gc.properties
  tests/src/com.squareup.moshi/moshi/1.15.2/.gradle/buildOutputCleanup/outputFiles.bin
  tests/src/com.squareup.moshi/moshi/1.15.2/.gradle/buildOutputCleanup/buildOutputCleanup.lock
  tests/src/com.squareup.moshi/moshi/1.15.2/.gradle/buildOutputCleanup/cache.properties
  tests/src/com.squareup.moshi/moshi/1.15.2/.gradle/vcs-1/gc.properties
  tests/src/com.squareup.moshi/moshi/1.15.2/.gradle/file-system.probe
  tests/src/com.squareup.moshi/moshi/1.15.2/.gradle/noVersion/buildLogic.lock
  tests/src/com.squareup.moshi/moshi/1.15.2/build/jacoco/test.exec
  tests/src/com.squareup.moshi/moshi/1.15.2/build/reports/dynamic-access/dynamic-access-coverage.json
  tests/src/com.squareup.moshi/moshi/1.15.2/build/reports/problems/problems-report.html
  tests/src/com.squareup.moshi/moshi/1.15.2/build/native/nativeTestCompile/libmanagement_ext.so
  tests/src/com.squareup.moshi/moshi/1.15.2/build/native/nativeTestCompile/com.squareup.moshi.moshi_tests-tests
  tests/src/com.squareup.moshi/moshi/1.15.2/build/libs/com.squareup.moshi.moshi_tests.jar
  tests/src/com.squareup.moshi/moshi/1.15.2/build/test-results/test/TEST-com_squareup_moshi.moshi.TypesTest.xml
  tests/src/com.squareup.moshi/moshi/1.15.2/build/test-results/test/TEST-com_squareup_moshi.moshi.UtilTest.xml
  tests/src/com.squareup.moshi/moshi/1.15.2/build/tmp/jar/MANIFEST.MF
  tests/src/com.squareup.moshi/moshi/1.15.2/build.gradle
[tool-exec] end id=call_57OkPY9O60M16UkztmxRK9bX|fc_0d8c31fa336f7f3d0169f98557920481a2b89955e9c6381e9f name=bash status=success
  tests/src/com.squareup.moshi/moshi/1.15.2/test-results-native/test/TEST-junit-jupiter.xml
  tests/src/com.squareup.moshi/moshi/1.15.2/test-results-native/test/TEST-junit-vintage.xml
  tests/src/com.squareup.moshi/moshi/1.15.2/user-code-filter.json
  tests/src/com.squareup.moshi/moshi/1.15.2/gradle.properties
  tests/src/com.squareup.moshi/moshi/1.15.2/.gitignore
  tests/src/com.squareup.moshi/moshi/1.15.2/settings.gradle
  tests/src/com.squareup.moshi/moshi/1.15.2/.gradle/9.1.0/executionHistory/executionHistory.bin
  tests/src/com.squareup.moshi/moshi/1.15.2/.gradle/9.1.0/executionHistory/executionHistory.lock
  tests/src/com.squareup.moshi/moshi/1.15.2/.gradle/9.1.0/fileHashes/resourceHashesCache.bin
  tests/src/com.squareup.moshi/moshi/1.15.2/.gradle/9.1.0/fileHashes/fileHashes.bin
  tests/src/com.squareup.moshi/moshi/1.15.2/.gradle/9.1.0/fileHashes/fileHashes.lock
  tests/src/com.squareup.moshi/moshi/1.15.2/.gradle/9.1.0/fileChanges/last-build.bin
  tests/src/com.squareup.moshi/moshi/1.15.2/.gradle/9.1.0/expanded/expanded.lock
  tests/src/com.squareup.moshi/moshi/1.15.2/.gradle/9.1.0/checksums/md5-checksums.bin
  tests/src/com.squareup.moshi/moshi/1.15.2/.gradle/9.1.0/checksums/checksums.lock
  tests/src/com.squareup.moshi/moshi/1.15.2/.gradle/9.1.0/checksums/sha1-checksums.bin
  tests/src/com.squareup.moshi/moshi/1.15.2/.gradle/9.1.0/gc.properties
  tests/src/com.squareup.moshi/moshi/1.15.2/.gradle/buildOutputCleanup/outputFiles.bin
  tests/src/com.squareup.moshi/moshi/1.15.2/.gradle/buildOutputCleanup/buildOutputCleanup.lock
  tests/src/com.squareup.moshi/moshi/1.15.2/.gradle/buildOutputCleanup/cache.properties
  tests/src/com.squareup.moshi/moshi/1.15.2/.gradle/vcs-1/gc.properties
  tests/src/com.squareup.moshi/moshi/1.15.2/.gradle/file-system.probe
  tests/src/com.squareup.moshi/moshi/1.15.2/.gradle/noVersion/buildLogic.lock
  tests/src/com.squareup.moshi/moshi/1.15.2/build/jacoco/test.exec
  tests/src/com.squareup.moshi/moshi/1.15.2/build/reports/dynamic-access/dynamic-access-coverage.json
  tests/src/com.squareup.moshi/moshi/1.15.2/build/reports/problems/problems-report.html
  tests/src/com.squareup.moshi/moshi/1.15.2/build/native/nativeTestCompile/libmanagement_ext.so
  tests/src/com.squareup.moshi/moshi/1.15.2/build/native/nativeTestCompile/com.squareup.moshi.moshi_tests-tests
  tests/src/com.squareup.moshi/moshi/1.15.2/build/libs/com.squareup.moshi.moshi_tests.jar
  tests/src/com.squareup.moshi/moshi/1.15.2/build/test-results/test/TEST-com_squareup_moshi.moshi.TypesTest.xml
  tests/src/com.squareup.moshi/moshi/1.15.2/build/test-results/test/TEST-com_squareup_moshi.moshi.UtilTest.xml
  tests/src/com.squareup.moshi/moshi/1.15.2/build/tmp/jar/MANIFEST.MF
  tests/src/com.squareup.moshi/moshi/1.15.2/build.gradle
[recv] {"type": "message_start", "message": {"role": "toolResult", "toolCallId": "call_57OkPY9O60M16UkztmxRK9bX|fc_0d8c31fa336f7f3d0169f98557920481a2b89955e9c6381e9f", "toolName": "bash", "content": [{"type": "text", "text": "tests/src/com.squareup.moshi/moshi/1.15.2/test-results-native/test/TEST-junit-jupiter.xml\ntests/src/com.squareup.moshi/moshi/1.15.2/test-results-native/test/TEST-junit-vintage.xml\ntests/src/com.squareup.moshi/moshi/1.15.2/user-code-filter.json\ntests/src/com.squareup.moshi/moshi/1.15.2/gradle.properties\ntests/src/com.squareup.moshi/moshi/1.15.2/.gitignore\ntests/src/com.squareup.moshi/moshi/1.15.2/settings.gradle\ntests/src/com.squareup.moshi/moshi/1.15.2/.gradle/9.1.0/executionHistory/executionHistory.bin\ntests/src/com.squareup.moshi/moshi/1.15.2/.gradle/9.1.0/executionHistory/executionHistory.lock\ntests/src/com.squareup.moshi/moshi/1.15.2/.gradle/9.1.0/fileHashes/resourceHashesCache.bin\ntests/src/com.squareup.moshi/moshi/1.15.2/.gradle/9.1.0/fileHashes/fileHashes.bin\ntests/src/com.squareup.moshi/moshi/1.15.2/.gradle/9.1.0/fileHashes/fileHashes.lock\ntests/src/com.squareup.moshi/moshi/1.15.2/.gradle/9.1.0/fileChanges/last-build.bin\ntests/src/com.squareup.moshi/moshi/1.15.2/.gradle/9.1.0/expanded/expanded.lock\ntests/src/com.squareup.moshi/moshi/1.15.2/.gradle/9.1.0/checksums/md5-checksums.bin\ntests/src/com.squareup.moshi/moshi/1.15.2/.gradle/9.1.0/checksums/checksums.lock\ntests/src/com.squareup.moshi/moshi/1.15.2/.gradle/9.1.0/checksums/sha1-checksums.bin\ntests/src/com.squareup.moshi/moshi/1.15.2/.gradle/9.1.0/gc.properties\ntests/src/com.squareup.moshi/moshi/1.15.2/.gradle/buildOutputCleanup/outputFiles.bin\ntests/src/com.squareup.moshi/moshi/1.15.2/.gradle/buildOutputCleanup/buildOutputCleanup.lock\ntests/src/com.squareup.moshi/moshi/1.15.2/.gradle/buildOutputCleanup/cache.properties\ntests/src/com.squareup.moshi/moshi/1.15.2/.gradle/vcs-1/gc.properties\ntests/src/com.squareup.moshi/moshi/1.15.2/.gradle/file-system.probe\ntests/src/com.squareup.moshi/moshi/1.15.2/.gradle/noVersion/buildLogic.lock\ntests/src/com.squareup.moshi/moshi/1.15.2/build/jacoco/test.exec\ntests/src/com.squareup.moshi/moshi/1.15.2/build/reports/dynamic-access/dynamic-access-coverage.json\ntests/src/com.squareup.moshi/moshi/1.15.2/build/reports/problems/problems-report.html\ntests/src/com.squareup.moshi/moshi/1.15.2/build/native/nativeTestCompile/libmanagement_ext.so\ntests/src/com.squareup.moshi/moshi/1.15.2/build/native/nativeTestCompile/com.squareup.moshi.moshi_tests-tests\ntests/src/com.squareup.moshi/moshi/1.15.2/build/libs/com.squareup.moshi.moshi_tests.jar\ntests/src/com.squareup.moshi/moshi/1.15.2/build/test-results/test/TEST-com_squareup_moshi.moshi.TypesTest.xml\ntests/src/com.squareup.moshi/moshi/1.15.2/build/test-results/test/TEST-com_squareup_moshi.moshi.UtilTest.xml\ntests/src/com.squareup.moshi/moshi/1.15.2/build/tmp/jar/MANIFEST.MF\ntests/src/com.squareup.moshi/moshi/1.15.2/build.gradle\n"}], "isError": false, "timestamp": 1777960279904}}
[recv] {"type": "message_end", "message": {"role": "toolResult", "toolCallId": "call_57OkPY9O60M16UkztmxRK9bX|fc_0d8c31fa336f7f3d0169f98557920481a2b89955e9c6381e9f", "toolName": "bash", "content": [{"type": "text", "text": "tests/src/com.squareup.moshi/moshi/1.15.2/test-results-native/test/TEST-junit-jupiter.xml\ntests/src/com.squareup.moshi/moshi/1.15.2/test-results-native/test/TEST-junit-vintage.xml\ntests/src/com.squareup.moshi/moshi/1.15.2/user-code-filter.json\ntests/src/com.squareup.moshi/moshi/1.15.2/gradle.properties\ntests/src/com.squareup.moshi/moshi/1.15.2/.gitignore\ntests/src/com.squareup.moshi/moshi/1.15.2/settings.gradle\ntests/src/com.squareup.moshi/moshi/1.15.2/.gradle/9.1.0/executionHistory/executionHistory.bin\ntests/src/com.squareup.moshi/moshi/1.15.2/.gradle/9.1.0/executionHistory/executionHistory.lock\ntests/src/com.squareup.moshi/moshi/1.15.2/.gradle/9.1.0/fileHashes/resourceHashesCache.bin\ntests/src/com.squareup.moshi/moshi/1.15.2/.gradle/9.1.0/fileHashes/fileHashes.bin\ntests/src/com.squareup.moshi/moshi/1.15.2/.gradle/9.1.0/fileHashes/fileHashes.lock\ntests/src/com.squareup.moshi/moshi/1.15.2/.gradle/9.1.0/fileChanges/last-build.bin\ntests/src/com.squareup.moshi/moshi/1.15.2/.gradle/9.1.0/expanded/expanded.lock\ntests/src/com.squareup.moshi/moshi/1.15.2/.gradle/9.1.0/checksums/md5-checksums.bin\ntests/src/com.squareup.moshi/moshi/1.15.2/.gradle/9.1.0/checksums/checksums.lock\ntests/src/com.squareup.moshi/moshi/1.15.2/.gradle/9.1.0/checksums/sha1-checksums.bin\ntests/src/com.squareup.moshi/moshi/1.15.2/.gradle/9.1.0/gc.properties\ntests/src/com.squareup.moshi/moshi/1.15.2/.gradle/buildOutputCleanup/outputFiles.bin\ntests/src/com.squareup.moshi/moshi/1.15.2/.gradle/buildOutputCleanup/buildOutputCleanup.lock\ntests/src/com.squareup.moshi/moshi/1.15.2/.gradle/buildOutputCleanup/cache.properties\ntests/src/com.squareup.moshi/moshi/1.15.2/.gradle/vcs-1/gc.properties\ntests/src/com.squareup.moshi/moshi/1.15.2/.gradle/file-system.probe\ntests/src/com.squareup.moshi/moshi/1.15.2/.gradle/noVersion/buildLogic.lock\ntests/src/com.squareup.moshi/moshi/1.15.2/build/jacoco/test.exec\ntests/src/com.squareup.moshi/moshi/1.15.2/build/reports/dynamic-access/dynamic-access-coverage.json\ntests/src/com.squareup.moshi/moshi/1.15.2/build/reports/problems/problems-report.html\ntests/src/com.squareup.moshi/moshi/1.15.2/build/native/nativeTestCompile/libmanagement_ext.so\ntests/src/com.squareup.moshi/moshi/1.15.2/build/native/nativeTestCompile/com.squareup.moshi.moshi_tests-tests\ntests/src/com.squareup.moshi/moshi/1.15.2/build/libs/com.squareup.moshi.moshi_tests.jar\ntests/src/com.squareup.moshi/moshi/1.15.2/build/test-results/test/TEST-com_squareup_moshi.moshi.TypesTest.xml\ntests/src/com.squareup.moshi/moshi/1.15.2/build/test-results/test/TEST-com_squareup_moshi.moshi.UtilTest.xml\ntests/src/com.squareup.moshi/moshi/1.15.2/build/tmp/jar/MANIFEST.MF\ntests/src/com.squareup.moshi/moshi/1.15.2/build.gradle\n"}], "isError": false, "timestamp": 1777960279904}}
[recv] {"type": "turn_end", "message": {"role": "assistant", "content": [{"type": "thinking", "thinking": "**Searching for moshi tests**\n\nI need to find tests related to Moshi. It seems like I should look into various sources or maybe even code repositories to locate what I'm looking for. I'm thinking checking documentation or GitHub could be good places to start. Moshi testing could involve looking at certain libraries or frameworks that utilize it. I wonder what kinds of tests are most common and how I can best find them. Let's go ahead and search!", "thinkingSignature": "{\"id\":\"rs_0d8c31fa336f7f3d0169f98555aaa881a280c895b9309b78bc\",\"type\":\"reasoning\",\"encrypted_content\":\"gAAAAABp-YVXYsSBJ3rZvM-zAKpPYMoMh2XkTbyNMrRaZU1aSjWm9D2kbugDPuLNoDu9d9g9keqKTD5T-MldfehAFJ4xkZ4Uy7e1gKO-03T8Ph2K2f9MQ4mqARz3AB2UFed4jM2-yPg5KAJioYMiHK94z7_Dbx_7x_zq6b4e1V30a3qdVr0XVteT_LISmXgNNAsuqr_DcuYBQU1JSqdNBJnzqLwI9I_6QcxE0D2leEV9WsOaJLKtxVLySFL1hnlFUsEZ8VXBqkwF4zu-JCqWaTioPs3mRW0ijF2bSa3FDgmNLdyfSLGZVRUMCMHqVf9f45vyIOYd57i6DKtCQ2BBiDDRwF5bDd1fz8PlOzqitGNyQSfNadmGCgMTNvS6Y9hgUXFFHltI0koX8zMHbJ2G6T-djofLD4jm7P__MommamTAua5ojgYA5YUTlz77khOXV5z7dmeXQo7_sKe2W6CB-W4bgZvjLIvyCdRFYOnN4G5ze7zAcBkVhWpMtno37eB8doFeW8Svk_a5F24s5KpfzocWjgh6qjQ_fVXvOWVtBkgdT6yYmLkWXxBQEVP5SrBe1bbFnBkGC1MPivAjFL7DG_wTMhDArFmglPHljupih-gG-OchPeh-2ywxTk563LIAL0zJpOzTjJlsB9j1bQG1GCM8z1F8NnWNdENGLrwAye6QsmI2ul2EoEjE1aEpf5px2Kj9J0CkYSi8TA4aBLR0frZfDQ-rmbJ0WOkupOPV9F2ym8esyIYTnbGR0byJ51sa-Y2XpseltqRfV9e1LPs-TFRUvKmTCbxIZsGdlpOO6Y4jNKwt0zToTmV_GU4knnh63q2Om34vAlL8WWQ3Yh_W_NGfo4bzIhBpvpsBmKTK4mmAeD3JhiELUY1ErmShOERCXlKKDgRZq659vd-RifAnySHrkrGT9Np_psoNbl6cbZnRuvovOhy_XyAR0dGOVmpVyVz0BMfIt6KokYi_csaT8Lz6dQKfhGmhTQ==\",\"summary\":[{\"type\":\"summary_text\",\"text\":\"**Searching for moshi tests**\\n\\nI need to find tests related to Moshi. It seems like I should look into various sources or maybe even code repositories to locate what I'm looking for. I'm thinking checking documentation or GitHub could be good places to start. Moshi testing could involve looking at certain libraries or frameworks that utilize it. I wonder what kinds of tests are most common and how I can best find them. Let's go ahead and search!\"}]}"}, {"type": "toolCall", "id": "call_57OkPY9O60M16UkztmxRK9bX|fc_0d8c31fa336f7f3d0169f98557920481a2b89955e9c6381e9f", "name": "bash", "arguments": {"command": "find tests -path '*moshi*' -maxdepth 8 -type f | head -50"}}], "api": "openai-responses", "provider": "OCA", "model": "gpt-5.5", "usage": {"input": 405, "output": 50, "cacheRead": 7168, "cacheWrite": 0, "totalTokens": 7623, "cost": {"input": 0, "output": 0, "cacheRead": 0, "cacheWrite": 0, "total": 0}}, "stopReason": "toolUse", "timestamp": 1777960276774, "responseId": "resp_0d8c31fa336f7f3d0169f98555041081a29ae70c63d85a2b57"}, "toolResults": [{"role": "toolResult", "toolCallId": "call_57OkPY9O60M16UkztmxRK9bX|fc_0d8c31fa336f7f3d0169f98557920481a2b89955e9c6381e9f", "toolName": "bash", "content": [{"type": "text", "text": "tests/src/com.squareup.moshi/moshi/1.15.2/test-results-native/test/TEST-junit-jupiter.xml\ntests/src/com.squareup.moshi/moshi/1.15.2/test-results-native/test/TEST-junit-vintage.xml\ntests/src/com.squareup.moshi/moshi/1.15.2/user-code-filter.json\ntests/src/com.squareup.moshi/moshi/1.15.2/gradle.properties\ntests/src/com.squareup.moshi/moshi/1.15.2/.gitignore\ntests/src/com.squareup.moshi/moshi/1.15.2/settings.gradle\ntests/src/com.squareup.moshi/moshi/1.15.2/.gradle/9.1.0/executionHistory/executionHistory.bin\ntests/src/com.squareup.moshi/moshi/1.15.2/.gradle/9.1.0/executionHistory/executionHistory.lock\ntests/src/com.squareup.moshi/moshi/1.15.2/.gradle/9.1.0/fileHashes/resourceHashesCache.bin\ntests/src/com.squareup.moshi/moshi/1.15.2/.gradle/9.1.0/fileHashes/fileHashes.bin\ntests/src/com.squareup.moshi/moshi/1.15.2/.gradle/9.1.0/fileHashes/fileHashes.lock\ntests/src/com.squareup.moshi/moshi/1.15.2/.gradle/9.1.0/fileChanges/last-build.bin\ntests/src/com.squareup.moshi/moshi/1.15.2/.gradle/9.1.0/expanded/expanded.lock\ntests/src/com.squareup.moshi/moshi/1.15.2/.gradle/9.1.0/checksums/md5-checksums.bin\ntests/src/com.squareup.moshi/moshi/1.15.2/.gradle/9.1.0/checksums/checksums.lock\ntests/src/com.squareup.moshi/moshi/1.15.2/.gradle/9.1.0/checksums/sha1-checksums.bin\ntests/src/com.squareup.moshi/moshi/1.15.2/.gradle/9.1.0/gc.properties\ntests/src/com.squareup.moshi/moshi/1.15.2/.gradle/buildOutputCleanup/outputFiles.bin\ntests/src/com.squareup.moshi/moshi/1.15.2/.gradle/buildOutputCleanup/buildOutputCleanup.lock\ntests/src/com.squareup.moshi/moshi/1.15.2/.gradle/buildOutputCleanup/cache.properties\ntests/src/com.squareup.moshi/moshi/1.15.2/.gradle/vcs-1/gc.properties\ntests/src/com.squareup.moshi/moshi/1.15.2/.gradle/file-system.probe\ntests/src/com.squareup.moshi/moshi/1.15.2/.gradle/noVersion/buildLogic.lock\ntests/src/com.squareup.moshi/moshi/1.15.2/build/jacoco/test.exec\ntests/src/com.squareup.moshi/moshi/1.15.2/build/reports/dynamic-access/dynamic-access-coverage.json\ntests/src/com.squareup.moshi/moshi/1.15.2/build/reports/problems/problems-report.html\ntests/src/com.squareup.moshi/moshi/1.15.2/build/native/nativeTestCompile/libmanagement_ext.so\ntests/src/com.squareup.moshi/moshi/1.15.2/build/native/nativeTestCompile/com.squareup.moshi.moshi_tests-tests\ntests/src/com.squareup.moshi/moshi/1.15.2/build/libs/com.squareup.moshi.moshi_tests.jar\ntests/src/com.squareup.moshi/moshi/1.15.2/build/test-results/test/TEST-com_squareup_moshi.moshi.TypesTest.xml\ntests/src/com.squareup.moshi/moshi/1.15.2/build/test-results/test/TEST-com_squareup_moshi.moshi.UtilTest.xml\ntests/src/com.squareup.moshi/moshi/1.15.2/build/tmp/jar/MANIFEST.MF\ntests/src/com.squareup.moshi/moshi/1.15.2/build.gradle\n"}], "isError": false, "timestamp": 1777960279904}]}
[recv] {"type": "turn_start"}
[recv] {"type": "message_start", "message": {"role": "assistant", "content": [], "api": "openai-responses", "provider": "OCA", "model": "gpt-5.5", "usage": {"input": 0, "output": 0, "cacheRead": 0, "cacheWrite": 0, "totalTokens": 0, "cost": {"input": 0, "output": 0, "cacheRead": 0, "cacheWrite": 0, "total": 0}}, "stopReason": "stop", "timestamp": 1777960279912}}
[tool-call] start id=unknown
[tool-call] delta {"command":"find tests/src/com.squareup.moshi/moshi/1.15.2/src/test -type f -maxdepth 5 -print"}
[tool-call] end id=call_XnolkX2qoGmgA6dB6RNBpC36|fc_0d8c31fa336f7f3d0169f985598aa881a2accfca000a083acb name=bash args={"command": "find tests/src/com.squareup.moshi/moshi/1.15.2/src/test -type f -maxdepth 5 -print"}
[recv] {"type": "message_end", "message": {"role": "assistant", "content": [{"type": "toolCall", "id": "call_XnolkX2qoGmgA6dB6RNBpC36|fc_0d8c31fa336f7f3d0169f985598aa881a2accfca000a083acb", "name": "bash", "arguments": {"command": "find tests/src/com.squareup.moshi/moshi/1.15.2/src/test -type f -maxdepth 5 -print"}}], "api": "openai-responses", "provider": "OCA", "model": "gpt-5.5", "usage": {"input": 1317, "output": 44, "cacheRead": 7168, "cacheWrite": 0, "totalTokens": 8529, "cost": {"input": 0, "output": 0, "cacheRead": 0, "cacheWrite": 0, "total": 0}}, "stopReason": "toolUse", "timestamp": 1777960279912, "responseId": "resp_0d8c31fa336f7f3d0169f9855826a881a2bec6cd0b6a1761dc"}}
[tool-exec] start id=call_XnolkX2qoGmgA6dB6RNBpC36|fc_0d8c31fa336f7f3d0169f985598aa881a2accfca000a083acb name=bash args={"command": "find tests/src/com.squareup.moshi/moshi/1.15.2/src/test -type f -maxdepth 5 -print"}
[tool-exec] update id=call_XnolkX2qoGmgA6dB6RNBpC36|fc_0d8c31fa336f7f3d0169f985598aa881a2accfca000a083acb name=bash
[tool-exec] update id=call_XnolkX2qoGmgA6dB6RNBpC36|fc_0d8c31fa336f7f3d0169f985598aa881a2accfca000a083acb name=bash
  tests/src/com.squareup.moshi/moshi/1.15.2/src/test/kotlin/com_squareup_moshi/moshi/UtilTest.kt
  tests/src/com.squareup.moshi/moshi/1.15.2/src/test/kotlin/com_squareup_moshi/moshi/TypesTest.kt
  tests/src/com.squareup.moshi/moshi/1.15.2/src/test/resources/META-INF/native-image/reachability-metadata.json
[tool-exec] end id=call_XnolkX2qoGmgA6dB6RNBpC36|fc_0d8c31fa336f7f3d0169f985598aa881a2accfca000a083acb name=bash status=success
  tests/src/com.squareup.moshi/moshi/1.15.2/src/test/kotlin/com_squareup_moshi/moshi/UtilTest.kt
  tests/src/com.squareup.moshi/moshi/1.15.2/src/test/kotlin/com_squareup_moshi/moshi/TypesTest.kt
  tests/src/com.squareup.moshi/moshi/1.15.2/src/test/resources/META-INF/native-image/reachability-metadata.json
[recv] {"type": "message_start", "message": {"role": "toolResult", "toolCallId": "call_XnolkX2qoGmgA6dB6RNBpC36|fc_0d8c31fa336f7f3d0169f985598aa881a2accfca000a083acb", "toolName": "bash", "content": [{"type": "text", "text": "tests/src/com.squareup.moshi/moshi/1.15.2/src/test/kotlin/com_squareup_moshi/moshi/UtilTest.kt\ntests/src/com.squareup.moshi/moshi/1.15.2/src/test/kotlin/com_squareup_moshi/moshi/TypesTest.kt\ntests/src/com.squareup.moshi/moshi/1.15.2/src/test/resources/META-INF/native-image/reachability-metadata.json\n"}], "isError": false, "timestamp": 1777960282074}}
[recv] {"type": "message_end", "message": {"role": "toolResult", "toolCallId": "call_XnolkX2qoGmgA6dB6RNBpC36|fc_0d8c31fa336f7f3d0169f985598aa881a2accfca000a083acb", "toolName": "bash", "content": [{"type": "text", "text": "tests/src/com.squareup.moshi/moshi/1.15.2/src/test/kotlin/com_squareup_moshi/moshi/UtilTest.kt\ntests/src/com.squareup.moshi/moshi/1.15.2/src/test/kotlin/com_squareup_moshi/moshi/TypesTest.kt\ntests/src/com.squareup.moshi/moshi/1.15.2/src/test/resources/META-INF/native-image/reachability-metadata.json\n"}], "isError": false, "timestamp": 1777960282074}}
[recv] {"type": "turn_end", "message": {"role": "assistant", "content": [{"type": "toolCall", "id": "call_XnolkX2qoGmgA6dB6RNBpC36|fc_0d8c31fa336f7f3d0169f985598aa881a2accfca000a083acb", "name": "bash", "arguments": {"command": "find tests/src/com.squareup.moshi/moshi/1.15.2/src/test -type f -maxdepth 5 -print"}}], "api": "openai-responses", "provider": "OCA", "model": "gpt-5.5", "usage": {"input": 1317, "output": 44, "cacheRead": 7168, "cacheWrite": 0, "totalTokens": 8529, "cost": {"input": 0, "output": 0, "cacheRead": 0, "cacheWrite": 0, "total": 0}}, "stopReason": "toolUse", "timestamp": 1777960279912, "responseId": "resp_0d8c31fa336f7f3d0169f9855826a881a2bec6cd0b6a1761dc"}, "toolResults": [{"role": "toolResult", "toolCallId": "call_XnolkX2qoGmgA6dB6RNBpC36|fc_0d8c31fa336f7f3d0169f985598aa881a2accfca000a083acb", "toolName": "bash", "content": [{"type": "text", "text": "tests/src/com.squareup.moshi/moshi/1.15.2/src/test/kotlin/com_squareup_moshi/moshi/UtilTest.kt\ntests/src/com.squareup.moshi/moshi/1.15.2/src/test/kotlin/com_squareup_moshi/moshi/TypesTest.kt\ntests/src/com.squareup.moshi/moshi/1.15.2/src/test/resources/META-INF/native-image/reachability-metadata.json\n"}], "isError": false, "timestamp": 1777960282074}]}
[recv] {"type": "turn_start"}
[recv] {"type": "message_start", "message": {"role": "assistant", "content": [], "api": "openai-responses", "provider": "OCA", "model": "gpt-5.5", "usage": {"input": 0, "output": 0, "cacheRead": 0, "cacheWrite": 0, "totalTokens": 0, "cost": {"input": 0, "output": 0, "cacheRead": 0, "cacheWrite": 0, "total": 0}}, "stopReason": "stop", "timestamp": 1777960282080}}
[assistant-event] thinking_start
[assistant-event] thinking_end
[tool-call] start id=unknown
[tool-call] delta {"path":"local_repositories/source_context/com.squareup.moshi/moshi/1.15.2/main/extracted/main/com/squareup/moshi/RecordJsonAdapter.java"}
[tool-call] end id=call_QGyxYnhLuRCADVoOQx4hejMR|fc_0d8c31fa336f7f3d0169f9855c111c81a2836d0b64eefe2dc5 name=read args={"path": "local_repositories/source_context/com.squareup.moshi/moshi/1.15.2/main/extracted/main/com/squareup/moshi/RecordJsonAdapter.java"}
[recv] {"type": "message_end", "message": {"role": "assistant", "content": [{"type": "thinking", "thinking": "", "thinkingSignature": "{\"id\":\"rs_0d8c31fa336f7f3d0169f9855b676081a293f868a626c95199\",\"type\":\"reasoning\",\"encrypted_content\":\"gAAAAABp-YVck9SrW-F3M54wt5lRR5nP6-Yh7kadQN3HPN4PKbG_P9iv3AO1uzBYYM07BEpp8nNWC6259qIuNsfGZTiJzhQZlHRD-H9nLJWxWr2xR2skBavBaw96nU3Ehs5a0J_K44xQSqV-Cn_Gwil5cuFRXll0t5cXZh_jKl022G3ZjXmL9Cqvx2LERqXlTdkR2P_4biN3B5sANeuvo21IxyQUEB-pS-fz3mkfCko-OKbwxqcNPXEmohnzrXjkm-18dbunXUMIe_lXmyoyqBvJi8PlN7wcKBgv4aE-3ypJHaahucMBdqsNv_3mdFDyE3C2coOQtgVF_3TSp2PEqpVmVvuoFZYKbhG4utufIep8JP9zVcbzUfqfhnGYWciM3XTmYNH33fXyOvEXNYbzr0kkC2dXl8LYqYKe8pzhghDo8F1QHaC4LLrms2L3f237_yTSmHMNAucZQ4sZQPIY2rXq3Q1cxvBMVmD2N0raHF6cHGJNN_DF3_hTiu3QqEFFRgTvrinJsakVVQDpl3pzTXJRsc_KNsjmqFkicb-hiesivYt_yehOfJW-DvD1vj6JHppKjmTcGk96E5Y_cyeAi2Ln3-VZxQAnWZAIks47xZWCuSgehE-u9xVP6HX5pRjLsaDFajVG6zwtTppSL9mJvqdfR86WpgxfRTbKIgy6N2_wJuJ9Hg2-psr52HpGF_bauEbXOyZaOgJA0q-Rda0EId346ttmarhVlHU9u5iYnHExJcReqs5H-MDos0Qwf9Yq6pnE-S3oTEjSw_8EHVBlU6LYC-Si-RruEZemT_rzS1X0PUGk9N7L1jpeCw6VBxpqR7MRX1CcUnRNRyslkJYi6szZlPLOiZnvJC16MUXdYJgGvELokvs0WVuTXTXp4SPKFW4D_Rmtx4wIhTrnmO5itca_LnRo49unzUteR3NS670VU9L21ePtnVfptxWO7ilKCW6lkMNbbgSHv5sTIxoTGDyIaqUkqDuQ9My400U4_BHUzbsHyeh8hApVbTUT4gyHcXMvsLD4N3-nudz7kskiAQ2iumw5ZSBaU-n2dTYzS-y6zbYG2v3dnJwA2Ic_XRL86GlBbVV5qLKp_BuJ38PzNHad3bmxEso-qBkzPo36YJbb429x1o7viOc=\",\"summary\":[]}"}, {"type": "toolCall", "id": "call_QGyxYnhLuRCADVoOQx4hejMR|fc_0d8c31fa336f7f3d0169f9855c111c81a2836d0b64eefe2dc5", "name": "read", "arguments": {"path": "local_repositories/source_context/com.squareup.moshi/moshi/1.15.2/main/extracted/main/com/squareup/moshi/RecordJsonAdapter.java"}}], "api": "openai-responses", "provider": "OCA", "model": "gpt-5.5", "usage": {"input": 437, "output": 81, "cacheRead": 8192, "cacheWrite": 0, "totalTokens": 8710, "cost": {"input": 0, "output": 0, "cacheRead": 0, "cacheWrite": 0, "total": 0}}, "stopReason": "toolUse", "timestamp": 1777960282080, "responseId": "resp_0d8c31fa336f7f3d0169f9855a53cc81a2b162eeda25a34fec"}}
[tool-exec] start id=call_QGyxYnhLuRCADVoOQx4hejMR|fc_0d8c31fa336f7f3d0169f9855c111c81a2836d0b64eefe2dc5 name=read args={"path": "local_repositories/source_context/com.squareup.moshi/moshi/1.15.2/main/extracted/main/com/squareup/moshi/RecordJsonAdapter.java"}
[tool-exec] end id=call_QGyxYnhLuRCADVoOQx4hejMR|fc_0d8c31fa336f7f3d0169f9855c111c81a2836d0b64eefe2dc5 name=read status=error
  ENOENT: no such file or directory, access '/home/vjovanov/c/forge/forge8/graalvm-reachability-metadata/forge/local_repositories/forge_worktrees/4490-2eb21853/local_repositories/source_context/com.squareup.moshi/moshi/1.15.2/main/extracted/main/com/squareup/moshi/RecordJsonAdapter.java'
[recv] {"type": "message_start", "message": {"role": "toolResult", "toolCallId": "call_QGyxYnhLuRCADVoOQx4hejMR|fc_0d8c31fa336f7f3d0169f9855c111c81a2836d0b64eefe2dc5", "toolName": "read", "content": [{"type": "text", "text": "ENOENT: no such file or directory, access '/home/vjovanov/c/forge/forge8/graalvm-reachability-metadata/forge/local_repositories/forge_worktrees/4490-2eb21853/local_repositories/source_context/com.squareup.moshi/moshi/1.15.2/main/extracted/main/com/squareup/moshi/RecordJsonAdapter.java'"}], "details": {}, "isError": true, "timestamp": 1777960284332}}
[recv] {"type": "message_end", "message": {"role": "toolResult", "toolCallId": "call_QGyxYnhLuRCADVoOQx4hejMR|fc_0d8c31fa336f7f3d0169f9855c111c81a2836d0b64eefe2dc5", "toolName": "read", "content": [{"type": "text", "text": "ENOENT: no such file or directory, access '/home/vjovanov/c/forge/forge8/graalvm-reachability-metadata/forge/local_repositories/forge_worktrees/4490-2eb21853/local_repositories/source_context/com.squareup.moshi/moshi/1.15.2/main/extracted/main/com/squareup/moshi/RecordJsonAdapter.java'"}], "details": {}, "isError": true, "timestamp": 1777960284332}}
[recv] {"type": "turn_end", "message": {"role": "assistant", "content": [{"type": "thinking", "thinking": "", "thinkingSignature": "{\"id\":\"rs_0d8c31fa336f7f3d0169f9855b676081a293f868a626c95199\",\"type\":\"reasoning\",\"encrypted_content\":\"gAAAAABp-YVck9SrW-F3M54wt5lRR5nP6-Yh7kadQN3HPN4PKbG_P9iv3AO1uzBYYM07BEpp8nNWC6259qIuNsfGZTiJzhQZlHRD-H9nLJWxWr2xR2skBavBaw96nU3Ehs5a0J_K44xQSqV-Cn_Gwil5cuFRXll0t5cXZh_jKl022G3ZjXmL9Cqvx2LERqXlTdkR2P_4biN3B5sANeuvo21IxyQUEB-pS-fz3mkfCko-OKbwxqcNPXEmohnzrXjkm-18dbunXUMIe_lXmyoyqBvJi8PlN7wcKBgv4aE-3ypJHaahucMBdqsNv_3mdFDyE3C2coOQtgVF_3TSp2PEqpVmVvuoFZYKbhG4utufIep8JP9zVcbzUfqfhnGYWciM3XTmYNH33fXyOvEXNYbzr0kkC2dXl8LYqYKe8pzhghDo8F1QHaC4LLrms2L3f237_yTSmHMNAucZQ4sZQPIY2rXq3Q1cxvBMVmD2N0raHF6cHGJNN_DF3_hTiu3QqEFFRgTvrinJsakVVQDpl3pzTXJRsc_KNsjmqFkicb-hiesivYt_yehOfJW-DvD1vj6JHppKjmTcGk96E5Y_cyeAi2Ln3-VZxQAnWZAIks47xZWCuSgehE-u9xVP6HX5pRjLsaDFajVG6zwtTppSL9mJvqdfR86WpgxfRTbKIgy6N2_wJuJ9Hg2-psr52HpGF_bauEbXOyZaOgJA0q-Rda0EId346ttmarhVlHU9u5iYnHExJcReqs5H-MDos0Qwf9Yq6pnE-S3oTEjSw_8EHVBlU6LYC-Si-RruEZemT_rzS1X0PUGk9N7L1jpeCw6VBxpqR7MRX1CcUnRNRyslkJYi6szZlPLOiZnvJC16MUXdYJgGvELokvs0WVuTXTXp4SPKFW4D_Rmtx4wIhTrnmO5itca_LnRo49unzUteR3NS670VU9L21ePtnVfptxWO7ilKCW6lkMNbbgSHv5sTIxoTGDyIaqUkqDuQ9My400U4_BHUzbsHyeh8hApVbTUT4gyHcXMvsLD4N3-nudz7kskiAQ2iumw5ZSBaU-n2dTYzS-y6zbYG2v3dnJwA2Ic_XRL86GlBbVV5qLKp_BuJ38PzNHad3bmxEso-qBkzPo36YJbb429x1o7viOc=\",\"summary\":[]}"}, {"type": "toolCall", "id": "call_QGyxYnhLuRCADVoOQx4hejMR|fc_0d8c31fa336f7f3d0169f9855c111c81a2836d0b64eefe2dc5", "name": "read", "arguments": {"path": "local_repositories/source_context/com.squareup.moshi/moshi/1.15.2/main/extracted/main/com/squareup/moshi/RecordJsonAdapter.java"}}], "api": "openai-responses", "provider": "OCA", "model": "gpt-5.5", "usage": {"input": 437, "output": 81, "cacheRead": 8192, "cacheWrite": 0, "totalTokens": 8710, "cost": {"input": 0, "output": 0, "cacheRead": 0, "cacheWrite": 0, "total": 0}}, "stopReason": "toolUse", "timestamp": 1777960282080, "responseId": "resp_0d8c31fa336f7f3d0169f9855a53cc81a2b162eeda25a34fec"}, "toolResults": [{"role": "toolResult", "toolCallId": "call_QGyxYnhLuRCADVoOQx4hejMR|fc_0d8c31fa336f7f3d0169f9855c111c81a2836d0b64eefe2dc5", "toolName": "read", "content": [{"type": "text", "text": "ENOENT: no such file or directory, access '/home/vjovanov/c/forge/forge8/graalvm-reachability-metadata/forge/local_repositories/forge_worktrees/4490-2eb21853/local_repositories/source_context/com.squareup.moshi/moshi/1.15.2/main/extracted/main/com/squareup/moshi/RecordJsonAdapter.java'"}], "details": {}, "isError": true, "timestamp": 1777960284332}]}
[recv] {"type": "turn_start"}
[recv] {"type": "message_start", "message": {"role": "assistant", "content": [], "api": "openai-responses", "provider": "OCA", "model": "gpt-5.5", "usage": {"input": 0, "output": 0, "cacheRead": 0, "cacheWrite": 0, "totalTokens": 0, "cost": {"input": 0, "output": 0, "cacheRead": 0, "cacheWrite": 0, "total": 0}}, "stopReason": "stop", "timestamp": 1777960284340}}
[assistant-event] thinking_start
[assistant-event] thinking_end
[tool-call] start id=unknown
[tool-call] delta {"path":"/home/vjovanov/c/forge/forge8/graalvm-reachability-metadata/forge/local_repositories/source_context/com.squareup.moshi/moshi/1.15.2/main/extracted/main/com/squareup/moshi/RecordJsonAdapter.java"}
[tool-call] end id=call_OsZBayS1NWAWAZ5qDNyWRrnL|fc_0d8c31fa336f7f3d0169f9855f1b5c81a2b7a4e51cbff3010c name=read args={"path": "/home/vjovanov/c/forge/forge8/graalvm-reachability-metadata/forge/local_repositories/source_context/com.squareup.moshi/moshi/1.15.2/main/extracted/main/com/squareup/moshi/RecordJsonAdapter.java"}
[recv] {"type": "message_end", "message": {"role": "assistant", "content": [{"type": "thinking", "thinking": "", "thinkingSignature": "{\"id\":\"rs_0d8c31fa336f7f3d0169f9855d497c81a2b0658195d115a24c\",\"type\":\"reasoning\",\"encrypted_content\":\"gAAAAABp-YVflwR86F6ZhrBhPvr4feu8IRPjejpq0MjWVBiAY9qHbFULyepsXW4z-OYuUR7WHRXmlKyDHV-a0gIJFKWk27NVxOMtRKeuUEX4xQMn8mzDtKKiPQcSM1IInicKUQlJO5xnjl6_ET410akISYZkDKzK6Gf0yJDY5ofoR0JfEDhQUfqmcZH79YTdCNI72h2YXJkDpqLEW1ImB2blHjo0s4IzwnaZ5n8rljIbOF5Rt-FE-lirpj8J0Kx2VWQbu_gbzsDYOHuO8OCfbBOLUI8IJ_Ng1rSINgFUNVCDpTKAn3dQfkKHEH5lmvoF6QyemrYBWg9TvB-DINMq4tMlK1cPKz_VdinsKqTZIDlP6EqGdJcO7Lsa9E9rmN5IdzZtPJHpMlEDSfA60xN_ssswwAo29y5xV0z3HwRXZxMRI2CZ7ZgU0p_4jB4c4R9i8FxwxdZ2JZG5aXJlM5CSCmKrarOpBZI3EXRnBbXBpQgAiZY16phnbfIQGTFakXbwynw12tIB7Wa21-4K894maBOlalnChIduQXDXArlfSntuo1WLuCAfyas66WGuiPTjHxiNa2_plP7jdM6jkaKFPDAEl_aJcQWxY90urwABBAlXoqR9kT0fPbed3mukpYFGrqIb-KuAz8FpwbPyHPK0P359CPcCtLayEE4ykVW-r7k9JFbtE1D-3cJXiQ7nRmiqu2WD7adF0WZNOdOX3KM09zXBJI2eEFQVUHuE4424Af0Vg5ZU9yqyR4sD4Ee3LLdqLTc5BRWAgOGEeA3Fic3nBRKYa7bgq8MyqqWpUY6cXnpanoXMd_uA_v6cOypmD1qoIynVAVZLiqCKs2VrH8QT7n_vMLlwOz5WX-QfuoMo5TjfuNEXYARU9P1qfBb2mEiLO2NT1PFdSfAIDZicmpiyYZ2h3gFCd0xsa0Y3ewi7KhK224jr527Xm1k-jPat7vAG9v6CFU2qkzlzCus4RU__XlIr0FL2nRBhfZVkSUdsazqsOc2fvp7tJQiNYdOPkDWfQCVW0aorhst6VSdt6gm11cIPWzj5UeJDv9FiIt_ylpTREnsnvsoegcsFZk2PDOY6ZazbRG9wKaQTHUskq7sgcRpz6PY_fnovDNQwRBgnaw2PfE-omLjsQvgItgRZiA7BS20GoIGxCFyi\",\"summary\":[]}"}, {"type": "toolCall", "id": "call_OsZBayS1NWAWAZ5qDNyWRrnL|fc_0d8c31fa336f7f3d0169f9855f1b5c81a2b7a4e51cbff3010c", "name": "read", "arguments": {"path": "/home/vjovanov/c/forge/forge8/graalvm-reachability-metadata/forge/local_repositories/source_context/com.squareup.moshi/moshi/1.15.2/main/extracted/main/com/squareup/moshi/RecordJsonAdapter.java"}}], "api": "openai-responses", "provider": "OCA", "model": "gpt-5.5", "usage": {"input": 608, "output": 110, "cacheRead": 8192, "cacheWrite": 0, "totalTokens": 8910, "cost": {"input": 0, "output": 0, "cacheRead": 0, "cacheWrite": 0, "total": 0}}, "stopReason": "toolUse", "timestamp": 1777960284340, "responseId": "resp_0d8c31fa336f7f3d0169f9855cafe881a29f18d49d4f0f7edb"}}
[tool-exec] start id=call_OsZBayS1NWAWAZ5qDNyWRrnL|fc_0d8c31fa336f7f3d0169f9855f1b5c81a2b7a4e51cbff3010c name=read args={"path": "/home/vjovanov/c/forge/forge8/graalvm-reachability-metadata/forge/local_repositories/source_context/com.squareup.moshi/moshi/1.15.2/main/extracted/main/com/squareup/moshi/RecordJsonAdapter.java"}
[tool-exec] end id=call_OsZBayS1NWAWAZ5qDNyWRrnL|fc_0d8c31fa336f7f3d0169f9855f1b5c81a2b7a4e51cbff3010c name=read status=success
  /*
   * Copyright (C) 2021 Square, Inc.
   *
   * Licensed under the Apache License, Version 2.0 (the "License");
   * you may not use this file except in compliance with the License.
   * You may obtain a copy of the License at
   *
   *    https://www.apache.org/licenses/LICENSE-2.0
   *
   * Unless required by applicable law or agreed to in writing, software
   * distributed under the License is distributed on an "AS IS" BASIS,
   * WITHOUT WARRANTIES OR CONDITIONS OF ANY KIND, either express or implied.
   * See the License for the specific language governing permissions and
   * limitations under the License.
   */
  package com.squareup.moshi;
  
  import java.io.IOException;
  import java.lang.annotation.Annotation;
  import java.lang.reflect.Type;
  import java.util.Set;
  import javax.annotation.Nullable;
  
  /**
   * This is just a simple shim for linking in {@link StandardJsonAdapters} and swapped with a real
   * implementation in Java 16 via MR Jar.
   */
  final class RecordJsonAdapter<T> extends JsonAdapter<T> {
  
    static final JsonAdapter.Factory FACTORY =
        new JsonAdapter.Factory() {
  
          @Nullable
          @Override
          public JsonAdapter<?> create(
              Type type, Set<? extends Annotation> annotations, Moshi moshi) {
            return null;
          }
        };
  
    @Nullable
    @Override
    public T fromJson(JsonReader reader) throws IOException {
      throw new AssertionError();
    }
  
    @Override
    public void toJson(JsonWriter writer, @Nullable T value) throws IOException {
      throw new AssertionError();
    }
  }
[recv] {"type": "message_start", "message": {"role": "toolResult", "toolCallId": "call_OsZBayS1NWAWAZ5qDNyWRrnL|fc_0d8c31fa336f7f3d0169f9855f1b5c81a2b7a4e51cbff3010c", "toolName": "read", "content": [{"type": "text", "text": "/*\n * Copyright (C) 2021 Square, Inc.\n *\n * Licensed under the Apache License, Version 2.0 (the \"License\");\n * you may not use this file except in compliance with the License.\n * You may obtain a copy of the License at\n *\n *    https://www.apache.org/licenses/LICENSE-2.0\n *\n * Unless required by applicable law or agreed to in writing, software\n * distributed under the License is distributed on an \"AS IS\" BASIS,\n * WITHOUT WARRANTIES OR CONDITIONS OF ANY KIND, either express or implied.\n * See the License for the specific language governing permissions and\n * limitations under the License.\n */\npackage com.squareup.moshi;\n\nimport java.io.IOException;\nimport java.lang.annotation.Annotation;\nimport java.lang.reflect.Type;\nimport java.util.Set;\nimport javax.annotation.Nullable;\n\n/**\n * This is just a simple shim for linking in {@link StandardJsonAdapters} and swapped with a real\n * implementation in Java 16 via MR Jar.\n */\nfinal class RecordJsonAdapter<T> extends JsonAdapter<T> {\n\n  static final JsonAdapter.Factory FACTORY =\n      new JsonAdapter.Factory() {\n\n        @Nullable\n        @Override\n        public JsonAdapter<?> create(\n            Type type, Set<? extends Annotation> annotations, Moshi moshi) {\n          return null;\n        }\n      };\n\n  @Nullable\n  @Override\n  public T fromJson(JsonReader reader) throws IOException {\n    throw new AssertionError();\n  }\n\n  @Override\n  public void toJson(JsonWriter writer, @Nullable T value) throws IOException {\n    throw new AssertionError();\n  }\n}\n"}], "isError": false, "timestamp": 1777960287432}}
[recv] {"type": "message_end", "message": {"role": "toolResult", "toolCallId": "call_OsZBayS1NWAWAZ5qDNyWRrnL|fc_0d8c31fa336f7f3d0169f9855f1b5c81a2b7a4e51cbff3010c", "toolName": "read", "content": [{"type": "text", "text": "/*\n * Copyright (C) 2021 Square, Inc.\n *\n * Licensed under the Apache License, Version 2.0 (the \"License\");\n * you may not use this file except in compliance with the License.\n * You may obtain a copy of the License at\n *\n *    https://www.apache.org/licenses/LICENSE-2.0\n *\n * Unless required by applicable law or agreed to in writing, software\n * distributed under the License is distributed on an \"AS IS\" BASIS,\n * WITHOUT WARRANTIES OR CONDITIONS OF ANY KIND, either express or implied.\n * See the License for the specific language governing permissions and\n * limitations under the License.\n */\npackage com.squareup.moshi;\n\nimport java.io.IOException;\nimport java.lang.annotation.Annotation;\nimport java.lang.reflect.Type;\nimport java.util.Set;\nimport javax.annotation.Nullable;\n\n/**\n * This is just a simple shim for linking in {@link StandardJsonAdapters} and swapped with a real\n * implementation in Java 16 via MR Jar.\n */\nfinal class RecordJsonAdapter<T> extends JsonAdapter<T> {\n\n  static final JsonAdapter.Factory FACTORY =\n      new JsonAdapter.Factory() {\n\n        @Nullable\n        @Override\n        public JsonAdapter<?> create(\n            Type type, Set<? extends Annotation> annotations, Moshi moshi) {\n          return null;\n        }\n      };\n\n  @Nullable\n  @Override\n  public T fromJson(JsonReader reader) throws IOException {\n    throw new AssertionError();\n  }\n\n  @Override\n  public void toJson(JsonWriter writer, @Nullable T value) throws IOException {\n    throw new AssertionError();\n  }\n}\n"}], "isError": false, "timestamp": 1777960287432}}
[recv] {"type": "turn_end", "message": {"role": "assistant", "content": [{"type": "thinking", "thinking": "", "thinkingSignature": "{\"id\":\"rs_0d8c31fa336f7f3d0169f9855d497c81a2b0658195d115a24c\",\"type\":\"reasoning\",\"encrypted_content\":\"gAAAAABp-YVflwR86F6ZhrBhPvr4feu8IRPjejpq0MjWVBiAY9qHbFULyepsXW4z-OYuUR7WHRXmlKyDHV-a0gIJFKWk27NVxOMtRKeuUEX4xQMn8mzDtKKiPQcSM1IInicKUQlJO5xnjl6_ET410akISYZkDKzK6Gf0yJDY5ofoR0JfEDhQUfqmcZH79YTdCNI72h2YXJkDpqLEW1ImB2blHjo0s4IzwnaZ5n8rljIbOF5Rt-FE-lirpj8J0Kx2VWQbu_gbzsDYOHuO8OCfbBOLUI8IJ_Ng1rSINgFUNVCDpTKAn3dQfkKHEH5lmvoF6QyemrYBWg9TvB-DINMq4tMlK1cPKz_VdinsKqTZIDlP6EqGdJcO7Lsa9E9rmN5IdzZtPJHpMlEDSfA60xN_ssswwAo29y5xV0z3HwRXZxMRI2CZ7ZgU0p_4jB4c4R9i8FxwxdZ2JZG5aXJlM5CSCmKrarOpBZI3EXRnBbXBpQgAiZY16phnbfIQGTFakXbwynw12tIB7Wa21-4K894maBOlalnChIduQXDXArlfSntuo1WLuCAfyas66WGuiPTjHxiNa2_plP7jdM6jkaKFPDAEl_aJcQWxY90urwABBAlXoqR9kT0fPbed3mukpYFGrqIb-KuAz8FpwbPyHPK0P359CPcCtLayEE4ykVW-r7k9JFbtE1D-3cJXiQ7nRmiqu2WD7adF0WZNOdOX3KM09zXBJI2eEFQVUHuE4424Af0Vg5ZU9yqyR4sD4Ee3LLdqLTc5BRWAgOGEeA3Fic3nBRKYa7bgq8MyqqWpUY6cXnpanoXMd_uA_v6cOypmD1qoIynVAVZLiqCKs2VrH8QT7n_vMLlwOz5WX-QfuoMo5TjfuNEXYARU9P1qfBb2mEiLO2NT1PFdSfAIDZicmpiyYZ2h3gFCd0xsa0Y3ewi7KhK224jr527Xm1k-jPat7vAG9v6CFU2qkzlzCus4RU__XlIr0FL2nRBhfZVkSUdsazqsOc2fvp7tJQiNYdOPkDWfQCVW0aorhst6VSdt6gm11cIPWzj5UeJDv9FiIt_ylpTREnsnvsoegcsFZk2PDOY6ZazbRG9wKaQTHUskq7sgcRpz6PY_fnovDNQwRBgnaw2PfE-omLjsQvgItgRZiA7BS20GoIGxCFyi\",\"summary\":[]}"}, {"type": "toolCall", "id": "call_OsZBayS1NWAWAZ5qDNyWRrnL|fc_0d8c31fa336f7f3d0169f9855f1b5c81a2b7a4e51cbff3010c", "name": "read", "arguments": {"path": "/home/vjovanov/c/forge/forge8/graalvm-reachability-metadata/forge/local_repositories/source_context/com.squareup.moshi/moshi/1.15.2/main/extracted/main/com/squareup/moshi/RecordJsonAdapter.java"}}], "api": "openai-responses", "provider": "OCA", "model": "gpt-5.5", "usage": {"input": 608, "output": 110, "cacheRead": 8192, "cacheWrite": 0, "totalTokens": 8910, "cost": {"input": 0, "output": 0, "cacheRead": 0, "cacheWrite": 0, "total": 0}}, "stopReason": "toolUse", "timestamp": 1777960284340, "responseId": "resp_0d8c31fa336f7f3d0169f9855cafe881a29f18d49d4f0f7edb"}, "toolResults": [{"role": "toolResult", "toolCallId": "call_OsZBayS1NWAWAZ5qDNyWRrnL|fc_0d8c31fa336f7f3d0169f9855f1b5c81a2b7a4e51cbff3010c", "toolName": "read", "content": [{"type": "text", "text": "/*\n * Copyright (C) 2021 Square, Inc.\n *\n * Licensed under the Apache License, Version 2.0 (the \"License\");\n * you may not use this file except in compliance with the License.\n * You may obtain a copy of the License at\n *\n *    https://www.apache.org/licenses/LICENSE-2.0\n *\n * Unless required by applicable law or agreed to in writing, software\n * distributed under the License is distributed on an \"AS IS\" BASIS,\n * WITHOUT WARRANTIES OR CONDITIONS OF ANY KIND, either express or implied.\n * See the License for the specific language governing permissions and\n * limitations under the License.\n */\npackage com.squareup.moshi;\n\nimport java.io.IOException;\nimport java.lang.annotation.Annotation;\nimport java.lang.reflect.Type;\nimport java.util.Set;\nimport javax.annotation.Nullable;\n\n/**\n * This is just a simple shim for linking in {@link StandardJsonAdapters} and swapped with a real\n * implementation in Java 16 via MR Jar.\n */\nfinal class RecordJsonAdapter<T> extends JsonAdapter<T> {\n\n  static final JsonAdapter.Factory FACTORY =\n      new JsonAdapter.Factory() {\n\n        @Nullable\n        @Override\n        public JsonAdapter<?> create(\n            Type type, Set<? extends Annotation> annotations, Moshi moshi) {\n          return null;\n        }\n      };\n\n  @Nullable\n  @Override\n  public T fromJson(JsonReader reader) throws IOException {\n    throw new AssertionError();\n  }\n\n  @Override\n  public void toJson(JsonWriter writer, @Nullable T value) throws IOException {\n    throw new AssertionError();\n  }\n}\n"}], "isError": false, "timestamp": 1777960287432}]}
[recv] {"type": "turn_start"}
[recv] {"type": "message_start", "message": {"role": "assistant", "content": [], "api": "openai-responses", "provider": "OCA", "model": "gpt-5.5", "usage": {"input": 0, "output": 0, "cacheRead": 0, "cacheWrite": 0, "totalTokens": 0, "cost": {"input": 0, "output": 0, "cacheRead": 0, "cacheWrite": 0, "total": 0}}, "stopReason": "stop", "timestamp": 1777960287436}}
[assistant-event] thinking_start
[assistant-event] thinking_end
[tool-call] start id=unknown
[tool-call] delta {"command":"find /home/vjovanov/c/forge/forge8/graalvm-reachability-metadata/forge/local_repositories/source_context/com.squareup.moshi/moshi/1.15.2 -name 'RecordJsonAdapter.java' -print"}
[tool-call] end id=call_KGFRJ6cCESevJ1vCZwTa2a8t|fc_0d8c31fa336f7f3d0169f98560f85481a2a784a4f1813038d6 name=bash args={"command": "find /home/vjovanov/c/forge/forge8/graalvm-reachability-metadata/forge/local_repositories/source_context/com.squareup.moshi/moshi/1.15.2 -name 'RecordJsonAdapter.java' -print"}
[recv] {"type": "message_end", "message": {"role": "assistant", "content": [{"type": "thinking", "thinking": "", "thinkingSignature": "{\"id\":\"rs_0d8c31fa336f7f3d0169f985605d4881a2aa749da7e6f01268\",\"type\":\"reasoning\",\"encrypted_content\":\"gAAAAABp-YVgO0bOlmT4Sb2F5WfntX9Lc3V671dCqHpWzyAByfinZlIDYO6Q3Aye4YZ9s52orGMreWsFUkDXFeNuGfaXqCgf-Zbii8i_etwafXsZikY3Cca_JCYabJMjuxgl-b5qz0Dz8Fbt0r2rR_qYmU6BCtOMbG6S_2-7fsoKVSXadx_t5LGQfxuTg1JMCIZ_L6ponrnKHq7OA53sh2BnmK_YxhSTmKJpqPs6FUwKblI38zcur9OMQhIh-0N_vB7xMZq7bwE4cgNJm3p64qJ65_M_nzDeizHNbMv-2k6-YpmAC3ba60TnVyPHtayuThCrFX4-9kjd7jPws6Z3_-Vj4FFo8POjWy4B48cpwNK0RRJI51k0BmYkw849XcjLh4o5vXnto6DFd9p8tU-xxAadHflVHjFPHHt1S12dsCZAX0QkvCkZhbHXBQCKkKtU0oobQEOcxr95J1lzI5rPERpqYidY4GJIe52zd6lvlsiYgYhMdmMCCWUGFw0fq-_cb4yKTJHkJFmA-zMQ1h7BjCrsLrKkJuodmtyS85sH_4Ws179haI7ZFOdCx3SXGjtNId-4mL47hnF28EGF9yB4xfmuWou5mpo0UD51qgA530RjzvCOYdrmhkN7N1TpGi6CGwAUEFvoAHdQUAPQHISeCAVK30YkTuBEgrPxjGhJJs0GM9i6ci7Cvx5WnNDGEwf5Bx8Tjup7T-KP-pzyfMjTZ4uvXq1mEKudl1zt63bJTP2iufLPPcbEZJ2Fbptf4RSy1r7rhPAxrhRQWiwSyedLHZS3vyuFVh2nNuNjcxfQ433iAZGCN9eNmu5zEFaKs5cyVsgOAWocD5n1VUlPD93yTrR_EeAVsqzw2dQiNVQB1MxgrzuX27eK5baUPYMtXMWOcbAe4vc5bkx3Tn32Xlhk-qQCjXNElrXOnFYyea1qTSuHJwVqdJrfAicffwLe-nS92JjfRWu9LuqPwtrZ3mg5fZOcBNqC4iRQt9sB3H-JWaa7kdlqEPKrtHI2jbcqN4YHRzGOH69GHC7vD8H6yF09L3wMPrc52hdkseJvea4vYyVIMHejXBvUKxY=\",\"summary\":[]}"}, {"type": "toolCall", "id": "call_KGFRJ6cCESevJ1vCZwTa2a8t|fc_0d8c31fa336f7f3d0169f98560f85481a2a784a4f1813038d6", "name": "bash", "arguments": {"command": "find /home/vjovanov/c/forge/forge8/graalvm-reachability-metadata/forge/local_repositories/source_context/com.squareup.moshi/moshi/1.15.2 -name 'RecordJsonAdapter.java' -print"}}], "api": "openai-responses", "provider": "OCA", "model": "gpt-5.5", "usage": {"input": 544, "output": 95, "cacheRead": 8704, "cacheWrite": 0, "totalTokens": 9343, "cost": {"input": 0, "output": 0, "cacheRead": 0, "cacheWrite": 0, "total": 0}}, "stopReason": "toolUse", "timestamp": 1777960287436, "responseId": "resp_0d8c31fa336f7f3d0169f9855fc60081a2aff2ea12d4964a45"}}
[tool-exec] start id=call_KGFRJ6cCESevJ1vCZwTa2a8t|fc_0d8c31fa336f7f3d0169f98560f85481a2a784a4f1813038d6 name=bash args={"command": "find /home/vjovanov/c/forge/forge8/graalvm-reachability-metadata/forge/local_repositories/source_context/com.squareup.moshi/moshi/1.15.2 -name 'RecordJsonAdapter.java' -print"}
[tool-exec] update id=call_KGFRJ6cCESevJ1vCZwTa2a8t|fc_0d8c31fa336f7f3d0169f98560f85481a2a784a4f1813038d6 name=bash
[tool-exec] update id=call_KGFRJ6cCESevJ1vCZwTa2a8t|fc_0d8c31fa336f7f3d0169f98560f85481a2a784a4f1813038d6 name=bash
  /home/vjovanov/c/forge/forge8/graalvm-reachability-metadata/forge/local_repositories/source_context/com.squareup.moshi/moshi/1.15.2/main/extracted/main/com/squareup/moshi/RecordJsonAdapter.java
[tool-exec] end id=call_KGFRJ6cCESevJ1vCZwTa2a8t|fc_0d8c31fa336f7f3d0169f98560f85481a2a784a4f1813038d6 name=bash status=success
  /home/vjovanov/c/forge/forge8/graalvm-reachability-metadata/forge/local_repositories/source_context/com.squareup.moshi/moshi/1.15.2/main/extracted/main/com/squareup/moshi/RecordJsonAdapter.java
[recv] {"type": "message_start", "message": {"role": "toolResult", "toolCallId": "call_KGFRJ6cCESevJ1vCZwTa2a8t|fc_0d8c31fa336f7f3d0169f98560f85481a2a784a4f1813038d6", "toolName": "bash", "content": [{"type": "text", "text": "/home/vjovanov/c/forge/forge8/graalvm-reachability-metadata/forge/local_repositories/source_context/com.squareup.moshi/moshi/1.15.2/main/extracted/main/com/squareup/moshi/RecordJsonAdapter.java\n"}], "isError": false, "timestamp": 1777960289380}}
[recv] {"type": "message_end", "message": {"role": "toolResult", "toolCallId": "call_KGFRJ6cCESevJ1vCZwTa2a8t|fc_0d8c31fa336f7f3d0169f98560f85481a2a784a4f1813038d6", "toolName": "bash", "content": [{"type": "text", "text": "/home/vjovanov/c/forge/forge8/graalvm-reachability-metadata/forge/local_repositories/source_context/com.squareup.moshi/moshi/1.15.2/main/extracted/main/com/squareup/moshi/RecordJsonAdapter.java\n"}], "isError": false, "timestamp": 1777960289380}}
[recv] {"type": "turn_end", "message": {"role": "assistant", "content": [{"type": "thinking", "thinking": "", "thinkingSignature": "{\"id\":\"rs_0d8c31fa336f7f3d0169f985605d4881a2aa749da7e6f01268\",\"type\":\"reasoning\",\"encrypted_content\":\"gAAAAABp-YVgO0bOlmT4Sb2F5WfntX9Lc3V671dCqHpWzyAByfinZlIDYO6Q3Aye4YZ9s52orGMreWsFUkDXFeNuGfaXqCgf-Zbii8i_etwafXsZikY3Cca_JCYabJMjuxgl-b5qz0Dz8Fbt0r2rR_qYmU6BCtOMbG6S_2-7fsoKVSXadx_t5LGQfxuTg1JMCIZ_L6ponrnKHq7OA53sh2BnmK_YxhSTmKJpqPs6FUwKblI38zcur9OMQhIh-0N_vB7xMZq7bwE4cgNJm3p64qJ65_M_nzDeizHNbMv-2k6-YpmAC3ba60TnVyPHtayuThCrFX4-9kjd7jPws6Z3_-Vj4FFo8POjWy4B48cpwNK0RRJI51k0BmYkw849XcjLh4o5vXnto6DFd9p8tU-xxAadHflVHjFPHHt1S12dsCZAX0QkvCkZhbHXBQCKkKtU0oobQEOcxr95J1lzI5rPERpqYidY4GJIe52zd6lvlsiYgYhMdmMCCWUGFw0fq-_cb4yKTJHkJFmA-zMQ1h7BjCrsLrKkJuodmtyS85sH_4Ws179haI7ZFOdCx3SXGjtNId-4mL47hnF28EGF9yB4xfmuWou5mpo0UD51qgA530RjzvCOYdrmhkN7N1TpGi6CGwAUEFvoAHdQUAPQHISeCAVK30YkTuBEgrPxjGhJJs0GM9i6ci7Cvx5WnNDGEwf5Bx8Tjup7T-KP-pzyfMjTZ4uvXq1mEKudl1zt63bJTP2iufLPPcbEZJ2Fbptf4RSy1r7rhPAxrhRQWiwSyedLHZS3vyuFVh2nNuNjcxfQ433iAZGCN9eNmu5zEFaKs5cyVsgOAWocD5n1VUlPD93yTrR_EeAVsqzw2dQiNVQB1MxgrzuX27eK5baUPYMtXMWOcbAe4vc5bkx3Tn32Xlhk-qQCjXNElrXOnFYyea1qTSuHJwVqdJrfAicffwLe-nS92JjfRWu9LuqPwtrZ3mg5fZOcBNqC4iRQt9sB3H-JWaa7kdlqEPKrtHI2jbcqN4YHRzGOH69GHC7vD8H6yF09L3wMPrc52hdkseJvea4vYyVIMHejXBvUKxY=\",\"summary\":[]}"}, {"type": "toolCall", "id": "call_KGFRJ6cCESevJ1vCZwTa2a8t|fc_0d8c31fa336f7f3d0169f98560f85481a2a784a4f1813038d6", "name": "bash", "arguments": {"command": "find /home/vjovanov/c/forge/forge8/graalvm-reachability-metadata/forge/local_repositories/source_context/com.squareup.moshi/moshi/1.15.2 -name 'RecordJsonAdapter.java' -print"}}], "api": "openai-responses", "provider": "OCA", "model": "gpt-5.5", "usage": {"input": 544, "output": 95, "cacheRead": 8704, "cacheWrite": 0, "totalTokens": 9343, "cost": {"input": 0, "output": 0, "cacheRead": 0, "cacheWrite": 0, "total": 0}}, "stopReason": "toolUse", "timestamp": 1777960287436, "responseId": "resp_0d8c31fa336f7f3d0169f9855fc60081a2aff2ea12d4964a45"}, "toolResults": [{"role": "toolResult", "toolCallId": "call_KGFRJ6cCESevJ1vCZwTa2a8t|fc_0d8c31fa336f7f3d0169f98560f85481a2a784a4f1813038d6", "toolName": "bash", "content": [{"type": "text", "text": "/home/vjovanov/c/forge/forge8/graalvm-reachability-metadata/forge/local_repositories/source_context/com.squareup.moshi/moshi/1.15.2/main/extracted/main/com/squareup/moshi/RecordJsonAdapter.java\n"}], "isError": false, "timestamp": 1777960289380}]}
[recv] {"type": "turn_start"}
[recv] {"type": "message_start", "message": {"role": "assistant", "content": [], "api": "openai-responses", "provider": "OCA", "model": "gpt-5.5", "usage": {"input": 0, "output": 0, "cacheRead": 0, "cacheWrite": 0, "totalTokens": 0, "cost": {"input": 0, "output": 0, "cacheRead": 0, "cacheWrite": 0, "total": 0}}, "stopReason": "stop", "timestamp": 1777960289383}}
[assistant-event] thinking_start
[assistant-event] thinking_end
[tool-call] start id=unknown
[tool-call] delta {"path":"tests/src/com.squareup.moshi/moshi/1.15.2/build.gradle"}
[tool-call] end id=call_nUtFGuqzqHzhekx4CrNw8WFM|fc_0d8c31fa336f7f3d0169f985631f1081a2b64e003b59c7fc04 name=read args={"path": "tests/src/com.squareup.moshi/moshi/1.15.2/build.gradle"}
[recv] {"type": "message_end", "message": {"role": "assistant", "content": [{"type": "thinking", "thinking": "", "thinkingSignature": "{\"id\":\"rs_0d8c31fa336f7f3d0169f985627a4081a2bc9fb488eea26e9c\",\"type\":\"reasoning\",\"encrypted_content\":\"gAAAAABp-YVjOo8RPMfpBEyF-fN9Y5sWWTqVOPQugKsd7nb51ui1LTeAoSvfi_99Pz2zVvSSKYtxVu5K37yVPsph-sLscw0d-S_wVFlREPj_2aE35zbpch5XXyU_kC0M9aWNo5C1n_ZLlXoLXVbMiMX2f0dk-ZP313cMJRW1LFxKTnZxAz_G-6znL_F4cuu47TGgbZRFRLEswFgDhdK3W4pqfJG7RIheOhX7ESo0m2ZPMLlupntvXz6uUzmgrLWJgNCKfgbld6Gqj_ao-wRFE1Tz2B96Cdt6rmxJVxqsa720iKWPc_rvmMGiOAQ6F_RTgwAzJXsjXKNJwfhKK730GTCkv9TOwtx7gQqCtDnpTbJgoLizdv5xO6u1rT5Xc8PE2KuPKnYA9RWq-g4i782rC5eiul4XwrNQv3rnLpS3KrkmQT-hagxLm5WfVXyRhAsNM8WnOhw2jJu3LEFsuXidb1RJoS-bqvQ6Tb_UuWmoQ1lpy0_sB8_rKbuszNEnIPem5lvhqN2y0K85D0PwL-DaSqbD-EITuFv-6TAIGKtJN8LZo3EaISyWBX7muZ223_s5_wdn7CxeEBbKsIsHG2_dDT6ZYPY83NUQx4GeUpZSmdMqC1jyqCIammQyEOnPj5i-3aentktXhC7Q56UsiURGQrvnv5RcDN1I0dznECbpeO10hyD-3umq4Wf-S6g8iBPA0Y0fPE6lDYhvnC5YdpePzSA1hxrNCVSpMul5bv1MIOurpacjXfoZ0EukcjmcU-uLbC3Dcw4zMzbvztffmX8_K_-6Fx7TSdtfPi8ptxfgAA9al-1fM6L6Lyb5QQVuadz3rmS7psjSsx63ASNaD6hJXddqt3D8Df5UjKq7sxoLyhPeW73C4j3tMhO7TIrPm4NAujcZ0ziwenFvuCbWIeqmx_1rWoCgTU_fnZekcyIzUsmTkktlP0uO8O4bcyf39_Kf-QSgigBfunSEJ_oVtTzE1vc2jKGhCSREAYFp3xE5NhcKzFIvE1GsXhYBff6gSoMaggcMFHejPn_nTHbRzWXiwF-8OdDO3th-bg==\",\"summary\":[]}"}, {"type": "toolCall", "id": "call_nUtFGuqzqHzhekx4CrNw8WFM|fc_0d8c31fa336f7f3d0169f985631f1081a2b64e003b59c7fc04", "name": "read", "arguments": {"path": "tests/src/com.squareup.moshi/moshi/1.15.2/build.gradle"}}], "api": "openai-responses", "provider": "OCA", "model": "gpt-5.5", "usage": {"input": 704, "output": 55, "cacheRead": 8704, "cacheWrite": 0, "totalTokens": 9463, "cost": {"input": 0, "output": 0, "cacheRead": 0, "cacheWrite": 0, "total": 0}}, "stopReason": "toolUse", "timestamp": 1777960289383, "responseId": "resp_0d8c31fa336f7f3d0169f98561eeac81a29ce03ff8a5dbd7c2"}}
[tool-exec] start id=call_nUtFGuqzqHzhekx4CrNw8WFM|fc_0d8c31fa336f7f3d0169f985631f1081a2b64e003b59c7fc04 name=read args={"path": "tests/src/com.squareup.moshi/moshi/1.15.2/build.gradle"}
[tool-exec] end id=call_nUtFGuqzqHzhekx4CrNw8WFM|fc_0d8c31fa336f7f3d0169f985631f1081a2b64e003b59c7fc04 name=read status=success
  /*
   * Copyright and related rights waived via CC0
   *
   * You should have received a copy of the CC0 legalcode along with this
   * work. If not, see <http://creativecommons.org/publicdomain/zero/1.0/>.
   */
  plugins {
      id "org.graalvm.internal.tck"
      id "org.jetbrains.kotlin.jvm" version "2.3.20"
  }
  
  String libraryVersion = tck.testedLibraryVersion.get()
  
  dependencies {
      testImplementation "com.squareup.moshi:moshi:$libraryVersion"
      testImplementation 'org.assertj:assertj-core:3.22.0'
  }
  
  kotlin {
      jvmToolchain(21)
  }
  
  compileTestKotlin {
      kotlinOptions.jvmTarget = "21"
  }
  
  graalvmNative {
      agent {
          defaultMode = "conditional"
          modes {
              conditional {
                  userCodeFilterPath = "user-code-filter.json"
              }
          }
      }
  }
[recv] {"type": "message_start", "message": {"role": "toolResult", "toolCallId": "call_nUtFGuqzqHzhekx4CrNw8WFM|fc_0d8c31fa336f7f3d0169f985631f1081a2b64e003b59c7fc04", "toolName": "read", "content": [{"type": "text", "text": "/*\n * Copyright and related rights waived via CC0\n *\n * You should have received a copy of the CC0 legalcode along with this\n * work. If not, see <http://creativecommons.org/publicdomain/zero/1.0/>.\n */\nplugins {\n    id \"org.graalvm.internal.tck\"\n    id \"org.jetbrains.kotlin.jvm\" version \"2.3.20\"\n}\n\nString libraryVersion = tck.testedLibraryVersion.get()\n\ndependencies {\n    testImplementation \"com.squareup.moshi:moshi:$libraryVersion\"\n    testImplementation 'org.assertj:assertj-core:3.22.0'\n}\n\nkotlin {\n    jvmToolchain(21)\n}\n\ncompileTestKotlin {\n    kotlinOptions.jvmTarget = \"21\"\n}\n\ngraalvmNative {\n    agent {\n        defaultMode = \"conditional\"\n        modes {\n            conditional {\n                userCodeFilterPath = \"user-code-filter.json\"\n            }\n        }\n    }\n}\n"}], "isError": false, "timestamp": 1777960291435}}
[recv] {"type": "message_end", "message": {"role": "toolResult", "toolCallId": "call_nUtFGuqzqHzhekx4CrNw8WFM|fc_0d8c31fa336f7f3d0169f985631f1081a2b64e003b59c7fc04", "toolName": "read", "content": [{"type": "text", "text": "/*\n * Copyright and related rights waived via CC0\n *\n * You should have received a copy of the CC0 legalcode along with this\n * work. If not, see <http://creativecommons.org/publicdomain/zero/1.0/>.\n */\nplugins {\n    id \"org.graalvm.internal.tck\"\n    id \"org.jetbrains.kotlin.jvm\" version \"2.3.20\"\n}\n\nString libraryVersion = tck.testedLibraryVersion.get()\n\ndependencies {\n    testImplementation \"com.squareup.moshi:moshi:$libraryVersion\"\n    testImplementation 'org.assertj:assertj-core:3.22.0'\n}\n\nkotlin {\n    jvmToolchain(21)\n}\n\ncompileTestKotlin {\n    kotlinOptions.jvmTarget = \"21\"\n}\n\ngraalvmNative {\n    agent {\n        defaultMode = \"conditional\"\n        modes {\n            conditional {\n                userCodeFilterPath = \"user-code-filter.json\"\n            }\n        }\n    }\n}\n"}], "isError": false, "timestamp": 1777960291435}}
[recv] {"type": "turn_end", "message": {"role": "assistant", "content": [{"type": "thinking", "thinking": "", "thinkingSignature": "{\"id\":\"rs_0d8c31fa336f7f3d0169f985627a4081a2bc9fb488eea26e9c\",\"type\":\"reasoning\",\"encrypted_content\":\"gAAAAABp-YVjOo8RPMfpBEyF-fN9Y5sWWTqVOPQugKsd7nb51ui1LTeAoSvfi_99Pz2zVvSSKYtxVu5K37yVPsph-sLscw0d-S_wVFlREPj_2aE35zbpch5XXyU_kC0M9aWNo5C1n_ZLlXoLXVbMiMX2f0dk-ZP313cMJRW1LFxKTnZxAz_G-6znL_F4cuu47TGgbZRFRLEswFgDhdK3W4pqfJG7RIheOhX7ESo0m2ZPMLlupntvXz6uUzmgrLWJgNCKfgbld6Gqj_ao-wRFE1Tz2B96Cdt6rmxJVxqsa720iKWPc_rvmMGiOAQ6F_RTgwAzJXsjXKNJwfhKK730GTCkv9TOwtx7gQqCtDnpTbJgoLizdv5xO6u1rT5Xc8PE2KuPKnYA9RWq-g4i782rC5eiul4XwrNQv3rnLpS3KrkmQT-hagxLm5WfVXyRhAsNM8WnOhw2jJu3LEFsuXidb1RJoS-bqvQ6Tb_UuWmoQ1lpy0_sB8_rKbuszNEnIPem5lvhqN2y0K85D0PwL-DaSqbD-EITuFv-6TAIGKtJN8LZo3EaISyWBX7muZ223_s5_wdn7CxeEBbKsIsHG2_dDT6ZYPY83NUQx4GeUpZSmdMqC1jyqCIammQyEOnPj5i-3aentktXhC7Q56UsiURGQrvnv5RcDN1I0dznECbpeO10hyD-3umq4Wf-S6g8iBPA0Y0fPE6lDYhvnC5YdpePzSA1hxrNCVSpMul5bv1MIOurpacjXfoZ0EukcjmcU-uLbC3Dcw4zMzbvztffmX8_K_-6Fx7TSdtfPi8ptxfgAA9al-1fM6L6Lyb5QQVuadz3rmS7psjSsx63ASNaD6hJXddqt3D8Df5UjKq7sxoLyhPeW73C4j3tMhO7TIrPm4NAujcZ0ziwenFvuCbWIeqmx_1rWoCgTU_fnZekcyIzUsmTkktlP0uO8O4bcyf39_Kf-QSgigBfunSEJ_oVtTzE1vc2jKGhCSREAYFp3xE5NhcKzFIvE1GsXhYBff6gSoMaggcMFHejPn_nTHbRzWXiwF-8OdDO3th-bg==\",\"summary\":[]}"}, {"type": "toolCall", "id": "call_nUtFGuqzqHzhekx4CrNw8WFM|fc_0d8c31fa336f7f3d0169f985631f1081a2b64e003b59c7fc04", "name": "read", "arguments": {"path": "tests/src/com.squareup.moshi/moshi/1.15.2/build.gradle"}}], "api": "openai-responses", "provider": "OCA", "model": "gpt-5.5", "usage": {"input": 704, "output": 55, "cacheRead": 8704, "cacheWrite": 0, "totalTokens": 9463, "cost": {"input": 0, "output": 0, "cacheRead": 0, "cacheWrite": 0, "total": 0}}, "stopReason": "toolUse", "timestamp": 1777960289383, "responseId": "resp_0d8c31fa336f7f3d0169f98561eeac81a29ce03ff8a5dbd7c2"}, "toolResults": [{"role": "toolResult", "toolCallId": "call_nUtFGuqzqHzhekx4CrNw8WFM|fc_0d8c31fa336f7f3d0169f985631f1081a2b64e003b59c7fc04", "toolName": "read", "content": [{"type": "text", "text": "/*\n * Copyright and related rights waived via CC0\n *\n * You should have received a copy of the CC0 legalcode along with this\n * work. If not, see <http://creativecommons.org/publicdomain/zero/1.0/>.\n */\nplugins {\n    id \"org.graalvm.internal.tck\"\n    id \"org.jetbrains.kotlin.jvm\" version \"2.3.20\"\n}\n\nString libraryVersion = tck.testedLibraryVersion.get()\n\ndependencies {\n    testImplementation \"com.squareup.moshi:moshi:$libraryVersion\"\n    testImplementation 'org.assertj:assertj-core:3.22.0'\n}\n\nkotlin {\n    jvmToolchain(21)\n}\n\ncompileTestKotlin {\n    kotlinOptions.jvmTarget = \"21\"\n}\n\ngraalvmNative {\n    agent {\n        defaultMode = \"conditional\"\n        modes {\n            conditional {\n                userCodeFilterPath = \"user-code-filter.json\"\n            }\n        }\n    }\n}\n"}], "isError": false, "timestamp": 1777960291435}]}
[recv] {"type": "turn_start"}
[recv] {"type": "message_start", "message": {"role": "assistant", "content": [], "api": "openai-responses", "provider": "OCA", "model": "gpt-5.5", "usage": {"input": 0, "output": 0, "cacheRead": 0, "cacheWrite": 0, "totalTokens": 0, "cost": {"input": 0, "output": 0, "cacheRead": 0, "cacheWrite": 0, "total": 0}}, "stopReason": "stop", "timestamp": 1777960291443}}
[tool-call] start id=unknown
[tool-call] delta {"path":"tests/src/com.squareup.moshi/moshi/1.15.2/src/test/kotlin/com_squareup_moshi/moshi/TypesTest.kt"}
[tool-call] end id=call_NsxnNP7KO1Kej8vnR3kA89KX|fc_0d8c31fa336f7f3d0169f98564a48081a2a7455b6d97157877 name=read args={"path": "tests/src/com.squareup.moshi/moshi/1.15.2/src/test/kotlin/com_squareup_moshi/moshi/TypesTest.kt"}
[recv] {"type": "message_end", "message": {"role": "assistant", "content": [{"type": "toolCall", "id": "call_NsxnNP7KO1Kej8vnR3kA89KX|fc_0d8c31fa336f7f3d0169f98564a48081a2a7455b6d97157877", "name": "read", "arguments": {"path": "tests/src/com.squareup.moshi/moshi/1.15.2/src/test/kotlin/com_squareup_moshi/moshi/TypesTest.kt"}}], "api": "openai-responses", "provider": "OCA", "model": "gpt-5.5", "usage": {"input": 452, "output": 45, "cacheRead": 9216, "cacheWrite": 0, "totalTokens": 9713, "cost": {"input": 0, "output": 0, "cacheRead": 0, "cacheWrite": 0, "total": 0}}, "stopReason": "toolUse", "timestamp": 1777960291443, "responseId": "resp_0d8c31fa336f7f3d0169f98563e7dc81a29f5cf434bb769c74"}}
[tool-exec] start id=call_NsxnNP7KO1Kej8vnR3kA89KX|fc_0d8c31fa336f7f3d0169f98564a48081a2a7455b6d97157877 name=read args={"path": "tests/src/com.squareup.moshi/moshi/1.15.2/src/test/kotlin/com_squareup_moshi/moshi/TypesTest.kt"}
[tool-exec] end id=call_NsxnNP7KO1Kej8vnR3kA89KX|fc_0d8c31fa336f7f3d0169f98564a48081a2a7455b6d97157877 name=read status=success
  /*
   * Copyright and related rights waived via CC0
   *
   * You should have received a copy of the CC0 legalcode along with this
   * work. If not, see <http://creativecommons.org/publicdomain/zero/1.0/>.
   */
  package com_squareup_moshi.moshi
  
  import com.squareup.moshi.JsonAdapter
  import com.squareup.moshi.JsonQualifier
  import com.squareup.moshi.JsonReader
  import com.squareup.moshi.JsonWriter
  import com.squareup.moshi.Moshi
  import com.squareup.moshi.Types
  import java.lang.reflect.Type
  import org.assertj.core.api.Assertions.assertThat
  import org.junit.jupiter.api.Test
  
  public class TypesTest {
      @Test
      fun getRawTypeCreatesArrayClassForGenericArrayType(): Unit {
          val arrayType: Type = Types.arrayOf(String::class.java)
  
          val rawType: Class<*> = Types.getRawType(arrayType)
  
          assertThat(rawType).isEqualTo(Array<String>::class.java)
      }
  
      @Test
      @Suppress("DEPRECATION")
      fun getFieldJsonQualifierAnnotationsReturnsQualifierOnDeclaredField(): Unit {
          val annotations: Set<out Annotation> = Types.getFieldJsonQualifierAnnotations(
              FieldQualifierHolder::class.java,
              "qualifiedValue",
          )
  
          assertThat(annotations).hasSize(1)
          assertThat(annotations.single().annotationClass.java).isEqualTo(SampleQualifier::class.java)
      }
  
      @Test
      fun adapterWithQualifierClassCreatesRuntimeQualifierImplementation(): Unit {
          val moshi: Moshi = Moshi.Builder()
              .add(QualifiedStringAdapterFactory)
              .build()
  
          val adapter: JsonAdapter<String> = moshi.adapter(
              String::class.java,
              SampleQualifier::class.java,
          )
  
          assertThat(adapter.fromJson("\"input\"")).isEqualTo("qualified:input")
          assertThat(adapter.toJson("output")).isEqualTo("\"qualified:output\"")
      }
  }
  
  @JsonQualifier
  @Retention(AnnotationRetention.RUNTIME)
  @Target(AnnotationTarget.FIELD, AnnotationTarget.VALUE_PARAMETER, AnnotationTarget.FUNCTION)
  public annotation class SampleQualifier
  
  public class FieldQualifierHolder(
      @field:SampleQualifier
      public val qualifiedValue: String,
  )
  
  public object QualifiedStringAdapterFactory : JsonAdapter.Factory {
      override fun create(
          type: Type,
          annotations: Set<Annotation>,
          moshi: Moshi,
      ): JsonAdapter<*>? {
          val nextAnnotations: Set<out Annotation> = Types.nextAnnotations(
              annotations,
              SampleQualifier::class.java,
          ) ?: return null
          if (type != String::class.java || nextAnnotations.isNotEmpty()) {
              return null
          }
          return QualifiedStringAdapter
      }
  }
  
  public object QualifiedStringAdapter : JsonAdapter<String>() {
      override fun fromJson(reader: JsonReader): String {
          return "qualified:${reader.nextString()}"
      }
  
      override fun toJson(writer: JsonWriter, value: String?): Unit {
          writer.value("qualified:$value")
      }
  }
[recv] {"type": "message_start", "message": {"role": "toolResult", "toolCallId": "call_NsxnNP7KO1Kej8vnR3kA89KX|fc_0d8c31fa336f7f3d0169f98564a48081a2a7455b6d97157877", "toolName": "read", "content": [{"type": "text", "text": "/*\n * Copyright and related rights waived via CC0\n *\n * You should have received a copy of the CC0 legalcode along with this\n * work. If not, see <http://creativecommons.org/publicdomain/zero/1.0/>.\n */\npackage com_squareup_moshi.moshi\n\nimport com.squareup.moshi.JsonAdapter\nimport com.squareup.moshi.JsonQualifier\nimport com.squareup.moshi.JsonReader\nimport com.squareup.moshi.JsonWriter\nimport com.squareup.moshi.Moshi\nimport com.squareup.moshi.Types\nimport java.lang.reflect.Type\nimport org.assertj.core.api.Assertions.assertThat\nimport org.junit.jupiter.api.Test\n\npublic class TypesTest {\n    @Test\n    fun getRawTypeCreatesArrayClassForGenericArrayType(): Unit {\n        val arrayType: Type = Types.arrayOf(String::class.java)\n\n        val rawType: Class<*> = Types.getRawType(arrayType)\n\n        assertThat(rawType).isEqualTo(Array<String>::class.java)\n    }\n\n    @Test\n    @Suppress(\"DEPRECATION\")\n    fun getFieldJsonQualifierAnnotationsReturnsQualifierOnDeclaredField(): Unit {\n        val annotations: Set<out Annotation> = Types.getFieldJsonQualifierAnnotations(\n            FieldQualifierHolder::class.java,\n            \"qualifiedValue\",\n        )\n\n        assertThat(annotations).hasSize(1)\n        assertThat(annotations.single().annotationClass.java).isEqualTo(SampleQualifier::class.java)\n    }\n\n    @Test\n    fun adapterWithQualifierClassCreatesRuntimeQualifierImplementation(): Unit {\n        val moshi: Moshi = Moshi.Builder()\n            .add(QualifiedStringAdapterFactory)\n            .build()\n\n        val adapter: JsonAdapter<String> = moshi.adapter(\n            String::class.java,\n            SampleQualifier::class.java,\n        )\n\n        assertThat(adapter.fromJson(\"\\\"input\\\"\")).isEqualTo(\"qualified:input\")\n        assertThat(adapter.toJson(\"output\")).isEqualTo(\"\\\"qualified:output\\\"\")\n    }\n}\n\n@JsonQualifier\n@Retention(AnnotationRetention.RUNTIME)\n@Target(AnnotationTarget.FIELD, AnnotationTarget.VALUE_PARAMETER, AnnotationTarget.FUNCTION)\npublic annotation class SampleQualifier\n\npublic class FieldQualifierHolder(\n    @field:SampleQualifier\n    public val qualifiedValue: String,\n)\n\npublic object QualifiedStringAdapterFactory : JsonAdapter.Factory {\n    override fun create(\n        type: Type,\n        annotations: Set<Annotation>,\n        moshi: Moshi,\n    ): JsonAdapter<*>? {\n        val nextAnnotations: Set<out Annotation> = Types.nextAnnotations(\n            annotations,\n            SampleQualifier::class.java,\n        ) ?: return null\n        if (type != String::class.java || nextAnnotations.isNotEmpty()) {\n            return null\n        }\n        return QualifiedStringAdapter\n    }\n}\n\npublic object QualifiedStringAdapter : JsonAdapter<String>() {\n    override fun fromJson(reader: JsonReader): String {\n        return \"qualified:${reader.nextString()}\"\n    }\n\n    override fun toJson(writer: JsonWriter, value: String?): Unit {\n        writer.value(\"qualified:$value\")\n    }\n}\n"}], "isError": false, "timestamp": 1777960293131}}
[recv] {"type": "message_end", "message": {"role": "toolResult", "toolCallId": "call_NsxnNP7KO1Kej8vnR3kA89KX|fc_0d8c31fa336f7f3d0169f98564a48081a2a7455b6d97157877", "toolName": "read", "content": [{"type": "text", "text": "/*\n * Copyright and related rights waived via CC0\n *\n * You should have received a copy of the CC0 legalcode along with this\n * work. If not, see <http://creativecommons.org/publicdomain/zero/1.0/>.\n */\npackage com_squareup_moshi.moshi\n\nimport com.squareup.moshi.JsonAdapter\nimport com.squareup.moshi.JsonQualifier\nimport com.squareup.moshi.JsonReader\nimport com.squareup.moshi.JsonWriter\nimport com.squareup.moshi.Moshi\nimport com.squareup.moshi.Types\nimport java.lang.reflect.Type\nimport org.assertj.core.api.Assertions.assertThat\nimport org.junit.jupiter.api.Test\n\npublic class TypesTest {\n    @Test\n    fun getRawTypeCreatesArrayClassForGenericArrayType(): Unit {\n        val arrayType: Type = Types.arrayOf(String::class.java)\n\n        val rawType: Class<*> = Types.getRawType(arrayType)\n\n        assertThat(rawType).isEqualTo(Array<String>::class.java)\n    }\n\n    @Test\n    @Suppress(\"DEPRECATION\")\n    fun getFieldJsonQualifierAnnotationsReturnsQualifierOnDeclaredField(): Unit {\n        val annotations: Set<out Annotation> = Types.getFieldJsonQualifierAnnotations(\n            FieldQualifierHolder::class.java,\n            \"qualifiedValue\",\n        )\n\n        assertThat(annotations).hasSize(1)\n        assertThat(annotations.single().annotationClass.java).isEqualTo(SampleQualifier::class.java)\n    }\n\n    @Test\n    fun adapterWithQualifierClassCreatesRuntimeQualifierImplementation(): Unit {\n        val moshi: Moshi = Moshi.Builder()\n            .add(QualifiedStringAdapterFactory)\n            .build()\n\n        val adapter: JsonAdapter<String> = moshi.adapter(\n            String::class.java,\n            SampleQualifier::class.java,\n        )\n\n        assertThat(adapter.fromJson(\"\\\"input\\\"\")).isEqualTo(\"qualified:input\")\n        assertThat(adapter.toJson(\"output\")).isEqualTo(\"\\\"qualified:output\\\"\")\n    }\n}\n\n@JsonQualifier\n@Retention(AnnotationRetention.RUNTIME)\n@Target(AnnotationTarget.FIELD, AnnotationTarget.VALUE_PARAMETER, AnnotationTarget.FUNCTION)\npublic annotation class SampleQualifier\n\npublic class FieldQualifierHolder(\n    @field:SampleQualifier\n    public val qualifiedValue: String,\n)\n\npublic object QualifiedStringAdapterFactory : JsonAdapter.Factory {\n    override fun create(\n        type: Type,\n        annotations: Set<Annotation>,\n        moshi: Moshi,\n    ): JsonAdapter<*>? {\n        val nextAnnotations: Set<out Annotation> = Types.nextAnnotations(\n            annotations,\n            SampleQualifier::class.java,\n        ) ?: return null\n        if (type != String::class.java || nextAnnotations.isNotEmpty()) {\n            return null\n        }\n        return QualifiedStringAdapter\n    }\n}\n\npublic object QualifiedStringAdapter : JsonAdapter<String>() {\n    override fun fromJson(reader: JsonReader): String {\n        return \"qualified:${reader.nextString()}\"\n    }\n\n    override fun toJson(writer: JsonWriter, value: String?): Unit {\n        writer.value(\"qualified:$value\")\n    }\n}\n"}], "isError": false, "timestamp": 1777960293131}}
[recv] {"type": "turn_end", "message": {"role": "assistant", "content": [{"type": "toolCall", "id": "call_NsxnNP7KO1Kej8vnR3kA89KX|fc_0d8c31fa336f7f3d0169f98564a48081a2a7455b6d97157877", "name": "read", "arguments": {"path": "tests/src/com.squareup.moshi/moshi/1.15.2/src/test/kotlin/com_squareup_moshi/moshi/TypesTest.kt"}}], "api": "openai-responses", "provider": "OCA", "model": "gpt-5.5", "usage": {"input": 452, "output": 45, "cacheRead": 9216, "cacheWrite": 0, "totalTokens": 9713, "cost": {"input": 0, "output": 0, "cacheRead": 0, "cacheWrite": 0, "total": 0}}, "stopReason": "toolUse", "timestamp": 1777960291443, "responseId": "resp_0d8c31fa336f7f3d0169f98563e7dc81a29f5cf434bb769c74"}, "toolResults": [{"role": "toolResult", "toolCallId": "call_NsxnNP7KO1Kej8vnR3kA89KX|fc_0d8c31fa336f7f3d0169f98564a48081a2a7455b6d97157877", "toolName": "read", "content": [{"type": "text", "text": "/*\n * Copyright and related rights waived via CC0\n *\n * You should have received a copy of the CC0 legalcode along with this\n * work. If not, see <http://creativecommons.org/publicdomain/zero/1.0/>.\n */\npackage com_squareup_moshi.moshi\n\nimport com.squareup.moshi.JsonAdapter\nimport com.squareup.moshi.JsonQualifier\nimport com.squareup.moshi.JsonReader\nimport com.squareup.moshi.JsonWriter\nimport com.squareup.moshi.Moshi\nimport com.squareup.moshi.Types\nimport java.lang.reflect.Type\nimport org.assertj.core.api.Assertions.assertThat\nimport org.junit.jupiter.api.Test\n\npublic class TypesTest {\n    @Test\n    fun getRawTypeCreatesArrayClassForGenericArrayType(): Unit {\n        val arrayType: Type = Types.arrayOf(String::class.java)\n\n        val rawType: Class<*> = Types.getRawType(arrayType)\n\n        assertThat(rawType).isEqualTo(Array<String>::class.java)\n    }\n\n    @Test\n    @Suppress(\"DEPRECATION\")\n    fun getFieldJsonQualifierAnnotationsReturnsQualifierOnDeclaredField(): Unit {\n        val annotations: Set<out Annotation> = Types.getFieldJsonQualifierAnnotations(\n            FieldQualifierHolder::class.java,\n            \"qualifiedValue\",\n        )\n\n        assertThat(annotations).hasSize(1)\n        assertThat(annotations.single().annotationClass.java).isEqualTo(SampleQualifier::class.java)\n    }\n\n    @Test\n    fun adapterWithQualifierClassCreatesRuntimeQualifierImplementation(): Unit {\n        val moshi: Moshi = Moshi.Builder()\n            .add(QualifiedStringAdapterFactory)\n            .build()\n\n        val adapter: JsonAdapter<String> = moshi.adapter(\n            String::class.java,\n            SampleQualifier::class.java,\n        )\n\n        assertThat(adapter.fromJson(\"\\\"input\\\"\")).isEqualTo(\"qualified:input\")\n        assertThat(adapter.toJson(\"output\")).isEqualTo(\"\\\"qualified:output\\\"\")\n    }\n}\n\n@JsonQualifier\n@Retention(AnnotationRetention.RUNTIME)\n@Target(AnnotationTarget.FIELD, AnnotationTarget.VALUE_PARAMETER, AnnotationTarget.FUNCTION)\npublic annotation class SampleQualifier\n\npublic class FieldQualifierHolder(\n    @field:SampleQualifier\n    public val qualifiedValue: String,\n)\n\npublic object QualifiedStringAdapterFactory : JsonAdapter.Factory {\n    override fun create(\n        type: Type,\n        annotations: Set<Annotation>,\n        moshi: Moshi,\n    ): JsonAdapter<*>? {\n        val nextAnnotations: Set<out Annotation> = Types.nextAnnotations(\n            annotations,\n            SampleQualifier::class.java,\n        ) ?: return null\n        if (type != String::class.java || nextAnnotations.isNotEmpty()) {\n            return null\n        }\n        return QualifiedStringAdapter\n    }\n}\n\npublic object QualifiedStringAdapter : JsonAdapter<String>() {\n    override fun fromJson(reader: JsonReader): String {\n        return \"qualified:${reader.nextString()}\"\n    }\n\n    override fun toJson(writer: JsonWriter, value: String?): Unit {\n        writer.value(\"qualified:$value\")\n    }\n}\n"}], "isError": false, "timestamp": 1777960293131}]}
[recv] {"type": "turn_start"}
[recv] {"type": "message_start", "message": {"role": "assistant", "content": [], "api": "openai-responses", "provider": "OCA", "model": "gpt-5.5", "usage": {"input": 0, "output": 0, "cacheRead": 0, "cacheWrite": 0, "totalTokens": 0, "cost": {"input": 0, "output": 0, "cacheRead": 0, "cacheWrite": 0, "total": 0}}, "stopReason": "stop", "timestamp": 1777960293135}}
[tool-call] start id=unknown
[tool-call] delta {"path":"tests/src/com.squareup.moshi/moshi/1.15.2/src/test/kotlin/com_squareup_moshi/moshi/UtilTest.kt"}
[tool-call] end id=call_sU1YuCVRgqV4vgLTYueAfnhU|fc_0d8c31fa336f7f3d0169f985662bd081a2a61bb75e35ca6f62 name=read args={"path": "tests/src/com.squareup.moshi/moshi/1.15.2/src/test/kotlin/com_squareup_moshi/moshi/UtilTest.kt"}
[recv] {"type": "message_end", "message": {"role": "assistant", "content": [{"type": "toolCall", "id": "call_sU1YuCVRgqV4vgLTYueAfnhU|fc_0d8c31fa336f7f3d0169f985662bd081a2a61bb75e35ca6f62", "name": "read", "arguments": {"path": "tests/src/com.squareup.moshi/moshi/1.15.2/src/test/kotlin/com_squareup_moshi/moshi/UtilTest.kt"}}], "api": "openai-responses", "provider": "OCA", "model": "gpt-5.5", "usage": {"input": 1132, "output": 45, "cacheRead": 9216, "cacheWrite": 0, "totalTokens": 10393, "cost": {"input": 0, "output": 0, "cacheRead": 0, "cacheWrite": 0, "total": 0}}, "stopReason": "toolUse", "timestamp": 1777960293135, "responseId": "resp_0d8c31fa336f7f3d0169f985657b8c81a2b2b029d5237a85f6"}}
[tool-exec] start id=call_sU1YuCVRgqV4vgLTYueAfnhU|fc_0d8c31fa336f7f3d0169f985662bd081a2a61bb75e35ca6f62 name=read args={"path": "tests/src/com.squareup.moshi/moshi/1.15.2/src/test/kotlin/com_squareup_moshi/moshi/UtilTest.kt"}
[tool-exec] end id=call_sU1YuCVRgqV4vgLTYueAfnhU|fc_0d8c31fa336f7f3d0169f985662bd081a2a61bb75e35ca6f62 name=read status=success
  /*
   * Copyright and related rights waived via CC0
   *
   * You should have received a copy of the CC0 legalcode along with this
   * work. If not, see <http://creativecommons.org/publicdomain/zero/1.0/>.
   */
  package com_squareup_moshi.moshi
  
  import com.squareup.moshi.JsonAdapter
  import com.squareup.moshi.JsonClass
  import com.squareup.moshi.JsonReader
  import com.squareup.moshi.JsonWriter
  import com.squareup.moshi.Moshi
  import com.squareup.moshi.Types
  import com.squareup.moshi.internal.Util
  import java.lang.reflect.Type
  import org.assertj.core.api.Assertions.assertThat
  import org.junit.jupiter.api.Test
  
  public class UtilTest {
      @Test
      fun generatedAdapterUsesMoshiConstructorForPlainType(): Unit {
          val moshi: Moshi = Moshi.Builder().build()
          val adapter: JsonAdapter<PlainWithMoshi> = moshi.adapter(PlainWithMoshi::class.java)
  
          assertThat(adapter.toJson(PlainWithMoshi("unused"))).isEqualTo("\"plain-moshi\"")
      }
  
      @Test
      fun generatedAdapterFallsBackToNoArgumentConstructorForPlainType(): Unit {
          val moshi: Moshi = Moshi.Builder().build()
          val adapter: JsonAdapter<PlainWithoutMoshi> = moshi.adapter(PlainWithoutMoshi::class.java)
  
          assertThat(adapter.toJson(PlainWithoutMoshi("unused"))).isEqualTo("\"plain-no-args\"")
      }
  
      @Test
      fun generatedAdapterUsesMoshiAndTypeArrayConstructorForParameterizedType(): Unit {
          val moshi: Moshi = Moshi.Builder().build()
          val type: Type = Types.newParameterizedType(BoxWithMoshi::class.java, String::class.java)
          val adapter: JsonAdapter<BoxWithMoshi<String>> = moshi.adapter(type)
  
          assertThat(adapter.toJson(BoxWithMoshi("unused")))
              .isEqualTo("\"box-moshi-java.lang.String\"")
      }
  
      @Test
      fun generatedAdapterFallsBackToTypeArrayConstructorForParameterizedType(): Unit {
          val moshi: Moshi = Moshi.Builder().build()
          val type: Type = Types.newParameterizedType(BoxWithoutMoshi::class.java, String::class.java)
          val adapter: JsonAdapter<BoxWithoutMoshi<String>> = moshi.adapter(type)
  
          assertThat(adapter.toJson(BoxWithoutMoshi("unused")))
              .isEqualTo("\"box-types-java.lang.String\"")
      }
  
      @Test
      fun lookupDefaultsConstructorFindsKotlinDefaultsConstructor(): Unit {
          val constructor = Util.lookupDefaultsConstructor(KotlinDefaultTarget::class.java)
  
          assertThat(constructor.parameterTypes.last().name)
              .isEqualTo("kotlin.jvm.internal.DefaultConstructorMarker")
      }
  }
  
  @JsonClass(generateAdapter = true)
  public data class PlainWithMoshi(val value: String)
  
  public class PlainWithMoshiJsonAdapter(private val moshi: Moshi) : JsonAdapter<PlainWithMoshi>() {
      override fun fromJson(reader: JsonReader): PlainWithMoshi {
          reader.skipValue()
          return PlainWithMoshi("from-json")
      }
  
      override fun toJson(writer: JsonWriter, value: PlainWithMoshi?): Unit {
          writer.value("plain-moshi")
      }
  }
  
  @JsonClass(generateAdapter = true)
  public data class PlainWithoutMoshi(val value: String)
  
  public class PlainWithoutMoshiJsonAdapter : JsonAdapter<PlainWithoutMoshi>() {
      override fun fromJson(reader: JsonReader): PlainWithoutMoshi {
          reader.skipValue()
          return PlainWithoutMoshi("from-json")
      }
  
      override fun toJson(writer: JsonWriter, value: PlainWithoutMoshi?): Unit {
          writer.value("plain-no-args")
      }
  }
  
  @JsonClass(generateAdapter = true)
  public data class BoxWithMoshi<T>(val value: T)
  
  public class BoxWithMoshiJsonAdapter<T>(
      private val moshi: Moshi,
      private val typeArguments: Array<Type>,
  ) : JsonAdapter<BoxWithMoshi<T>>() {
      override fun fromJson(reader: JsonReader): BoxWithMoshi<T> {
          reader.skipValue()
          throw UnsupportedOperationException("fromJson is not used by this coverage test")
      }
  
      override fun toJson(writer: JsonWriter, value: BoxWithMoshi<T>?): Unit {
          writer.value("box-moshi-${typeArguments.single().typeName}")
      }
  }
  
  @JsonClass(generateAdapter = true)
  public data class BoxWithoutMoshi<T>(val value: T)
  
  public class BoxWithoutMoshiJsonAdapter<T>(
      private val typeArguments: Array<Type>,
  ) : JsonAdapter<BoxWithoutMoshi<T>>() {
      override fun fromJson(reader: JsonReader): BoxWithoutMoshi<T> {
          reader.skipValue()
          throw UnsupportedOperationException("fromJson is not used by this coverage test")
      }
  
      override fun toJson(writer: JsonWriter, value: BoxWithoutMoshi<T>?): Unit {
          writer.value("box-types-${typeArguments.single().typeName}")
      }
  }
  
  public data class KotlinDefaultTarget(val name: String = "default")
[recv] {"type": "message_start", "message": {"role": "toolResult", "toolCallId": "call_sU1YuCVRgqV4vgLTYueAfnhU|fc_0d8c31fa336f7f3d0169f985662bd081a2a61bb75e35ca6f62", "toolName": "read", "content": [{"type": "text", "text": "/*\n * Copyright and related rights waived via CC0\n *\n * You should have received a copy of the CC0 legalcode along with this\n * work. If not, see <http://creativecommons.org/publicdomain/zero/1.0/>.\n */\npackage com_squareup_moshi.moshi\n\nimport com.squareup.moshi.JsonAdapter\nimport com.squareup.moshi.JsonClass\nimport com.squareup.moshi.JsonReader\nimport com.squareup.moshi.JsonWriter\nimport com.squareup.moshi.Moshi\nimport com.squareup.moshi.Types\nimport com.squareup.moshi.internal.Util\nimport java.lang.reflect.Type\nimport org.assertj.core.api.Assertions.assertThat\nimport org.junit.jupiter.api.Test\n\npublic class UtilTest {\n    @Test\n    fun generatedAdapterUsesMoshiConstructorForPlainType(): Unit {\n        val moshi: Moshi = Moshi.Builder().build()\n        val adapter: JsonAdapter<PlainWithMoshi> = moshi.adapter(PlainWithMoshi::class.java)\n\n        assertThat(adapter.toJson(PlainWithMoshi(\"unused\"))).isEqualTo(\"\\\"plain-moshi\\\"\")\n    }\n\n    @Test\n    fun generatedAdapterFallsBackToNoArgumentConstructorForPlainType(): Unit {\n        val moshi: Moshi = Moshi.Builder().build()\n        val adapter: JsonAdapter<PlainWithoutMoshi> = moshi.adapter(PlainWithoutMoshi::class.java)\n\n        assertThat(adapter.toJson(PlainWithoutMoshi(\"unused\"))).isEqualTo(\"\\\"plain-no-args\\\"\")\n    }\n\n    @Test\n    fun generatedAdapterUsesMoshiAndTypeArrayConstructorForParameterizedType(): Unit {\n        val moshi: Moshi = Moshi.Builder().build()\n        val type: Type = Types.newParameterizedType(BoxWithMoshi::class.java, String::class.java)\n        val adapter: JsonAdapter<BoxWithMoshi<String>> = moshi.adapter(type)\n\n        assertThat(adapter.toJson(BoxWithMoshi(\"unused\")))\n            .isEqualTo(\"\\\"box-moshi-java.lang.String\\\"\")\n    }\n\n    @Test\n    fun generatedAdapterFallsBackToTypeArrayConstructorForParameterizedType(): Unit {\n        val moshi: Moshi = Moshi.Builder().build()\n        val type: Type = Types.newParameterizedType(BoxWithoutMoshi::class.java, String::class.java)\n        val adapter: JsonAdapter<BoxWithoutMoshi<String>> = moshi.adapter(type)\n\n        assertThat(adapter.toJson(BoxWithoutMoshi(\"unused\")))\n            .isEqualTo(\"\\\"box-types-java.lang.String\\\"\")\n    }\n\n    @Test\n    fun lookupDefaultsConstructorFindsKotlinDefaultsConstructor(): Unit {\n        val constructor = Util.lookupDefaultsConstructor(KotlinDefaultTarget::class.java)\n\n        assertThat(constructor.parameterTypes.last().name)\n            .isEqualTo(\"kotlin.jvm.internal.DefaultConstructorMarker\")\n    }\n}\n\n@JsonClass(generateAdapter = true)\npublic data class PlainWithMoshi(val value: String)\n\npublic class PlainWithMoshiJsonAdapter(private val moshi: Moshi) : JsonAdapter<PlainWithMoshi>() {\n    override fun fromJson(reader: JsonReader): PlainWithMoshi {\n        reader.skipValue()\n        return PlainWithMoshi(\"from-json\")\n    }\n\n    override fun toJson(writer: JsonWriter, value: PlainWithMoshi?): Unit {\n        writer.value(\"plain-moshi\")\n    }\n}\n\n@JsonClass(generateAdapter = true)\npublic data class PlainWithoutMoshi(val value: String)\n\npublic class PlainWithoutMoshiJsonAdapter : JsonAdapter<PlainWithoutMoshi>() {\n    override fun fromJson(reader: JsonReader): PlainWithoutMoshi {\n        reader.skipValue()\n        return PlainWithoutMoshi(\"from-json\")\n    }\n\n    override fun toJson(writer: JsonWriter, value: PlainWithoutMoshi?): Unit {\n        writer.value(\"plain-no-args\")\n    }\n}\n\n@JsonClass(generateAdapter = true)\npublic data class BoxWithMoshi<T>(val value: T)\n\npublic class BoxWithMoshiJsonAdapter<T>(\n    private val moshi: Moshi,\n    private val typeArguments: Array<Type>,\n) : JsonAdapter<BoxWithMoshi<T>>() {\n    override fun fromJson(reader: JsonReader): BoxWithMoshi<T> {\n        reader.skipValue()\n        throw UnsupportedOperationException(\"fromJson is not used by this coverage test\")\n    }\n\n    override fun toJson(writer: JsonWriter, value: BoxWithMoshi<T>?): Unit {\n        writer.value(\"box-moshi-${typeArguments.single().typeName}\")\n    }\n}\n\n@JsonClass(generateAdapter = true)\npublic data class BoxWithoutMoshi<T>(val value: T)\n\npublic class BoxWithoutMoshiJsonAdapter<T>(\n    private val typeArguments: Array<Type>,\n) : JsonAdapter<BoxWithoutMoshi<T>>() {\n    override fun fromJson(reader: JsonReader): BoxWithoutMoshi<T> {\n        reader.skipValue()\n        throw UnsupportedOperationException(\"fromJson is not used by this coverage test\")\n    }\n\n    override fun toJson(writer: JsonWriter, value: BoxWithoutMoshi<T>?): Unit {\n        writer.value(\"box-types-${typeArguments.single().typeName}\")\n    }\n}\n\npublic data class KotlinDefaultTarget(val name: String = \"default\")\n"}], "isError": false, "timestamp": 1777960294626}}
[recv] {"type": "message_end", "message": {"role": "toolResult", "toolCallId": "call_sU1YuCVRgqV4vgLTYueAfnhU|fc_0d8c31fa336f7f3d0169f985662bd081a2a61bb75e35ca6f62", "toolName": "read", "content": [{"type": "text", "text": "/*\n * Copyright and related rights waived via CC0\n *\n * You should have received a copy of the CC0 legalcode along with this\n * work. If not, see <http://creativecommons.org/publicdomain/zero/1.0/>.\n */\npackage com_squareup_moshi.moshi\n\nimport com.squareup.moshi.JsonAdapter\nimport com.squareup.moshi.JsonClass\nimport com.squareup.moshi.JsonReader\nimport com.squareup.moshi.JsonWriter\nimport com.squareup.moshi.Moshi\nimport com.squareup.moshi.Types\nimport com.squareup.moshi.internal.Util\nimport java.lang.reflect.Type\nimport org.assertj.core.api.Assertions.assertThat\nimport org.junit.jupiter.api.Test\n\npublic class UtilTest {\n    @Test\n    fun generatedAdapterUsesMoshiConstructorForPlainType(): Unit {\n        val moshi: Moshi = Moshi.Builder().build()\n        val adapter: JsonAdapter<PlainWithMoshi> = moshi.adapter(PlainWithMoshi::class.java)\n\n        assertThat(adapter.toJson(PlainWithMoshi(\"unused\"))).isEqualTo(\"\\\"plain-moshi\\\"\")\n    }\n\n    @Test\n    fun generatedAdapterFallsBackToNoArgumentConstructorForPlainType(): Unit {\n        val moshi: Moshi = Moshi.Builder().build()\n        val adapter: JsonAdapter<PlainWithoutMoshi> = moshi.adapter(PlainWithoutMoshi::class.java)\n\n        assertThat(adapter.toJson(PlainWithoutMoshi(\"unused\"))).isEqualTo(\"\\\"plain-no-args\\\"\")\n    }\n\n    @Test\n    fun generatedAdapterUsesMoshiAndTypeArrayConstructorForParameterizedType(): Unit {\n        val moshi: Moshi = Moshi.Builder().build()\n        val type: Type = Types.newParameterizedType(BoxWithMoshi::class.java, String::class.java)\n        val adapter: JsonAdapter<BoxWithMoshi<String>> = moshi.adapter(type)\n\n        assertThat(adapter.toJson(BoxWithMoshi(\"unused\")))\n            .isEqualTo(\"\\\"box-moshi-java.lang.String\\\"\")\n    }\n\n    @Test\n    fun generatedAdapterFallsBackToTypeArrayConstructorForParameterizedType(): Unit {\n        val moshi: Moshi = Moshi.Builder().build()\n        val type: Type = Types.newParameterizedType(BoxWithoutMoshi::class.java, String::class.java)\n        val adapter: JsonAdapter<BoxWithoutMoshi<String>> = moshi.adapter(type)\n\n        assertThat(adapter.toJson(BoxWithoutMoshi(\"unused\")))\n            .isEqualTo(\"\\\"box-types-java.lang.String\\\"\")\n    }\n\n    @Test\n    fun lookupDefaultsConstructorFindsKotlinDefaultsConstructor(): Unit {\n        val constructor = Util.lookupDefaultsConstructor(KotlinDefaultTarget::class.java)\n\n        assertThat(constructor.parameterTypes.last().name)\n            .isEqualTo(\"kotlin.jvm.internal.DefaultConstructorMarker\")\n    }\n}\n\n@JsonClass(generateAdapter = true)\npublic data class PlainWithMoshi(val value: String)\n\npublic class PlainWithMoshiJsonAdapter(private val moshi: Moshi) : JsonAdapter<PlainWithMoshi>() {\n    override fun fromJson(reader: JsonReader): PlainWithMoshi {\n        reader.skipValue()\n        return PlainWithMoshi(\"from-json\")\n    }\n\n    override fun toJson(writer: JsonWriter, value: PlainWithMoshi?): Unit {\n        writer.value(\"plain-moshi\")\n    }\n}\n\n@JsonClass(generateAdapter = true)\npublic data class PlainWithoutMoshi(val value: String)\n\npublic class PlainWithoutMoshiJsonAdapter : JsonAdapter<PlainWithoutMoshi>() {\n    override fun fromJson(reader: JsonReader): PlainWithoutMoshi {\n        reader.skipValue()\n        return PlainWithoutMoshi(\"from-json\")\n    }\n\n    override fun toJson(writer: JsonWriter, value: PlainWithoutMoshi?): Unit {\n        writer.value(\"plain-no-args\")\n    }\n}\n\n@JsonClass(generateAdapter = true)\npublic data class BoxWithMoshi<T>(val value: T)\n\npublic class BoxWithMoshiJsonAdapter<T>(\n    private val moshi: Moshi,\n    private val typeArguments: Array<Type>,\n) : JsonAdapter<BoxWithMoshi<T>>() {\n    override fun fromJson(reader: JsonReader): BoxWithMoshi<T> {\n        reader.skipValue()\n        throw UnsupportedOperationException(\"fromJson is not used by this coverage test\")\n    }\n\n    override fun toJson(writer: JsonWriter, value: BoxWithMoshi<T>?): Unit {\n        writer.value(\"box-moshi-${typeArguments.single().typeName}\")\n    }\n}\n\n@JsonClass(generateAdapter = true)\npublic data class BoxWithoutMoshi<T>(val value: T)\n\npublic class BoxWithoutMoshiJsonAdapter<T>(\n    private val typeArguments: Array<Type>,\n) : JsonAdapter<BoxWithoutMoshi<T>>() {\n    override fun fromJson(reader: JsonReader): BoxWithoutMoshi<T> {\n        reader.skipValue()\n        throw UnsupportedOperationException(\"fromJson is not used by this coverage test\")\n    }\n\n    override fun toJson(writer: JsonWriter, value: BoxWithoutMoshi<T>?): Unit {\n        writer.value(\"box-types-${typeArguments.single().typeName}\")\n    }\n}\n\npublic data class KotlinDefaultTarget(val name: String = \"default\")\n"}], "isError": false, "timestamp": 1777960294626}}
[recv] {"type": "turn_end", "message": {"role": "assistant", "content": [{"type": "toolCall", "id": "call_sU1YuCVRgqV4vgLTYueAfnhU|fc_0d8c31fa336f7f3d0169f985662bd081a2a61bb75e35ca6f62", "name": "read", "arguments": {"path": "tests/src/com.squareup.moshi/moshi/1.15.2/src/test/kotlin/com_squareup_moshi/moshi/UtilTest.kt"}}], "api": "openai-responses", "provider": "OCA", "model": "gpt-5.5", "usage": {"input": 1132, "output": 45, "cacheRead": 9216, "cacheWrite": 0, "totalTokens": 10393, "cost": {"input": 0, "output": 0, "cacheRead": 0, "cacheWrite": 0, "total": 0}}, "stopReason": "toolUse", "timestamp": 1777960293135, "responseId": "resp_0d8c31fa336f7f3d0169f985657b8c81a2b2b029d5237a85f6"}, "toolResults": [{"role": "toolResult", "toolCallId": "call_sU1YuCVRgqV4vgLTYueAfnhU|fc_0d8c31fa336f7f3d0169f985662bd081a2a61bb75e35ca6f62", "toolName": "read", "content": [{"type": "text", "text": "/*\n * Copyright and related rights waived via CC0\n *\n * You should have received a copy of the CC0 legalcode along with this\n * work. If not, see <http://creativecommons.org/publicdomain/zero/1.0/>.\n */\npackage com_squareup_moshi.moshi\n\nimport com.squareup.moshi.JsonAdapter\nimport com.squareup.moshi.JsonClass\nimport com.squareup.moshi.JsonReader\nimport com.squareup.moshi.JsonWriter\nimport com.squareup.moshi.Moshi\nimport com.squareup.moshi.Types\nimport com.squareup.moshi.internal.Util\nimport java.lang.reflect.Type\nimport org.assertj.core.api.Assertions.assertThat\nimport org.junit.jupiter.api.Test\n\npublic class UtilTest {\n    @Test\n    fun generatedAdapterUsesMoshiConstructorForPlainType(): Unit {\n        val moshi: Moshi = Moshi.Builder().build()\n        val adapter: JsonAdapter<PlainWithMoshi> = moshi.adapter(PlainWithMoshi::class.java)\n\n        assertThat(adapter.toJson(PlainWithMoshi(\"unused\"))).isEqualTo(\"\\\"plain-moshi\\\"\")\n    }\n\n    @Test\n    fun generatedAdapterFallsBackToNoArgumentConstructorForPlainType(): Unit {\n        val moshi: Moshi = Moshi.Builder().build()\n        val adapter: JsonAdapter<PlainWithoutMoshi> = moshi.adapter(PlainWithoutMoshi::class.java)\n\n        assertThat(adapter.toJson(PlainWithoutMoshi(\"unused\"))).isEqualTo(\"\\\"plain-no-args\\\"\")\n    }\n\n    @Test\n    fun generatedAdapterUsesMoshiAndTypeArrayConstructorForParameterizedType(): Unit {\n        val moshi: Moshi = Moshi.Builder().build()\n        val type: Type = Types.newParameterizedType(BoxWithMoshi::class.java, String::class.java)\n        val adapter: JsonAdapter<BoxWithMoshi<String>> = moshi.adapter(type)\n\n        assertThat(adapter.toJson(BoxWithMoshi(\"unused\")))\n            .isEqualTo(\"\\\"box-moshi-java.lang.String\\\"\")\n    }\n\n    @Test\n    fun generatedAdapterFallsBackToTypeArrayConstructorForParameterizedType(): Unit {\n        val moshi: Moshi = Moshi.Builder().build()\n        val type: Type = Types.newParameterizedType(BoxWithoutMoshi::class.java, String::class.java)\n        val adapter: JsonAdapter<BoxWithoutMoshi<String>> = moshi.adapter(type)\n\n        assertThat(adapter.toJson(BoxWithoutMoshi(\"unused\")))\n            .isEqualTo(\"\\\"box-types-java.lang.String\\\"\")\n    }\n\n    @Test\n    fun lookupDefaultsConstructorFindsKotlinDefaultsConstructor(): Unit {\n        val constructor = Util.lookupDefaultsConstructor(KotlinDefaultTarget::class.java)\n\n        assertThat(constructor.parameterTypes.last().name)\n            .isEqualTo(\"kotlin.jvm.internal.DefaultConstructorMarker\")\n    }\n}\n\n@JsonClass(generateAdapter = true)\npublic data class PlainWithMoshi(val value: String)\n\npublic class PlainWithMoshiJsonAdapter(private val moshi: Moshi) : JsonAdapter<PlainWithMoshi>() {\n    override fun fromJson(reader: JsonReader): PlainWithMoshi {\n        reader.skipValue()\n        return PlainWithMoshi(\"from-json\")\n    }\n\n    override fun toJson(writer: JsonWriter, value: PlainWithMoshi?): Unit {\n        writer.value(\"plain-moshi\")\n    }\n}\n\n@JsonClass(generateAdapter = true)\npublic data class PlainWithoutMoshi(val value: String)\n\npublic class PlainWithoutMoshiJsonAdapter : JsonAdapter<PlainWithoutMoshi>() {\n    override fun fromJson(reader: JsonReader): PlainWithoutMoshi {\n        reader.skipValue()\n        return PlainWithoutMoshi(\"from-json\")\n    }\n\n    override fun toJson(writer: JsonWriter, value: PlainWithoutMoshi?): Unit {\n        writer.value(\"plain-no-args\")\n    }\n}\n\n@JsonClass(generateAdapter = true)\npublic data class BoxWithMoshi<T>(val value: T)\n\npublic class BoxWithMoshiJsonAdapter<T>(\n    private val moshi: Moshi,\n    private val typeArguments: Array<Type>,\n) : JsonAdapter<BoxWithMoshi<T>>() {\n    override fun fromJson(reader: JsonReader): BoxWithMoshi<T> {\n        reader.skipValue()\n        throw UnsupportedOperationException(\"fromJson is not used by this coverage test\")\n    }\n\n    override fun toJson(writer: JsonWriter, value: BoxWithMoshi<T>?): Unit {\n        writer.value(\"box-moshi-${typeArguments.single().typeName}\")\n    }\n}\n\n@JsonClass(generateAdapter = true)\npublic data class BoxWithoutMoshi<T>(val value: T)\n\npublic class BoxWithoutMoshiJsonAdapter<T>(\n    private val typeArguments: Array<Type>,\n) : JsonAdapter<BoxWithoutMoshi<T>>() {\n    override fun fromJson(reader: JsonReader): BoxWithoutMoshi<T> {\n        reader.skipValue()\n        throw UnsupportedOperationException(\"fromJson is not used by this coverage test\")\n    }\n\n    override fun toJson(writer: JsonWriter, value: BoxWithoutMoshi<T>?): Unit {\n        writer.value(\"box-types-${typeArguments.single().typeName}\")\n    }\n}\n\npublic data class KotlinDefaultTarget(val name: String = \"default\")\n"}], "isError": false, "timestamp": 1777960294626}]}
[recv] {"type": "turn_start"}
[recv] {"type": "message_start", "message": {"role": "assistant", "content": [], "api": "openai-responses", "provider": "OCA", "model": "gpt-5.5", "usage": {"input": 0, "output": 0, "cacheRead": 0, "cacheWrite": 0, "totalTokens": 0, "cost": {"input": 0, "output": 0, "cacheRead": 0, "cacheWrite": 0, "total": 0}}, "stopReason": "stop", "timestamp": 1777960294633}}
[assistant-event] thinking_start
[assistant-event] thinking_end
[tool-call] start id=unknown
[tool-call] delta {"command":"find ~/.gradle/caches/modules-2/files-2.1/com.squareup.moshi/moshi/1.15.2 -type f -maxdepth 2 -print"}
[tool-call] end id=call_DDgZBfHnPonlnUNH84WOhtac|fc_0d8c31fa336f7f3d0169f98569dd2481a28f3a7c817fddf0db name=bash args={"command": "find ~/.gradle/caches/modules-2/files-2.1/com.squareup.moshi/moshi/1.15.2 -type f -maxdepth 2 -print"}
[recv] {"type": "message_end", "message": {"role": "assistant", "content": [{"type": "thinking", "thinking": "", "thinkingSignature": "{\"id\":\"rs_0d8c31fa336f7f3d0169f98567999881a291757f04aac2c8d5\",\"type\":\"reasoning\",\"encrypted_content\":\"gAAAAABp-YVpWKd8hdRUyO18V-gvwZpL66AKEwrDTgSa2ljzacxw8zWWRdulXlNQ82cFFX0ftMVU1iYJ7IyvLoOklR-Tt3ZG-N2iEDhI8f_8Fl4SUq0CHg86vyhgvzyc4U74CPPGbbQj7PI6mRC32xM5kK8dbEbpQfeMgyPyFtLvSd7Y_SWK5TquLkRbNmS89JFkVNpLu1jeqmd0BA7hVppIr9aoafqWWKddPzd30Ou_CqnH3qyDI5PgKCJCRRE8ZZKWMuDwrZxJzEqMS1otuEPbPvSHmfBZ-bE8vMRgLmBDDX_vFB8q7JmWNBEAjmvD1iUEbndccH3o5jqeIDof3ktF6rMiLRW1YkIna34ya2FxHWV7I-QKAY9ErV6EvlZHJJW7yd8TLWiMuuykBD6WeFKOxvXj4MNZh95MYAb6NOSxobRPZRBNXWM-DMhjas7n6B-E4C13hnrfVApiiahVJopRB4Qt-4PBCnPsUGdQAAUvhzfdx27MJO_O4a_wCcXI5lYLBGRUCJmSrVQFBhmu4249cklERg_EIw79tocfJbkAPw4iX7o3tB56qQdhT3d9vtni_y-7LtuaFxe8xFoyCXcyRfuqG5EF4Ll2Vz2J0gf1wIS61BTIVWx6VvGvAgeeHj7RhbvRAOYm9GWgpWIWU21SXW8m1xkjx0NKYBMCf3TYyrA33AUmr3JeWmIL9f5NWQmbGEAt3KDEv4Mhzs10aSYK_DHBAT5hYWV6k9urmxPa3-ZDUDt3M42IUXwo-vDqlTKDp-aME3ciPAYi1FXr5F_0xz57YeGF1ryweOaVA3wCaB6ho-fPNEIFsH1DyLbiOBBLYVFE_2wiunwFBBbLvTvkvWUAaooIJXbPN9A84xetBjMLCBsnq-2ZkRe4xZCE4yoQvjKXTVWSs64u-wwzQHIfLT9dSBZQlUuPelU2dhRF7nJUWNRG77RX-mNyg086yHjOSIIRXlo1QafDWsXiwDw9UP7vzEv6-yY8SVkp53dCosrPt6XLa5Kmsro8EESh_QSS3JGTI3MnQ_LyLGwNjMw9qgpnKVuffN-ZImIery0gsS516JWYpaW2jnRXC9-ICCMaS9az0EY7UnWfRjruXiQnK0VHOy9Rf_lc2EbNWkOJEl-Z405PY0NMxKxYI3AvUrnKSCe1f9IeLz5ebb9KFJOcXCPcLjsQ63PHtacHo_MUhw61RA6Ji-cByk-g9z0PXkWFUcQKh_ziXE5BhEbfgmIqRfk-KEGqkaiZo84qXyQpWyCIsbts1A0go1SOHKZ5cHD51vMu0_GJc-a-r2J5kYFfqxSw6N607gJO9_Y4ow3V0ru2UM4pb_AgE09YC1K-MbkfzIJTqJo8cuSI7ON1qh511YFvMNY80qnEzxx64QVUZpiqgpnscAFy2U91JERaOzsoIzV8_ImOQj0TWa4CaxeToXNjYbfFFC6fDfCBETJEuhNIURUvJvmO2yX6xEgfUx4vRNd0noqPJ6crRT5PtBRVTdJvyrelwoOBYQvBQsxw79z6OFtI-g2ONqf21Tu9a3uqA46yKMD3NJB0GwLuNfBHrE43Mk_X9R7nRiTXxRpdmJpnYHN862W3myGAufUcFrO03z_hBTdMx1EDOMf1tPsus535dk7md23CQL6L-t9fYAgxshzjkScSlfrDu--PgSzRlYFCyebotVaQTeKeIXvW48dCQ32wivASCZgh6kUxLQqku9moqYSuW4cyXEDPNkYSKKdD7k74jFGlwr00SSPxJBlhSwT8w8OlW_wgOA9eTlwAW9qjO9ok5y5cjPPq9nllH_yvWDR0VWVH15r6bO5PVB4zYLgrHKdAVyLN1h_xzzU6NTPNRR8C9UhwlKTY_xnMNuSV8J_QodvH5aPRE26FbJW508hjo3n2s2rtQx2RbW9Vwfx8xbM=\",\"summary\":[]}"}, {"type": "toolCall", "id": "call_DDgZBfHnPonlnUNH84WOhtac|fc_0d8c31fa336f7f3d0169f98569dd2481a28f3a7c817fddf0db", "name": "bash", "arguments": {"command": "find ~/.gradle/caches/modules-2/files-2.1/com.squareup.moshi/moshi/1.15.2 -type f -maxdepth 2 -print"}}], "api": "openai-responses", "provider": "OCA", "model": "gpt-5.5", "usage": {"input": 1233, "output": 208, "cacheRead": 10240, "cacheWrite": 0, "totalTokens": 11681, "cost": {"input": 0, "output": 0, "cacheRead": 0, "cacheWrite": 0, "total": 0}}, "stopReason": "toolUse", "timestamp": 1777960294633, "responseId": "resp_0d8c31fa336f7f3d0169f98566f6dc81a2a829bc6f64a17e42"}}
[tool-exec] start id=call_DDgZBfHnPonlnUNH84WOhtac|fc_0d8c31fa336f7f3d0169f98569dd2481a28f3a7c817fddf0db name=bash args={"command": "find ~/.gradle/caches/modules-2/files-2.1/com.squareup.moshi/moshi/1.15.2 -type f -maxdepth 2 -print"}
[tool-exec] update id=call_DDgZBfHnPonlnUNH84WOhtac|fc_0d8c31fa336f7f3d0169f98569dd2481a28f3a7c817fddf0db name=bash
[tool-exec] update id=call_DDgZBfHnPonlnUNH84WOhtac|fc_0d8c31fa336f7f3d0169f98569dd2481a28f3a7c817fddf0db name=bash
  /home/vjovanov/.gradle/caches/modules-2/files-2.1/com.squareup.moshi/moshi/1.15.2/bf0b164a4b59ecaaf11b4278c702ce478f852c68/moshi-1.15.2.module
  /home/vjovanov/.gradle/caches/modules-2/files-2.1/com.squareup.moshi/moshi/1.15.2/8e9a6b11929c7c162a4ded3bb064cbd514af639a/moshi-1.15.2.jar
  /home/vjovanov/.gradle/caches/modules-2/files-2.1/com.squareup.moshi/moshi/1.15.2/ead7e7676201d9e53e774503d5058bcf28188f3a/moshi-1.15.2.pom
[tool-exec] end id=call_DDgZBfHnPonlnUNH84WOhtac|fc_0d8c31fa336f7f3d0169f98569dd2481a28f3a7c817fddf0db name=bash status=success
  /home/vjovanov/.gradle/caches/modules-2/files-2.1/com.squareup.moshi/moshi/1.15.2/bf0b164a4b59ecaaf11b4278c702ce478f852c68/moshi-1.15.2.module
  /home/vjovanov/.gradle/caches/modules-2/files-2.1/com.squareup.moshi/moshi/1.15.2/8e9a6b11929c7c162a4ded3bb064cbd514af639a/moshi-1.15.2.jar
  /home/vjovanov/.gradle/caches/modules-2/files-2.1/com.squareup.moshi/moshi/1.15.2/ead7e7676201d9e53e774503d5058bcf28188f3a/moshi-1.15.2.pom
[recv] {"type": "message_start", "message": {"role": "toolResult", "toolCallId": "call_DDgZBfHnPonlnUNH84WOhtac|fc_0d8c31fa336f7f3d0169f98569dd2481a28f3a7c817fddf0db", "toolName": "bash", "content": [{"type": "text", "text": "/home/vjovanov/.gradle/caches/modules-2/files-2.1/com.squareup.moshi/moshi/1.15.2/bf0b164a4b59ecaaf11b4278c702ce478f852c68/moshi-1.15.2.module\n/home/vjovanov/.gradle/caches/modules-2/files-2.1/com.squareup.moshi/moshi/1.15.2/8e9a6b11929c7c162a4ded3bb064cbd514af639a/moshi-1.15.2.jar\n/home/vjovanov/.gradle/caches/modules-2/files-2.1/com.squareup.moshi/moshi/1.15.2/ead7e7676201d9e53e774503d5058bcf28188f3a/moshi-1.15.2.pom\n"}], "isError": false, "timestamp": 1777960298212}}
[recv] {"type": "message_end", "message": {"role": "toolResult", "toolCallId": "call_DDgZBfHnPonlnUNH84WOhtac|fc_0d8c31fa336f7f3d0169f98569dd2481a28f3a7c817fddf0db", "toolName": "bash", "content": [{"type": "text", "text": "/home/vjovanov/.gradle/caches/modules-2/files-2.1/com.squareup.moshi/moshi/1.15.2/bf0b164a4b59ecaaf11b4278c702ce478f852c68/moshi-1.15.2.module\n/home/vjovanov/.gradle/caches/modules-2/files-2.1/com.squareup.moshi/moshi/1.15.2/8e9a6b11929c7c162a4ded3bb064cbd514af639a/moshi-1.15.2.jar\n/home/vjovanov/.gradle/caches/modules-2/files-2.1/com.squareup.moshi/moshi/1.15.2/ead7e7676201d9e53e774503d5058bcf28188f3a/moshi-1.15.2.pom\n"}], "isError": false, "timestamp": 1777960298212}}
[recv] {"type": "turn_end", "message": {"role": "assistant", "content": [{"type": "thinking", "thinking": "", "thinkingSignature": "{\"id\":\"rs_0d8c31fa336f7f3d0169f98567999881a291757f04aac2c8d5\",\"type\":\"reasoning\",\"encrypted_content\":\"gAAAAABp-YVpWKd8hdRUyO18V-gvwZpL66AKEwrDTgSa2ljzacxw8zWWRdulXlNQ82cFFX0ftMVU1iYJ7IyvLoOklR-Tt3ZG-N2iEDhI8f_8Fl4SUq0CHg86vyhgvzyc4U74CPPGbbQj7PI6mRC32xM5kK8dbEbpQfeMgyPyFtLvSd7Y_SWK5TquLkRbNmS89JFkVNpLu1jeqmd0BA7hVppIr9aoafqWWKddPzd30Ou_CqnH3qyDI5PgKCJCRRE8ZZKWMuDwrZxJzEqMS1otuEPbPvSHmfBZ-bE8vMRgLmBDDX_vFB8q7JmWNBEAjmvD1iUEbndccH3o5jqeIDof3ktF6rMiLRW1YkIna34ya2FxHWV7I-QKAY9ErV6EvlZHJJW7yd8TLWiMuuykBD6WeFKOxvXj4MNZh95MYAb6NOSxobRPZRBNXWM-DMhjas7n6B-E4C13hnrfVApiiahVJopRB4Qt-4PBCnPsUGdQAAUvhzfdx27MJO_O4a_wCcXI5lYLBGRUCJmSrVQFBhmu4249cklERg_EIw79tocfJbkAPw4iX7o3tB56qQdhT3d9vtni_y-7LtuaFxe8xFoyCXcyRfuqG5EF4Ll2Vz2J0gf1wIS61BTIVWx6VvGvAgeeHj7RhbvRAOYm9GWgpWIWU21SXW8m1xkjx0NKYBMCf3TYyrA33AUmr3JeWmIL9f5NWQmbGEAt3KDEv4Mhzs10aSYK_DHBAT5hYWV6k9urmxPa3-ZDUDt3M42IUXwo-vDqlTKDp-aME3ciPAYi1FXr5F_0xz57YeGF1ryweOaVA3wCaB6ho-fPNEIFsH1DyLbiOBBLYVFE_2wiunwFBBbLvTvkvWUAaooIJXbPN9A84xetBjMLCBsnq-2ZkRe4xZCE4yoQvjKXTVWSs64u-wwzQHIfLT9dSBZQlUuPelU2dhRF7nJUWNRG77RX-mNyg086yHjOSIIRXlo1QafDWsXiwDw9UP7vzEv6-yY8SVkp53dCosrPt6XLa5Kmsro8EESh_QSS3JGTI3MnQ_LyLGwNjMw9qgpnKVuffN-ZImIery0gsS516JWYpaW2jnRXC9-ICCMaS9az0EY7UnWfRjruXiQnK0VHOy9Rf_lc2EbNWkOJEl-Z405PY0NMxKxYI3AvUrnKSCe1f9IeLz5ebb9KFJOcXCPcLjsQ63PHtacHo_MUhw61RA6Ji-cByk-g9z0PXkWFUcQKh_ziXE5BhEbfgmIqRfk-KEGqkaiZo84qXyQpWyCIsbts1A0go1SOHKZ5cHD51vMu0_GJc-a-r2J5kYFfqxSw6N607gJO9_Y4ow3V0ru2UM4pb_AgE09YC1K-MbkfzIJTqJo8cuSI7ON1qh511YFvMNY80qnEzxx64QVUZpiqgpnscAFy2U91JERaOzsoIzV8_ImOQj0TWa4CaxeToXNjYbfFFC6fDfCBETJEuhNIURUvJvmO2yX6xEgfUx4vRNd0noqPJ6crRT5PtBRVTdJvyrelwoOBYQvBQsxw79z6OFtI-g2ONqf21Tu9a3uqA46yKMD3NJB0GwLuNfBHrE43Mk_X9R7nRiTXxRpdmJpnYHN862W3myGAufUcFrO03z_hBTdMx1EDOMf1tPsus535dk7md23CQL6L-t9fYAgxshzjkScSlfrDu--PgSzRlYFCyebotVaQTeKeIXvW48dCQ32wivASCZgh6kUxLQqku9moqYSuW4cyXEDPNkYSKKdD7k74jFGlwr00SSPxJBlhSwT8w8OlW_wgOA9eTlwAW9qjO9ok5y5cjPPq9nllH_yvWDR0VWVH15r6bO5PVB4zYLgrHKdAVyLN1h_xzzU6NTPNRR8C9UhwlKTY_xnMNuSV8J_QodvH5aPRE26FbJW508hjo3n2s2rtQx2RbW9Vwfx8xbM=\",\"summary\":[]}"}, {"type": "toolCall", "id": "call_DDgZBfHnPonlnUNH84WOhtac|fc_0d8c31fa336f7f3d0169f98569dd2481a28f3a7c817fddf0db", "name": "bash", "arguments": {"command": "find ~/.gradle/caches/modules-2/files-2.1/com.squareup.moshi/moshi/1.15.2 -type f -maxdepth 2 -print"}}], "api": "openai-responses", "provider": "OCA", "model": "gpt-5.5", "usage": {"input": 1233, "output": 208, "cacheRead": 10240, "cacheWrite": 0, "totalTokens": 11681, "cost": {"input": 0, "output": 0, "cacheRead": 0, "cacheWrite": 0, "total": 0}}, "stopReason": "toolUse", "timestamp": 1777960294633, "responseId": "resp_0d8c31fa336f7f3d0169f98566f6dc81a2a829bc6f64a17e42"}, "toolResults": [{"role": "toolResult", "toolCallId": "call_DDgZBfHnPonlnUNH84WOhtac|fc_0d8c31fa336f7f3d0169f98569dd2481a28f3a7c817fddf0db", "toolName": "bash", "content": [{"type": "text", "text": "/home/vjovanov/.gradle/caches/modules-2/files-2.1/com.squareup.moshi/moshi/1.15.2/bf0b164a4b59ecaaf11b4278c702ce478f852c68/moshi-1.15.2.module\n/home/vjovanov/.gradle/caches/modules-2/files-2.1/com.squareup.moshi/moshi/1.15.2/8e9a6b11929c7c162a4ded3bb064cbd514af639a/moshi-1.15.2.jar\n/home/vjovanov/.gradle/caches/modules-2/files-2.1/com.squareup.moshi/moshi/1.15.2/ead7e7676201d9e53e774503d5058bcf28188f3a/moshi-1.15.2.pom\n"}], "isError": false, "timestamp": 1777960298212}]}
[recv] {"type": "turn_start"}
[recv] {"type": "message_start", "message": {"role": "assistant", "content": [], "api": "openai-responses", "provider": "OCA", "model": "gpt-5.5", "usage": {"input": 0, "output": 0, "cacheRead": 0, "cacheWrite": 0, "totalTokens": 0, "cost": {"input": 0, "output": 0, "cacheRead": 0, "cacheWrite": 0, "total": 0}}, "stopReason": "stop", "timestamp": 1777960298215}}
[tool-call] start id=unknown
[tool-call] delta {"command":"jar tf /home/vjovanov/.gradle/caches/modules-2/files-2.1/com.squareup.moshi/moshi/1.15.2/8e9a6b11929c7c162a4ded3bb064cbd514af639a/moshi-1.15.2.jar | grep RecordJsonAdapter"}
[tool-call] end id=call_6ftdTwO11ZG5U7tuYqZqR86h|fc_0d8c31fa336f7f3d0169f9856b4c4881a2803a58115d66ec83 name=bash args={"command": "jar tf /home/vjovanov/.gradle/caches/modules-2/files-2.1/com.squareup.moshi/moshi/1.15.2/8e9a6b11929c7c162a4ded3bb064cbd514af639a/moshi-1.15.2.jar | grep RecordJsonAdapter"}
[recv] {"type": "message_end", "message": {"role": "assistant", "content": [{"type": "toolCall", "id": "call_6ftdTwO11ZG5U7tuYqZqR86h|fc_0d8c31fa336f7f3d0169f9856b4c4881a2803a58115d66ec83", "name": "bash", "arguments": {"command": "jar tf /home/vjovanov/.gradle/caches/modules-2/files-2.1/com.squareup.moshi/moshi/1.15.2/8e9a6b11929c7c162a4ded3bb064cbd514af639a/moshi-1.15.2.jar | grep RecordJsonAdapter"}}], "api": "openai-responses", "provider": "OCA", "model": "gpt-5.5", "usage": {"input": 621, "output": 89, "cacheRead": 11264, "cacheWrite": 0, "totalTokens": 11974, "cost": {"input": 0, "output": 0, "cacheRead": 0, "cacheWrite": 0, "total": 0}}, "stopReason": "toolUse", "timestamp": 1777960298215, "responseId": "resp_0d8c31fa336f7f3d0169f9856a91ec81a29cbc8d364a7bb0a6"}}
[tool-exec] start id=call_6ftdTwO11ZG5U7tuYqZqR86h|fc_0d8c31fa336f7f3d0169f9856b4c4881a2803a58115d66ec83 name=bash args={"command": "jar tf /home/vjovanov/.gradle/caches/modules-2/files-2.1/com.squareup.moshi/moshi/1.15.2/8e9a6b11929c7c162a4ded3bb064cbd514af639a/moshi-1.15.2.jar | grep RecordJsonAdapter"}
[tool-exec] update id=call_6ftdTwO11ZG5U7tuYqZqR86h|fc_0d8c31fa336f7f3d0169f9856b4c4881a2803a58115d66ec83 name=bash
[tool-exec] update id=call_6ftdTwO11ZG5U7tuYqZqR86h|fc_0d8c31fa336f7f3d0169f9856b4c4881a2803a58115d66ec83 name=bash
  com/squareup/moshi/RecordJsonAdapter$1.class
  com/squareup/moshi/RecordJsonAdapter.class
  META-INF/versions/16/com/squareup/moshi/RecordJsonAdapter$1.class
  META-INF/versions/16/com/squareup/moshi/RecordJsonAdapter.class
  META-INF/versions/16/com/squareup/moshi/RecordJsonAdapter$ComponentBinding.class
[tool-exec] end id=call_6ftdTwO11ZG5U7tuYqZqR86h|fc_0d8c31fa336f7f3d0169f9856b4c4881a2803a58115d66ec83 name=bash status=success
  com/squareup/moshi/RecordJsonAdapter$1.class
  com/squareup/moshi/RecordJsonAdapter.class
  META-INF/versions/16/com/squareup/moshi/RecordJsonAdapter$1.class
  META-INF/versions/16/com/squareup/moshi/RecordJsonAdapter.class
  META-INF/versions/16/com/squareup/moshi/RecordJsonAdapter$ComponentBinding.class
[recv] {"type": "message_start", "message": {"role": "toolResult", "toolCallId": "call_6ftdTwO11ZG5U7tuYqZqR86h|fc_0d8c31fa336f7f3d0169f9856b4c4881a2803a58115d66ec83", "toolName": "bash", "content": [{"type": "text", "text": "com/squareup/moshi/RecordJsonAdapter$1.class\ncom/squareup/moshi/RecordJsonAdapter.class\nMETA-INF/versions/16/com/squareup/moshi/RecordJsonAdapter$1.class\nMETA-INF/versions/16/com/squareup/moshi/RecordJsonAdapter.class\nMETA-INF/versions/16/com/squareup/moshi/RecordJsonAdapter$ComponentBinding.class\n"}], "isError": false, "timestamp": 1777960300182}}
[recv] {"type": "message_end", "message": {"role": "toolResult", "toolCallId": "call_6ftdTwO11ZG5U7tuYqZqR86h|fc_0d8c31fa336f7f3d0169f9856b4c4881a2803a58115d66ec83", "toolName": "bash", "content": [{"type": "text", "text": "com/squareup/moshi/RecordJsonAdapter$1.class\ncom/squareup/moshi/RecordJsonAdapter.class\nMETA-INF/versions/16/com/squareup/moshi/RecordJsonAdapter$1.class\nMETA-INF/versions/16/com/squareup/moshi/RecordJsonAdapter.class\nMETA-INF/versions/16/com/squareup/moshi/RecordJsonAdapter$ComponentBinding.class\n"}], "isError": false, "timestamp": 1777960300182}}
[recv] {"type": "turn_end", "message": {"role": "assistant", "content": [{"type": "toolCall", "id": "call_6ftdTwO11ZG5U7tuYqZqR86h|fc_0d8c31fa336f7f3d0169f9856b4c4881a2803a58115d66ec83", "name": "bash", "arguments": {"command": "jar tf /home/vjovanov/.gradle/caches/modules-2/files-2.1/com.squareup.moshi/moshi/1.15.2/8e9a6b11929c7c162a4ded3bb064cbd514af639a/moshi-1.15.2.jar | grep RecordJsonAdapter"}}], "api": "openai-responses", "provider": "OCA", "model": "gpt-5.5", "usage": {"input": 621, "output": 89, "cacheRead": 11264, "cacheWrite": 0, "totalTokens": 11974, "cost": {"input": 0, "output": 0, "cacheRead": 0, "cacheWrite": 0, "total": 0}}, "stopReason": "toolUse", "timestamp": 1777960298215, "responseId": "resp_0d8c31fa336f7f3d0169f9856a91ec81a29cbc8d364a7bb0a6"}, "toolResults": [{"role": "toolResult", "toolCallId": "call_6ftdTwO11ZG5U7tuYqZqR86h|fc_0d8c31fa336f7f3d0169f9856b4c4881a2803a58115d66ec83", "toolName": "bash", "content": [{"type": "text", "text": "com/squareup/moshi/RecordJsonAdapter$1.class\ncom/squareup/moshi/RecordJsonAdapter.class\nMETA-INF/versions/16/com/squareup/moshi/RecordJsonAdapter$1.class\nMETA-INF/versions/16/com/squareup/moshi/RecordJsonAdapter.class\nMETA-INF/versions/16/com/squareup/moshi/RecordJsonAdapter$ComponentBinding.class\n"}], "isError": false, "timestamp": 1777960300182}]}
[recv] {"type": "turn_start"}
[recv] {"type": "message_start", "message": {"role": "assistant", "content": [], "api": "openai-responses", "provider": "OCA", "model": "gpt-5.5", "usage": {"input": 0, "output": 0, "cacheRead": 0, "cacheWrite": 0, "totalTokens": 0, "cost": {"input": 0, "output": 0, "cacheRead": 0, "cacheWrite": 0, "total": 0}}, "stopReason": "stop", "timestamp": 1777960300186}}
[tool-call] start id=unknown
[tool-call] delta {"command":"javap -classpath /home/vjovanov/.gradle/caches/modules-2/files-2.1/com.squareup.moshi/moshi/1.15.2/8e9a6b11929c7c162a4ded3bb064cbd514af639a/moshi-1.15.2.jar -c -p --multi-release 16 com.squareup.moshi.RecordJsonAdapter\\$1 | head -200"}
[tool-call] end id=call_iWMNhEU2b9RB7L6vzzebvW4D|fc_0d8c31fa336f7f3d0169f9856d54c481a283a6b2ecf243250e name=bash args={"command": "javap -classpath /home/vjovanov/.gradle/caches/modules-2/files-2.1/com.squareup.moshi/moshi/1.15.2/8e9a6b11929c7c162a4ded3bb064cbd514af639a/moshi-1.15.2.jar -c -p --multi-release 16 com.squareup.moshi.RecordJsonAdapter\\$1 | head -200"}
[recv] {"type": "message_end", "message": {"role": "assistant", "content": [{"type": "toolCall", "id": "call_iWMNhEU2b9RB7L6vzzebvW4D|fc_0d8c31fa336f7f3d0169f9856d54c481a283a6b2ecf243250e", "name": "bash", "arguments": {"command": "javap -classpath /home/vjovanov/.gradle/caches/modules-2/files-2.1/com.squareup.moshi/moshi/1.15.2/8e9a6b11929c7c162a4ded3bb064cbd514af639a/moshi-1.15.2.jar -c -p --multi-release 16 com.squareup.moshi.RecordJsonAdapter\\$1 | head -200"}}], "api": "openai-responses", "provider": "OCA", "model": "gpt-5.5", "usage": {"input": 294, "output": 109, "cacheRead": 11776, "cacheWrite": 0, "totalTokens": 12179, "cost": {"input": 0, "output": 0, "cacheRead": 0, "cacheWrite": 0, "total": 0}}, "stopReason": "toolUse", "timestamp": 1777960300186, "responseId": "resp_0d8c31fa336f7f3d0169f9856c888081a2a09783e8b957a98f"}}
[tool-exec] start id=call_iWMNhEU2b9RB7L6vzzebvW4D|fc_0d8c31fa336f7f3d0169f9856d54c481a283a6b2ecf243250e name=bash args={"command": "javap -classpath /home/vjovanov/.gradle/caches/modules-2/files-2.1/com.squareup.moshi/moshi/1.15.2/8e9a6b11929c7c162a4ded3bb064cbd514af639a/moshi-1.15.2.jar -c -p --multi-release 16 com.squareup.moshi.RecordJsonAdapter\\$1 | head -200"}
[tool-exec] update id=call_iWMNhEU2b9RB7L6vzzebvW4D|fc_0d8c31fa336f7f3d0169f9856d54c481a283a6b2ecf243250e name=bash
[tool-exec] update id=call_iWMNhEU2b9RB7L6vzzebvW4D|fc_0d8c31fa336f7f3d0169f9856d54c481a283a6b2ecf243250e name=bash
  Compiled from "RecordJsonAdapter.java"
  class com.squareup.moshi.RecordJsonAdapter$1 implements com.squareup.moshi.JsonAdapter$Factory {
    com.squareup.moshi.RecordJsonAdapter$1();
      Code:
           0: aload_0
           1: invokespecial #1                  // Method java/lang/Object."<init>":()V
           4: return
  
    public com.squareup.moshi.JsonAdapter<?> create(java.lang.reflect.Type, java.util.Set<? extends java.lang.annotation.Annotation>, com.squareup.moshi.Moshi);
      Code:
           0: aload_2
           1: invokeinterface #7,  1            // InterfaceMethod java/util/Set.isEmpty:()Z
           6: ifne          11
           9: aconst_null
          10: areturn
          11: aload_1
          12: instanceof    #13                 // class java/lang/Class
          15: ifne          27
          18: aload_1
          19: instanceof    #15                 // class java/lang/reflect/ParameterizedType
          22: ifne          27
          25: aconst_null
          26: areturn
          27: aload_1
          28: invokestatic  #17                 // Method com/squareup/moshi/Types.getRawType:(Ljava/lang/reflect/Type;)Ljava/lang/Class;
          31: astore        4
          33: aload         4
          35: invokevirtual #23                 // Method java/lang/Class.isRecord:()Z
          38: ifne          43
          41: aconst_null
          42: areturn
          43: aload         4
          45: invokevirtual #26                 // Method java/lang/Class.getRecordComponents:()[Ljava/lang/reflect/RecordComponent;
          48: astore        5
          50: new           #30                 // class java/util/LinkedHashMap
          53: dup
          54: invokespecial #32                 // Method java/util/LinkedHashMap."<init>":()V
          57: astore        6
          59: aload         5
          61: arraylength
          62: anewarray     #13                 // class java/lang/Class
          65: astore        7
          67: invokestatic  #33                 // Method java/lang/invoke/MethodHandles.lookup:()Ljava/lang/invoke/MethodHandles$Lookup;
          70: astore        8
          72: iconst_0
          73: istore        9
          75: aload         5
          77: arraylength
          78: istore        10
          80: iload         9
          82: iload         10
          84: if_icmpge     168
          87: aload         5
          89: iload         9
          91: aaload
          92: astore        11
          94: aload         7
          96: iload         9
          98: aload         11
         100: invokevirtual #39                 // Method java/lang/reflect/RecordComponent.getType:()Ljava/lang/Class;
         103: aastore
         104: aload_1
         105: aload         4
         107: aload_3
         108: aload         8
         110: aload         11
         112: invokestatic  #45                 // Method createComponentBinding:(Ljava/lang/reflect/Type;Ljava/lang/Class;Lcom/squareup/moshi/Moshi;Ljava/lang/invoke/MethodHandles$Lookup;Ljava/lang/reflect/RecordComponent;)Lcom/squareup/moshi/RecordJsonAdapter$ComponentBinding;
         115: astore        12
         117: aload         6
         119: aload         12
         121: getfield      #51                 // Field com/squareup/moshi/RecordJsonAdapter$ComponentBinding.jsonName:Ljava/lang/String;
         124: aload         12
         126: invokevirtual #57                 // Method java/util/LinkedHashMap.put:(Ljava/lang/Object;Ljava/lang/Object;)Ljava/lang/Object;
         129: checkcast     #52                 // class com/squareup/moshi/RecordJsonAdapter$ComponentBinding
         132: astore        13
         134: aload         13
         136: ifnull        162
         139: new           #61                 // class java/lang/IllegalArgumentException
         142: dup
         143: aload         13
         145: getfield      #63                 // Field com/squareup/moshi/RecordJsonAdapter$ComponentBinding.componentName:Ljava/lang/String;
         148: aload         12
         150: getfield      #63                 // Field com/squareup/moshi/RecordJsonAdapter$ComponentBinding.componentName:Ljava/lang/String;
         153: invokedynamic #66,  0             // I
[tool-exec] update id=call_iWMNhEU2b9RB7L6vzzebvW4D|fc_0d8c31fa336f7f3d0169f9856d54c481a283a6b2ecf243250e name=bash
  Compiled from "RecordJsonAdapter.java"
  class com.squareup.moshi.RecordJsonAdapter$1 implements com.squareup.moshi.JsonAdapter$Factory {
    com.squareup.moshi.RecordJsonAdapter$1();
      Code:
           0: aload_0
           1: invokespecial #1                  // Method java/lang/Object."<init>":()V
           4: return
  
    public com.squareup.moshi.JsonAdapter<?> create(java.lang.reflect.Type, java.util.Set<? extends java.lang.annotation.Annotation>, com.squareup.moshi.Moshi);
      Code:
           0: aload_2
           1: invokeinterface #7,  1            // InterfaceMethod java/util/Set.isEmpty:()Z
           6: ifne          11
           9: aconst_null
          10: areturn
          11: aload_1
          12: instanceof    #13                 // class java/lang/Class
          15: ifne          27
          18: aload_1
          19: instanceof    #15                 // class java/lang/reflect/ParameterizedType
          22: ifne          27
          25: aconst_null
          26: areturn
          27: aload_1
          28: invokestatic  #17                 // Method com/squareup/moshi/Types.getRawType:(Ljava/lang/reflect/Type;)Ljava/lang/Class;
          31: astore        4
          33: aload         4
          35: invokevirtual #23                 // Method java/lang/Class.isRecord:()Z
          38: ifne          43
          41: aconst_null
          42: areturn
          43: aload         4
          45: invokevirtual #26                 // Method java/lang/Class.getRecordComponents:()[Ljava/lang/reflect/RecordComponent;
          48: astore        5
          50: new           #30                 // class java/util/LinkedHashMap
          53: dup
          54: invokespecial #32                 // Method java/util/LinkedHashMap."<init>":()V
          57: astore        6
          59: aload         5
          61: arraylength
          62: anewarray     #13                 // class java/lang/Class
          65: astore        7
          67: invokestatic  #33                 // Method java/lang/invoke/MethodHandles.lookup:()Ljava/lang/invoke/MethodHandles$Lookup;
          70: astore        8
          72: iconst_0
          73: istore        9
          75: aload         5
          77: arraylength
          78: istore        10
          80: iload         9
          82: iload         10
          84: if_icmpge     168
          87: aload         5
          89: iload         9
          91: aaload
          92: astore        11
          94: aload         7
          96: iload         9
          98: aload         11
         100: invokevirtual #39                 // Method java/lang/reflect/RecordComponent.getType:()Ljava/lang/Class;
         103: aastore
         104: aload_1
         105: aload         4
         107: aload_3
         108: aload         8
         110: aload         11
         112: invokestatic  #45                 // Method createComponentBinding:(Ljava/lang/reflect/Type;Ljava/lang/Class;Lcom/squareup/moshi/Moshi;Ljava/lang/invoke/MethodHandles$Lookup;Ljava/lang/reflect/RecordComponent;)Lcom/squareup/moshi/RecordJsonAdapter$ComponentBinding;
         115: astore        12
         117: aload         6
         119: aload         12
         121: getfield      #51                 // Field com/squareup/moshi/RecordJsonAdapter$ComponentBinding.jsonName:Ljava/lang/String;
         124: aload         12
         126: invokevirtual #57                 // Method java/util/LinkedHashMap.put:(Ljava/lang/Object;Ljava/lang/Object;)Ljava/lang/Object;
         129: checkcast     #52                 // class com/squareup/moshi/RecordJsonAdapter$ComponentBinding
         132: astore        13
         134: aload         13
         136: ifnull        162
         139: new           #61                 // class java/lang/IllegalArgumentException
         142: dup
         143: aload         13
         145: getfield      #63                 // Field com/squareup/moshi/RecordJsonAdapter$ComponentBinding.componentName:Ljava/lang/String;
         148: aload         12
         150: getfield      #63                 // Field com/squareup/moshi/RecordJsonAdapter$ComponentBinding.componentName:Ljava/lang/String;
         153: invokedynamic #66,  0             // InvokeDynamic #0:makeConcatWithConstants:(Ljava/lang/String;Ljava/lang/String;)Ljava/lang/String;
         158: invokespecial #70                 // Method java/lang/IllegalArgumentException."<init>":(Ljava/lang/String;)V
         161: athrow
         162: iinc          9, 1
         165: goto          80
         168: aload         8
         170: aload         4
         172: getstatic     #73                 // Field java/lang/Void.TYPE:Ljava/lang/Class;
         175: aload         7
         177: invokestatic  #79                 // Method java/lang/invoke/MethodType.methodType:(Ljava/lang/Class;[Ljava/lang/Class;)Ljava/lang/invoke/MethodType;
         180: invokevirtual #85                 // Method java/lang/invoke/MethodHandles$Lookup.findConstructor:(Ljava/lang/Class;Ljava/lang/invoke/MethodType;)Ljava/lang/invoke/MethodHandle;
         183: astore        9
         185: goto          200
         188: astore        10
         190: new           #95                 // class java/lang/AssertionError
         193: dup
         194: aload         10
         196: invokespecial #97                 // Method java/lang/AssertionError."<init>":(Ljava/lang/Object;)V
         199: athrow
         200: new           #100                // class com/squareup/moshi/RecordJsonAdapter
         203: dup
         204: aload         9
         206: aload         4
         208: invokevirtual #102                // Method java/lang/Class.getSimpleName:()Ljava/lang/String;
         211: aload         6
         213: invokespecial #106                // Method com/squareup/moshi/RecordJsonAdapter."<init>":(Ljava/lang/invoke/MethodHandle;Ljava/lang/String;Ljava/util/Map;)V
         216: invokevirtual #109                // Method com/squareup/moshi/RecordJsonAdapter.nullSafe:()Lcom/squareup/moshi/JsonAdapter;
         219: areturn
        Exception table:
           from    to  target type
             168   185   188   Class java/lang/NoSuchMethodException
             168   185   188   Class java/lang/IllegalAccessException
  
    private static com.squareup.moshi.RecordJsonAdapter$ComponentBinding<java.lang.Object> createComponentBinding(java.lang.reflect.Type, java.lang.Class<?>, com.squareup.moshi.Moshi, java.lang.invoke.MethodHandles$Lookup, java.lang.reflect.RecordComponent);
      Code:
           0: aload         4
           2: invokevirtual #113                // Method java/lang/reflect/RecordComponent.getName:()Ljava/lang/String;
           5: astore        5
           7: aload         5
           9: aload         4
          11: invokestatic  #116                // Method com/squareup/moshi/internal/Util.jsonName:(Ljava/lang/String;Ljava/lang/reflect/AnnotatedElement;)Ljava/lang/String;
          14: astore        6
          16: aload_0
          17: aload_1
          18: aload         4
          20: invokevirtual #121                // Method java/lang/reflect/RecordComponent.getGenericType:()Ljava/lang/reflect/Type;
          23: invokestatic  #125                // Method com/squareup/moshi/internal/Util.resolve:(Ljava/lang/reflect/Type;Ljava/lang/Class;Ljava/lang/reflect/Type;)Ljava/lang/reflect/Type;
          26: astore        7
          28: aload         4
          30: invokestatic  #129                // Method com/squareup/moshi/internal/Util.jsonAnnotations:(Ljava/lang/reflect/AnnotatedElement;)Ljava/util/Set;
          33: astore        8
          35: aload_2
          36: aload         7
          38: aload         8
          40: invokevirtual #133                // Method com/squareup/moshi/Moshi.adapter:(Ljava/lang/reflect/Type;Ljava/util/Set;)Lcom/squareup/moshi/JsonAdapter;
          43: astore        9
          45: aload_3
          46: aload         4
          48: invokevirtual #139                // Method java/lang/reflect/RecordComponent.getAccessor:()Ljava/lang/reflect/Method;
          51: invokevirtual #143                // Method java/lang/invoke/MethodHandles$Lookup.unreflect:(Ljava/lang/reflect/Method;)Ljava/lang/invoke/MethodHandle;
          54: astore        10
          56: goto          71
          59: astore        11
          61: new           #95                 // class java/lang/AssertionError
[tool-exec] update id=call_iWMNhEU2b9RB7L6vzzebvW4D|fc_0d8c31fa336f7f3d0169f9856d54c481a283a6b2ecf243250e name=bash
  Compiled from "RecordJsonAdapter.java"
  class com.squareup.moshi.RecordJsonAdapter$1 implements com.squareup.moshi.JsonAdapter$Factory {
    com.squareup.moshi.RecordJsonAdapter$1();
      Code:
           0: aload_0
           1: invokespecial #1                  // Method java/lang/Object."<init>":()V
           4: return
  
    public com.squareup.moshi.JsonAdapter<?> create(java.lang.reflect.Type, java.util.Set<? extends java.lang.annotation.Annotation>, com.squareup.moshi.Moshi);
      Code:
           0: aload_2
           1: invokeinterface #7,  1            // InterfaceMethod java/util/Set.isEmpty:()Z
           6: ifne          11
           9: aconst_null
          10: areturn
          11: aload_1
          12: instanceof    #13                 // class java/lang/Class
          15: ifne          27
          18: aload_1
          19: instanceof    #15                 // class java/lang/reflect/ParameterizedType
          22: ifne          27
          25: aconst_null
          26: areturn
          27: aload_1
          28: invokestatic  #17                 // Method com/squareup/moshi/Types.getRawType:(Ljava/lang/reflect/Type;)Ljava/lang/Class;
          31: astore        4
          33: aload         4
          35: invokevirtual #23                 // Method java/lang/Class.isRecord:()Z
          38: ifne          43
          41: aconst_null
          42: areturn
          43: aload         4
          45: invokevirtual #26                 // Method java/lang/Class.getRecordComponents:()[Ljava/lang/reflect/RecordComponent;
          48: astore        5
          50: new           #30                 // class java/util/LinkedHashMap
          53: dup
          54: invokespecial #32                 // Method java/util/LinkedHashMap."<init>":()V
          57: astore        6
          59: aload         5
          61: arraylength
          62: anewarray     #13                 // class java/lang/Class
          65: astore        7
          67: invokestatic  #33                 // Method java/lang/invoke/MethodHandles.lookup:()Ljava/lang/invoke/MethodHandles$Lookup;
          70: astore        8
          72: iconst_0
          73: istore        9
          75: aload         5
          77: arraylength
          78: istore        10
          80: iload         9
          82: iload         10
          84: if_icmpge     168
          87: aload         5
          89: iload         9
          91: aaload
          92: astore        11
          94: aload         7
          96: iload         9
          98: aload         11
         100: invokevirtual #39                 // Method java/lang/reflect/RecordComponent.getType:()Ljava/lang/Class;
         103: aastore
         104: aload_1
         105: aload         4
         107: aload_3
         108: aload         8
         110: aload         11
         112: invokestatic  #45                 // Method createComponentBinding:(Ljava/lang/reflect/Type;Ljava/lang/Class;Lcom/squareup/moshi/Moshi;Ljava/lang/invoke/MethodHandles$Lookup;Ljava/lang/reflect/RecordComponent;)Lcom/squareup/moshi/RecordJsonAdapter$ComponentBinding;
         115: astore        12
         117: aload         6
         119: aload         12
         121: getfield      #51                 // Field com/squareup/moshi/RecordJsonAdapter$ComponentBinding.jsonName:Ljava/lang/String;
         124: aload         12
         126: invokevirtual #57                 // Method java/util/LinkedHashMap.put:(Ljava/lang/Object;Ljava/lang/Object;)Ljava/lang/Object;
         129: checkcast     #52                 // class com/squareup/moshi/RecordJsonAdapter$ComponentBinding
         132: astore        13
         134: aload         13
         136: ifnull        162
         139: new           #61                 // class java/lang/IllegalArgumentException
         142: dup
         143: aload         13
         145: getfield      #63                 // Field com/squareup/moshi/RecordJsonAdapter$ComponentBinding.componentName:Ljava/lang/String;
         148: aload         12
         150: getfield      #63                 // Field com/squareup/moshi/RecordJsonAdapter$ComponentBinding.componentName:Ljava/lang/String;
         153: invokedynamic #66,  0             // InvokeDynamic #0:makeConcatWithConstants:(Ljava/lang/String;Ljava/lang/String;)Ljava/lang/String;
         158: invokespecial #70                 // Method java/lang/IllegalArgumentException."<init>":(Ljava/lang/String;)V
         161: athrow
         162: iinc          9, 1
         165: goto          80
         168: aload         8
         170: aload         4
         172: getstatic     #73                 // Field java/lang/Void.TYPE:Ljava/lang/Class;
         175: aload         7
         177: invokestatic  #79                 // Method java/lang/invoke/MethodType.methodType:(Ljava/lang/Class;[Ljava/lang/Class;)Ljava/lang/invoke/MethodType;
         180: invokevirtual #85                 // Method java/lang/invoke/MethodHandles$Lookup.findConstructor:(Ljava/lang/Class;Ljava/lang/invoke/MethodType;)Ljava/lang/invoke/MethodHandle;
         183: astore        9
         185: goto          200
         188: astore        10
         190: new           #95                 // class java/lang/AssertionError
         193: dup
         194: aload         10
         196: invokespecial #97                 // Method java/lang/AssertionError."<init>":(Ljava/lang/Object;)V
         199: athrow
         200: new           #100                // class com/squareup/moshi/RecordJsonAdapter
         203: dup
         204: aload         9
         206: aload         4
         208: invokevirtual #102                // Method java/lang/Class.getSimpleName:()Ljava/lang/String;
         211: aload         6
         213: invokespecial #106                // Method com/squareup/moshi/RecordJsonAdapter."<init>":(Ljava/lang/invoke/MethodHandle;Ljava/lang/String;Ljava/util/Map;)V
         216: invokevirtual #109                // Method com/squareup/moshi/RecordJsonAdapter.nullSafe:()Lcom/squareup/moshi/JsonAdapter;
         219: areturn
        Exception table:
           from    to  target type
             168   185   188   Class java/lang/NoSuchMethodException
             168   185   188   Class java/lang/IllegalAccessException
  
    private static com.squareup.moshi.RecordJsonAdapter$ComponentBinding<java.lang.Object> createComponentBinding(java.lang.reflect.Type, java.lang.Class<?>, com.squareup.moshi.Moshi, java.lang.invoke.MethodHandles$Lookup, java.lang.reflect.RecordComponent);
      Code:
           0: aload         4
           2: invokevirtual #113                // Method java/lang/reflect/RecordComponent.getName:()Ljava/lang/String;
           5: astore        5
           7: aload         5
           9: aload         4
          11: invokestatic  #116                // Method com/squareup/moshi/internal/Util.jsonName:(Ljava/lang/String;Ljava/lang/reflect/AnnotatedElement;)Ljava/lang/String;
          14: astore        6
          16: aload_0
          17: aload_1
          18: aload         4
          20: invokevirtual #121                // Method java/lang/reflect/RecordComponent.getGenericType:()Ljava/lang/reflect/Type;
          23: invokestatic  #125                // Method com/squareup/moshi/internal/Util.resolve:(Ljava/lang/reflect/Type;Ljava/lang/Class;Ljava/lang/reflect/Type;)Ljava/lang/reflect/Type;
          26: astore        7
          28: aload         4
          30: invokestatic  #129                // Method com/squareup/moshi/internal/Util.jsonAnnotations:(Ljava/lang/reflect/AnnotatedElement;)Ljava/util/Set;
          33: astore        8
          35: aload_2
          36: aload         7
          38: aload         8
          40: invokevirtual #133                // Method com/squareup/moshi/Moshi.adapter:(Ljava/lang/reflect/Type;Ljava/util/Set;)Lcom/squareup/moshi/JsonAdapter;
          43: astore        9
          45: aload_3
          46: aload         4
          48: invokevirtual #139                // Method java/lang/reflect/RecordComponent.getAccessor:()Ljava/lang/reflect/Method;
          51: invokevirtual #143                // Method java/lang/invoke/MethodHandles$Lookup.unreflect:(Ljava/lang/reflect/Method;)Ljava/lang/invoke/MethodHandle;
          54: astore        10
          56: goto          71
          59: astore        11
          61: new           #95                 // class java/lang/AssertionError
          64: dup
          65: aload         11
          67: invokespecial #97                 // Method java/lang/AssertionError."<init>":(Ljava/lang/Object;)V
          70: athrow
          71: new           #52                 // class com/squareup/moshi/RecordJsonAdapter$ComponentBinding
          74: dup
          75: aload         5
          77: aload         6
          79: aload         9
          81: aload         10
          83: invokespecial #147                // Method com/squareup/moshi/RecordJsonAdapter$ComponentBinding."<init>":(Ljava/lang/String;Ljava/lang/String;Lcom/squareup/moshi/JsonAdapter;Ljava/lang/invoke/MethodHandle;)V
          86: areturn
        Exception table:
           from    to  target type
              45    56    59   Class java/lang/IllegalAccessException
  }
[tool-exec] end id=call_iWMNhEU2b9RB7L6vzzebvW4D|fc_0d8c31fa336f7f3d0169f9856d54c481a283a6b2ecf243250e name=bash status=success
  Compiled from "RecordJsonAdapter.java"
  class com.squareup.moshi.RecordJsonAdapter$1 implements com.squareup.moshi.JsonAdapter$Factory {
    com.squareup.moshi.RecordJsonAdapter$1();
      Code:
           0: aload_0
           1: invokespecial #1                  // Method java/lang/Object."<init>":()V
           4: return
  
    public com.squareup.moshi.JsonAdapter<?> create(java.lang.reflect.Type, java.util.Set<? extends java.lang.annotation.Annotation>, com.squareup.moshi.Moshi);
      Code:
           0: aload_2
           1: invokeinterface #7,  1            // InterfaceMethod java/util/Set.isEmpty:()Z
           6: ifne          11
           9: aconst_null
          10: areturn
          11: aload_1
          12: instanceof    #13                 // class java/lang/Class
          15: ifne          27
          18: aload_1
          19: instanceof    #15                 // class java/lang/reflect/ParameterizedType
          22: ifne          27
          25: aconst_null
          26: areturn
          27: aload_1
          28: invokestatic  #17                 // Method com/squareup/moshi/Types.getRawType:(Ljava/lang/reflect/Type;)Ljava/lang/Class;
          31: astore        4
          33: aload         4
          35: invokevirtual #23                 // Method java/lang/Class.isRecord:()Z
          38: ifne          43
          41: aconst_null
          42: areturn
          43: aload         4
          45: invokevirtual #26                 // Method java/lang/Class.getRecordComponents:()[Ljava/lang/reflect/RecordComponent;
          48: astore        5
          50: new           #30                 // class java/util/LinkedHashMap
          53: dup
          54: invokespecial #32                 // Method java/util/LinkedHashMap."<init>":()V
          57: astore        6
          59: aload         5
          61: arraylength
          62: anewarray     #13                 // class java/lang/Class
          65: astore        7
          67: invokestatic  #33                 // Method java/lang/invoke/MethodHandles.lookup:()Ljava/lang/invoke/MethodHandles$Lookup;
          70: astore        8
          72: iconst_0
          73: istore        9
          75: aload         5
          77: arraylength
          78: istore        10
          80: iload         9
          82: iload         10
          84: if_icmpge     168
          87: aload         5
          89: iload         9
          91: aaload
          92: astore        11
          94: aload         7
          96: iload         9
          98: aload         11
         100: invokevirtual #39                 // Method java/lang/reflect/RecordComponent.getType:()Ljava/lang/Class;
         103: aastore
         104: aload_1
         105: aload         4
         107: aload_3
         108: aload         8
         110: aload         11
         112: invokestatic  #45                 // Method createComponentBinding:(Ljava/lang/reflect/Type;Ljava/lang/Class;Lcom/squareup/moshi/Moshi;Ljava/lang/invoke/MethodHandles$Lookup;Ljava/lang/reflect/RecordComponent;)Lcom/squareup/moshi/RecordJsonAdapter$ComponentBinding;
         115: astore        12
         117: aload         6
         119: aload         12
         121: getfield      #51                 // Field com/squareup/moshi/RecordJsonAdapter$ComponentBinding.jsonName:Ljava/lang/String;
         124: aload         12
         126: invokevirtual #57                 // Method java/util/LinkedHashMap.put:(Ljava/lang/Object;Ljava/lang/Object;)Ljava/lang/Object;
         129: checkcast     #52                 // class com/squareup/moshi/RecordJsonAdapter$ComponentBinding
         132: astore        13
         134: aload         13
         136: ifnull        162
         139: new           #61                 // class java/lang/IllegalArgumentException
         142: dup
         143: aload         13
         145: getfield      #63                 // Field com/squareup/moshi/RecordJsonAdapter$ComponentBinding.componentName:Ljava/lang/String;
         148: aload         12
         150: getfield      #63                 // Field com/squareup/moshi/RecordJsonAdapter$ComponentBinding.componentName:Ljava/lang/String;
         153: invokedynamic #66,  0             // InvokeDynamic #0:makeConcatWithConstants:(Ljava/lang/String;Ljava/lang/String;)Ljava/lang/String;
         158: invokespecial #70                 // Method java/lang/IllegalArgumentException."<init>":(Ljava/lang/String;)V
         161: athrow
         162: iinc          9, 1
         165: goto          80
         168: aload         8
         170: aload         4
         172: getstatic     #73                 // Field java/lang/Void.TYPE:Ljava/lang/Class;
         175: aload         7
         177: invokestatic  #79                 // Method java/lang/invoke/MethodType.methodType:(Ljava/lang/Class;[Ljava/lang/Class;)Ljava/lang/invoke/MethodType;
         180: invokevirtual #85                 // Method java/lang/invoke/MethodHandles$Lookup.findConstructor:(Ljava/lang/Class;Ljava/lang/invoke/MethodType;)Ljava/lang/invoke/MethodHandle;
         183: astore        9
         185: goto          200
         188: astore        10
         190: new           #95                 // class java/lang/AssertionError
         193: dup
         194: aload         10
         196: invokespecial #97                 // Method java/lang/AssertionError."<init>":(Ljava/lang/Object;)V
         199: athrow
         200: new           #100                // class com/squareup/moshi/RecordJsonAdapter
         203: dup
         204: aload         9
         206: aload         4
         208: invokevirtual #102                // Method java/lang/Class.getSimpleName:()Ljava/lang/String;
         211: aload         6
         213: invokespecial #106                // Method com/squareup/moshi/RecordJsonAdapter."<init>":(Ljava/lang/invoke/MethodHandle;Ljava/lang/String;Ljava/util/Map;)V
         216: invokevirtual #109                // Method com/squareup/moshi/RecordJsonAdapter.nullSafe:()Lcom/squareup/moshi/JsonAdapter;
         219: areturn
        Exception table:
           from    to  target type
             168   185   188   Class java/lang/NoSuchMethodException
             168   185   188   Class java/lang/IllegalAccessException
  
    private static com.squareup.moshi.RecordJsonAdapter$ComponentBinding<java.lang.Object> createComponentBinding(java.lang.reflect.Type, java.lang.Class<?>, com.squareup.moshi.Moshi, java.lang.invoke.MethodHandles$Lookup, java.lang.reflect.RecordComponent);
      Code:
           0: aload         4
           2: invokevirtual #113                // Method java/lang/reflect/RecordComponent.getName:()Ljava/lang/String;
           5: astore        5
           7: aload         5
           9: aload         4
          11: invokestatic  #116                // Method com/squareup/moshi/internal/Util.jsonName:(Ljava/lang/String;Ljava/lang/reflect/AnnotatedElement;)Ljava/lang/String;
          14: astore        6
          16: aload_0
          17: aload_1
          18: aload         4
          20: invokevirtual #121                // Method java/lang/reflect/RecordComponent.getGenericType:()Ljava/lang/reflect/Type;
          23: invokestatic  #125                // Method com/squareup/moshi/internal/Util.resolve:(Ljava/lang/reflect/Type;Ljava/lang/Class;Ljava/lang/reflect/Type;)Ljava/lang/reflect/Type;
          26: astore        7
          28: aload         4
          30: invokestatic  #129                // Method com/squareup/moshi/internal/Util.jsonAnnotations:(Ljava/lang/reflect/AnnotatedElement;)Ljava/util/Set;
          33: astore        8
          35: aload_2
          36: aload         7
          38: aload         8
          40: invokevirtual #133                // Method com/squareup/moshi/Moshi.adapter:(Ljava/lang/reflect/Type;Ljava/util/Set;)Lcom/squareup/moshi/JsonAdapter;
          43: astore        9
          45: aload_3
          46: aload         4
          48: invokevirtual #139                // Method java/lang/reflect/RecordComponent.getAccessor:()Ljava/lang/reflect/Method;
          51: invokevirtual #143                // Method java/lang/invoke/MethodHandles$Lookup.unreflect:(Ljava/lang/reflect/Method;)Ljava/lang/invoke/MethodHandle;
          54: astore        10
          56: goto          71
          59: astore        11
          61: new           #95                 // class java/lang/AssertionError
          64: dup
          65: aload         11
          67: invokespecial #97                 // Method java/lang/AssertionError."<init>":(Ljava/lang/Object;)V
          70: athrow
          71: new           #52                 // class com/squareup/moshi/RecordJsonAdapter$ComponentBinding
          74: dup
          75: aload         5
          77: aload         6
          79: aload         9
          81: aload         10
          83: invokespecial #147                // Method com/squareup/moshi/RecordJsonAdapter$ComponentBinding."<init>":(Ljava/lang/String;Ljava/lang/String;Lcom/squareup/moshi/JsonAdapter;Ljava/lang/invoke/MethodHandle;)V
          86: areturn
        Exception table:
           from    to  target type
              45    56    59   Class java/lang/IllegalAccessException
  }
[recv] {"type": "message_start", "message": {"role": "toolResult", "toolCallId": "call_iWMNhEU2b9RB7L6vzzebvW4D|fc_0d8c31fa336f7f3d0169f9856d54c481a283a6b2ecf243250e", "toolName": "bash", "content": [{"type": "text", "text": "Compiled from \"RecordJsonAdapter.java\"\nclass com.squareup.moshi.RecordJsonAdapter$1 implements com.squareup.moshi.JsonAdapter$Factory {\n  com.squareup.moshi.RecordJsonAdapter$1();\n    Code:\n         0: aload_0\n         1: invokespecial #1                  // Method java/lang/Object.\"<init>\":()V\n         4: return\n\n  public com.squareup.moshi.JsonAdapter<?> create(java.lang.reflect.Type, java.util.Set<? extends java.lang.annotation.Annotation>, com.squareup.moshi.Moshi);\n    Code:\n         0: aload_2\n         1: invokeinterface #7,  1            // InterfaceMethod java/util/Set.isEmpty:()Z\n         6: ifne          11\n         9: aconst_null\n        10: areturn\n        11: aload_1\n        12: instanceof    #13                 // class java/lang/Class\n        15: ifne          27\n        18: aload_1\n        19: instanceof    #15                 // class java/lang/reflect/ParameterizedType\n        22: ifne          27\n        25: aconst_null\n        26: areturn\n        27: aload_1\n        28: invokestatic  #17                 // Method com/squareup/moshi/Types.getRawType:(Ljava/lang/reflect/Type;)Ljava/lang/Class;\n        31: astore        4\n        33: aload         4\n        35: invokevirtual #23                 // Method java/lang/Class.isRecord:()Z\n        38: ifne          43\n        41: aconst_null\n        42: areturn\n        43: aload         4\n        45: invokevirtual #26                 // Method java/lang/Class.getRecordComponents:()[Ljava/lang/reflect/RecordComponent;\n        48: astore        5\n        50: new           #30                 // class java/util/LinkedHashMap\n        53: dup\n        54: invokespecial #32                 // Method java/util/LinkedHashMap.\"<init>\":()V\n        57: astore        6\n        59: aload         5\n        61: arraylength\n        62: anewarray     #13                 // class java/lang/Class\n        65: astore        7\n        67: invokestatic  #33                 // Method java/lang/invoke/MethodHandles.lookup:()Ljava/lang/invoke/MethodHandles$Lookup;\n        70: astore        8\n        72: iconst_0\n        73: istore        9\n        75: aload         5\n        77: arraylength\n        78: istore        10\n        80: iload         9\n        82: iload         10\n        84: if_icmpge     168\n        87: aload         5\n        89: iload         9\n        91: aaload\n        92: astore        11\n        94: aload         7\n        96: iload         9\n        98: aload         11\n       100: invokevirtual #39                 // Method java/lang/reflect/RecordComponent.getType:()Ljava/lang/Class;\n       103: aastore\n       104: aload_1\n       105: aload         4\n       107: aload_3\n       108: aload         8\n       110: aload         11\n       112: invokestatic  #45                 // Method createComponentBinding:(Ljava/lang/reflect/Type;Ljava/lang/Class;Lcom/squareup/moshi/Moshi;Ljava/lang/invoke/MethodHandles$Lookup;Ljava/lang/reflect/RecordComponent;)Lcom/squareup/moshi/RecordJsonAdapter$ComponentBinding;\n       115: astore        12\n       117: aload         6\n       119: aload         12\n       121: getfield      #51                 // Field com/squareup/moshi/RecordJsonAdapter$ComponentBinding.jsonName:Ljava/lang/String;\n       124: aload         12\n       126: invokevirtual #57                 // Method java/util/LinkedHashMap.put:(Ljava/lang/Object;Ljava/lang/Object;)Ljava/lang/Object;\n       129: checkcast     #52                 // class com/squareup/moshi/RecordJsonAdapter$ComponentBinding\n       132: astore        13\n       134: aload         13\n       136: ifnull        162\n       139: new           #61                 // class java/lang/IllegalArgumentException\n       142: dup\n       143: aload         13\n       145: getfield      #63                 // Field com/squareup/moshi/RecordJsonAdapter$ComponentBinding.componentName:Ljava/lang/String;\n       148: aload         12\n       150: getfield      #63                 // Field com/squareup/moshi/RecordJsonAdapter$ComponentBinding.componentName:Ljava/lang/String;\n       153: invokedynamic #66,  0             // InvokeDynamic #0:makeConcatWithConstants:(Ljava/lang/String;Ljava/lang/String;)Ljava/lang/String;\n       158: invokespecial #70                 // Method java/lang/IllegalArgumentException.\"<init>\":(Ljava/lang/String;)V\n       161: athrow\n       162: iinc          9, 1\n       165: goto          80\n       168: aload         8\n       170: aload         4\n       172: getstatic     #73                 // Field java/lang/Void.TYPE:Ljava/lang/Class;\n       175: aload         7\n       177: invokestatic  #79                 // Method java/lang/invoke/MethodType.methodType:(Ljava/lang/Class;[Ljava/lang/Class;)Ljava/lang/invoke/MethodType;\n       180: invokevirtual #85                 // Method java/lang/invoke/MethodHandles$Lookup.findConstructor:(Ljava/lang/Class;Ljava/lang/invoke/MethodType;)Ljava/lang/invoke/MethodHandle;\n       183: astore        9\n       185: goto          200\n       188: astore        10\n       190: new           #95                 // class java/lang/AssertionError\n       193: dup\n       194: aload         10\n       196: invokespecial #97                 // Method java/lang/AssertionError.\"<init>\":(Ljava/lang/Object;)V\n       199: athrow\n       200: new           #100                // class com/squareup/moshi/RecordJsonAdapter\n       203: dup\n       204: aload         9\n       206: aload         4\n       208: invokevirtual #102                // Method java/lang/Class.getSimpleName:()Ljava/lang/String;\n       211: aload         6\n       213: invokespecial #106                // Method com/squareup/moshi/RecordJsonAdapter.\"<init>\":(Ljava/lang/invoke/MethodHandle;Ljava/lang/String;Ljava/util/Map;)V\n       216: invokevirtual #109                // Method com/squareup/moshi/RecordJsonAdapter.nullSafe:()Lcom/squareup/moshi/JsonAdapter;\n       219: areturn\n      Exception table:\n         from    to  target type\n           168   185   188   Class java/lang/NoSuchMethodException\n           168   185   188   Class java/lang/IllegalAccessException\n\n  private static com.squareup.moshi.RecordJsonAdapter$ComponentBinding<java.lang.Object> createComponentBinding(java.lang.reflect.Type, java.lang.Class<?>, com.squareup.moshi.Moshi, java.lang.invoke.MethodHandles$Lookup, java.lang.reflect.RecordComponent);\n    Code:\n         0: aload         4\n         2: invokevirtual #113                // Method java/lang/reflect/RecordComponent.getName:()Ljava/lang/String;\n         5: astore        5\n         7: aload         5\n         9: aload         4\n        11: invokestatic  #116                // Method com/squareup/moshi/internal/Util.jsonName:(Ljava/lang/String;Ljava/lang/reflect/AnnotatedElement;)Ljava/lang/String;\n        14: astore        6\n        16: aload_0\n        17: aload_1\n        18: aload         4\n        20: invokevirtual #121                // Method java/lang/reflect/RecordComponent.getGenericType:()Ljava/lang/reflect/Type;\n        23: invokestatic  #125                // Method com/squareup/moshi/internal/Util.resolve:(Ljava/lang/reflect/Type;Ljava/lang/Class;Ljava/lang/reflect/Type;)Ljava/lang/reflect/Type;\n        26: astore        7\n        28: aload         4\n        30: invokestatic  #129                // Method com/squareup/moshi/internal/Util.jsonAnnotations:(Ljava/lang/reflect/AnnotatedElement;)Ljava/util/Set;\n        33: astore        8\n        35: aload_2\n        36: aload         7\n        38: aload         8\n        40: invokevirtual #133                // Method com/squareup/moshi/Moshi.adapter:(Ljava/lang/reflect/Type;Ljava/util/Set;)Lcom/squareup/moshi/JsonAdapter;\n        43: astore        9\n        45: aload_3\n        46: aload         4\n        48: invokevirtual #139                // Method java/lang/reflect/RecordComponent.getAccessor:()Ljava/lang/reflect/Method;\n        51: invokevirtual #143                // Method java/lang/invoke/MethodHandles$Lookup.unreflect:(Ljava/lang/reflect/Method;)Ljava/lang/invoke/MethodHandle;\n        54: astore        10\n        56: goto          71\n        59: astore        11\n        61: new           #95                 // class java/lang/AssertionError\n        64: dup\n        65: aload         11\n        67: invokespecial #97                 // Method java/lang/AssertionError.\"<init>\":(Ljava/lang/Object;)V\n        70: athrow\n        71: new           #52                 // class com/squareup/moshi/RecordJsonAdapter$ComponentBinding\n        74: dup\n        75: aload         5\n        77: aload         6\n        79: aload         9\n        81: aload         10\n        83: invokespecial #147                // Method com/squareup/moshi/RecordJsonAdapter$ComponentBinding.\"<init>\":(Ljava/lang/String;Ljava/lang/String;Lcom/squareup/moshi/JsonAdapter;Ljava/lang/invoke/MethodHandle;)V\n        86: areturn\n      Exception table:\n         from    to  target type\n            45    56    59   Class java/lang/IllegalAccessException\n}\n"}], "isError": false, "timestamp": 1777960302562}}
[recv] {"type": "message_end", "message": {"role": "toolResult", "toolCallId": "call_iWMNhEU2b9RB7L6vzzebvW4D|fc_0d8c31fa336f7f3d0169f9856d54c481a283a6b2ecf243250e", "toolName": "bash", "content": [{"type": "text", "text": "Compiled from \"RecordJsonAdapter.java\"\nclass com.squareup.moshi.RecordJsonAdapter$1 implements com.squareup.moshi.JsonAdapter$Factory {\n  com.squareup.moshi.RecordJsonAdapter$1();\n    Code:\n         0: aload_0\n         1: invokespecial #1                  // Method java/lang/Object.\"<init>\":()V\n         4: return\n\n  public com.squareup.moshi.JsonAdapter<?> create(java.lang.reflect.Type, java.util.Set<? extends java.lang.annotation.Annotation>, com.squareup.moshi.Moshi);\n    Code:\n         0: aload_2\n         1: invokeinterface #7,  1            // InterfaceMethod java/util/Set.isEmpty:()Z\n         6: ifne          11\n         9: aconst_null\n        10: areturn\n        11: aload_1\n        12: instanceof    #13                 // class java/lang/Class\n        15: ifne          27\n        18: aload_1\n        19: instanceof    #15                 // class java/lang/reflect/ParameterizedType\n        22: ifne          27\n        25: aconst_null\n        26: areturn\n        27: aload_1\n        28: invokestatic  #17                 // Method com/squareup/moshi/Types.getRawType:(Ljava/lang/reflect/Type;)Ljava/lang/Class;\n        31: astore        4\n        33: aload         4\n        35: invokevirtual #23                 // Method java/lang/Class.isRecord:()Z\n        38: ifne          43\n        41: aconst_null\n        42: areturn\n        43: aload         4\n        45: invokevirtual #26                 // Method java/lang/Class.getRecordComponents:()[Ljava/lang/reflect/RecordComponent;\n        48: astore        5\n        50: new           #30                 // class java/util/LinkedHashMap\n        53: dup\n        54: invokespecial #32                 // Method java/util/LinkedHashMap.\"<init>\":()V\n        57: astore        6\n        59: aload         5\n        61: arraylength\n        62: anewarray     #13                 // class java/lang/Class\n        65: astore        7\n        67: invokestatic  #33                 // Method java/lang/invoke/MethodHandles.lookup:()Ljava/lang/invoke/MethodHandles$Lookup;\n        70: astore        8\n        72: iconst_0\n        73: istore        9\n        75: aload         5\n        77: arraylength\n        78: istore        10\n        80: iload         9\n        82: iload         10\n        84: if_icmpge     168\n        87: aload         5\n        89: iload         9\n        91: aaload\n        92: astore        11\n        94: aload         7\n        96: iload         9\n        98: aload         11\n       100: invokevirtual #39                 // Method java/lang/reflect/RecordComponent.getType:()Ljava/lang/Class;\n       103: aastore\n       104: aload_1\n       105: aload         4\n       107: aload_3\n       108: aload         8\n       110: aload         11\n       112: invokestatic  #45                 // Method createComponentBinding:(Ljava/lang/reflect/Type;Ljava/lang/Class;Lcom/squareup/moshi/Moshi;Ljava/lang/invoke/MethodHandles$Lookup;Ljava/lang/reflect/RecordComponent;)Lcom/squareup/moshi/RecordJsonAdapter$ComponentBinding;\n       115: astore        12\n       117: aload         6\n       119: aload         12\n       121: getfield      #51                 // Field com/squareup/moshi/RecordJsonAdapter$ComponentBinding.jsonName:Ljava/lang/String;\n       124: aload         12\n       126: invokevirtual #57                 // Method java/util/LinkedHashMap.put:(Ljava/lang/Object;Ljava/lang/Object;)Ljava/lang/Object;\n       129: checkcast     #52                 // class com/squareup/moshi/RecordJsonAdapter$ComponentBinding\n       132: astore        13\n       134: aload         13\n       136: ifnull        162\n       139: new           #61                 // class java/lang/IllegalArgumentException\n       142: dup\n       143: aload         13\n       145: getfield      #63                 // Field com/squareup/moshi/RecordJsonAdapter$ComponentBinding.componentName:Ljava/lang/String;\n       148: aload         12\n       150: getfield      #63                 // Field com/squareup/moshi/RecordJsonAdapter$ComponentBinding.componentName:Ljava/lang/String;\n       153: invokedynamic #66,  0             // InvokeDynamic #0:makeConcatWithConstants:(Ljava/lang/String;Ljava/lang/String;)Ljava/lang/String;\n       158: invokespecial #70                 // Method java/lang/IllegalArgumentException.\"<init>\":(Ljava/lang/String;)V\n       161: athrow\n       162: iinc          9, 1\n       165: goto          80\n       168: aload         8\n       170: aload         4\n       172: getstatic     #73                 // Field java/lang/Void.TYPE:Ljava/lang/Class;\n       175: aload         7\n       177: invokestatic  #79                 // Method java/lang/invoke/MethodType.methodType:(Ljava/lang/Class;[Ljava/lang/Class;)Ljava/lang/invoke/MethodType;\n       180: invokevirtual #85                 // Method java/lang/invoke/MethodHandles$Lookup.findConstructor:(Ljava/lang/Class;Ljava/lang/invoke/MethodType;)Ljava/lang/invoke/MethodHandle;\n       183: astore        9\n       185: goto          200\n       188: astore        10\n       190: new           #95                 // class java/lang/AssertionError\n       193: dup\n       194: aload         10\n       196: invokespecial #97                 // Method java/lang/AssertionError.\"<init>\":(Ljava/lang/Object;)V\n       199: athrow\n       200: new           #100                // class com/squareup/moshi/RecordJsonAdapter\n       203: dup\n       204: aload         9\n       206: aload         4\n       208: invokevirtual #102                // Method java/lang/Class.getSimpleName:()Ljava/lang/String;\n       211: aload         6\n       213: invokespecial #106                // Method com/squareup/moshi/RecordJsonAdapter.\"<init>\":(Ljava/lang/invoke/MethodHandle;Ljava/lang/String;Ljava/util/Map;)V\n       216: invokevirtual #109                // Method com/squareup/moshi/RecordJsonAdapter.nullSafe:()Lcom/squareup/moshi/JsonAdapter;\n       219: areturn\n      Exception table:\n         from    to  target type\n           168   185   188   Class java/lang/NoSuchMethodException\n           168   185   188   Class java/lang/IllegalAccessException\n\n  private static com.squareup.moshi.RecordJsonAdapter$ComponentBinding<java.lang.Object> createComponentBinding(java.lang.reflect.Type, java.lang.Class<?>, com.squareup.moshi.Moshi, java.lang.invoke.MethodHandles$Lookup, java.lang.reflect.RecordComponent);\n    Code:\n         0: aload         4\n         2: invokevirtual #113                // Method java/lang/reflect/RecordComponent.getName:()Ljava/lang/String;\n         5: astore        5\n         7: aload         5\n         9: aload         4\n        11: invokestatic  #116                // Method com/squareup/moshi/internal/Util.jsonName:(Ljava/lang/String;Ljava/lang/reflect/AnnotatedElement;)Ljava/lang/String;\n        14: astore        6\n        16: aload_0\n        17: aload_1\n        18: aload         4\n        20: invokevirtual #121                // Method java/lang/reflect/RecordComponent.getGenericType:()Ljava/lang/reflect/Type;\n        23: invokestatic  #125                // Method com/squareup/moshi/internal/Util.resolve:(Ljava/lang/reflect/Type;Ljava/lang/Class;Ljava/lang/reflect/Type;)Ljava/lang/reflect/Type;\n        26: astore        7\n        28: aload         4\n        30: invokestatic  #129                // Method com/squareup/moshi/internal/Util.jsonAnnotations:(Ljava/lang/reflect/AnnotatedElement;)Ljava/util/Set;\n        33: astore        8\n        35: aload_2\n        36: aload         7\n        38: aload         8\n        40: invokevirtual #133                // Method com/squareup/moshi/Moshi.adapter:(Ljava/lang/reflect/Type;Ljava/util/Set;)Lcom/squareup/moshi/JsonAdapter;\n        43: astore        9\n        45: aload_3\n        46: aload         4\n        48: invokevirtual #139                // Method java/lang/reflect/RecordComponent.getAccessor:()Ljava/lang/reflect/Method;\n        51: invokevirtual #143                // Method java/lang/invoke/MethodHandles$Lookup.unreflect:(Ljava/lang/reflect/Method;)Ljava/lang/invoke/MethodHandle;\n        54: astore        10\n        56: goto          71\n        59: astore        11\n        61: new           #95                 // class java/lang/AssertionError\n        64: dup\n        65: aload         11\n        67: invokespecial #97                 // Method java/lang/AssertionError.\"<init>\":(Ljava/lang/Object;)V\n        70: athrow\n        71: new           #52                 // class com/squareup/moshi/RecordJsonAdapter$ComponentBinding\n        74: dup\n        75: aload         5\n        77: aload         6\n        79: aload         9\n        81: aload         10\n        83: invokespecial #147                // Method com/squareup/moshi/RecordJsonAdapter$ComponentBinding.\"<init>\":(Ljava/lang/String;Ljava/lang/String;Lcom/squareup/moshi/JsonAdapter;Ljava/lang/invoke/MethodHandle;)V\n        86: areturn\n      Exception table:\n         from    to  target type\n            45    56    59   Class java/lang/IllegalAccessException\n}\n"}], "isError": false, "timestamp": 1777960302562}}
[recv] {"type": "turn_end", "message": {"role": "assistant", "content": [{"type": "toolCall", "id": "call_iWMNhEU2b9RB7L6vzzebvW4D|fc_0d8c31fa336f7f3d0169f9856d54c481a283a6b2ecf243250e", "name": "bash", "arguments": {"command": "javap -classpath /home/vjovanov/.gradle/caches/modules-2/files-2.1/com.squareup.moshi/moshi/1.15.2/8e9a6b11929c7c162a4ded3bb064cbd514af639a/moshi-1.15.2.jar -c -p --multi-release 16 com.squareup.moshi.RecordJsonAdapter\\$1 | head -200"}}], "api": "openai-responses", "provider": "OCA", "model": "gpt-5.5", "usage": {"input": 294, "output": 109, "cacheRead": 11776, "cacheWrite": 0, "totalTokens": 12179, "cost": {"input": 0, "output": 0, "cacheRead": 0, "cacheWrite": 0, "total": 0}}, "stopReason": "toolUse", "timestamp": 1777960300186, "responseId": "resp_0d8c31fa336f7f3d0169f9856c888081a2a09783e8b957a98f"}, "toolResults": [{"role": "toolResult", "toolCallId": "call_iWMNhEU2b9RB7L6vzzebvW4D|fc_0d8c31fa336f7f3d0169f9856d54c481a283a6b2ecf243250e", "toolName": "bash", "content": [{"type": "text", "text": "Compiled from \"RecordJsonAdapter.java\"\nclass com.squareup.moshi.RecordJsonAdapter$1 implements com.squareup.moshi.JsonAdapter$Factory {\n  com.squareup.moshi.RecordJsonAdapter$1();\n    Code:\n         0: aload_0\n         1: invokespecial #1                  // Method java/lang/Object.\"<init>\":()V\n         4: return\n\n  public com.squareup.moshi.JsonAdapter<?> create(java.lang.reflect.Type, java.util.Set<? extends java.lang.annotation.Annotation>, com.squareup.moshi.Moshi);\n    Code:\n         0: aload_2\n         1: invokeinterface #7,  1            // InterfaceMethod java/util/Set.isEmpty:()Z\n         6: ifne          11\n         9: aconst_null\n        10: areturn\n        11: aload_1\n        12: instanceof    #13                 // class java/lang/Class\n        15: ifne          27\n        18: aload_1\n        19: instanceof    #15                 // class java/lang/reflect/ParameterizedType\n        22: ifne          27\n        25: aconst_null\n        26: areturn\n        27: aload_1\n        28: invokestatic  #17                 // Method com/squareup/moshi/Types.getRawType:(Ljava/lang/reflect/Type;)Ljava/lang/Class;\n        31: astore        4\n        33: aload         4\n        35: invokevirtual #23                 // Method java/lang/Class.isRecord:()Z\n        38: ifne          43\n        41: aconst_null\n        42: areturn\n        43: aload         4\n        45: invokevirtual #26                 // Method java/lang/Class.getRecordComponents:()[Ljava/lang/reflect/RecordComponent;\n        48: astore        5\n        50: new           #30                 // class java/util/LinkedHashMap\n        53: dup\n        54: invokespecial #32                 // Method java/util/LinkedHashMap.\"<init>\":()V\n        57: astore        6\n        59: aload         5\n        61: arraylength\n        62: anewarray     #13                 // class java/lang/Class\n        65: astore        7\n        67: invokestatic  #33                 // Method java/lang/invoke/MethodHandles.lookup:()Ljava/lang/invoke/MethodHandles$Lookup;\n        70: astore        8\n        72: iconst_0\n        73: istore        9\n        75: aload         5\n        77: arraylength\n        78: istore        10\n        80: iload         9\n        82: iload         10\n        84: if_icmpge     168\n        87: aload         5\n        89: iload         9\n        91: aaload\n        92: astore        11\n        94: aload         7\n        96: iload         9\n        98: aload         11\n       100: invokevirtual #39                 // Method java/lang/reflect/RecordComponent.getType:()Ljava/lang/Class;\n       103: aastore\n       104: aload_1\n       105: aload         4\n       107: aload_3\n       108: aload         8\n       110: aload         11\n       112: invokestatic  #45                 // Method createComponentBinding:(Ljava/lang/reflect/Type;Ljava/lang/Class;Lcom/squareup/moshi/Moshi;Ljava/lang/invoke/MethodHandles$Lookup;Ljava/lang/reflect/RecordComponent;)Lcom/squareup/moshi/RecordJsonAdapter$ComponentBinding;\n       115: astore        12\n       117: aload         6\n       119: aload         12\n       121: getfield      #51                 // Field com/squareup/moshi/RecordJsonAdapter$ComponentBinding.jsonName:Ljava/lang/String;\n       124: aload         12\n       126: invokevirtual #57                 // Method java/util/LinkedHashMap.put:(Ljava/lang/Object;Ljava/lang/Object;)Ljava/lang/Object;\n       129: checkcast     #52                 // class com/squareup/moshi/RecordJsonAdapter$ComponentBinding\n       132: astore        13\n       134: aload         13\n       136: ifnull        162\n       139: new           #61                 // class java/lang/IllegalArgumentException\n       142: dup\n       143: aload         13\n       145: getfield      #63                 // Field com/squareup/moshi/RecordJsonAdapter$ComponentBinding.componentName:Ljava/lang/String;\n       148: aload         12\n       150: getfield      #63                 // Field com/squareup/moshi/RecordJsonAdapter$ComponentBinding.componentName:Ljava/lang/String;\n       153: invokedynamic #66,  0             // InvokeDynamic #0:makeConcatWithConstants:(Ljava/lang/String;Ljava/lang/String;)Ljava/lang/String;\n       158: invokespecial #70                 // Method java/lang/IllegalArgumentException.\"<init>\":(Ljava/lang/String;)V\n       161: athrow\n       162: iinc          9, 1\n       165: goto          80\n       168: aload         8\n       170: aload         4\n       172: getstatic     #73                 // Field java/lang/Void.TYPE:Ljava/lang/Class;\n       175: aload         7\n       177: invokestatic  #79                 // Method java/lang/invoke/MethodType.methodType:(Ljava/lang/Class;[Ljava/lang/Class;)Ljava/lang/invoke/MethodType;\n       180: invokevirtual #85                 // Method java/lang/invoke/MethodHandles$Lookup.findConstructor:(Ljava/lang/Class;Ljava/lang/invoke/MethodType;)Ljava/lang/invoke/MethodHandle;\n       183: astore        9\n       185: goto          200\n       188: astore        10\n       190: new           #95                 // class java/lang/AssertionError\n       193: dup\n       194: aload         10\n       196: invokespecial #97                 // Method java/lang/AssertionError.\"<init>\":(Ljava/lang/Object;)V\n       199: athrow\n       200: new           #100                // class com/squareup/moshi/RecordJsonAdapter\n       203: dup\n       204: aload         9\n       206: aload         4\n       208: invokevirtual #102                // Method java/lang/Class.getSimpleName:()Ljava/lang/String;\n       211: aload         6\n       213: invokespecial #106                // Method com/squareup/moshi/RecordJsonAdapter.\"<init>\":(Ljava/lang/invoke/MethodHandle;Ljava/lang/String;Ljava/util/Map;)V\n       216: invokevirtual #109                // Method com/squareup/moshi/RecordJsonAdapter.nullSafe:()Lcom/squareup/moshi/JsonAdapter;\n       219: areturn\n      Exception table:\n         from    to  target type\n           168   185   188   Class java/lang/NoSuchMethodException\n           168   185   188   Class java/lang/IllegalAccessException\n\n  private static com.squareup.moshi.RecordJsonAdapter$ComponentBinding<java.lang.Object> createComponentBinding(java.lang.reflect.Type, java.lang.Class<?>, com.squareup.moshi.Moshi, java.lang.invoke.MethodHandles$Lookup, java.lang.reflect.RecordComponent);\n    Code:\n         0: aload         4\n         2: invokevirtual #113                // Method java/lang/reflect/RecordComponent.getName:()Ljava/lang/String;\n         5: astore        5\n         7: aload         5\n         9: aload         4\n        11: invokestatic  #116                // Method com/squareup/moshi/internal/Util.jsonName:(Ljava/lang/String;Ljava/lang/reflect/AnnotatedElement;)Ljava/lang/String;\n        14: astore        6\n        16: aload_0\n        17: aload_1\n        18: aload         4\n        20: invokevirtual #121                // Method java/lang/reflect/RecordComponent.getGenericType:()Ljava/lang/reflect/Type;\n        23: invokestatic  #125                // Method com/squareup/moshi/internal/Util.resolve:(Ljava/lang/reflect/Type;Ljava/lang/Class;Ljava/lang/reflect/Type;)Ljava/lang/reflect/Type;\n        26: astore        7\n        28: aload         4\n        30: invokestatic  #129                // Method com/squareup/moshi/internal/Util.jsonAnnotations:(Ljava/lang/reflect/AnnotatedElement;)Ljava/util/Set;\n        33: astore        8\n        35: aload_2\n        36: aload         7\n        38: aload         8\n        40: invokevirtual #133                // Method com/squareup/moshi/Moshi.adapter:(Ljava/lang/reflect/Type;Ljava/util/Set;)Lcom/squareup/moshi/JsonAdapter;\n        43: astore        9\n        45: aload_3\n        46: aload         4\n        48: invokevirtual #139                // Method java/lang/reflect/RecordComponent.getAccessor:()Ljava/lang/reflect/Method;\n        51: invokevirtual #143                // Method java/lang/invoke/MethodHandles$Lookup.unreflect:(Ljava/lang/reflect/Method;)Ljava/lang/invoke/MethodHandle;\n        54: astore        10\n        56: goto          71\n        59: astore        11\n        61: new           #95                 // class java/lang/AssertionError\n        64: dup\n        65: aload         11\n        67: invokespecial #97                 // Method java/lang/AssertionError.\"<init>\":(Ljava/lang/Object;)V\n        70: athrow\n        71: new           #52                 // class com/squareup/moshi/RecordJsonAdapter$ComponentBinding\n        74: dup\n        75: aload         5\n        77: aload         6\n        79: aload         9\n        81: aload         10\n        83: invokespecial #147                // Method com/squareup/moshi/RecordJsonAdapter$ComponentBinding.\"<init>\":(Ljava/lang/String;Ljava/lang/String;Lcom/squareup/moshi/JsonAdapter;Ljava/lang/invoke/MethodHandle;)V\n        86: areturn\n      Exception table:\n         from    to  target type\n            45    56    59   Class java/lang/IllegalAccessException\n}\n"}], "isError": false, "timestamp": 1777960302562}]}
[recv] {"type": "turn_start"}
[recv] {"type": "message_start", "message": {"role": "assistant", "content": [], "api": "openai-responses", "provider": "OCA", "model": "gpt-5.5", "usage": {"input": 0, "output": 0, "cacheRead": 0, "cacheWrite": 0, "totalTokens": 0, "cost": {"input": 0, "output": 0, "cacheRead": 0, "cacheWrite": 0, "total": 0}}, "stopReason": "stop", "timestamp": 1777960302566}}
[assistant-event] thinking_start
[thinking] **Considering test settings**
[thinking] 
[thinking] I see the test has a record type in the code, which means there's no manual configuration needed. The agent will capture everything, which is a good sign. I might want to ensure any existing resources under the native-image are respected and not modified or ignored. It seems like I need to create a file as part of this process. Let's get that sorted!
[thinking] 
[assistant-event] thinking_end
[tool-call] start id=unknown
[tool-call] delta {"path":"tests/src/com.squareup.moshi/moshi/1.15.2/src/test/kotlin/com_squareup_moshi/moshi/RecordJsonAdapterAnonymous1Test.kt","content":"/*\n * Copyright and related rights waived via CC0\n *\n * You should have received a copy of the CC0 legalcode along with this\n * work. If not, see <http://creativecommons.org/publicdomain/zero/1.0/>.\n */\npackage com_squareup_moshi.moshi\n\nimport com.squareup.moshi.JsonAdapter\nimport com.squareup.moshi.Moshi\nimport org.assertj.core.api.Assertions.assertThat\nimport org.junit.jupiter.api.Test\n\npublic class RecordJsonAdapterAnonymous1Test {\n    @Test\n    fun adapterCreatesRecordFromJsonObject(): Unit {\n        val moshi: Moshi = Moshi.Builder().build()\n        val adapter: JsonAdapter<PersonRecord> = moshi.adapter(PersonRecord::class.java)\n\n        val person: PersonRecord? = adapter.fromJson(\"\"\"{\"name\":\"Ada\",\"age\":37}\"\"\")\n\n        assertThat(person).isEqualTo(PersonRecord(\"Ada\", 37))\n        assertThat(adapter.toJson(PersonRecord(\"Grace\", 85)))\n            .isEqualTo(\"\"\"{\"name\":\"Grace\",\"age\":85}\"\"\")\n    }\n}\n\n@JvmRecord\npublic data class PersonRecord(\n    public val name: String,\n    public val age: Int,\n)\n"}
[tool-call] end id=call_fqnazD8QUfofmLR7f40P4C69|fc_0d8c31fa336f7f3d0169f9857bccb481a283cef7d5f3b46814 name=write args={"path": "tests/src/com.squareup.moshi/moshi/1.15.2/src/test/kotlin/com_squareup_moshi/moshi/RecordJsonAdapterAnonymous1Test.kt", "content": "/*\n * Copyright and related rights waived via CC0\n *\n * You should have received a copy of the CC0 legalcode along with this\n * work. If not, see <http://creativecommons.org/publicdomain/zero/1.0/>.\n */\npackage com_squareup_moshi.moshi\n\nimport com.squareup.moshi.JsonAdapter\nimport com.squareup.moshi.Moshi\nimport org.assertj.core.api.Assertions.assertThat\nimport org.junit.jupiter.api.Test\n\npublic class RecordJsonAdapterAnonymous1Test {\n    @Test\n    fun adapterCreatesRecordFromJsonObject(): Unit {\n        val moshi: Moshi = Moshi.Builder().build()\n        val adapter: JsonAdapter<PersonRecord> = moshi.adapter(PersonRecord::class.java)\n\n        val person: PersonRecord? = adapter.fromJson(\"\"\"{\"name\":\"Ada\",\"age\":37}\"\"\")\n\n        assertThat(person).isEqualTo(PersonRecord(\"Ada\", 37))\n        assertThat(adapter.toJson(PersonRecord(\"Grace\", 85)))\n            .isEqualTo(\"\"\"{\"name\":\"Grace\",\"age\":85}\"\"\")\n    }\n}\n\n@JvmRecord\npublic data class PersonRecord(\n    public val name: String,\n    public val age: Int,\n)\n"}
[recv] {"type": "message_end", "message": {"role": "assistant", "content": [{"type": "thinking", "thinking": "**Considering test settings**\n\nI see the test has a record type in the code, which means there's no manual configuration needed. The agent will capture everything, which is a good sign. I might want to ensure any existing resources under the native-image are respected and not modified or ignored. It seems like I need to create a file as part of this process. Let's get that sorted!", "thinkingSignature": "{\"id\":\"rs_0d8c31fa336f7f3d0169f98570115c81a2be26fe84207636e8\",\"type\":\"reasoning\",\"encrypted_content\":\"gAAAAABp-YV71OsIlfrjsECtqxghK3hfqsL9VW-Igf9ggPY0NMb2VxvGpdjjn3r6ovGLWGesgp7bGyAVdquoQtf_xj9-UhVY9T9cCc3X9DgDSP14Efrm_Ijy_OjsN0Dw9n29Yi2ESkEFMDZd3a8ehYpK5FZaxeiDOdvTm4JO3qXKgCYidhzWrjW7MECIXKHbYUoBP_YtDyJLY4Qe_zXyGm1P8yUgL3Twfnn29yV-EDmGX4QRdPqMYYeqQSkN0ZTcqzBwHpEkSyVCNlaefsmYJrC6jEGegMISkXOZIolBkJGBMfviLIAmF_rBLCkt2KBXZcZ_owO08tE0TrCyZt7QrUtaeZfuqQJVRbAJ_vAWynK0wwOIoJVJr4O4qFzM6TKw4jvcW3ivPJcAkbGpJyLffGRmq4mVUVJMrrdnu6iu1gWKjXPGvwLDDjC1n9Acleh9AGeP6YJXvgtJwlI1LuQTEzxah7UmhnD-72cdo-b_jEzY-5Rou_u1rNgqKmR_TWAHErM32p89CFjWkuUDcAI6kinrm8ZSTVb_8rI-ruB-3nUgfHvSYXUCvRS1FhkB0TwmeUYsHCjPivMHkT-iyMYBoUECAmybXX7xN-_dlR9MbGbs-_1fOJUD9DxWCOepA59yi-xjhKsQ-DTnLd3K-mKM3fTszYE7N0RfWVYvgLZaNCrL2StKQxbV7aRcH5khbzAQTqqeIWLznH7ghCE-RwOsL7jr6uRmiQAaCSUgg-qNyFt0-yA7h68wGR43AmdvZsoF715ivBVyUFdjq5E_mmV_iH1dSiqcr8MwHWxTPXAK5YriRp_6y21VU4sianoc_9zxneAkuAQRGPR_2gCA_nIJwaEhe_HXVTuEyM61RoX9zXeTFIxFUZpBEQSlqFGbNoMvW7swvPscdy8Jdh9Zr3CmPYrnfRj-bVdADWD94Eq138Men5MSD3jr2mMMLe-9SDcxFKcKgGz2QnDsItYMg5qofjUzvy8UW3lQvhytTqH_YwG6Wvt7H9woyyjdhYKFLy4DouhNKvP2Hksm8z7i_8sgs6bXH31YeVe0T2leXH_B4zAR6yQC4wsBtM3btWGw8lAJuaNPxseloVXYNZSNZXI-HVXF70LNOq62jIAxeW7b37w4M9AxZ761Sjy_gA0RjuIkRfTSkKvwNrNDuIXkNOj0LDF2JQrS2ipdeoUAtUMHStsv0uFB4ms4JmUqmP2Z8_Vm5MFFAt_CMs_BXrlTz3ZJ1Nq1uF9U1vcmkfgLO8sIvH3DP6NdRgwHOpBQPiaHGnFcUEgltwP5Ro7U-QH7Eva7a5Yffs7a_emfVEgL72biONmvxchl997mYqEirJTqQmqIytqtO03C6Iq0tdJ5Dv7mWC0u3B-HvWK0IrDrU5xbNgbrDuYYDz_wGGu6uZePw5n0Q4AKUkqf8rvfGnn4mxSUr8AS6qZrhfLUoVcHnDFYZoQIvnnqqGkrUFHWXO9ObWno27Tl5JlE6gcbiR9Wj2XXVf7asuVoyQCaHEjVmB2YBDy_vndrVgH-3gjof7q8uPval_G2cILMJtvslPx86I8XhfibPkTWPk1yJMtJkYOhmdagjWVwwMkehkA7qtRO1rHMM5tw6e3mTDoixp4PzO3cfQD_KoM5Lu4jhSHvvpPM2ZAGOYCKLCvUbVRMefsYcwzAFPRgU7F21BbHF3Eo8djJdYGUW4p6akDBnIFbbKomXLa06Z3WJ8F8c9AHBZMsNnP3vrvgmGlJZjY4c1dpwbKer2t3J_iOE9X1tTsHWhJXwCL9DemTJYWod_jG1vyMg9cLC08eEcMaUpPWoEzSA78ZLj3KdCkY6pTIicWJYWHeFXr2Wa9A6Zf7vkJRp2FtrXh6vn6tQDvkulyFEfBMFXJP1XvHp-xw1blKAKQk8Rd8wEIDKHwOLcWMuo86ZPHjMqIJySkxEqWtlbeO2I6gxCoXoQ05Lss4shWSXh4xtWK9urUHLLlztWItCQ-ZuqYJDuo2H1zCQH46b4FukNwrby-5oc11CnGraryJqE5HW8BBtrfXeY9gzMCT61HfsZnDdiKRxv_z_r-eX0fyeBDOc_5vJJN3st5SJZfsMkH1Am6R3o42VAmKLvqFbb1V36LOqd8scaS00Y1noqGH5NR1XD6m_G1mOWXT4ufJKvbornmN18egyn60aGHRxnuKpYBgo0RWqeZN_kTymfghZKsJaxWFIPfbldQbRzayKeFJ6s-Z6gZFA2cjokiMp6tBINrNSfM8sIX9_yoMnKyCUvmXCGdxwOVf07CxAxgUenDhGLsTzLKZzcuCAyh84vSes_FsNg8afnnLJJ5g0PODgAb75RA7Sx-JgGwlM80-VvAH3MpG1EpL14EKcYRieO1g7perZnya4fuk-mF4ZCrviPgiQV4DZNqh8xHUVAiEClEjhWDXpKNSdgRjk6EI96iESXRapmyVC9h31OnpKJRvlWzSyEuTI7gUkip0TLwxVFqpUlC-uARwXoX1uZ5nNhiIACffy1Yorov2o_NjmD7ENNPfxkMqNTuT4PrHwFvS5EEK-AJ9e3NF2762kLze0_Md87MbFGFI5o2vcSJxbBQSzT47N2o4wdtDgo8jizD8rq61Zy9QVbUKof9984wrUkIGl6PfVmUUyzNbYukt4t5zRjN5g9s6isYtAfhtUqExEGLH68XFm3LHZuKZEoGOUjK0C97Pr1B9MUFOhk_3jGl9zb5kg-Sh4v-1HzO2QkDIObvmY6pYmLZCQo2AmLViiKD3XdqBr8GloZJhnnApOAaRbBXXjbuOMgnfzykT7mBAd9xbjsfbIQCHdORVr80uW15014SzDYsVsKGveNRacywwiL_uMe8EItSqdvgwmOmfpslB2x3sLPRVPdVSQjR_VEU-7MjFn-FiXN4uhK23J9j4gGtxO-ymtakjTCFXUWtvn9b-eqlAT85NqvCk9jRVW4D34Iy1pAHiYRSzzmZhr3tPHH-z34fplGirH71DzROvDxqEefti33Oc5ySbNmkqtctmZM0BkC_ne5OCbLwDUMsTTHnYjYi_Kaf2qp8s3QXnEJaghAlfyQkyM49FOzgAkRtwrurrkQSlHHATgmzBVgYqvLYg4nHvoj46QRERlVON2sE99PkThtmpE9a_f-9jdp0eUfPF899E7Zosm_M1niQ_AFajNazVLaF_qzRyH5lFrx1_jo3cYiiWFE2CmEyK-mXko5k480c3j_KpGBDtRu2oA4FGYMnn-oplXO29aEimzz67-zit6EkSCDwZv-uwg_ZQDYKT9-jEp0zl8PSDoSoAZt9-wKSPke48breoPw2i524MwqjqSYwtxQ0a90nFP59hcqk2jg67-iXt9QoF1Yi-1RqqHAW7buAiGAcf0UEfIUWEnIuB3Kcfz-hGtiAjX-2zH4zcTRxIQAWMkRmKQ9siKW5UwLzwY23gEfjtdtQrwwXVY7hndKblel7izJWnfmH1nnOuAOpsmobTGZc2dFQT6KqDcXqFKAIxhB7QgwBWzfOOA5X30vDX6M7uTfMDFYcjVjLJxU7iUQ-UnI73MSLy5ELRzETA8UnwpvzVoF3cHL1IOn-XfhKSXo7QpCDHsMe3rsnhdsC_axWlfS8Y6bauVk2gzTbU-fwEzPnqinGm8MSw29rbmr0ERYc5pciJ89pW7fsbCdCeu0cvzb20IPKu2nt9tM2ftWaCtO946MHarGbA9BR-xCG6fOrhY5wQn6hT3MTt8P8AZf-pN49ZDHhiZIGPCvIaHxFKElvsPX7feXxL5V21Eve2iYSI4Zi0J6s8Xscd6QzV_VBgAm6-KlHrCJXQEZ--fpSBGMyNl5QNxP519FtwkCc6TnNkFVi1CyoXo1guTBolP7Yf1411HnhN9_lIGnHpBVTRa49ExjwYU6628xenCc2Ye63S657hRMH2owWLMoj39jt1Hxv6hoJU0g8jC0FxqRe0Zno2o5tN-_G3IvjZz90-U1Heu0FcRlTbU8w0N8GQyaEz3TeDgcN9G_6C9kqXeQ691pcu8socip2KKj_jzgyv-j3rOyw4SRdkZm5TTw9IhUHUdbYDWwd7muBFbFFUkg0h_YQd0g_uzmOzg_zo828nUYwe93fTp3Fww14CkepbBM2pd6Hx-viDkupt87dmBI8AFVMIFI13Ff3tcoKYB6nxjTcLcd14Zrd5lTtvrWVZAmurHizql2AZ-952wl4Pst7FJHxu_PMqIHAU9MlQzK1Pe52afb1sOnndKsXKBqPf--7f_IKC31W9BEEnVJpwEVyof__wNsmnZ0h6gBvroi23khMCEbxuVL435GNDbeEFamTFnjbwgHRB1X_ttLWewGIW6UNj30ZP7kNYC_h8j8-iReVDWOcETY3fdf73owzuHZDXXm2OKtvHq3j2g1D--hLMD5MTb6XyDaDYH02BQcCytlP9jz9zJNWX_eSSI_V6Vlj862puYlNnNjTaaq5p9X5FLuHni0amOYU5_83CyzdA9lzXOy0g2t4tqnwe77KqKFdNq-uL0BkSJzRJAFne32WEZ2KY6cGV0i4i3S1s3ZIGEQCL4-SjgohQuQwDipHYNbAejvMlLheqGnykvTLdsPCQqdFwYqHxEK87Ijd_ACJ6cmpeWG3t4cCxmjCMIfDX4FXevMerbJZA3YjYMmz59buXdmLmVsuk9w4SaLCMxRB-5QYVzQxI-x35RS5o3hyVADC7181KjCrCqfdR0IgIxg6U3oDofshEDIpMOaLtuM2A8WKx94VGBPAtX3GnOpmRvMizxDwG3jrFGKLxa5kaFvdGstygCU05qgUNnYIOeKcqG8T7yLKXvBFD5FEkvlYPVVObmCLrysgu3lTwG34SU7mZruIcr3jAi1QWvh-aYtFm3iKZq11FnBTzrgpmklbKadNaTnJRV3nwxk1FhaWBpwiDgd983FB0MlcTBIDm46FROa9t5247eQEofR_9MGMtBReuDucCK0ooLpCqAEVhemWnYJPs6GNQ3mW6E4Mzc4T8Um1uF0A6G-SzREOVczPBf0sRbe_2rHHmifFwLPLQx2FX7zEVJR5TgUtdtd8YQLhKP8VfpiAFeiANDAJQo1yVXMx6dfItfnqqBdTcwfs3IfHq_kUYcEpcSj7M3E2olEM_7Lo4d2uqK49wEA0QoUDK_iy4Vxl2VlONrdU29l0jtX079wS3WR6m6sySRySmugpEk-4_spxJBRSRaKt_sS7zmuK-TBnKzTicEJvo0PA2pACiZ_Q-XPZ7PVzzwMwMXFhrQ_bSAIGhzGaAfB3MWk3IZB5fOWR3MJMUKv9i_-9gjp4iIy7PqpdSXPRuN5nrayQp3lgLACkJF1JRZEHOUKurLIYYtKoAwCzT0HQVwbAvdF7sYpr70vb-sVHmGqCFch2R2BVOrQzL-bkq6zjW6tr10k7S_gXDpR2OMIkCLpb7U5bYZVQSDCWID5RPISS0NjWReZojhPAm8FAKS9fnl9f9wv-wT5ShmoznAh4rOOjKwzS5WgFXzNJ3DeYQQu9-mPfx6q1Jhn1pclZ0ofltuVgbue1aTiDPJNT6jFLZb0rxvkSKEAdfejMetBfz_LHTJ7Dk_N6YVnxuwkTKYlsI0NAnQjUp20Ehnvh_wRVpfm8_8wo-BAgQMJlzraNNQnllDZvCs-nRE8MMoOAacfIoaFe7HrG1msZ3IOW63UeHLDbB7B-EXmfNxHFXnQWlEwOKoJkBad6rzXwNdPN83XlrLtPnpP47L-oSHqqebG6QZLxZYILP9F_FR86HnY6hB0ncT_xOOHBo1cvICXK5lXjsMqDnMlC-EE5KW9lFbs_WPe9_nLXBIySqV5FHYS2Ig5zP8u2obpaKj68Kek_cLRvPlW18Xn21vz4V1eUD0V2v5cFg34lde6uvBlKRCe7WUzDnZZto1xh9JOWEs6FwKh6mU6da3u-25807gG2pzq5VDSyqcL-kZGt4BoHl8eoWy0j8JMvQbeTKGIQwrSoOStODvEFm3gFCnuNj2NSF3Xky9o-sqj8axUkjwb-xUmwckTvsrbYLIyIfgZq-koFbPcWpZDuZQuxtF0XZbEk_oMh4FSG3UZ0nvTe4B5cHiO6oWobUhaVJMxfoYJXywIiCn3AN6JQ8QDJpZzTB8Nusmx-xOeXHFBGspPyTrcxd13x6kjOxRpEz3FiTTpH6fMggaGcDMIRfmkxCtrGVSNTsxXOBOsfVb9Tnf1mylvXigUAAWbuGV-ChWq6xOVieci6hu_jh-eKax_xUSEnwzUk8GPQZxSgkC-HjoNaluxa23gEjo18W1jWl_L1ebLXnnC0qE3H5LN6ZWNINOYWDyooErPVMeHvUo-N1cmhOUf_DtKK0RXX_oJE4gEgOtjvhfpnu2t11jAKWrJZLAqiWIgIp\",\"summary\":[{\"type\":\"summary_text\",\"text\":\"**Considering test settings**\\n\\nI see the test has a record type in the code, which means there's no manual configuration needed. The agent will capture everything, which is a good sign. I might want to ensure any existing resources under the native-image are respected and not modified or ignored. It seems like I need to create a file as part of this process. Let's get that sorted!\"}]}"}, {"type": "toolCall", "id": "call_fqnazD8QUfofmLR7f40P4C69|fc_0d8c31fa336f7f3d0169f9857bccb481a283cef7d5f3b46814", "name": "write", "arguments": {"path": "tests/src/com.squareup.moshi/moshi/1.15.2/src/test/kotlin/com_squareup_moshi/moshi/RecordJsonAdapterAnonymous1Test.kt", "content": "/*\n * Copyright and related rights waived via CC0\n *\n * You should have received a copy of the CC0 legalcode along with this\n * work. If not, see <http://creativecommons.org/publicdomain/zero/1.0/>.\n */\npackage com_squareup_moshi.moshi\n\nimport com.squareup.moshi.JsonAdapter\nimport com.squareup.moshi.Moshi\nimport org.assertj.core.api.Assertions.assertThat\nimport org.junit.jupiter.api.Test\n\npublic class RecordJsonAdapterAnonymous1Test {\n    @Test\n    fun adapterCreatesRecordFromJsonObject(): Unit {\n        val moshi: Moshi = Moshi.Builder().build()\n        val adapter: JsonAdapter<PersonRecord> = moshi.adapter(PersonRecord::class.java)\n\n        val person: PersonRecord? = adapter.fromJson(\"\"\"{\"name\":\"Ada\",\"age\":37}\"\"\")\n\n        assertThat(person).isEqualTo(PersonRecord(\"Ada\", 37))\n        assertThat(adapter.toJson(PersonRecord(\"Grace\", 85)))\n            .isEqualTo(\"\"\"{\"name\":\"Grace\",\"age\":85}\"\"\")\n    }\n}\n\n@JvmRecord\npublic data class PersonRecord(\n    public val name: String,\n    public val age: Int,\n)\n"}}], "api": "openai-responses", "provider": "OCA", "model": "gpt-5.5", "usage": {"input": 2776, "output": 1090, "cacheRead": 11776, "cacheWrite": 0, "totalTokens": 15642, "cost": {"input": 0, "output": 0, "cacheRead": 0, "cacheWrite": 0, "total": 0}}, "stopReason": "toolUse", "timestamp": 1777960302566, "responseId": "resp_0d8c31fa336f7f3d0169f9856f017881a2af24984da9bd466a"}}
[tool-exec] start id=call_fqnazD8QUfofmLR7f40P4C69|fc_0d8c31fa336f7f3d0169f9857bccb481a283cef7d5f3b46814 name=write args={"path": "tests/src/com.squareup.moshi/moshi/1.15.2/src/test/kotlin/com_squareup_moshi/moshi/RecordJsonAdapterAnonymous1Test.kt", "content": "/*\n * Copyright and related rights waived via CC0\n *\n * You should have received a copy of the CC0 legalcode along with this\n * work. If not, see <http://creativecommons.org/publicdomain/zero/1.0/>.\n */\npackage com_squareup_moshi.moshi\n\nimport com.squareup.moshi.JsonAdapter\nimport com.squareup.moshi.Moshi\nimport org.assertj.core.api.Assertions.assertThat\nimport org.junit.jupiter.api.Test\n\npublic class RecordJsonAdapterAnonymous1Test {\n    @Test\n    fun adapterCreatesRecordFromJsonObject(): Unit {\n        val moshi: Moshi = Moshi.Builder().build()\n        val adapter: JsonAdapter<PersonRecord> = moshi.adapter(PersonRecord::class.java)\n\n        val person: PersonRecord? = adapter.fromJson(\"\"\"{\"name\":\"Ada\",\"age\":37}\"\"\")\n\n        assertThat(person).isEqualTo(PersonRecord(\"Ada\", 37))\n        assertThat(adapter.toJson(PersonRecord(\"Grace\", 85)))\n            .isEqualTo(\"\"\"{\"name\":\"Grace\",\"age\":85}\"\"\")\n    }\n}\n\n@JvmRecord\npublic data class PersonRecord(\n    public val name: String,\n    public val age: Int,\n)\n"}
[tool-exec] end id=call_fqnazD8QUfofmLR7f40P4C69|fc_0d8c31fa336f7f3d0169f9857bccb481a283cef7d5f3b46814 name=write status=success
  Successfully wrote 1016 bytes to tests/src/com.squareup.moshi/moshi/1.15.2/src/test/kotlin/com_squareup_moshi/moshi/RecordJsonAdapterAnonymous1Test.kt
[recv] {"type": "message_start", "message": {"role": "toolResult", "toolCallId": "call_fqnazD8QUfofmLR7f40P4C69|fc_0d8c31fa336f7f3d0169f9857bccb481a283cef7d5f3b46814", "toolName": "write", "content": [{"type": "text", "text": "Successfully wrote 1016 bytes to tests/src/com.squareup.moshi/moshi/1.15.2/src/test/kotlin/com_squareup_moshi/moshi/RecordJsonAdapterAnonymous1Test.kt"}], "isError": false, "timestamp": 1777960319817}}
[recv] {"type": "message_end", "message": {"role": "toolResult", "toolCallId": "call_fqnazD8QUfofmLR7f40P4C69|fc_0d8c31fa336f7f3d0169f9857bccb481a283cef7d5f3b46814", "toolName": "write", "content": [{"type": "text", "text": "Successfully wrote 1016 bytes to tests/src/com.squareup.moshi/moshi/1.15.2/src/test/kotlin/com_squareup_moshi/moshi/RecordJsonAdapterAnonymous1Test.kt"}], "isError": false, "timestamp": 1777960319817}}
[recv] {"type": "turn_end", "message": {"role": "assistant", "content": [{"type": "thinking", "thinking": "**Considering test settings**\n\nI see the test has a record type in the code, which means there's no manual configuration needed. The agent will capture everything, which is a good sign. I might want to ensure any existing resources under the native-image are respected and not modified or ignored. It seems like I need to create a file as part of this process. Let's get that sorted!", "thinkingSignature": "{\"id\":\"rs_0d8c31fa336f7f3d0169f98570115c81a2be26fe84207636e8\",\"type\":\"reasoning\",\"encrypted_content\":\"gAAAAABp-YV71OsIlfrjsECtqxghK3hfqsL9VW-Igf9ggPY0NMb2VxvGpdjjn3r6ovGLWGesgp7bGyAVdquoQtf_xj9-UhVY9T9cCc3X9DgDSP14Efrm_Ijy_OjsN0Dw9n29Yi2ESkEFMDZd3a8ehYpK5FZaxeiDOdvTm4JO3qXKgCYidhzWrjW7MECIXKHbYUoBP_YtDyJLY4Qe_zXyGm1P8yUgL3Twfnn29yV-EDmGX4QRdPqMYYeqQSkN0ZTcqzBwHpEkSyVCNlaefsmYJrC6jEGegMISkXOZIolBkJGBMfviLIAmF_rBLCkt2KBXZcZ_owO08tE0TrCyZt7QrUtaeZfuqQJVRbAJ_vAWynK0wwOIoJVJr4O4qFzM6TKw4jvcW3ivPJcAkbGpJyLffGRmq4mVUVJMrrdnu6iu1gWKjXPGvwLDDjC1n9Acleh9AGeP6YJXvgtJwlI1LuQTEzxah7UmhnD-72cdo-b_jEzY-5Rou_u1rNgqKmR_TWAHErM32p89CFjWkuUDcAI6kinrm8ZSTVb_8rI-ruB-3nUgfHvSYXUCvRS1FhkB0TwmeUYsHCjPivMHkT-iyMYBoUECAmybXX7xN-_dlR9MbGbs-_1fOJUD9DxWCOepA59yi-xjhKsQ-DTnLd3K-mKM3fTszYE7N0RfWVYvgLZaNCrL2StKQxbV7aRcH5khbzAQTqqeIWLznH7ghCE-RwOsL7jr6uRmiQAaCSUgg-qNyFt0-yA7h68wGR43AmdvZsoF715ivBVyUFdjq5E_mmV_iH1dSiqcr8MwHWxTPXAK5YriRp_6y21VU4sianoc_9zxneAkuAQRGPR_2gCA_nIJwaEhe_HXVTuEyM61RoX9zXeTFIxFUZpBEQSlqFGbNoMvW7swvPscdy8Jdh9Zr3CmPYrnfRj-bVdADWD94Eq138Men5MSD3jr2mMMLe-9SDcxFKcKgGz2QnDsItYMg5qofjUzvy8UW3lQvhytTqH_YwG6Wvt7H9woyyjdhYKFLy4DouhNKvP2Hksm8z7i_8sgs6bXH31YeVe0T2leXH_B4zAR6yQC4wsBtM3btWGw8lAJuaNPxseloVXYNZSNZXI-HVXF70LNOq62jIAxeW7b37w4M9AxZ761Sjy_gA0RjuIkRfTSkKvwNrNDuIXkNOj0LDF2JQrS2ipdeoUAtUMHStsv0uFB4ms4JmUqmP2Z8_Vm5MFFAt_CMs_BXrlTz3ZJ1Nq1uF9U1vcmkfgLO8sIvH3DP6NdRgwHOpBQPiaHGnFcUEgltwP5Ro7U-QH7Eva7a5Yffs7a_emfVEgL72biONmvxchl997mYqEirJTqQmqIytqtO03C6Iq0tdJ5Dv7mWC0u3B-HvWK0IrDrU5xbNgbrDuYYDz_wGGu6uZePw5n0Q4AKUkqf8rvfGnn4mxSUr8AS6qZrhfLUoVcHnDFYZoQIvnnqqGkrUFHWXO9ObWno27Tl5JlE6gcbiR9Wj2XXVf7asuVoyQCaHEjVmB2YBDy_vndrVgH-3gjof7q8uPval_G2cILMJtvslPx86I8XhfibPkTWPk1yJMtJkYOhmdagjWVwwMkehkA7qtRO1rHMM5tw6e3mTDoixp4PzO3cfQD_KoM5Lu4jhSHvvpPM2ZAGOYCKLCvUbVRMefsYcwzAFPRgU7F21BbHF3Eo8djJdYGUW4p6akDBnIFbbKomXLa06Z3WJ8F8c9AHBZMsNnP3vrvgmGlJZjY4c1dpwbKer2t3J_iOE9X1tTsHWhJXwCL9DemTJYWod_jG1vyMg9cLC08eEcMaUpPWoEzSA78ZLj3KdCkY6pTIicWJYWHeFXr2Wa9A6Zf7vkJRp2FtrXh6vn6tQDvkulyFEfBMFXJP1XvHp-xw1blKAKQk8Rd8wEIDKHwOLcWMuo86ZPHjMqIJySkxEqWtlbeO2I6gxCoXoQ05Lss4shWSXh4xtWK9urUHLLlztWItCQ-ZuqYJDuo2H1zCQH46b4FukNwrby-5oc11CnGraryJqE5HW8BBtrfXeY9gzMCT61HfsZnDdiKRxv_z_r-eX0fyeBDOc_5vJJN3st5SJZfsMkH1Am6R3o42VAmKLvqFbb1V36LOqd8scaS00Y1noqGH5NR1XD6m_G1mOWXT4ufJKvbornmN18egyn60aGHRxnuKpYBgo0RWqeZN_kTymfghZKsJaxWFIPfbldQbRzayKeFJ6s-Z6gZFA2cjokiMp6tBINrNSfM8sIX9_yoMnKyCUvmXCGdxwOVf07CxAxgUenDhGLsTzLKZzcuCAyh84vSes_FsNg8afnnLJJ5g0PODgAb75RA7Sx-JgGwlM80-VvAH3MpG1EpL14EKcYRieO1g7perZnya4fuk-mF4ZCrviPgiQV4DZNqh8xHUVAiEClEjhWDXpKNSdgRjk6EI96iESXRapmyVC9h31OnpKJRvlWzSyEuTI7gUkip0TLwxVFqpUlC-uARwXoX1uZ5nNhiIACffy1Yorov2o_NjmD7ENNPfxkMqNTuT4PrHwFvS5EEK-AJ9e3NF2762kLze0_Md87MbFGFI5o2vcSJxbBQSzT47N2o4wdtDgo8jizD8rq61Zy9QVbUKof9984wrUkIGl6PfVmUUyzNbYukt4t5zRjN5g9s6isYtAfhtUqExEGLH68XFm3LHZuKZEoGOUjK0C97Pr1B9MUFOhk_3jGl9zb5kg-Sh4v-1HzO2QkDIObvmY6pYmLZCQo2AmLViiKD3XdqBr8GloZJhnnApOAaRbBXXjbuOMgnfzykT7mBAd9xbjsfbIQCHdORVr80uW15014SzDYsVsKGveNRacywwiL_uMe8EItSqdvgwmOmfpslB2x3sLPRVPdVSQjR_VEU-7MjFn-FiXN4uhK23J9j4gGtxO-ymtakjTCFXUWtvn9b-eqlAT85NqvCk9jRVW4D34Iy1pAHiYRSzzmZhr3tPHH-z34fplGirH71DzROvDxqEefti33Oc5ySbNmkqtctmZM0BkC_ne5OCbLwDUMsTTHnYjYi_Kaf2qp8s3QXnEJaghAlfyQkyM49FOzgAkRtwrurrkQSlHHATgmzBVgYqvLYg4nHvoj46QRERlVON2sE99PkThtmpE9a_f-9jdp0eUfPF899E7Zosm_M1niQ_AFajNazVLaF_qzRyH5lFrx1_jo3cYiiWFE2CmEyK-mXko5k480c3j_KpGBDtRu2oA4FGYMnn-oplXO29aEimzz67-zit6EkSCDwZv-uwg_ZQDYKT9-jEp0zl8PSDoSoAZt9-wKSPke48breoPw2i524MwqjqSYwtxQ0a90nFP59hcqk2jg67-iXt9QoF1Yi-1RqqHAW7buAiGAcf0UEfIUWEnIuB3Kcfz-hGtiAjX-2zH4zcTRxIQAWMkRmKQ9siKW5UwLzwY23gEfjtdtQrwwXVY7hndKblel7izJWnfmH1nnOuAOpsmobTGZc2dFQT6KqDcXqFKAIxhB7QgwBWzfOOA5X30vDX6M7uTfMDFYcjVjLJxU7iUQ-UnI73MSLy5ELRzETA8UnwpvzVoF3cHL1IOn-XfhKSXo7QpCDHsMe3rsnhdsC_axWlfS8Y6bauVk2gzTbU-fwEzPnqinGm8MSw29rbmr0ERYc5pciJ89pW7fsbCdCeu0cvzb20IPKu2nt9tM2ftWaCtO946MHarGbA9BR-xCG6fOrhY5wQn6hT3MTt8P8AZf-pN49ZDHhiZIGPCvIaHxFKElvsPX7feXxL5V21Eve2iYSI4Zi0J6s8Xscd6QzV_VBgAm6-KlHrCJXQEZ--fpSBGMyNl5QNxP519FtwkCc6TnNkFVi1CyoXo1guTBolP7Yf1411HnhN9_lIGnHpBVTRa49ExjwYU6628xenCc2Ye63S657hRMH2owWLMoj39jt1Hxv6hoJU0g8jC0FxqRe0Zno2o5tN-_G3IvjZz90-U1Heu0FcRlTbU8w0N8GQyaEz3TeDgcN9G_6C9kqXeQ691pcu8socip2KKj_jzgyv-j3rOyw4SRdkZm5TTw9IhUHUdbYDWwd7muBFbFFUkg0h_YQd0g_uzmOzg_zo828nUYwe93fTp3Fww14CkepbBM2pd6Hx-viDkupt87dmBI8AFVMIFI13Ff3tcoKYB6nxjTcLcd14Zrd5lTtvrWVZAmurHizql2AZ-952wl4Pst7FJHxu_PMqIHAU9MlQzK1Pe52afb1sOnndKsXKBqPf--7f_IKC31W9BEEnVJpwEVyof__wNsmnZ0h6gBvroi23khMCEbxuVL435GNDbeEFamTFnjbwgHRB1X_ttLWewGIW6UNj30ZP7kNYC_h8j8-iReVDWOcETY3fdf73owzuHZDXXm2OKtvHq3j2g1D--hLMD5MTb6XyDaDYH02BQcCytlP9jz9zJNWX_eSSI_V6Vlj862puYlNnNjTaaq5p9X5FLuHni0amOYU5_83CyzdA9lzXOy0g2t4tqnwe77KqKFdNq-uL0BkSJzRJAFne32WEZ2KY6cGV0i4i3S1s3ZIGEQCL4-SjgohQuQwDipHYNbAejvMlLheqGnykvTLdsPCQqdFwYqHxEK87Ijd_ACJ6cmpeWG3t4cCxmjCMIfDX4FXevMerbJZA3YjYMmz59buXdmLmVsuk9w4SaLCMxRB-5QYVzQxI-x35RS5o3hyVADC7181KjCrCqfdR0IgIxg6U3oDofshEDIpMOaLtuM2A8WKx94VGBPAtX3GnOpmRvMizxDwG3jrFGKLxa5kaFvdGstygCU05qgUNnYIOeKcqG8T7yLKXvBFD5FEkvlYPVVObmCLrysgu3lTwG34SU7mZruIcr3jAi1QWvh-aYtFm3iKZq11FnBTzrgpmklbKadNaTnJRV3nwxk1FhaWBpwiDgd983FB0MlcTBIDm46FROa9t5247eQEofR_9MGMtBReuDucCK0ooLpCqAEVhemWnYJPs6GNQ3mW6E4Mzc4T8Um1uF0A6G-SzREOVczPBf0sRbe_2rHHmifFwLPLQx2FX7zEVJR5TgUtdtd8YQLhKP8VfpiAFeiANDAJQo1yVXMx6dfItfnqqBdTcwfs3IfHq_kUYcEpcSj7M3E2olEM_7Lo4d2uqK49wEA0QoUDK_iy4Vxl2VlONrdU29l0jtX079wS3WR6m6sySRySmugpEk-4_spxJBRSRaKt_sS7zmuK-TBnKzTicEJvo0PA2pACiZ_Q-XPZ7PVzzwMwMXFhrQ_bSAIGhzGaAfB3MWk3IZB5fOWR3MJMUKv9i_-9gjp4iIy7PqpdSXPRuN5nrayQp3lgLACkJF1JRZEHOUKurLIYYtKoAwCzT0HQVwbAvdF7sYpr70vb-sVHmGqCFch2R2BVOrQzL-bkq6zjW6tr10k7S_gXDpR2OMIkCLpb7U5bYZVQSDCWID5RPISS0NjWReZojhPAm8FAKS9fnl9f9wv-wT5ShmoznAh4rOOjKwzS5WgFXzNJ3DeYQQu9-mPfx6q1Jhn1pclZ0ofltuVgbue1aTiDPJNT6jFLZb0rxvkSKEAdfejMetBfz_LHTJ7Dk_N6YVnxuwkTKYlsI0NAnQjUp20Ehnvh_wRVpfm8_8wo-BAgQMJlzraNNQnllDZvCs-nRE8MMoOAacfIoaFe7HrG1msZ3IOW63UeHLDbB7B-EXmfNxHFXnQWlEwOKoJkBad6rzXwNdPN83XlrLtPnpP47L-oSHqqebG6QZLxZYILP9F_FR86HnY6hB0ncT_xOOHBo1cvICXK5lXjsMqDnMlC-EE5KW9lFbs_WPe9_nLXBIySqV5FHYS2Ig5zP8u2obpaKj68Kek_cLRvPlW18Xn21vz4V1eUD0V2v5cFg34lde6uvBlKRCe7WUzDnZZto1xh9JOWEs6FwKh6mU6da3u-25807gG2pzq5VDSyqcL-kZGt4BoHl8eoWy0j8JMvQbeTKGIQwrSoOStODvEFm3gFCnuNj2NSF3Xky9o-sqj8axUkjwb-xUmwckTvsrbYLIyIfgZq-koFbPcWpZDuZQuxtF0XZbEk_oMh4FSG3UZ0nvTe4B5cHiO6oWobUhaVJMxfoYJXywIiCn3AN6JQ8QDJpZzTB8Nusmx-xOeXHFBGspPyTrcxd13x6kjOxRpEz3FiTTpH6fMggaGcDMIRfmkxCtrGVSNTsxXOBOsfVb9Tnf1mylvXigUAAWbuGV-ChWq6xOVieci6hu_jh-eKax_xUSEnwzUk8GPQZxSgkC-HjoNaluxa23gEjo18W1jWl_L1ebLXnnC0qE3H5LN6ZWNINOYWDyooErPVMeHvUo-N1cmhOUf_DtKK0RXX_oJE4gEgOtjvhfpnu2t11jAKWrJZLAqiWIgIp\",\"summary\":[{\"type\":\"summary_text\",\"text\":\"**Considering test settings**\\n\\nI see the test has a record type in the code, which means there's no manual configuration needed. The agent will capture everything, which is a good sign. I might want to ensure any existing resources under the native-image are respected and not modified or ignored. It seems like I need to create a file as part of this process. Let's get that sorted!\"}]}"}, {"type": "toolCall", "id": "call_fqnazD8QUfofmLR7f40P4C69|fc_0d8c31fa336f7f3d0169f9857bccb481a283cef7d5f3b46814", "name": "write", "arguments": {"path": "tests/src/com.squareup.moshi/moshi/1.15.2/src/test/kotlin/com_squareup_moshi/moshi/RecordJsonAdapterAnonymous1Test.kt", "content": "/*\n * Copyright and related rights waived via CC0\n *\n * You should have received a copy of the CC0 legalcode along with this\n * work. If not, see <http://creativecommons.org/publicdomain/zero/1.0/>.\n */\npackage com_squareup_moshi.moshi\n\nimport com.squareup.moshi.JsonAdapter\nimport com.squareup.moshi.Moshi\nimport org.assertj.core.api.Assertions.assertThat\nimport org.junit.jupiter.api.Test\n\npublic class RecordJsonAdapterAnonymous1Test {\n    @Test\n    fun adapterCreatesRecordFromJsonObject(): Unit {\n        val moshi: Moshi = Moshi.Builder().build()\n        val adapter: JsonAdapter<PersonRecord> = moshi.adapter(PersonRecord::class.java)\n\n        val person: PersonRecord? = adapter.fromJson(\"\"\"{\"name\":\"Ada\",\"age\":37}\"\"\")\n\n        assertThat(person).isEqualTo(PersonRecord(\"Ada\", 37))\n        assertThat(adapter.toJson(PersonRecord(\"Grace\", 85)))\n            .isEqualTo(\"\"\"{\"name\":\"Grace\",\"age\":85}\"\"\")\n    }\n}\n\n@JvmRecord\npublic data class PersonRecord(\n    public val name: String,\n    public val age: Int,\n)\n"}}], "api": "openai-responses", "provider": "OCA", "model": "gpt-5.5", "usage": {"input": 2776, "output": 1090, "cacheRead": 11776, "cacheWrite": 0, "totalTokens": 15642, "cost": {"input": 0, "output": 0, "cacheRead": 0, "cacheWrite": 0, "total": 0}}, "stopReason": "toolUse", "timestamp": 1777960302566, "responseId": "resp_0d8c31fa336f7f3d0169f9856f017881a2af24984da9bd466a"}, "toolResults": [{"role": "toolResult", "toolCallId": "call_fqnazD8QUfofmLR7f40P4C69|fc_0d8c31fa336f7f3d0169f9857bccb481a283cef7d5f3b46814", "toolName": "write", "content": [{"type": "text", "text": "Successfully wrote 1016 bytes to tests/src/com.squareup.moshi/moshi/1.15.2/src/test/kotlin/com_squareup_moshi/moshi/RecordJsonAdapterAnonymous1Test.kt"}], "isError": false, "timestamp": 1777960319817}]}
[recv] {"type": "turn_start"}
[recv] {"type": "message_start", "message": {"role": "assistant", "content": [], "api": "openai-responses", "provider": "OCA", "model": "gpt-5.5", "usage": {"input": 0, "output": 0, "cacheRead": 0, "cacheWrite": 0, "totalTokens": 0, "cost": {"input": 0, "output": 0, "cacheRead": 0, "cacheWrite": 0, "total": 0}}, "stopReason": "stop", "timestamp": 1777960319827}}
[assistant-event] thinking_start
[thinking] **Evaluating Kotlin Properties**
[thinking] 
[thinking] I'm considering Kotlin's @JvmRecord and how it organizes component order for properties. That seems like a good feature! However, I notice that the mention of "Main sources local files only 34" feels irrelevant and might be cluttering my thoughts. I need to focus on crafting a final, concise conclusion about the components without any distractions. Let's streamline that information to keep it clear and effective!
[thinking] 
[assistant-event] thinking_end
[assistant-event] text_start
[assistant] Added a dedicated Kotlin coverage test for `com.squareup.moshi.RecordJsonAdapter$1`:
[assistant] 
[assistant] - `tests/src/com.squareup.moshi/moshi/1.15.2/src/test/kotlin/com_squareup_moshi/moshi/RecordJsonAdapterAnonymous1Test.kt`
[assistant] 
[assistant] The test defines a JVM record via `@JvmRecord`, creates a Moshi adapter for it, and performs JSON deserialization/serialization. Adapter creation should execute the active factory path and reach:
[assistant] 
[assistant] - `Class#getRecordComponents()`
[assistant] - `MethodHandles.Lookup#findConstructor(...)`
[assistant] - `MethodHandles.Lookup#unreflect(...)`
[assistant] 
[assistant] I did not run or compile tests, per instructions.
[assistant-event] text_end
[recv] {"type": "message_end", "message": {"role": "assistant", "content": [{"type": "thinking", "thinking": "**Evaluating Kotlin Properties**\n\nI'm considering Kotlin's @JvmRecord and how it organizes component order for properties. That seems like a good feature! However, I notice that the mention of \"Main sources local files only 34\" feels irrelevant and might be cluttering my thoughts. I need to focus on crafting a final, concise conclusion about the components without any distractions. Let's streamline that information to keep it clear and effective!", "thinkingSignature": "{\"id\":\"rs_0d8c31fa336f7f3d0169f985825da481a2a85ee9bce97ce2f1\",\"type\":\"reasoning\",\"encrypted_content\":\"gAAAAABp-YWHk8t3eWguLbqT5WAPCfnjJycOfvJ-DMpW4Bn4qBeCF8laXYQ8pT-Jo8pnfdKNCqhtxcSH7LRu-2QOlTeYM9apnl1ZnekDXePsMxJCm1RW9dEf4gROO5fO7S-IzBPPx6dKNZbEFmUIB_Qi2hl00mJbqt42i4Qgpn9cwM5wBbLt1XyQwO20tlRClhasxHuPuwKwFVmWE8MpHZODJ-gGcGkSHhDo0z__f0OQxYF09P8JQk-Q6PAgYLIpX2v443PDSueVcg6TaTgQKi8LbPTjK0LRmb-McU8BYOXEQcZGD_TuJ50QLoa2Rk9dgnmItSPjGdN9OXVaThS4WrOFaNyxbVt670DWNHpDsbu1Hug4C9lbDzgGZCn-LOj3XQXgjNsLSB3fUw0qEb0o-RE_UMPjQxhv4TNzhgwMVhY9VJHmqAkkOGEPpB6X-PoXFYByayx_JAIi4NPahxSN4boxqy1CuLZ9ySCG738-KeMoFdZhxsiMkHfn9mTXILrCFXWHeX04KZYuHhpBlT0sOol29PTJINStJ9GeWLvgakmTRslIGDtHEbyFlfm0zh5i36EglLqR6G2w7K6y4jeFYYajfm9-Htg5o72DlzrElQmuxSogEwcnEUNDpQtkVHdDAXXIStyWmN9z13JZlJ_OC-cCNueqH-R7HTIohhGEaOz6Gov0gTPkuNw-wLP_8cna_ilhRoACX96Q303r24wpLigrRjtMIg3npx32KSymfIaa3Ycdd5TzKwu_MIEGcAlSLoPm0-_-r3xO3_GXbpA8F_xElBUwVxrZRJTLYxDssl46LVoAkUh_qJCcFiN1UAsZy4Ocx7OWSR0G1qwc-rZ87MniOtz4XbGwVpnQ0sfljfFRHbJ7tgtjGIxDguNatslOZg8MPIYWEfMeoYS4_kmOliNe-SXfGYtjcWiHwGOkX-ehyR8HjecTgQ6zkyi4k9rFY1GURo75DcKejts6snCLLwjS4r9FJnEAzqv5RIe1REpIYeos-lvvarWlfaNhe6yJdfU0lTgKLin9xjT72qJyAN6G1LGT90ad0ub1u6WiWrpt24F-j_YmQoadUEth3lSyI0VhizRRvmzIarB7CWl2R7rDeArD7mrOX3g0_Yx88ow3gw6Fk4tthE96Q7MEXpYa44FBbC2MLjkt3XYa0GLxvcyWcuyFU7TI30a9SygsSfSLTS6Fxu8qejDKpkJFoXExyVsNeF0EruByfpSwcS4GshiCYKIqCiNK3UHh9ylqPFc3SoKc7SD7UyBuKU1iAGyHffhWwC75ppvDBSwGGk4io2nFGLWwY0KqM72HN5Wt0PdZctHNTt5Ij9_0qJBWY9ImynYIxaOqXVKDB-i8_iVddSSEVYwePBvwluhiSupJru9-RGujOGJnpFDI-nqtQ1P_zWGSH8m3YAxrq0FUAgxiwgQX5KApSMKuvzbIhSQEd2L654YH1d6r5-O7h4CyWbgU_evO32lrUlZELIq2yMQnHqhFshv7-r9voX0jafRL2W_51ZzX68EX0oauwxTGiv--Fl-qYN39zYN_NoFS9CT6jJlk3AFSbBJl5CxTLrw9Qvb4YmIdUJ90IvFgfOQ7DWrdlMNmkeFInQ16NSRxWpsjHZAaPmlpxM82K3Y5n146RSPLQOZd8mTTKzEsKhIb1z4N-PUSFCLZn5xnNr6MY73ajYt45hAlJyy5iR9tRt023ykd6j-g87UN2bjZxCe7wN494cAH7ldlm82N2H_QBSNIu20XDWToashGwiJHP_w-neFZc93SSdGPnhSoZt9Nug1eUkW0StIwUyzqjMS43z7pwYO8RsUDfOVPpdd6cbz17ki7Fzt801nSEn1iLK6_egm9iR_55yAw1sR1Jf8cm9vZ5NzIePN63O4tWyXOLobn1zTwPYqLCBlqEgNKtsVwME_qQSFMgUFAHHLhcnceI4pHZMa2OaKZK7uL7tKDlIikLyAZqbT6sSo0e6689_yeehA_ZNpNm7IRb6POLYlBfji2CrUBWCEkSEiXvUUkRYTrtH9SwmJnLnA7Cuh_986VW-wf6QzkGheUbcCG86ME9OrlyrxtaLW_imj8KgLFO2h52850ZoUKUE6d9Q6Al9yzwHrHU5sDI34ONe0bbpHtcCWs6EcXlcuDPBYNG6v6pNC7SYMuAAuyshL9r4DCvOTO-YBDktYuOjDcj8pw_VSx5EtWlC-gNdKxDgcjJSHrCh14zsvfat0OnkhPPXIfmnDO-b-L8ens6u8v-jDdGQxTfoQRMMXEZ_T3_GJj40Y-WxrsvWNymsNfInkW02y8ob_YkTPXWmtYNMsdX4NHs9B2FkC5lGRCRWJspPvu-m1W8_1FePMGzV_C6KR3bKEig9x4pZQwG__b6_7_Kns7mAwcSVKIho8-MyDxvvJul3KmwFxJPAzeEFKHkQt5kV8fgolxV4rEKDQrLXGHKTvJF-KvO2FV9TGu9BjDF_QE0A==\",\"summary\":[{\"type\":\"summary_text\",\"text\":\"**Evaluating Kotlin Properties**\\n\\nI'm considering Kotlin's @JvmRecord and how it organizes component order for properties. That seems like a good feature! However, I notice that the mention of \\\"Main sources local files only 34\\\" feels irrelevant and might be cluttering my thoughts. I need to focus on crafting a final, concise conclusion about the components without any distractions. Let's streamline that information to keep it clear and effective!\"}]}"}, {"type": "text", "text": "Added a dedicated Kotlin coverage test for `com.squareup.moshi.RecordJsonAdapter$1`:\n\n- `tests/src/com.squareup.moshi/moshi/1.15.2/src/test/kotlin/com_squareup_moshi/moshi/RecordJsonAdapterAnonymous1Test.kt`\n\nThe test defines a JVM record via `@JvmRecord`, creates a Moshi adapter for it, and performs JSON deserialization/serialization. Adapter creation should execute the active factory path and reach:\n\n- `Class#getRecordComponents()`\n- `MethodHandles.Lookup#findConstructor(...)`\n- `MethodHandles.Lookup#unreflect(...)`\n\nI did not run or compile tests, per instructions.", "textSignature": "{\"v\":1,\"id\":\"msg_0d8c31fa336f7f3d0169f985876ba081a2ae922467d4cfb341\",\"phase\":\"final_answer\"}"}], "api": "openai-responses", "provider": "OCA", "model": "gpt-5.5", "usage": {"input": 1356, "output": 381, "cacheRead": 14336, "cacheWrite": 0, "totalTokens": 16073, "cost": {"input": 0, "output": 0, "cacheRead": 0, "cacheWrite": 0, "total": 0}}, "stopReason": "stop", "timestamp": 1777960319827, "responseId": "resp_0d8c31fa336f7f3d0169f985815b3c81a2b39847a8ebb7673d"}}
[recv] {"type": "turn_end", "message": {"role": "assistant", "content": [{"type": "thinking", "thinking": "**Evaluating Kotlin Properties**\n\nI'm considering Kotlin's @JvmRecord and how it organizes component order for properties. That seems like a good feature! However, I notice that the mention of \"Main sources local files only 34\" feels irrelevant and might be cluttering my thoughts. I need to focus on crafting a final, concise conclusion about the components without any distractions. Let's streamline that information to keep it clear and effective!", "thinkingSignature": "{\"id\":\"rs_0d8c31fa336f7f3d0169f985825da481a2a85ee9bce97ce2f1\",\"type\":\"reasoning\",\"encrypted_content\":\"gAAAAABp-YWHk8t3eWguLbqT5WAPCfnjJycOfvJ-DMpW4Bn4qBeCF8laXYQ8pT-Jo8pnfdKNCqhtxcSH7LRu-2QOlTeYM9apnl1ZnekDXePsMxJCm1RW9dEf4gROO5fO7S-IzBPPx6dKNZbEFmUIB_Qi2hl00mJbqt42i4Qgpn9cwM5wBbLt1XyQwO20tlRClhasxHuPuwKwFVmWE8MpHZODJ-gGcGkSHhDo0z__f0OQxYF09P8JQk-Q6PAgYLIpX2v443PDSueVcg6TaTgQKi8LbPTjK0LRmb-McU8BYOXEQcZGD_TuJ50QLoa2Rk9dgnmItSPjGdN9OXVaThS4WrOFaNyxbVt670DWNHpDsbu1Hug4C9lbDzgGZCn-LOj3XQXgjNsLSB3fUw0qEb0o-RE_UMPjQxhv4TNzhgwMVhY9VJHmqAkkOGEPpB6X-PoXFYByayx_JAIi4NPahxSN4boxqy1CuLZ9ySCG738-KeMoFdZhxsiMkHfn9mTXILrCFXWHeX04KZYuHhpBlT0sOol29PTJINStJ9GeWLvgakmTRslIGDtHEbyFlfm0zh5i36EglLqR6G2w7K6y4jeFYYajfm9-Htg5o72DlzrElQmuxSogEwcnEUNDpQtkVHdDAXXIStyWmN9z13JZlJ_OC-cCNueqH-R7HTIohhGEaOz6Gov0gTPkuNw-wLP_8cna_ilhRoACX96Q303r24wpLigrRjtMIg3npx32KSymfIaa3Ycdd5TzKwu_MIEGcAlSLoPm0-_-r3xO3_GXbpA8F_xElBUwVxrZRJTLYxDssl46LVoAkUh_qJCcFiN1UAsZy4Ocx7OWSR0G1qwc-rZ87MniOtz4XbGwVpnQ0sfljfFRHbJ7tgtjGIxDguNatslOZg8MPIYWEfMeoYS4_kmOliNe-SXfGYtjcWiHwGOkX-ehyR8HjecTgQ6zkyi4k9rFY1GURo75DcKejts6snCLLwjS4r9FJnEAzqv5RIe1REpIYeos-lvvarWlfaNhe6yJdfU0lTgKLin9xjT72qJyAN6G1LGT90ad0ub1u6WiWrpt24F-j_YmQoadUEth3lSyI0VhizRRvmzIarB7CWl2R7rDeArD7mrOX3g0_Yx88ow3gw6Fk4tthE96Q7MEXpYa44FBbC2MLjkt3XYa0GLxvcyWcuyFU7TI30a9SygsSfSLTS6Fxu8qejDKpkJFoXExyVsNeF0EruByfpSwcS4GshiCYKIqCiNK3UHh9ylqPFc3SoKc7SD7UyBuKU1iAGyHffhWwC75ppvDBSwGGk4io2nFGLWwY0KqM72HN5Wt0PdZctHNTt5Ij9_0qJBWY9ImynYIxaOqXVKDB-i8_iVddSSEVYwePBvwluhiSupJru9-RGujOGJnpFDI-nqtQ1P_zWGSH8m3YAxrq0FUAgxiwgQX5KApSMKuvzbIhSQEd2L654YH1d6r5-O7h4CyWbgU_evO32lrUlZELIq2yMQnHqhFshv7-r9voX0jafRL2W_51ZzX68EX0oauwxTGiv--Fl-qYN39zYN_NoFS9CT6jJlk3AFSbBJl5CxTLrw9Qvb4YmIdUJ90IvFgfOQ7DWrdlMNmkeFInQ16NSRxWpsjHZAaPmlpxM82K3Y5n146RSPLQOZd8mTTKzEsKhIb1z4N-PUSFCLZn5xnNr6MY73ajYt45hAlJyy5iR9tRt023ykd6j-g87UN2bjZxCe7wN494cAH7ldlm82N2H_QBSNIu20XDWToashGwiJHP_w-neFZc93SSdGPnhSoZt9Nug1eUkW0StIwUyzqjMS43z7pwYO8RsUDfOVPpdd6cbz17ki7Fzt801nSEn1iLK6_egm9iR_55yAw1sR1Jf8cm9vZ5NzIePN63O4tWyXOLobn1zTwPYqLCBlqEgNKtsVwME_qQSFMgUFAHHLhcnceI4pHZMa2OaKZK7uL7tKDlIikLyAZqbT6sSo0e6689_yeehA_ZNpNm7IRb6POLYlBfji2CrUBWCEkSEiXvUUkRYTrtH9SwmJnLnA7Cuh_986VW-wf6QzkGheUbcCG86ME9OrlyrxtaLW_imj8KgLFO2h52850ZoUKUE6d9Q6Al9yzwHrHU5sDI34ONe0bbpHtcCWs6EcXlcuDPBYNG6v6pNC7SYMuAAuyshL9r4DCvOTO-YBDktYuOjDcj8pw_VSx5EtWlC-gNdKxDgcjJSHrCh14zsvfat0OnkhPPXIfmnDO-b-L8ens6u8v-jDdGQxTfoQRMMXEZ_T3_GJj40Y-WxrsvWNymsNfInkW02y8ob_YkTPXWmtYNMsdX4NHs9B2FkC5lGRCRWJspPvu-m1W8_1FePMGzV_C6KR3bKEig9x4pZQwG__b6_7_Kns7mAwcSVKIho8-MyDxvvJul3KmwFxJPAzeEFKHkQt5kV8fgolxV4rEKDQrLXGHKTvJF-KvO2FV9TGu9BjDF_QE0A==\",\"summary\":[{\"type\":\"summary_text\",\"text\":\"**Evaluating Kotlin Properties**\\n\\nI'm considering Kotlin's @JvmRecord and how it organizes component order for properties. That seems like a good feature! However, I notice that the mention of \\\"Main sources local files only 34\\\" feels irrelevant and might be cluttering my thoughts. I need to focus on crafting a final, concise conclusion about the components without any distractions. Let's streamline that information to keep it clear and effective!\"}]}"}, {"type": "text", "text": "Added a dedicated Kotlin coverage test for `com.squareup.moshi.RecordJsonAdapter$1`:\n\n- `tests/src/com.squareup.moshi/moshi/1.15.2/src/test/kotlin/com_squareup_moshi/moshi/RecordJsonAdapterAnonymous1Test.kt`\n\nThe test defines a JVM record via `@JvmRecord`, creates a Moshi adapter for it, and performs JSON deserialization/serialization. Adapter creation should execute the active factory path and reach:\n\n- `Class#getRecordComponents()`\n- `MethodHandles.Lookup#findConstructor(...)`\n- `MethodHandles.Lookup#unreflect(...)`\n\nI did not run or compile tests, per instructions.", "textSignature": "{\"v\":1,\"id\":\"msg_0d8c31fa336f7f3d0169f985876ba081a2ae922467d4cfb341\",\"phase\":\"final_answer\"}"}], "api": "openai-responses", "provider": "OCA", "model": "gpt-5.5", "usage": {"input": 1356, "output": 381, "cacheRead": 14336, "cacheWrite": 0, "totalTokens": 16073, "cost": {"input": 0, "output": 0, "cacheRead": 0, "cacheWrite": 0, "total": 0}}, "stopReason": "stop", "timestamp": 1777960319827, "responseId": "resp_0d8c31fa336f7f3d0169f985815b3c81a2b39847a8ebb7673d"}, "toolResults": []}
[recv] agent_end
[send] get_state
[recv] get_state success
  sessionFile: ../../../../../../../../.pi/agent/sessions/--home-vjovanov-c-forge-forge8-graalvm-reachability-metadata-forge-local_repositories-forge_worktrees-4490-2eb21853--/2026-05-05T05-51-11-813Z_019df6b0-bfc5-7029-84b2-889dc76a0676.jsonl
  sessionId: 019df6b0-bfc5-7029-84b2-889dc76a0676
[send] get_session_stats
[recv] get_session_stats success
  tokens: input=19303 output=2438 cacheRead=125952 cacheWrite=0 total=147693

