================================================================================
Timestamp: 2026-05-09T19:15:51.960657+00:00
Session: ../../../../../../../../.pi/agent/sessions/--home-vjovanov-c-forge-forge8-graalvm-reachability-metadata-forge-local_repositories-forge_worktrees-2428-8b9c7e6e--/2026-05-09T19-15-12-466Z_019e0e2a-47d2-70d5-af15-96f11a75e417.jsonl
Persistent instructions: configured (2992 chars)
Event Trace:
[send] prompt
  Role: You are an expert JVM test engineer specializing in high-coverage integration testing for external libraries.
  
  Task:
  Improve test coverage for the active dynamic-access class in `org.codehaus.plexus:plexus-velocity:1.1.7`.
  
  Source Context:
  Coordinate: org.codehaus.plexus:plexus-velocity:1.1.7
  Repository URL: https://github.com/codehaus-plexus/plexus-velocity
  Main sources:
  - URL: https://repo.maven.apache.org/maven2/org/codehaus/plexus/plexus-velocity/1.1.7/plexus-velocity-1.1.7-sources.jar
  - Local path: local_repositories/source_context/org.codehaus.plexus/plexus-velocity/1.1.7/main
  - Files available: 6
  
  Active class:
  - Class: org.codehaus.plexus.velocity.VelocityComponent$1
  - Source file: /home/vjovanov/c/forge/forge8/graalvm-reachability-metadata/forge/local_repositories/source_context/org.codehaus.plexus/plexus-velocity/1.1.7/main/extracted/org/codehaus/plexus/velocity/VelocityComponent.java
  
  Progress since the previous dynamic-access report:
  - Attempts used for this class so far: 0
  - Newly covered call sites: none
  - Remaining uncovered call sites after the last report: 1
  
  Remaining uncovered dynamic-access call sites for this class:
  - [reflection] java.lang.Class#forName(java.lang.String) <- org.codehaus.plexus.velocity.VelocityComponent$1.class$(VelocityComponent.java:23) (line 23)
  
  Rules:
  - Add or refine tests so execution reaches the remaining uncovered call sites for the active class.
  - Focus on the active class only.
[recv] prompt success
[recv] {"type": "agent_start"}
[recv] {"type": "turn_start"}
[recv] {"type": "message_start", "message": {"role": "user", "content": [{"type": "text", "text": "Role: You are an expert JVM test engineer specializing in high-coverage integration testing for external libraries.\n\nTask:\nImprove test coverage for the active dynamic-access class in `org.codehaus.plexus:plexus-velocity:1.1.7`.\n\nSource Context:\nCoordinate: org.codehaus.plexus:plexus-velocity:1.1.7\nRepository URL: https://github.com/codehaus-plexus/plexus-velocity\nMain sources:\n- URL: https://repo.maven.apache.org/maven2/org/codehaus/plexus/plexus-velocity/1.1.7/plexus-velocity-1.1.7-sources.jar\n- Local path: local_repositories/source_context/org.codehaus.plexus/plexus-velocity/1.1.7/main\n- Files available: 6\n\nActive class:\n- Class: org.codehaus.plexus.velocity.VelocityComponent$1\n- Source file: /home/vjovanov/c/forge/forge8/graalvm-reachability-metadata/forge/local_repositories/source_context/org.codehaus.plexus/plexus-velocity/1.1.7/main/extracted/org/codehaus/plexus/velocity/VelocityComponent.java\n\nProgress since the previous dynamic-access report:\n- Attempts used for this class so far: 0\n- Newly covered call sites: none\n- Remaining uncovered call sites after the last report: 1\n\nRemaining uncovered dynamic-access call sites for this class:\n- [reflection] java.lang.Class#forName(java.lang.String) <- org.codehaus.plexus.velocity.VelocityComponent$1.class$(VelocityComponent.java:23) (line 23)\n\nRules:\n- Add or refine tests so execution reaches the remaining uncovered call sites for the active class.\n- Focus on the active class only.\n"}], "timestamp": 1778354112514}}
[recv] {"type": "message_end", "message": {"role": "user", "content": [{"type": "text", "text": "Role: You are an expert JVM test engineer specializing in high-coverage integration testing for external libraries.\n\nTask:\nImprove test coverage for the active dynamic-access class in `org.codehaus.plexus:plexus-velocity:1.1.7`.\n\nSource Context:\nCoordinate: org.codehaus.plexus:plexus-velocity:1.1.7\nRepository URL: https://github.com/codehaus-plexus/plexus-velocity\nMain sources:\n- URL: https://repo.maven.apache.org/maven2/org/codehaus/plexus/plexus-velocity/1.1.7/plexus-velocity-1.1.7-sources.jar\n- Local path: local_repositories/source_context/org.codehaus.plexus/plexus-velocity/1.1.7/main\n- Files available: 6\n\nActive class:\n- Class: org.codehaus.plexus.velocity.VelocityComponent$1\n- Source file: /home/vjovanov/c/forge/forge8/graalvm-reachability-metadata/forge/local_repositories/source_context/org.codehaus.plexus/plexus-velocity/1.1.7/main/extracted/org/codehaus/plexus/velocity/VelocityComponent.java\n\nProgress since the previous dynamic-access report:\n- Attempts used for this class so far: 0\n- Newly covered call sites: none\n- Remaining uncovered call sites after the last report: 1\n\nRemaining uncovered dynamic-access call sites for this class:\n- [reflection] java.lang.Class#forName(java.lang.String) <- org.codehaus.plexus.velocity.VelocityComponent$1.class$(VelocityComponent.java:23) (line 23)\n\nRules:\n- Add or refine tests so execution reaches the remaining uncovered call sites for the active class.\n- Focus on the active class only.\n"}], "timestamp": 1778354112514}}
[recv] {"type": "message_start", "message": {"role": "assistant", "content": [], "api": "openai-responses", "provider": "OCA", "model": "gpt-5.5", "usage": {"input": 0, "output": 0, "cacheRead": 0, "cacheWrite": 0, "totalTokens": 0, "cost": {"input": 0, "output": 0, "cacheRead": 0, "cacheWrite": 0, "total": 0}}, "stopReason": "stop", "timestamp": 1778354112532}}
[assistant-event] thinking_start
[thinking] **Evaluating test modifications**
[thinking] 
[thinking] I realize I need to modify the tests, so I should dive into the repository to inspect the existing code. By inspecting it, I can identify what changes are necessary for the tests to be effective. This step is crucial to ensure everything functions correctly. I'm thinking through how to make these changes and what needs the most attention. I'll tackle it methodically to get it right!
[thinking] 
[assistant-event] thinking_end
[tool-call] start id=unknown
[tool-call] delta {"command": "pwd && ls"}
[tool-call] end id=call_RonYV1dvLksbh5x2ivZVOjsx|fc_049667505a9e91930169ff87c3ba5c81a3ab89b77318e30b3a name=bash args={"command": "pwd && ls"}
[recv] {"type": "message_end", "message": {"role": "assistant", "content": [{"type": "thinking", "thinking": "**Evaluating test modifications**\n\nI realize I need to modify the tests, so I should dive into the repository to inspect the existing code. By inspecting it, I can identify what changes are necessary for the tests to be effective. This step is crucial to ensure everything functions correctly. I'm thinking through how to make these changes and what needs the most attention. I'll tackle it methodically to get it right!", "thinkingSignature": "{\"id\":\"rs_049667505a9e91930169ff87c2709481a3b505b5e5585157f5\",\"type\":\"reasoning\",\"encrypted_content\":\"gAAAAABp_4fDfjJ8W80hcG03ft95pOu2ipDgrMTea4iWuIdn69_3iW1pJL-WqUxNOpt0xK_EZc4UiGIHfpjr66Rzzamr14uP0lScq_Nm19DEflS1e5DE4jPxuFjt0EX5_2_e8igCOD8wnOqr7vK6PAJ_84Cf_bwY2-r3kidi3vsyAuDE7RRUrYPnM9veOrbaqKYPWomY6z9pBxYVwQSu6MT0M1V1ewWNohbOyg41gpEUrd2Gj2CpdFSGo586LYDPDq0kaj0gvSfGRA14nynnpWn11kRftZ-yjO-onPN8LXKz0NfGhfJdja7RZghc-fYUyjSzB6WBUPt46OG6Iq5VO5EfuwyUy8RdqVOvV8a2riKMCnSTrrIFgkoGRAA4GE04isxLXiOhkdPEVnNKjKWWj3UhWR-AVkuYsm-cnFNdACeeicMDrb1G6WbNdiWhQHBUMu_202LBujQSVjJPyDD_tnYd0qYtc_lLGZm2C10zM7DmM4eIMRhYd-nC_en7ZL41pyXTHq4K6BVlSCNhucwz78VGxWjSMYs8ObW4ZMLC0a8_hnwFkl_PaZZybvbinT9IxSMlkamNj5kNgNIYr3Du7acQYSz8iFym4FRhJYdqdm2e_ayStte2TxftJIJwosp1XBKXUS5ZN0KpHriiRUrKaH4WYqhkNnhqjh12n2f846_EC2cKsSE_PjBKXDzuSVM7hcygTF2opSzZV7Ky-9pqc5sH333OL9lZKtlwVOuAbHUa_mWM4ijDZ4QKCygJzaN4CFTHVM2k_GtDVCXkPUXcAh9TN-gNlezI-rvdt4m8BfNYtxxIdrvDrgi7qcubR0JYozN8wqg2DpNqfSvze6XhffysxDTA9krF_GhlQuMoxgnwvZbYbAWJKV51llcSRyu5OmBTGxo3Xtd7CPc1RCr-L8Q5SK0OAJnyt1Wsz0wtOKno8WtSQ3TBQ6Xuo0oVzUSZuROtlKAUNjvkf0R9DcemTlBx2zP4kj7T_yIw5PZJDL0krUPoexSbCe4=\",\"summary\":[{\"type\":\"summary_text\",\"text\":\"**Evaluating test modifications**\\n\\nI realize I need to modify the tests, so I should dive into the repository to inspect the existing code. By inspecting it, I can identify what changes are necessary for the tests to be effective. This step is crucial to ensure everything functions correctly. I'm thinking through how to make these changes and what needs the most attention. I'll tackle it methodically to get it right!\"}]}"}, {"type": "toolCall", "id": "call_RonYV1dvLksbh5x2ivZVOjsx|fc_049667505a9e91930169ff87c3ba5c81a3ab89b77318e30b3a", "name": "bash", "arguments": {"command": "pwd && ls"}}], "api": "openai-responses", "provider": "OCA", "model": "gpt-5.5", "usage": {"input": 5872, "output": 36, "cacheRead": 1536, "cacheWrite": 0, "totalTokens": 7444, "cost": {"input": 0, "output": 0, "cacheRead": 0, "cacheWrite": 0, "total": 0}}, "stopReason": "toolUse", "timestamp": 1778354112532, "responseId": "resp_049667505a9e91930169ff87c1a02081a3aa2a2c7a266c8f2a"}}
[tool-exec] start id=call_RonYV1dvLksbh5x2ivZVOjsx|fc_049667505a9e91930169ff87c3ba5c81a3ab89b77318e30b3a name=bash args={"command": "pwd && ls"}
[tool-exec] update id=call_RonYV1dvLksbh5x2ivZVOjsx|fc_049667505a9e91930169ff87c3ba5c81a3ab89b77318e30b3a name=bash
[tool-exec] update id=call_RonYV1dvLksbh5x2ivZVOjsx|fc_049667505a9e91930169ff87c3ba5c81a3ab89b77318e30b3a name=bash
  /home/vjovanov/c/forge/forge8/graalvm-reachability-metadata/forge/local_repositories/forge_worktrees/2428-8b9c7e6e
[tool-exec] update id=call_RonYV1dvLksbh5x2ivZVOjsx|fc_049667505a9e91930169ff87c3ba5c81a3ab89b77318e30b3a name=bash
  /home/vjovanov/c/forge/forge8/graalvm-reachability-metadata/forge/local_repositories/forge_worktrees/2428-8b9c7e6e
  AGENTS.md
  build
  build.gradle
  build_spec.yaml
  check-library-support.sh
  ci.json
  CLAUDE.md
  COVERAGE.md
  docs
  forge
  gradle
  gradle.properties
  gradlew
  gradlew.bat
  LICENSE
  metadata
  README.md
  settings.gradle
  skills
  stats
  tests
[tool-exec] end id=call_RonYV1dvLksbh5x2ivZVOjsx|fc_049667505a9e91930169ff87c3ba5c81a3ab89b77318e30b3a name=bash status=success
  /home/vjovanov/c/forge/forge8/graalvm-reachability-metadata/forge/local_repositories/forge_worktrees/2428-8b9c7e6e
  AGENTS.md
  build
  build.gradle
  build_spec.yaml
  check-library-support.sh
  ci.json
  CLAUDE.md
  COVERAGE.md
  docs
  forge
  gradle
  gradle.properties
  gradlew
  gradlew.bat
  LICENSE
  metadata
  README.md
  settings.gradle
  skills
  stats
  tests
[recv] {"type": "message_start", "message": {"role": "toolResult", "toolCallId": "call_RonYV1dvLksbh5x2ivZVOjsx|fc_049667505a9e91930169ff87c3ba5c81a3ab89b77318e30b3a", "toolName": "bash", "content": [{"type": "text", "text": "/home/vjovanov/c/forge/forge8/graalvm-reachability-metadata/forge/local_repositories/forge_worktrees/2428-8b9c7e6e\nAGENTS.md\nbuild\nbuild.gradle\nbuild_spec.yaml\ncheck-library-support.sh\nci.json\nCLAUDE.md\nCOVERAGE.md\ndocs\nforge\ngradle\ngradle.properties\ngradlew\ngradlew.bat\nLICENSE\nmetadata\nREADME.md\nsettings.gradle\nskills\nstats\ntests\n"}], "isError": false, "timestamp": 1778354116149}}
[recv] {"type": "message_end", "message": {"role": "toolResult", "toolCallId": "call_RonYV1dvLksbh5x2ivZVOjsx|fc_049667505a9e91930169ff87c3ba5c81a3ab89b77318e30b3a", "toolName": "bash", "content": [{"type": "text", "text": "/home/vjovanov/c/forge/forge8/graalvm-reachability-metadata/forge/local_repositories/forge_worktrees/2428-8b9c7e6e\nAGENTS.md\nbuild\nbuild.gradle\nbuild_spec.yaml\ncheck-library-support.sh\nci.json\nCLAUDE.md\nCOVERAGE.md\ndocs\nforge\ngradle\ngradle.properties\ngradlew\ngradlew.bat\nLICENSE\nmetadata\nREADME.md\nsettings.gradle\nskills\nstats\ntests\n"}], "isError": false, "timestamp": 1778354116149}}
[recv] {"type": "turn_end", "message": {"role": "assistant", "content": [{"type": "thinking", "thinking": "**Evaluating test modifications**\n\nI realize I need to modify the tests, so I should dive into the repository to inspect the existing code. By inspecting it, I can identify what changes are necessary for the tests to be effective. This step is crucial to ensure everything functions correctly. I'm thinking through how to make these changes and what needs the most attention. I'll tackle it methodically to get it right!", "thinkingSignature": "{\"id\":\"rs_049667505a9e91930169ff87c2709481a3b505b5e5585157f5\",\"type\":\"reasoning\",\"encrypted_content\":\"gAAAAABp_4fDfjJ8W80hcG03ft95pOu2ipDgrMTea4iWuIdn69_3iW1pJL-WqUxNOpt0xK_EZc4UiGIHfpjr66Rzzamr14uP0lScq_Nm19DEflS1e5DE4jPxuFjt0EX5_2_e8igCOD8wnOqr7vK6PAJ_84Cf_bwY2-r3kidi3vsyAuDE7RRUrYPnM9veOrbaqKYPWomY6z9pBxYVwQSu6MT0M1V1ewWNohbOyg41gpEUrd2Gj2CpdFSGo586LYDPDq0kaj0gvSfGRA14nynnpWn11kRftZ-yjO-onPN8LXKz0NfGhfJdja7RZghc-fYUyjSzB6WBUPt46OG6Iq5VO5EfuwyUy8RdqVOvV8a2riKMCnSTrrIFgkoGRAA4GE04isxLXiOhkdPEVnNKjKWWj3UhWR-AVkuYsm-cnFNdACeeicMDrb1G6WbNdiWhQHBUMu_202LBujQSVjJPyDD_tnYd0qYtc_lLGZm2C10zM7DmM4eIMRhYd-nC_en7ZL41pyXTHq4K6BVlSCNhucwz78VGxWjSMYs8ObW4ZMLC0a8_hnwFkl_PaZZybvbinT9IxSMlkamNj5kNgNIYr3Du7acQYSz8iFym4FRhJYdqdm2e_ayStte2TxftJIJwosp1XBKXUS5ZN0KpHriiRUrKaH4WYqhkNnhqjh12n2f846_EC2cKsSE_PjBKXDzuSVM7hcygTF2opSzZV7Ky-9pqc5sH333OL9lZKtlwVOuAbHUa_mWM4ijDZ4QKCygJzaN4CFTHVM2k_GtDVCXkPUXcAh9TN-gNlezI-rvdt4m8BfNYtxxIdrvDrgi7qcubR0JYozN8wqg2DpNqfSvze6XhffysxDTA9krF_GhlQuMoxgnwvZbYbAWJKV51llcSRyu5OmBTGxo3Xtd7CPc1RCr-L8Q5SK0OAJnyt1Wsz0wtOKno8WtSQ3TBQ6Xuo0oVzUSZuROtlKAUNjvkf0R9DcemTlBx2zP4kj7T_yIw5PZJDL0krUPoexSbCe4=\",\"summary\":[{\"type\":\"summary_text\",\"text\":\"**Evaluating test modifications**\\n\\nI realize I need to modify the tests, so I should dive into the repository to inspect the existing code. By inspecting it, I can identify what changes are necessary for the tests to be effective. This step is crucial to ensure everything functions correctly. I'm thinking through how to make these changes and what needs the most attention. I'll tackle it methodically to get it right!\"}]}"}, {"type": "toolCall", "id": "call_RonYV1dvLksbh5x2ivZVOjsx|fc_049667505a9e91930169ff87c3ba5c81a3ab89b77318e30b3a", "name": "bash", "arguments": {"command": "pwd && ls"}}], "api": "openai-responses", "provider": "OCA", "model": "gpt-5.5", "usage": {"input": 5872, "output": 36, "cacheRead": 1536, "cacheWrite": 0, "totalTokens": 7444, "cost": {"input": 0, "output": 0, "cacheRead": 0, "cacheWrite": 0, "total": 0}}, "stopReason": "toolUse", "timestamp": 1778354112532, "responseId": "resp_049667505a9e91930169ff87c1a02081a3aa2a2c7a266c8f2a"}, "toolResults": [{"role": "toolResult", "toolCallId": "call_RonYV1dvLksbh5x2ivZVOjsx|fc_049667505a9e91930169ff87c3ba5c81a3ab89b77318e30b3a", "toolName": "bash", "content": [{"type": "text", "text": "/home/vjovanov/c/forge/forge8/graalvm-reachability-metadata/forge/local_repositories/forge_worktrees/2428-8b9c7e6e\nAGENTS.md\nbuild\nbuild.gradle\nbuild_spec.yaml\ncheck-library-support.sh\nci.json\nCLAUDE.md\nCOVERAGE.md\ndocs\nforge\ngradle\ngradle.properties\ngradlew\ngradlew.bat\nLICENSE\nmetadata\nREADME.md\nsettings.gradle\nskills\nstats\ntests\n"}], "isError": false, "timestamp": 1778354116149}]}
[recv] {"type": "turn_start"}
[recv] {"type": "message_start", "message": {"role": "assistant", "content": [], "api": "openai-responses", "provider": "OCA", "model": "gpt-5.5", "usage": {"input": 0, "output": 0, "cacheRead": 0, "cacheWrite": 0, "totalTokens": 0, "cost": {"input": 0, "output": 0, "cacheRead": 0, "cacheWrite": 0, "total": 0}}, "stopReason": "stop", "timestamp": 1778354116151}}
[assistant-event] thinking_start
[assistant-event] thinking_end
[tool-call] start id=unknown
[tool-call] delta {"command":"find tests -path '*plexus-velocity*' -maxdepth 10 -type f | sort"}
[tool-call] end id=call_jmrRFPFVMnBtYtLmUzrYRZOD|fc_049667505a9e91930169ff87c686e481a38a3287429ed39cb9 name=bash args={"command": "find tests -path '*plexus-velocity*' -maxdepth 10 -type f | sort"}
[recv] {"type": "message_end", "message": {"role": "assistant", "content": [{"type": "thinking", "thinking": "", "thinkingSignature": "{\"id\":\"rs_049667505a9e91930169ff87c4fbec81a3be89f897fff339b3\",\"type\":\"reasoning\",\"encrypted_content\":\"gAAAAABp_4fGzzSdO7DK8p5NB8pVuBOXDQjbLLBt_Ke4N_u5b5YPbYJ7zRAejFz5xrubWwDLSvikQCBWkghPBjEcVizYCAaUnDrsLZndE67ZA47_udbrzvvY8RJ_TWti3ZdaRpHH2r15PsPjObQ41ofpNFkvQSeK99OzZqfD4zO4FwNOKGrNTGo1X13y3rTLj4jRylN7JxywZUmAaABqmFZb-3EnvowB9VWdnSse56UEowDLNmHYIrlI5_DUQIc-YynRi8thO7djDyfjufQTG3vh8LGJvtaVJb_5iPVYeg9EjziVeCt977gZ92FTBAN_CfTv6v_F9IgwRHoC_bCH_9ST_B79gQLuEDc7JwWacYc6BqO4he2lSEp9aTuKMpnFq_3mhTDoPqjGMbidaohn9UU5FhStdA-7j5WMa3bc3G77tWtlzVl46dEumiqCXpoqffsG2XwClGdqfblr4zOuK9hMfVxyB_tjnoz5e8R-TabtxD4dQroFDIUVgyiaP64BSmXCivsiCM59ltAdgsDFlMAX2LeOmZNPg7MUZHQoOyb6Olpd7l0PBccF3PAPJuR6nXDkD6TabI9tKoP8S1ajsvhDiMtDPISmwGf28hir-zflgEGK2kejGMLe1U1EEkOVtzhKkkyrVtUFE_h2C5JrjbkhWYZ4GZ1WKRvYfWtMy1k8_7NFCz9Al7ADLYD7klof6mbRuEyjDfojxSXcBMmcAhwHn1KignUQ_bwJ4o63ibAKoF3G3cfUGph2svWQna4ASiTW_TXKJGaoQ9WI0boyPRQ_zZdj6KxJAE_lVEhsGy_o2xvvPPBjp6PNw3txaqCyDbKs29PWNmv6HC7k0ewARw3VONAp7_kmwQhi616EvGgvWtAsdtuG2aQCkMpzzkmCXI83UxJdJ-RmlGsg4T_uGBBvO01HyCIeYD6yf_Eoq9a6GJ1veYgANK_Aw0OD0G4vaJanhVCYInwqY8BrSK9sqn6KE2bPyot4Xw==\",\"summary\":[]}"}, {"type": "toolCall", "id": "call_jmrRFPFVMnBtYtLmUzrYRZOD|fc_049667505a9e91930169ff87c686e481a38a3287429ed39cb9", "name": "bash", "arguments": {"command": "find tests -path '*plexus-velocity*' -maxdepth 10 -type f | sort"}}], "api": "openai-responses", "provider": "OCA", "model": "gpt-5.5", "usage": {"input": 393, "output": 50, "cacheRead": 7168, "cacheWrite": 0, "totalTokens": 7611, "cost": {"input": 0, "output": 0, "cacheRead": 0, "cacheWrite": 0, "total": 0}}, "stopReason": "toolUse", "timestamp": 1778354116151, "responseId": "resp_049667505a9e91930169ff87c473bc81a392b3ad183c4c55bb"}}
[tool-exec] start id=call_jmrRFPFVMnBtYtLmUzrYRZOD|fc_049667505a9e91930169ff87c686e481a38a3287429ed39cb9 name=bash args={"command": "find tests -path '*plexus-velocity*' -maxdepth 10 -type f | sort"}
[tool-exec] update id=call_jmrRFPFVMnBtYtLmUzrYRZOD|fc_049667505a9e91930169ff87c686e481a38a3287429ed39cb9 name=bash
[tool-exec] update id=call_jmrRFPFVMnBtYtLmUzrYRZOD|fc_049667505a9e91930169ff87c686e481a38a3287429ed39cb9 name=bash
  tests/src/org.codehaus.plexus/plexus-velocity/1.1.7/build.gradle
  tests/src/org.codehaus.plexus/plexus-velocity/1.1.7/build/jacoco/test.exec
  tests/src/org.codehaus.plexus/plexus-velocity/1.1.7/build/libs/org.codehaus.plexus.plexus-velocity_tests.jar
  tests/src/org.codehaus.plexus/plexus-velocity/1.1.7/build/native/generated/generateTestResourcesConfigFile/resource-config.json
  tests/src/org.codehaus.plexus/plexus-velocity/1.1.7/build/native/nativeTestCompile/dynamic-access/plexus-velocity-1.1.7/reflection-calls.json
  tests/src/org.codehaus.plexus/plexus-velocity/1.1.7/build/native/nativeTestCompile/dynamic-access/plexus-velocity-1.1.7/resource-calls.json
  tests/src/org.codehaus.plexus/plexus-velocity/1.1.7/build/native/nativeTestCompile/libmanagement_ext.so
  tests/src/org.codehaus.plexus/plexus-velocity/1.1.7/build/native/nativeTestCompile/org.codehaus.plexus.plexus-velocity_tests-tests
  tests/src/org.codehaus.plexus/plexus-velocity/1.1.7/build/reports/dynamic-access/dynamic-access-coverage.json
  tests/src/org.codehaus.plexus/plexus-velocity/1.1.7/build/reports/jacoco/test/jacocoTestReport.xml
  tests/src/org.codehaus.plexus/plexus-velocity/1.1.7/build/reports/problems/problems-report.html
  tests/src/org.codehaus.plexus/plexus-velocity/1.1.7/build/reports/tests/test/classes/org_codehaus_plexus.plexus_velocity.ContextClassLoaderResourceLoaderTest.html
  tests/src/org.codehaus.plexus/plexus-velocity/1.1.7/build/reports/tests/test/css/base-style.css
  tests/src/org.codehaus.plexus/plexus-velocity/1.1.7/build/reports/tests/test/css/style.css
  tests/src/org.codehaus.plexus/plexus-velocity/1.1.7/build/reports/tests/test/index.html
  tests/src/org.codehaus.plexus/plexus-velocity/1.1.7/build/reports/tests/test/js/report.js
  tests/src/org.codehaus.plexus/plexus-velocity/1.1.7/build/reports/tests/test/packages/org_codehaus_plexus.plexus_velocity.html
  tests/src/org.codehaus.plexus/plexus-velocity/1.1.7/build/resources/test/templates/context-class-loader-resource-loader-template.vm
  tests/src/org.codehaus.plexus/plexus-velocity/1.1.7/build/test-results/test/binary/output.bin
  tests/src/org.codehaus.plexus/plexus-velocity/1.1.7/build/test-results/test/binary/output.bin.idx
  tests/src/org.codehaus.plexus/plexus-velocity/1.1.7/build/test-results/test/binary/results.bin
  tests/src/org.codehaus.plexus/plexus-velocity/1.1.7/build/test-results/test/testlist/junit-platform-unique-ids-7863162912743115413.txt
  tests/src/org.codehaus.plexus/plexus-velocity/1.1.7/build/test-results/test/TEST-org_codehaus_plexus.plexus_velocity.ContextClassLoaderResourceLoaderTest.xml
  tests/src/org.codehaus.plexus/plexus-velocity/1.1.7/build/tmp/.cache/expanded/zip_9892ccb804f78c0637616b68610d363f/about.html
  tests/src/org.codehaus.plexus/plexus-velocity/1.1.7/build/tmp/.cache/expanded/zip_9892ccb804f78c0637616b68610d363f/jacocoagent.jar
  tests/src/org.codehaus.plexus/plexus-velocity/1.1.7/build/tmp/compileTestJava/compileTransaction/stash-dir/Plexus_velocityTest.class.uniqueId0
  tests/src/org.codehaus.plexus/plexus-velocity/1.1.7/build/tmp/compileTestJava/previous-compilation-data.bin
  tests/src/org.codehaus.plexus/plexus-velocity/1.1.7/build/tmp/jar/MANIFEST.MF
  tests/src/org.codehaus.plexus/plexus-velocity/1.1.7/.gitignore
  tests/src/org.codehaus.plexus/plexus-velocity/1.1.7/.gradle/9.1.0/checksums/checksums.lock
  tests/src/org.codehaus.plexus/plexus-velocity/1.1.7/.gradle/9.1.0/checksums/md5-checksums.bin
  tests/src/org.codehaus.plexus/plexus-velocity/1.1.7/.gradle/9.1.0/checksums/sha1-checksums.bin
  tests/src/org.codehaus.plexus/plexus-velocity/1.1.7/.gradle/9.1.0/executionHistory/executionHistory.bin
  tests/src/org.codehaus.plexus/plexus-velocity/1.1.7/.gradle/9.1.0/executionHistory/executionHistory.lock
  tests/src/org.codehaus.plexus/plexus-velocity/1.1.7/.gradle/9.1.0/expanded/expanded.lock
  tests/src/org.codehaus.plexus/plexus-velocity/1.1.7/.gradle/9.1.0/fileChanges/last-build.bin
  tests/src/org.codehaus.plexus/plexus-velocity/1.1.7/.gradle/9.1.0/fileHashes/fileHashes.bin
  tests/src/org.codehaus.plexus/plexus-velocity/1.1.7/.gradle/9.1.0/fileHashes/fileHashes.lock
  tests/src/org.codehaus.plexus/plexus-velocity/1.1.7/.gradle/9.1.0/fileHashes/resourceHashesCache.bin
  tests/src/org.codehaus.plexus/plexus-velocity/1.1.7/.gradle/9.1.0/gc.properties
  tests/src/org.codehaus.plexus/plexus-velocity/1.1.7/.gradle/buildOutputCleanup/buildOutputCleanup.lock
  tests/src/org.codehaus.plexus/plexus-velocity/1.1.7/.gradle/buildOutputCleanup/cache.properties
  tests/src/org.codehaus.plexus/plexus-velocity/1.1.7/.gradle/buildOutputCleanup/outputFiles.bin
  tests/src/org.codehaus.plexus/plexus-velocity/1.1.7/.gradle/file-system.probe
  tests/src/org.codehaus.plexus/plexus-velocity/1.1.7/.gradle/noVersion/buildLogic.lock
  tests/src/org.codehaus.plexus/plexus-velocity/1.1.7/gradle.properties
  tests/src/org.codehaus.plexus/plexus-velocity/1.1.7/.gradle/vcs-1/gc.properties
  tests/src/org.codehaus.plexus/plexus-velocity/1.1.7/settings.gradle
  tests/src/org.codehaus.plexus/plexus-velocity/1.1.7/src/test/java/org_codehaus_plexus/plexus_velocity/ContextClassLoaderResourceLoaderTest.java
  tests/src/org.codehaus.plexus/plexus-velocity/1.1.7/src/test/resources/templates/context-class-loader-resource-loader-template.vm
  tests/src/org.codehaus.plexus/plexus-velocity/1.1.7/test-results-native/test/TEST-junit-jupiter.xml
  tests/src/org.codehaus.plexus/plexus-velocity/1.1.7/test-results-native/test/TEST-junit-vintage.xml
  tests/src/org.codehaus.plexus/plexus-velocity/1.1.7/user-code-filter.json
[tool-exec] end id=call_jmrRFPFVMnBtYtLmUzrYRZOD|fc_049667505a9e91930169ff87c686e481a38a3287429ed39cb9 name=bash status=success
  tests/src/org.codehaus.plexus/plexus-velocity/1.1.7/build.gradle
  tests/src/org.codehaus.plexus/plexus-velocity/1.1.7/build/jacoco/test.exec
  tests/src/org.codehaus.plexus/plexus-velocity/1.1.7/build/libs/org.codehaus.plexus.plexus-velocity_tests.jar
  tests/src/org.codehaus.plexus/plexus-velocity/1.1.7/build/native/generated/generateTestResourcesConfigFile/resource-config.json
  tests/src/org.codehaus.plexus/plexus-velocity/1.1.7/build/native/nativeTestCompile/dynamic-access/plexus-velocity-1.1.7/reflection-calls.json
  tests/src/org.codehaus.plexus/plexus-velocity/1.1.7/build/native/nativeTestCompile/dynamic-access/plexus-velocity-1.1.7/resource-calls.json
  tests/src/org.codehaus.plexus/plexus-velocity/1.1.7/build/native/nativeTestCompile/libmanagement_ext.so
  tests/src/org.codehaus.plexus/plexus-velocity/1.1.7/build/native/nativeTestCompile/org.codehaus.plexus.plexus-velocity_tests-tests
  tests/src/org.codehaus.plexus/plexus-velocity/1.1.7/build/reports/dynamic-access/dynamic-access-coverage.json
  tests/src/org.codehaus.plexus/plexus-velocity/1.1.7/build/reports/jacoco/test/jacocoTestReport.xml
  tests/src/org.codehaus.plexus/plexus-velocity/1.1.7/build/reports/problems/problems-report.html
  tests/src/org.codehaus.plexus/plexus-velocity/1.1.7/build/reports/tests/test/classes/org_codehaus_plexus.plexus_velocity.ContextClassLoaderResourceLoaderTest.html
  tests/src/org.codehaus.plexus/plexus-velocity/1.1.7/build/reports/tests/test/css/base-style.css
  tests/src/org.codehaus.plexus/plexus-velocity/1.1.7/build/reports/tests/test/css/style.css
  tests/src/org.codehaus.plexus/plexus-velocity/1.1.7/build/reports/tests/test/index.html
  tests/src/org.codehaus.plexus/plexus-velocity/1.1.7/build/reports/tests/test/js/report.js
  tests/src/org.codehaus.plexus/plexus-velocity/1.1.7/build/reports/tests/test/packages/org_codehaus_plexus.plexus_velocity.html
  tests/src/org.codehaus.plexus/plexus-velocity/1.1.7/build/resources/test/templates/context-class-loader-resource-loader-template.vm
  tests/src/org.codehaus.plexus/plexus-velocity/1.1.7/build/test-results/test/binary/output.bin
  tests/src/org.codehaus.plexus/plexus-velocity/1.1.7/build/test-results/test/binary/output.bin.idx
  tests/src/org.codehaus.plexus/plexus-velocity/1.1.7/build/test-results/test/binary/results.bin
  tests/src/org.codehaus.plexus/plexus-velocity/1.1.7/build/test-results/test/testlist/junit-platform-unique-ids-7863162912743115413.txt
  tests/src/org.codehaus.plexus/plexus-velocity/1.1.7/build/test-results/test/TEST-org_codehaus_plexus.plexus_velocity.ContextClassLoaderResourceLoaderTest.xml
  tests/src/org.codehaus.plexus/plexus-velocity/1.1.7/build/tmp/.cache/expanded/zip_9892ccb804f78c0637616b68610d363f/about.html
  tests/src/org.codehaus.plexus/plexus-velocity/1.1.7/build/tmp/.cache/expanded/zip_9892ccb804f78c0637616b68610d363f/jacocoagent.jar
  tests/src/org.codehaus.plexus/plexus-velocity/1.1.7/build/tmp/compileTestJava/compileTransaction/stash-dir/Plexus_velocityTest.class.uniqueId0
  tests/src/org.codehaus.plexus/plexus-velocity/1.1.7/build/tmp/compileTestJava/previous-compilation-data.bin
  tests/src/org.codehaus.plexus/plexus-velocity/1.1.7/build/tmp/jar/MANIFEST.MF
  tests/src/org.codehaus.plexus/plexus-velocity/1.1.7/.gitignore
  tests/src/org.codehaus.plexus/plexus-velocity/1.1.7/.gradle/9.1.0/checksums/checksums.lock
  tests/src/org.codehaus.plexus/plexus-velocity/1.1.7/.gradle/9.1.0/checksums/md5-checksums.bin
  tests/src/org.codehaus.plexus/plexus-velocity/1.1.7/.gradle/9.1.0/checksums/sha1-checksums.bin
  tests/src/org.codehaus.plexus/plexus-velocity/1.1.7/.gradle/9.1.0/executionHistory/executionHistory.bin
  tests/src/org.codehaus.plexus/plexus-velocity/1.1.7/.gradle/9.1.0/executionHistory/executionHistory.lock
  tests/src/org.codehaus.plexus/plexus-velocity/1.1.7/.gradle/9.1.0/expanded/expanded.lock
  tests/src/org.codehaus.plexus/plexus-velocity/1.1.7/.gradle/9.1.0/fileChanges/last-build.bin
  tests/src/org.codehaus.plexus/plexus-velocity/1.1.7/.gradle/9.1.0/fileHashes/fileHashes.bin
  tests/src/org.codehaus.plexus/plexus-velocity/1.1.7/.gradle/9.1.0/fileHashes/fileHashes.lock
  tests/src/org.codehaus.plexus/plexus-velocity/1.1.7/.gradle/9.1.0/fileHashes/resourceHashesCache.bin
  tests/src/org.codehaus.plexus/plexus-velocity/1.1.7/.gradle/9.1.0/gc.properties
  tests/src/org.codehaus.plexus/plexus-velocity/1.1.7/.gradle/buildOutputCleanup/buildOutputCleanup.lock
  tests/src/org.codehaus.plexus/plexus-velocity/1.1.7/.gradle/buildOutputCleanup/cache.properties
  tests/src/org.codehaus.plexus/plexus-velocity/1.1.7/.gradle/buildOutputCleanup/outputFiles.bin
  tests/src/org.codehaus.plexus/plexus-velocity/1.1.7/.gradle/file-system.probe
  tests/src/org.codehaus.plexus/plexus-velocity/1.1.7/.gradle/noVersion/buildLogic.lock
  tests/src/org.codehaus.plexus/plexus-velocity/1.1.7/gradle.properties
  tests/src/org.codehaus.plexus/plexus-velocity/1.1.7/.gradle/vcs-1/gc.properties
  tests/src/org.codehaus.plexus/plexus-velocity/1.1.7/settings.gradle
  tests/src/org.codehaus.plexus/plexus-velocity/1.1.7/src/test/java/org_codehaus_plexus/plexus_velocity/ContextClassLoaderResourceLoaderTest.java
  tests/src/org.codehaus.plexus/plexus-velocity/1.1.7/src/test/resources/templates/context-class-loader-resource-loader-template.vm
  tests/src/org.codehaus.plexus/plexus-velocity/1.1.7/test-results-native/test/TEST-junit-jupiter.xml
  tests/src/org.codehaus.plexus/plexus-velocity/1.1.7/test-results-native/test/TEST-junit-vintage.xml
  tests/src/org.codehaus.plexus/plexus-velocity/1.1.7/user-code-filter.json
[recv] {"type": "message_start", "message": {"role": "toolResult", "toolCallId": "call_jmrRFPFVMnBtYtLmUzrYRZOD|fc_049667505a9e91930169ff87c686e481a38a3287429ed39cb9", "toolName": "bash", "content": [{"type": "text", "text": "tests/src/org.codehaus.plexus/plexus-velocity/1.1.7/build.gradle\ntests/src/org.codehaus.plexus/plexus-velocity/1.1.7/build/jacoco/test.exec\ntests/src/org.codehaus.plexus/plexus-velocity/1.1.7/build/libs/org.codehaus.plexus.plexus-velocity_tests.jar\ntests/src/org.codehaus.plexus/plexus-velocity/1.1.7/build/native/generated/generateTestResourcesConfigFile/resource-config.json\ntests/src/org.codehaus.plexus/plexus-velocity/1.1.7/build/native/nativeTestCompile/dynamic-access/plexus-velocity-1.1.7/reflection-calls.json\ntests/src/org.codehaus.plexus/plexus-velocity/1.1.7/build/native/nativeTestCompile/dynamic-access/plexus-velocity-1.1.7/resource-calls.json\ntests/src/org.codehaus.plexus/plexus-velocity/1.1.7/build/native/nativeTestCompile/libmanagement_ext.so\ntests/src/org.codehaus.plexus/plexus-velocity/1.1.7/build/native/nativeTestCompile/org.codehaus.plexus.plexus-velocity_tests-tests\ntests/src/org.codehaus.plexus/plexus-velocity/1.1.7/build/reports/dynamic-access/dynamic-access-coverage.json\ntests/src/org.codehaus.plexus/plexus-velocity/1.1.7/build/reports/jacoco/test/jacocoTestReport.xml\ntests/src/org.codehaus.plexus/plexus-velocity/1.1.7/build/reports/problems/problems-report.html\ntests/src/org.codehaus.plexus/plexus-velocity/1.1.7/build/reports/tests/test/classes/org_codehaus_plexus.plexus_velocity.ContextClassLoaderResourceLoaderTest.html\ntests/src/org.codehaus.plexus/plexus-velocity/1.1.7/build/reports/tests/test/css/base-style.css\ntests/src/org.codehaus.plexus/plexus-velocity/1.1.7/build/reports/tests/test/css/style.css\ntests/src/org.codehaus.plexus/plexus-velocity/1.1.7/build/reports/tests/test/index.html\ntests/src/org.codehaus.plexus/plexus-velocity/1.1.7/build/reports/tests/test/js/report.js\ntests/src/org.codehaus.plexus/plexus-velocity/1.1.7/build/reports/tests/test/packages/org_codehaus_plexus.plexus_velocity.html\ntests/src/org.codehaus.plexus/plexus-velocity/1.1.7/build/resources/test/templates/context-class-loader-resource-loader-template.vm\ntests/src/org.codehaus.plexus/plexus-velocity/1.1.7/build/test-results/test/binary/output.bin\ntests/src/org.codehaus.plexus/plexus-velocity/1.1.7/build/test-results/test/binary/output.bin.idx\ntests/src/org.codehaus.plexus/plexus-velocity/1.1.7/build/test-results/test/binary/results.bin\ntests/src/org.codehaus.plexus/plexus-velocity/1.1.7/build/test-results/test/testlist/junit-platform-unique-ids-7863162912743115413.txt\ntests/src/org.codehaus.plexus/plexus-velocity/1.1.7/build/test-results/test/TEST-org_codehaus_plexus.plexus_velocity.ContextClassLoaderResourceLoaderTest.xml\ntests/src/org.codehaus.plexus/plexus-velocity/1.1.7/build/tmp/.cache/expanded/zip_9892ccb804f78c0637616b68610d363f/about.html\ntests/src/org.codehaus.plexus/plexus-velocity/1.1.7/build/tmp/.cache/expanded/zip_9892ccb804f78c0637616b68610d363f/jacocoagent.jar\ntests/src/org.codehaus.plexus/plexus-velocity/1.1.7/build/tmp/compileTestJava/compileTransaction/stash-dir/Plexus_velocityTest.class.uniqueId0\ntests/src/org.codehaus.plexus/plexus-velocity/1.1.7/build/tmp/compileTestJava/previous-compilation-data.bin\ntests/src/org.codehaus.plexus/plexus-velocity/1.1.7/build/tmp/jar/MANIFEST.MF\ntests/src/org.codehaus.plexus/plexus-velocity/1.1.7/.gitignore\ntests/src/org.codehaus.plexus/plexus-velocity/1.1.7/.gradle/9.1.0/checksums/checksums.lock\ntests/src/org.codehaus.plexus/plexus-velocity/1.1.7/.gradle/9.1.0/checksums/md5-checksums.bin\ntests/src/org.codehaus.plexus/plexus-velocity/1.1.7/.gradle/9.1.0/checksums/sha1-checksums.bin\ntests/src/org.codehaus.plexus/plexus-velocity/1.1.7/.gradle/9.1.0/executionHistory/executionHistory.bin\ntests/src/org.codehaus.plexus/plexus-velocity/1.1.7/.gradle/9.1.0/executionHistory/executionHistory.lock\ntests/src/org.codehaus.plexus/plexus-velocity/1.1.7/.gradle/9.1.0/expanded/expanded.lock\ntests/src/org.codehaus.plexus/plexus-velocity/1.1.7/.gradle/9.1.0/fileChanges/last-build.bin\ntests/src/org.codehaus.plexus/plexus-velocity/1.1.7/.gradle/9.1.0/fileHashes/fileHashes.bin\ntests/src/org.codehaus.plexus/plexus-velocity/1.1.7/.gradle/9.1.0/fileHashes/fileHashes.lock\ntests/src/org.codehaus.plexus/plexus-velocity/1.1.7/.gradle/9.1.0/fileHashes/resourceHashesCache.bin\ntests/src/org.codehaus.plexus/plexus-velocity/1.1.7/.gradle/9.1.0/gc.properties\ntests/src/org.codehaus.plexus/plexus-velocity/1.1.7/.gradle/buildOutputCleanup/buildOutputCleanup.lock\ntests/src/org.codehaus.plexus/plexus-velocity/1.1.7/.gradle/buildOutputCleanup/cache.properties\ntests/src/org.codehaus.plexus/plexus-velocity/1.1.7/.gradle/buildOutputCleanup/outputFiles.bin\ntests/src/org.codehaus.plexus/plexus-velocity/1.1.7/.gradle/file-system.probe\ntests/src/org.codehaus.plexus/plexus-velocity/1.1.7/.gradle/noVersion/buildLogic.lock\ntests/src/org.codehaus.plexus/plexus-velocity/1.1.7/gradle.properties\ntests/src/org.codehaus.plexus/plexus-velocity/1.1.7/.gradle/vcs-1/gc.properties\ntests/src/org.codehaus.plexus/plexus-velocity/1.1.7/settings.gradle\ntests/src/org.codehaus.plexus/plexus-velocity/1.1.7/src/test/java/org_codehaus_plexus/plexus_velocity/ContextClassLoaderResourceLoaderTest.java\ntests/src/org.codehaus.plexus/plexus-velocity/1.1.7/src/test/resources/templates/context-class-loader-resource-loader-template.vm\ntests/src/org.codehaus.plexus/plexus-velocity/1.1.7/test-results-native/test/TEST-junit-jupiter.xml\ntests/src/org.codehaus.plexus/plexus-velocity/1.1.7/test-results-native/test/TEST-junit-vintage.xml\ntests/src/org.codehaus.plexus/plexus-velocity/1.1.7/user-code-filter.json\n"}], "isError": false, "timestamp": 1778354118803}}
[recv] {"type": "message_end", "message": {"role": "toolResult", "toolCallId": "call_jmrRFPFVMnBtYtLmUzrYRZOD|fc_049667505a9e91930169ff87c686e481a38a3287429ed39cb9", "toolName": "bash", "content": [{"type": "text", "text": "tests/src/org.codehaus.plexus/plexus-velocity/1.1.7/build.gradle\ntests/src/org.codehaus.plexus/plexus-velocity/1.1.7/build/jacoco/test.exec\ntests/src/org.codehaus.plexus/plexus-velocity/1.1.7/build/libs/org.codehaus.plexus.plexus-velocity_tests.jar\ntests/src/org.codehaus.plexus/plexus-velocity/1.1.7/build/native/generated/generateTestResourcesConfigFile/resource-config.json\ntests/src/org.codehaus.plexus/plexus-velocity/1.1.7/build/native/nativeTestCompile/dynamic-access/plexus-velocity-1.1.7/reflection-calls.json\ntests/src/org.codehaus.plexus/plexus-velocity/1.1.7/build/native/nativeTestCompile/dynamic-access/plexus-velocity-1.1.7/resource-calls.json\ntests/src/org.codehaus.plexus/plexus-velocity/1.1.7/build/native/nativeTestCompile/libmanagement_ext.so\ntests/src/org.codehaus.plexus/plexus-velocity/1.1.7/build/native/nativeTestCompile/org.codehaus.plexus.plexus-velocity_tests-tests\ntests/src/org.codehaus.plexus/plexus-velocity/1.1.7/build/reports/dynamic-access/dynamic-access-coverage.json\ntests/src/org.codehaus.plexus/plexus-velocity/1.1.7/build/reports/jacoco/test/jacocoTestReport.xml\ntests/src/org.codehaus.plexus/plexus-velocity/1.1.7/build/reports/problems/problems-report.html\ntests/src/org.codehaus.plexus/plexus-velocity/1.1.7/build/reports/tests/test/classes/org_codehaus_plexus.plexus_velocity.ContextClassLoaderResourceLoaderTest.html\ntests/src/org.codehaus.plexus/plexus-velocity/1.1.7/build/reports/tests/test/css/base-style.css\ntests/src/org.codehaus.plexus/plexus-velocity/1.1.7/build/reports/tests/test/css/style.css\ntests/src/org.codehaus.plexus/plexus-velocity/1.1.7/build/reports/tests/test/index.html\ntests/src/org.codehaus.plexus/plexus-velocity/1.1.7/build/reports/tests/test/js/report.js\ntests/src/org.codehaus.plexus/plexus-velocity/1.1.7/build/reports/tests/test/packages/org_codehaus_plexus.plexus_velocity.html\ntests/src/org.codehaus.plexus/plexus-velocity/1.1.7/build/resources/test/templates/context-class-loader-resource-loader-template.vm\ntests/src/org.codehaus.plexus/plexus-velocity/1.1.7/build/test-results/test/binary/output.bin\ntests/src/org.codehaus.plexus/plexus-velocity/1.1.7/build/test-results/test/binary/output.bin.idx\ntests/src/org.codehaus.plexus/plexus-velocity/1.1.7/build/test-results/test/binary/results.bin\ntests/src/org.codehaus.plexus/plexus-velocity/1.1.7/build/test-results/test/testlist/junit-platform-unique-ids-7863162912743115413.txt\ntests/src/org.codehaus.plexus/plexus-velocity/1.1.7/build/test-results/test/TEST-org_codehaus_plexus.plexus_velocity.ContextClassLoaderResourceLoaderTest.xml\ntests/src/org.codehaus.plexus/plexus-velocity/1.1.7/build/tmp/.cache/expanded/zip_9892ccb804f78c0637616b68610d363f/about.html\ntests/src/org.codehaus.plexus/plexus-velocity/1.1.7/build/tmp/.cache/expanded/zip_9892ccb804f78c0637616b68610d363f/jacocoagent.jar\ntests/src/org.codehaus.plexus/plexus-velocity/1.1.7/build/tmp/compileTestJava/compileTransaction/stash-dir/Plexus_velocityTest.class.uniqueId0\ntests/src/org.codehaus.plexus/plexus-velocity/1.1.7/build/tmp/compileTestJava/previous-compilation-data.bin\ntests/src/org.codehaus.plexus/plexus-velocity/1.1.7/build/tmp/jar/MANIFEST.MF\ntests/src/org.codehaus.plexus/plexus-velocity/1.1.7/.gitignore\ntests/src/org.codehaus.plexus/plexus-velocity/1.1.7/.gradle/9.1.0/checksums/checksums.lock\ntests/src/org.codehaus.plexus/plexus-velocity/1.1.7/.gradle/9.1.0/checksums/md5-checksums.bin\ntests/src/org.codehaus.plexus/plexus-velocity/1.1.7/.gradle/9.1.0/checksums/sha1-checksums.bin\ntests/src/org.codehaus.plexus/plexus-velocity/1.1.7/.gradle/9.1.0/executionHistory/executionHistory.bin\ntests/src/org.codehaus.plexus/plexus-velocity/1.1.7/.gradle/9.1.0/executionHistory/executionHistory.lock\ntests/src/org.codehaus.plexus/plexus-velocity/1.1.7/.gradle/9.1.0/expanded/expanded.lock\ntests/src/org.codehaus.plexus/plexus-velocity/1.1.7/.gradle/9.1.0/fileChanges/last-build.bin\ntests/src/org.codehaus.plexus/plexus-velocity/1.1.7/.gradle/9.1.0/fileHashes/fileHashes.bin\ntests/src/org.codehaus.plexus/plexus-velocity/1.1.7/.gradle/9.1.0/fileHashes/fileHashes.lock\ntests/src/org.codehaus.plexus/plexus-velocity/1.1.7/.gradle/9.1.0/fileHashes/resourceHashesCache.bin\ntests/src/org.codehaus.plexus/plexus-velocity/1.1.7/.gradle/9.1.0/gc.properties\ntests/src/org.codehaus.plexus/plexus-velocity/1.1.7/.gradle/buildOutputCleanup/buildOutputCleanup.lock\ntests/src/org.codehaus.plexus/plexus-velocity/1.1.7/.gradle/buildOutputCleanup/cache.properties\ntests/src/org.codehaus.plexus/plexus-velocity/1.1.7/.gradle/buildOutputCleanup/outputFiles.bin\ntests/src/org.codehaus.plexus/plexus-velocity/1.1.7/.gradle/file-system.probe\ntests/src/org.codehaus.plexus/plexus-velocity/1.1.7/.gradle/noVersion/buildLogic.lock\ntests/src/org.codehaus.plexus/plexus-velocity/1.1.7/gradle.properties\ntests/src/org.codehaus.plexus/plexus-velocity/1.1.7/.gradle/vcs-1/gc.properties\ntests/src/org.codehaus.plexus/plexus-velocity/1.1.7/settings.gradle\ntests/src/org.codehaus.plexus/plexus-velocity/1.1.7/src/test/java/org_codehaus_plexus/plexus_velocity/ContextClassLoaderResourceLoaderTest.java\ntests/src/org.codehaus.plexus/plexus-velocity/1.1.7/src/test/resources/templates/context-class-loader-resource-loader-template.vm\ntests/src/org.codehaus.plexus/plexus-velocity/1.1.7/test-results-native/test/TEST-junit-jupiter.xml\ntests/src/org.codehaus.plexus/plexus-velocity/1.1.7/test-results-native/test/TEST-junit-vintage.xml\ntests/src/org.codehaus.plexus/plexus-velocity/1.1.7/user-code-filter.json\n"}], "isError": false, "timestamp": 1778354118803}}
[recv] {"type": "turn_end", "message": {"role": "assistant", "content": [{"type": "thinking", "thinking": "", "thinkingSignature": "{\"id\":\"rs_049667505a9e91930169ff87c4fbec81a3be89f897fff339b3\",\"type\":\"reasoning\",\"encrypted_content\":\"gAAAAABp_4fGzzSdO7DK8p5NB8pVuBOXDQjbLLBt_Ke4N_u5b5YPbYJ7zRAejFz5xrubWwDLSvikQCBWkghPBjEcVizYCAaUnDrsLZndE67ZA47_udbrzvvY8RJ_TWti3ZdaRpHH2r15PsPjObQ41ofpNFkvQSeK99OzZqfD4zO4FwNOKGrNTGo1X13y3rTLj4jRylN7JxywZUmAaABqmFZb-3EnvowB9VWdnSse56UEowDLNmHYIrlI5_DUQIc-YynRi8thO7djDyfjufQTG3vh8LGJvtaVJb_5iPVYeg9EjziVeCt977gZ92FTBAN_CfTv6v_F9IgwRHoC_bCH_9ST_B79gQLuEDc7JwWacYc6BqO4he2lSEp9aTuKMpnFq_3mhTDoPqjGMbidaohn9UU5FhStdA-7j5WMa3bc3G77tWtlzVl46dEumiqCXpoqffsG2XwClGdqfblr4zOuK9hMfVxyB_tjnoz5e8R-TabtxD4dQroFDIUVgyiaP64BSmXCivsiCM59ltAdgsDFlMAX2LeOmZNPg7MUZHQoOyb6Olpd7l0PBccF3PAPJuR6nXDkD6TabI9tKoP8S1ajsvhDiMtDPISmwGf28hir-zflgEGK2kejGMLe1U1EEkOVtzhKkkyrVtUFE_h2C5JrjbkhWYZ4GZ1WKRvYfWtMy1k8_7NFCz9Al7ADLYD7klof6mbRuEyjDfojxSXcBMmcAhwHn1KignUQ_bwJ4o63ibAKoF3G3cfUGph2svWQna4ASiTW_TXKJGaoQ9WI0boyPRQ_zZdj6KxJAE_lVEhsGy_o2xvvPPBjp6PNw3txaqCyDbKs29PWNmv6HC7k0ewARw3VONAp7_kmwQhi616EvGgvWtAsdtuG2aQCkMpzzkmCXI83UxJdJ-RmlGsg4T_uGBBvO01HyCIeYD6yf_Eoq9a6GJ1veYgANK_Aw0OD0G4vaJanhVCYInwqY8BrSK9sqn6KE2bPyot4Xw==\",\"summary\":[]}"}, {"type": "toolCall", "id": "call_jmrRFPFVMnBtYtLmUzrYRZOD|fc_049667505a9e91930169ff87c686e481a38a3287429ed39cb9", "name": "bash", "arguments": {"command": "find tests -path '*plexus-velocity*' -maxdepth 10 -type f | sort"}}], "api": "openai-responses", "provider": "OCA", "model": "gpt-5.5", "usage": {"input": 393, "output": 50, "cacheRead": 7168, "cacheWrite": 0, "totalTokens": 7611, "cost": {"input": 0, "output": 0, "cacheRead": 0, "cacheWrite": 0, "total": 0}}, "stopReason": "toolUse", "timestamp": 1778354116151, "responseId": "resp_049667505a9e91930169ff87c473bc81a392b3ad183c4c55bb"}, "toolResults": [{"role": "toolResult", "toolCallId": "call_jmrRFPFVMnBtYtLmUzrYRZOD|fc_049667505a9e91930169ff87c686e481a38a3287429ed39cb9", "toolName": "bash", "content": [{"type": "text", "text": "tests/src/org.codehaus.plexus/plexus-velocity/1.1.7/build.gradle\ntests/src/org.codehaus.plexus/plexus-velocity/1.1.7/build/jacoco/test.exec\ntests/src/org.codehaus.plexus/plexus-velocity/1.1.7/build/libs/org.codehaus.plexus.plexus-velocity_tests.jar\ntests/src/org.codehaus.plexus/plexus-velocity/1.1.7/build/native/generated/generateTestResourcesConfigFile/resource-config.json\ntests/src/org.codehaus.plexus/plexus-velocity/1.1.7/build/native/nativeTestCompile/dynamic-access/plexus-velocity-1.1.7/reflection-calls.json\ntests/src/org.codehaus.plexus/plexus-velocity/1.1.7/build/native/nativeTestCompile/dynamic-access/plexus-velocity-1.1.7/resource-calls.json\ntests/src/org.codehaus.plexus/plexus-velocity/1.1.7/build/native/nativeTestCompile/libmanagement_ext.so\ntests/src/org.codehaus.plexus/plexus-velocity/1.1.7/build/native/nativeTestCompile/org.codehaus.plexus.plexus-velocity_tests-tests\ntests/src/org.codehaus.plexus/plexus-velocity/1.1.7/build/reports/dynamic-access/dynamic-access-coverage.json\ntests/src/org.codehaus.plexus/plexus-velocity/1.1.7/build/reports/jacoco/test/jacocoTestReport.xml\ntests/src/org.codehaus.plexus/plexus-velocity/1.1.7/build/reports/problems/problems-report.html\ntests/src/org.codehaus.plexus/plexus-velocity/1.1.7/build/reports/tests/test/classes/org_codehaus_plexus.plexus_velocity.ContextClassLoaderResourceLoaderTest.html\ntests/src/org.codehaus.plexus/plexus-velocity/1.1.7/build/reports/tests/test/css/base-style.css\ntests/src/org.codehaus.plexus/plexus-velocity/1.1.7/build/reports/tests/test/css/style.css\ntests/src/org.codehaus.plexus/plexus-velocity/1.1.7/build/reports/tests/test/index.html\ntests/src/org.codehaus.plexus/plexus-velocity/1.1.7/build/reports/tests/test/js/report.js\ntests/src/org.codehaus.plexus/plexus-velocity/1.1.7/build/reports/tests/test/packages/org_codehaus_plexus.plexus_velocity.html\ntests/src/org.codehaus.plexus/plexus-velocity/1.1.7/build/resources/test/templates/context-class-loader-resource-loader-template.vm\ntests/src/org.codehaus.plexus/plexus-velocity/1.1.7/build/test-results/test/binary/output.bin\ntests/src/org.codehaus.plexus/plexus-velocity/1.1.7/build/test-results/test/binary/output.bin.idx\ntests/src/org.codehaus.plexus/plexus-velocity/1.1.7/build/test-results/test/binary/results.bin\ntests/src/org.codehaus.plexus/plexus-velocity/1.1.7/build/test-results/test/testlist/junit-platform-unique-ids-7863162912743115413.txt\ntests/src/org.codehaus.plexus/plexus-velocity/1.1.7/build/test-results/test/TEST-org_codehaus_plexus.plexus_velocity.ContextClassLoaderResourceLoaderTest.xml\ntests/src/org.codehaus.plexus/plexus-velocity/1.1.7/build/tmp/.cache/expanded/zip_9892ccb804f78c0637616b68610d363f/about.html\ntests/src/org.codehaus.plexus/plexus-velocity/1.1.7/build/tmp/.cache/expanded/zip_9892ccb804f78c0637616b68610d363f/jacocoagent.jar\ntests/src/org.codehaus.plexus/plexus-velocity/1.1.7/build/tmp/compileTestJava/compileTransaction/stash-dir/Plexus_velocityTest.class.uniqueId0\ntests/src/org.codehaus.plexus/plexus-velocity/1.1.7/build/tmp/compileTestJava/previous-compilation-data.bin\ntests/src/org.codehaus.plexus/plexus-velocity/1.1.7/build/tmp/jar/MANIFEST.MF\ntests/src/org.codehaus.plexus/plexus-velocity/1.1.7/.gitignore\ntests/src/org.codehaus.plexus/plexus-velocity/1.1.7/.gradle/9.1.0/checksums/checksums.lock\ntests/src/org.codehaus.plexus/plexus-velocity/1.1.7/.gradle/9.1.0/checksums/md5-checksums.bin\ntests/src/org.codehaus.plexus/plexus-velocity/1.1.7/.gradle/9.1.0/checksums/sha1-checksums.bin\ntests/src/org.codehaus.plexus/plexus-velocity/1.1.7/.gradle/9.1.0/executionHistory/executionHistory.bin\ntests/src/org.codehaus.plexus/plexus-velocity/1.1.7/.gradle/9.1.0/executionHistory/executionHistory.lock\ntests/src/org.codehaus.plexus/plexus-velocity/1.1.7/.gradle/9.1.0/expanded/expanded.lock\ntests/src/org.codehaus.plexus/plexus-velocity/1.1.7/.gradle/9.1.0/fileChanges/last-build.bin\ntests/src/org.codehaus.plexus/plexus-velocity/1.1.7/.gradle/9.1.0/fileHashes/fileHashes.bin\ntests/src/org.codehaus.plexus/plexus-velocity/1.1.7/.gradle/9.1.0/fileHashes/fileHashes.lock\ntests/src/org.codehaus.plexus/plexus-velocity/1.1.7/.gradle/9.1.0/fileHashes/resourceHashesCache.bin\ntests/src/org.codehaus.plexus/plexus-velocity/1.1.7/.gradle/9.1.0/gc.properties\ntests/src/org.codehaus.plexus/plexus-velocity/1.1.7/.gradle/buildOutputCleanup/buildOutputCleanup.lock\ntests/src/org.codehaus.plexus/plexus-velocity/1.1.7/.gradle/buildOutputCleanup/cache.properties\ntests/src/org.codehaus.plexus/plexus-velocity/1.1.7/.gradle/buildOutputCleanup/outputFiles.bin\ntests/src/org.codehaus.plexus/plexus-velocity/1.1.7/.gradle/file-system.probe\ntests/src/org.codehaus.plexus/plexus-velocity/1.1.7/.gradle/noVersion/buildLogic.lock\ntests/src/org.codehaus.plexus/plexus-velocity/1.1.7/gradle.properties\ntests/src/org.codehaus.plexus/plexus-velocity/1.1.7/.gradle/vcs-1/gc.properties\ntests/src/org.codehaus.plexus/plexus-velocity/1.1.7/settings.gradle\ntests/src/org.codehaus.plexus/plexus-velocity/1.1.7/src/test/java/org_codehaus_plexus/plexus_velocity/ContextClassLoaderResourceLoaderTest.java\ntests/src/org.codehaus.plexus/plexus-velocity/1.1.7/src/test/resources/templates/context-class-loader-resource-loader-template.vm\ntests/src/org.codehaus.plexus/plexus-velocity/1.1.7/test-results-native/test/TEST-junit-jupiter.xml\ntests/src/org.codehaus.plexus/plexus-velocity/1.1.7/test-results-native/test/TEST-junit-vintage.xml\ntests/src/org.codehaus.plexus/plexus-velocity/1.1.7/user-code-filter.json\n"}], "isError": false, "timestamp": 1778354118803}]}
[recv] {"type": "turn_start"}
[recv] {"type": "message_start", "message": {"role": "assistant", "content": [], "api": "openai-responses", "provider": "OCA", "model": "gpt-5.5", "usage": {"input": 0, "output": 0, "cacheRead": 0, "cacheWrite": 0, "totalTokens": 0, "cost": {"input": 0, "output": 0, "cacheRead": 0, "cacheWrite": 0, "total": 0}}, "stopReason": "stop", "timestamp": 1778354118806}}
[assistant-event] thinking_start
[thinking] **Clarifying Java file requirements**
[thinking] 
[thinking] I’m considering the need for an active class to have its own dedicated Java file in a one-to-one format. This seems crucial to keep things organized. I’m also thinking about whether the current test is specifically for a resource loader. I should really read through the source to confirm that understanding. It's important to get the details right so everything functions as intended!
[thinking] 
[assistant-event] thinking_end
[tool-call] start id=unknown
[tool-call] delta {"path":"local_repositories/source_context/org.codehaus.plexus/plexus-velocity/1.1.7/main/extracted/org/codehaus/plexus/velocity/VelocityComponent.java"}
[tool-call] end id=call_Eecshe4qwV8BCJLUGUVLIQFp|fc_049667505a9e91930169ff87c94f5481a3bac6b2526faac9c2 name=read args={"path": "local_repositories/source_context/org.codehaus.plexus/plexus-velocity/1.1.7/main/extracted/org/codehaus/plexus/velocity/VelocityComponent.java"}
[tool-call] start id=unknown
[tool-call] delta {"path":"tests/src/org.codehaus.plexus/plexus-velocity/1.1.7/src/test/java/org_codehaus_plexus/plexus_velocity/ContextClassLoaderResourceLoaderTest.java"}
[tool-call] end id=call_35fw7MRjC0vCSjGDpuRqBHlX|fc_049667505a9e91930169ff87c94f6481a391dce51cf20f8e3a name=read args={"path": "tests/src/org.codehaus.plexus/plexus-velocity/1.1.7/src/test/java/org_codehaus_plexus/plexus_velocity/ContextClassLoaderResourceLoaderTest.java"}
[tool-call] start id=unknown
[tool-call] delta {"path":"tests/src/org.codehaus.plexus/plexus-velocity/1.1.7/build.gradle"}
[tool-call] end id=call_nS0k5KrQfmwQfhOjLXDQUCo0|fc_049667505a9e91930169ff87c94f6881a3b604c2bf77040638 name=read args={"path": "tests/src/org.codehaus.plexus/plexus-velocity/1.1.7/build.gradle"}
[recv] {"type": "message_end", "message": {"role": "assistant", "content": [{"type": "thinking", "thinking": "**Clarifying Java file requirements**\n\nI’m considering the need for an active class to have its own dedicated Java file in a one-to-one format. This seems crucial to keep things organized. I’m also thinking about whether the current test is specifically for a resource loader. I should really read through the source to confirm that understanding. It's important to get the details right so everything functions as intended!", "thinkingSignature": "{\"id\":\"rs_049667505a9e91930169ff87c7adc881a39890096b6592a9d2\",\"type\":\"reasoning\",\"encrypted_content\":\"gAAAAABp_4fJ7ibL8EGQaxf4kUWNw0dFsZDFS3dHltB67YYuH6rDN49SZS9eSwXMz8uJNk4fkuLtvYWjPs186kEzOk55iZDStxu-DV9uQjmvrT3acMUZV4-4Ww5JUTYoomeFe7LRlSzdJj4HWZi3wefW20EXI6dZG5jmlsldOIS0ZAS1Og4l5RLvEA9iLE6yrIfHnbfiuX_AS9n-GLB2nhIRm0Fk_duJnZo6XDGOELIY3kruoLyAkAaMFluQba2nr_BawRVe9OyXEi9DlGIMDVjc8P1oggRg-HsnSMD26mlBb4mHTJjKeXPDA3RAP2zjrIzQadiiaoHxZ-70k7bYklasFUX_hmkN8LbP-7NaUICGxwzeBfSLscvqmi-VCHNnfNup0zoxJ7wS6dWP2itY3pQPJCXXeh4ZcBWxpCtZWTp7FvxiBtKje-wVrwYFChF8N-ArXyUkAZaBf0oYWH3y0xYC1l88rz4uaaerJoPGvPArPcAt_FLa9LswzsiXo2YMk4ek8vm9KSGMqhiA1_4OXpERBkIFY_ozVMn05HoE3S3yFbbRdU3enm11U-Mc5334AgWzzHrsvUlp-_-hrYD4sTnC5dX6f0mS2jM86BFDAP0Uq7iKekV7UYZBXc_jtL_8OcWsAzCIu-bEOIOfCDOJ39zyYBOfeU-5aED3-eyAi0QVutXEUEdruaSsBN-v-ln_hDfD1qem3HHaVX4GytxM6afOD0GKS2WYAXgCriavzXy3TE1QxtsRkIWU5IuGTR58dhAio3qWYLeCJ3E-EuJ6GiFqWNE_uw2Ha-1qSSmJ_5GzklzvjDyHC36ZKUdqYAl17ZJd5RiyCHWmAv-k6k-cnRvmljn39kc46UvcZZ_9yz7Is7EknllVtw1jhkxjQpwMOXliC0T6L7gIrlltYe56jSw5UklWCQZWDhfZkxaeL2y6TiT1A7vsEYx0m6r0ibFSEmHietCxSyhpGTNK32houBybYc-S_kVC-VXYDoNot8WmTXQtR4uUXyjFAb_vdbdKf8JOtVljw8WFaynsxbqbDQ_M39tIsNSU8p49FEdhL8lGU9IGARUfByAwAobrQvN0aGqgCQ2Yu7WT\",\"summary\":[{\"type\":\"summary_text\",\"text\":\"**Clarifying Java file requirements**\\n\\nI’m considering the need for an active class to have its own dedicated Java file in a one-to-one format. This seems crucial to keep things organized. I’m also thinking about whether the current test is specifically for a resource loader. I should really read through the source to confirm that understanding. It's important to get the details right so everything functions as intended!\"}]}"}, {"type": "toolCall", "id": "call_Eecshe4qwV8BCJLUGUVLIQFp|fc_049667505a9e91930169ff87c94f5481a3bac6b2526faac9c2", "name": "read", "arguments": {"path": "local_repositories/source_context/org.codehaus.plexus/plexus-velocity/1.1.7/main/extracted/org/codehaus/plexus/velocity/VelocityComponent.java"}}, {"type": "toolCall", "id": "call_35fw7MRjC0vCSjGDpuRqBHlX|fc_049667505a9e91930169ff87c94f6481a391dce51cf20f8e3a", "name": "read", "arguments": {"path": "tests/src/org.codehaus.plexus/plexus-velocity/1.1.7/src/test/java/org_codehaus_plexus/plexus_velocity/ContextClassLoaderResourceLoaderTest.java"}}, {"type": "toolCall", "id": "call_nS0k5KrQfmwQfhOjLXDQUCo0|fc_049667505a9e91930169ff87c94f6881a3b604c2bf77040638", "name": "read", "arguments": {"path": "tests/src/org.codehaus.plexus/plexus-velocity/1.1.7/build.gradle"}}], "api": "openai-responses", "provider": "OCA", "model": "gpt-5.5", "usage": {"input": 2140, "output": 179, "cacheRead": 7168, "cacheWrite": 0, "totalTokens": 9487, "cost": {"input": 0, "output": 0, "cacheRead": 0, "cacheWrite": 0, "total": 0}}, "stopReason": "toolUse", "timestamp": 1778354118806, "responseId": "resp_049667505a9e91930169ff87c723a881a389cd3d3ad8df9f33"}}
[tool-exec] start id=call_Eecshe4qwV8BCJLUGUVLIQFp|fc_049667505a9e91930169ff87c94f5481a3bac6b2526faac9c2 name=read args={"path": "local_repositories/source_context/org.codehaus.plexus/plexus-velocity/1.1.7/main/extracted/org/codehaus/plexus/velocity/VelocityComponent.java"}
[tool-exec] start id=call_35fw7MRjC0vCSjGDpuRqBHlX|fc_049667505a9e91930169ff87c94f6481a391dce51cf20f8e3a name=read args={"path": "tests/src/org.codehaus.plexus/plexus-velocity/1.1.7/src/test/java/org_codehaus_plexus/plexus_velocity/ContextClassLoaderResourceLoaderTest.java"}
[tool-exec] start id=call_nS0k5KrQfmwQfhOjLXDQUCo0|fc_049667505a9e91930169ff87c94f6881a3b604c2bf77040638 name=read args={"path": "tests/src/org.codehaus.plexus/plexus-velocity/1.1.7/build.gradle"}
[tool-exec] end id=call_Eecshe4qwV8BCJLUGUVLIQFp|fc_049667505a9e91930169ff87c94f5481a3bac6b2526faac9c2 name=read status=error
  ENOENT: no such file or directory, access '/home/vjovanov/c/forge/forge8/graalvm-reachability-metadata/forge/local_repositories/forge_worktrees/2428-8b9c7e6e/local_repositories/source_context/org.codehaus.plexus/plexus-velocity/1.1.7/main/extracted/org/codehaus/plexus/velocity/VelocityComponent.java'
[recv] {"type": "message_start", "message": {"role": "toolResult", "toolCallId": "call_Eecshe4qwV8BCJLUGUVLIQFp|fc_049667505a9e91930169ff87c94f5481a3bac6b2526faac9c2", "toolName": "read", "content": [{"type": "text", "text": "ENOENT: no such file or directory, access '/home/vjovanov/c/forge/forge8/graalvm-reachability-metadata/forge/local_repositories/forge_worktrees/2428-8b9c7e6e/local_repositories/source_context/org.codehaus.plexus/plexus-velocity/1.1.7/main/extracted/org/codehaus/plexus/velocity/VelocityComponent.java'"}], "details": {}, "isError": true, "timestamp": 1778354121755}}
[recv] {"type": "message_end", "message": {"role": "toolResult", "toolCallId": "call_Eecshe4qwV8BCJLUGUVLIQFp|fc_049667505a9e91930169ff87c94f5481a3bac6b2526faac9c2", "toolName": "read", "content": [{"type": "text", "text": "ENOENT: no such file or directory, access '/home/vjovanov/c/forge/forge8/graalvm-reachability-metadata/forge/local_repositories/forge_worktrees/2428-8b9c7e6e/local_repositories/source_context/org.codehaus.plexus/plexus-velocity/1.1.7/main/extracted/org/codehaus/plexus/velocity/VelocityComponent.java'"}], "details": {}, "isError": true, "timestamp": 1778354121755}}
[tool-exec] end id=call_35fw7MRjC0vCSjGDpuRqBHlX|fc_049667505a9e91930169ff87c94f6481a391dce51cf20f8e3a name=read status=success
  /*
   * Copyright and related rights waived via CC0
   *
   * You should have received a copy of the CC0 legalcode along with this
   * work. If not, see <http://creativecommons.org/publicdomain/zero/1.0/>.
   */
  package org_codehaus_plexus.plexus_velocity;
  
  import static org.assertj.core.api.Assertions.assertThat;
  
  import java.io.InputStream;
  import java.nio.charset.StandardCharsets;
  
  import org.codehaus.plexus.velocity.ContextClassLoaderResourceLoader;
  import org.junit.jupiter.api.Test;
  
  public class ContextClassLoaderResourceLoaderTest {
      private static final String TEMPLATE_RESOURCE = "templates/context-class-loader-resource-loader-template.vm";
  
      @Test
      void getResourceStreamLoadsTemplateFromThreadContextClassLoader() throws Exception {
          Thread currentThread = Thread.currentThread();
          ClassLoader originalClassLoader = currentThread.getContextClassLoader();
          ClassLoader testClassLoader = ContextClassLoaderResourceLoaderTest.class.getClassLoader();
          currentThread.setContextClassLoader(testClassLoader);
  
          try {
              ContextClassLoaderResourceLoader loader = new ContextClassLoaderResourceLoader();
  
              try (InputStream stream = loader.getResourceStream(TEMPLATE_RESOURCE)) {
                  assertThat(stream).isNotNull();
                  assertThat(new String(stream.readAllBytes(), StandardCharsets.UTF_8))
                      .contains("Hello from the context class loader resource");
              }
          } finally {
              currentThread.setContextClassLoader(originalClassLoader);
          }
      }
  }
[recv] {"type": "message_start", "message": {"role": "toolResult", "toolCallId": "call_35fw7MRjC0vCSjGDpuRqBHlX|fc_049667505a9e91930169ff87c94f6481a391dce51cf20f8e3a", "toolName": "read", "content": [{"type": "text", "text": "/*\n * Copyright and related rights waived via CC0\n *\n * You should have received a copy of the CC0 legalcode along with this\n * work. If not, see <http://creativecommons.org/publicdomain/zero/1.0/>.\n */\npackage org_codehaus_plexus.plexus_velocity;\n\nimport static org.assertj.core.api.Assertions.assertThat;\n\nimport java.io.InputStream;\nimport java.nio.charset.StandardCharsets;\n\nimport org.codehaus.plexus.velocity.ContextClassLoaderResourceLoader;\nimport org.junit.jupiter.api.Test;\n\npublic class ContextClassLoaderResourceLoaderTest {\n    private static final String TEMPLATE_RESOURCE = \"templates/context-class-loader-resource-loader-template.vm\";\n\n    @Test\n    void getResourceStreamLoadsTemplateFromThreadContextClassLoader() throws Exception {\n        Thread currentThread = Thread.currentThread();\n        ClassLoader originalClassLoader = currentThread.getContextClassLoader();\n        ClassLoader testClassLoader = ContextClassLoaderResourceLoaderTest.class.getClassLoader();\n        currentThread.setContextClassLoader(testClassLoader);\n\n        try {\n            ContextClassLoaderResourceLoader loader = new ContextClassLoaderResourceLoader();\n\n            try (InputStream stream = loader.getResourceStream(TEMPLATE_RESOURCE)) {\n                assertThat(stream).isNotNull();\n                assertThat(new String(stream.readAllBytes(), StandardCharsets.UTF_8))\n                    .contains(\"Hello from the context class loader resource\");\n            }\n        } finally {\n            currentThread.setContextClassLoader(originalClassLoader);\n        }\n    }\n}\n"}], "isError": false, "timestamp": 1778354121757}}
[recv] {"type": "message_end", "message": {"role": "toolResult", "toolCallId": "call_35fw7MRjC0vCSjGDpuRqBHlX|fc_049667505a9e91930169ff87c94f6481a391dce51cf20f8e3a", "toolName": "read", "content": [{"type": "text", "text": "/*\n * Copyright and related rights waived via CC0\n *\n * You should have received a copy of the CC0 legalcode along with this\n * work. If not, see <http://creativecommons.org/publicdomain/zero/1.0/>.\n */\npackage org_codehaus_plexus.plexus_velocity;\n\nimport static org.assertj.core.api.Assertions.assertThat;\n\nimport java.io.InputStream;\nimport java.nio.charset.StandardCharsets;\n\nimport org.codehaus.plexus.velocity.ContextClassLoaderResourceLoader;\nimport org.junit.jupiter.api.Test;\n\npublic class ContextClassLoaderResourceLoaderTest {\n    private static final String TEMPLATE_RESOURCE = \"templates/context-class-loader-resource-loader-template.vm\";\n\n    @Test\n    void getResourceStreamLoadsTemplateFromThreadContextClassLoader() throws Exception {\n        Thread currentThread = Thread.currentThread();\n        ClassLoader originalClassLoader = currentThread.getContextClassLoader();\n        ClassLoader testClassLoader = ContextClassLoaderResourceLoaderTest.class.getClassLoader();\n        currentThread.setContextClassLoader(testClassLoader);\n\n        try {\n            ContextClassLoaderResourceLoader loader = new ContextClassLoaderResourceLoader();\n\n            try (InputStream stream = loader.getResourceStream(TEMPLATE_RESOURCE)) {\n                assertThat(stream).isNotNull();\n                assertThat(new String(stream.readAllBytes(), StandardCharsets.UTF_8))\n                    .contains(\"Hello from the context class loader resource\");\n            }\n        } finally {\n            currentThread.setContextClassLoader(originalClassLoader);\n        }\n    }\n}\n"}], "isError": false, "timestamp": 1778354121757}}
[tool-exec] end id=call_nS0k5KrQfmwQfhOjLXDQUCo0|fc_049667505a9e91930169ff87c94f6881a3b604c2bf77040638 name=read status=success
  /*
   * Copyright and related rights waived via CC0
   *
   * You should have received a copy of the CC0 legalcode along with this
   * work. If not, see <http://creativecommons.org/publicdomain/zero/1.0/>.
   */
  plugins {
      id "org.graalvm.internal.tck"
  }
  
  String libraryVersion = tck.testedLibraryVersion.get()
  
  dependencies {
      testImplementation "org.codehaus.plexus:plexus-velocity:$libraryVersion"
      testImplementation 'org.assertj:assertj-core:3.22.0'
  }
  
  graalvmNative {
      agent {
          defaultMode = "conditional"
          modes {
              conditional {
                  userCodeFilterPath = "user-code-filter.json"
              }
          }
      }
  }
[recv] {"type": "message_start", "message": {"role": "toolResult", "toolCallId": "call_nS0k5KrQfmwQfhOjLXDQUCo0|fc_049667505a9e91930169ff87c94f6881a3b604c2bf77040638", "toolName": "read", "content": [{"type": "text", "text": "/*\n * Copyright and related rights waived via CC0\n *\n * You should have received a copy of the CC0 legalcode along with this\n * work. If not, see <http://creativecommons.org/publicdomain/zero/1.0/>.\n */\nplugins {\n    id \"org.graalvm.internal.tck\"\n}\n\nString libraryVersion = tck.testedLibraryVersion.get()\n\ndependencies {\n    testImplementation \"org.codehaus.plexus:plexus-velocity:$libraryVersion\"\n    testImplementation 'org.assertj:assertj-core:3.22.0'\n}\n\ngraalvmNative {\n    agent {\n        defaultMode = \"conditional\"\n        modes {\n            conditional {\n                userCodeFilterPath = \"user-code-filter.json\"\n            }\n        }\n    }\n}\n"}], "isError": false, "timestamp": 1778354121757}}
[recv] {"type": "message_end", "message": {"role": "toolResult", "toolCallId": "call_nS0k5KrQfmwQfhOjLXDQUCo0|fc_049667505a9e91930169ff87c94f6881a3b604c2bf77040638", "toolName": "read", "content": [{"type": "text", "text": "/*\n * Copyright and related rights waived via CC0\n *\n * You should have received a copy of the CC0 legalcode along with this\n * work. If not, see <http://creativecommons.org/publicdomain/zero/1.0/>.\n */\nplugins {\n    id \"org.graalvm.internal.tck\"\n}\n\nString libraryVersion = tck.testedLibraryVersion.get()\n\ndependencies {\n    testImplementation \"org.codehaus.plexus:plexus-velocity:$libraryVersion\"\n    testImplementation 'org.assertj:assertj-core:3.22.0'\n}\n\ngraalvmNative {\n    agent {\n        defaultMode = \"conditional\"\n        modes {\n            conditional {\n                userCodeFilterPath = \"user-code-filter.json\"\n            }\n        }\n    }\n}\n"}], "isError": false, "timestamp": 1778354121757}}
[recv] {"type": "turn_end", "message": {"role": "assistant", "content": [{"type": "thinking", "thinking": "**Clarifying Java file requirements**\n\nI’m considering the need for an active class to have its own dedicated Java file in a one-to-one format. This seems crucial to keep things organized. I’m also thinking about whether the current test is specifically for a resource loader. I should really read through the source to confirm that understanding. It's important to get the details right so everything functions as intended!", "thinkingSignature": "{\"id\":\"rs_049667505a9e91930169ff87c7adc881a39890096b6592a9d2\",\"type\":\"reasoning\",\"encrypted_content\":\"gAAAAABp_4fJ7ibL8EGQaxf4kUWNw0dFsZDFS3dHltB67YYuH6rDN49SZS9eSwXMz8uJNk4fkuLtvYWjPs186kEzOk55iZDStxu-DV9uQjmvrT3acMUZV4-4Ww5JUTYoomeFe7LRlSzdJj4HWZi3wefW20EXI6dZG5jmlsldOIS0ZAS1Og4l5RLvEA9iLE6yrIfHnbfiuX_AS9n-GLB2nhIRm0Fk_duJnZo6XDGOELIY3kruoLyAkAaMFluQba2nr_BawRVe9OyXEi9DlGIMDVjc8P1oggRg-HsnSMD26mlBb4mHTJjKeXPDA3RAP2zjrIzQadiiaoHxZ-70k7bYklasFUX_hmkN8LbP-7NaUICGxwzeBfSLscvqmi-VCHNnfNup0zoxJ7wS6dWP2itY3pQPJCXXeh4ZcBWxpCtZWTp7FvxiBtKje-wVrwYFChF8N-ArXyUkAZaBf0oYWH3y0xYC1l88rz4uaaerJoPGvPArPcAt_FLa9LswzsiXo2YMk4ek8vm9KSGMqhiA1_4OXpERBkIFY_ozVMn05HoE3S3yFbbRdU3enm11U-Mc5334AgWzzHrsvUlp-_-hrYD4sTnC5dX6f0mS2jM86BFDAP0Uq7iKekV7UYZBXc_jtL_8OcWsAzCIu-bEOIOfCDOJ39zyYBOfeU-5aED3-eyAi0QVutXEUEdruaSsBN-v-ln_hDfD1qem3HHaVX4GytxM6afOD0GKS2WYAXgCriavzXy3TE1QxtsRkIWU5IuGTR58dhAio3qWYLeCJ3E-EuJ6GiFqWNE_uw2Ha-1qSSmJ_5GzklzvjDyHC36ZKUdqYAl17ZJd5RiyCHWmAv-k6k-cnRvmljn39kc46UvcZZ_9yz7Is7EknllVtw1jhkxjQpwMOXliC0T6L7gIrlltYe56jSw5UklWCQZWDhfZkxaeL2y6TiT1A7vsEYx0m6r0ibFSEmHietCxSyhpGTNK32houBybYc-S_kVC-VXYDoNot8WmTXQtR4uUXyjFAb_vdbdKf8JOtVljw8WFaynsxbqbDQ_M39tIsNSU8p49FEdhL8lGU9IGARUfByAwAobrQvN0aGqgCQ2Yu7WT\",\"summary\":[{\"type\":\"summary_text\",\"text\":\"**Clarifying Java file requirements**\\n\\nI’m considering the need for an active class to have its own dedicated Java file in a one-to-one format. This seems crucial to keep things organized. I’m also thinking about whether the current test is specifically for a resource loader. I should really read through the source to confirm that understanding. It's important to get the details right so everything functions as intended!\"}]}"}, {"type": "toolCall", "id": "call_Eecshe4qwV8BCJLUGUVLIQFp|fc_049667505a9e91930169ff87c94f5481a3bac6b2526faac9c2", "name": "read", "arguments": {"path": "local_repositories/source_context/org.codehaus.plexus/plexus-velocity/1.1.7/main/extracted/org/codehaus/plexus/velocity/VelocityComponent.java"}}, {"type": "toolCall", "id": "call_35fw7MRjC0vCSjGDpuRqBHlX|fc_049667505a9e91930169ff87c94f6481a391dce51cf20f8e3a", "name": "read", "arguments": {"path": "tests/src/org.codehaus.plexus/plexus-velocity/1.1.7/src/test/java/org_codehaus_plexus/plexus_velocity/ContextClassLoaderResourceLoaderTest.java"}}, {"type": "toolCall", "id": "call_nS0k5KrQfmwQfhOjLXDQUCo0|fc_049667505a9e91930169ff87c94f6881a3b604c2bf77040638", "name": "read", "arguments": {"path": "tests/src/org.codehaus.plexus/plexus-velocity/1.1.7/build.gradle"}}], "api": "openai-responses", "provider": "OCA", "model": "gpt-5.5", "usage": {"input": 2140, "output": 179, "cacheRead": 7168, "cacheWrite": 0, "totalTokens": 9487, "cost": {"input": 0, "output": 0, "cacheRead": 0, "cacheWrite": 0, "total": 0}}, "stopReason": "toolUse", "timestamp": 1778354118806, "responseId": "resp_049667505a9e91930169ff87c723a881a389cd3d3ad8df9f33"}, "toolResults": [{"role": "toolResult", "toolCallId": "call_Eecshe4qwV8BCJLUGUVLIQFp|fc_049667505a9e91930169ff87c94f5481a3bac6b2526faac9c2", "toolName": "read", "content": [{"type": "text", "text": "ENOENT: no such file or directory, access '/home/vjovanov/c/forge/forge8/graalvm-reachability-metadata/forge/local_repositories/forge_worktrees/2428-8b9c7e6e/local_repositories/source_context/org.codehaus.plexus/plexus-velocity/1.1.7/main/extracted/org/codehaus/plexus/velocity/VelocityComponent.java'"}], "details": {}, "isError": true, "timestamp": 1778354121755}, {"role": "toolResult", "toolCallId": "call_35fw7MRjC0vCSjGDpuRqBHlX|fc_049667505a9e91930169ff87c94f6481a391dce51cf20f8e3a", "toolName": "read", "content": [{"type": "text", "text": "/*\n * Copyright and related rights waived via CC0\n *\n * You should have received a copy of the CC0 legalcode along with this\n * work. If not, see <http://creativecommons.org/publicdomain/zero/1.0/>.\n */\npackage org_codehaus_plexus.plexus_velocity;\n\nimport static org.assertj.core.api.Assertions.assertThat;\n\nimport java.io.InputStream;\nimport java.nio.charset.StandardCharsets;\n\nimport org.codehaus.plexus.velocity.ContextClassLoaderResourceLoader;\nimport org.junit.jupiter.api.Test;\n\npublic class ContextClassLoaderResourceLoaderTest {\n    private static final String TEMPLATE_RESOURCE = \"templates/context-class-loader-resource-loader-template.vm\";\n\n    @Test\n    void getResourceStreamLoadsTemplateFromThreadContextClassLoader() throws Exception {\n        Thread currentThread = Thread.currentThread();\n        ClassLoader originalClassLoader = currentThread.getContextClassLoader();\n        ClassLoader testClassLoader = ContextClassLoaderResourceLoaderTest.class.getClassLoader();\n        currentThread.setContextClassLoader(testClassLoader);\n\n        try {\n            ContextClassLoaderResourceLoader loader = new ContextClassLoaderResourceLoader();\n\n            try (InputStream stream = loader.getResourceStream(TEMPLATE_RESOURCE)) {\n                assertThat(stream).isNotNull();\n                assertThat(new String(stream.readAllBytes(), StandardCharsets.UTF_8))\n                    .contains(\"Hello from the context class loader resource\");\n            }\n        } finally {\n            currentThread.setContextClassLoader(originalClassLoader);\n        }\n    }\n}\n"}], "isError": false, "timestamp": 1778354121757}, {"role": "toolResult", "toolCallId": "call_nS0k5KrQfmwQfhOjLXDQUCo0|fc_049667505a9e91930169ff87c94f6881a3b604c2bf77040638", "toolName": "read", "content": [{"type": "text", "text": "/*\n * Copyright and related rights waived via CC0\n *\n * You should have received a copy of the CC0 legalcode along with this\n * work. If not, see <http://creativecommons.org/publicdomain/zero/1.0/>.\n */\nplugins {\n    id \"org.graalvm.internal.tck\"\n}\n\nString libraryVersion = tck.testedLibraryVersion.get()\n\ndependencies {\n    testImplementation \"org.codehaus.plexus:plexus-velocity:$libraryVersion\"\n    testImplementation 'org.assertj:assertj-core:3.22.0'\n}\n\ngraalvmNative {\n    agent {\n        defaultMode = \"conditional\"\n        modes {\n            conditional {\n                userCodeFilterPath = \"user-code-filter.json\"\n            }\n        }\n    }\n}\n"}], "isError": false, "timestamp": 1778354121757}]}
[recv] {"type": "turn_start"}
[recv] {"type": "message_start", "message": {"role": "assistant", "content": [], "api": "openai-responses", "provider": "OCA", "model": "gpt-5.5", "usage": {"input": 0, "output": 0, "cacheRead": 0, "cacheWrite": 0, "totalTokens": 0, "cost": {"input": 0, "output": 0, "cacheRead": 0, "cacheWrite": 0, "total": 0}}, "stopReason": "stop", "timestamp": 1778354121760}}
[assistant-event] thinking_start
[thinking] **Figuring out source paths**
[thinking] 
[thinking] I’m thinking about the source path being relative. It seems like we’re working in a specific directory structure, namely under "forge/local_repositories/forge_worktrees.” I wonder if the "source_context" is a sibling and would need to reference it as "../../source_context.” I need to confirm this to ensure I’m on the right track!
[thinking] 
[assistant-event] thinking_end
[tool-call] start id=unknown
[tool-call] delta {"command":"find ../.. -path '*plexus-velocity/1.1.7/main/extracted/org/codehaus/plexus/velocity/VelocityComponent.java' -print"}
[tool-call] end id=call_Jwzj3T0EjTij1sBlwjsJIvJn|fc_049667505a9e91930169ff87ccb13881a3a6c7cc99bd5589e9 name=bash args={"command": "find ../.. -path '*plexus-velocity/1.1.7/main/extracted/org/codehaus/plexus/velocity/VelocityComponent.java' -print"}
[recv] {"type": "message_end", "message": {"role": "assistant", "content": [{"type": "thinking", "thinking": "**Figuring out source paths**\n\nI’m thinking about the source path being relative. It seems like we’re working in a specific directory structure, namely under \"forge/local_repositories/forge_worktrees.” I wonder if the \"source_context\" is a sibling and would need to reference it as \"../../source_context.” I need to confirm this to ensure I’m on the right track!", "thinkingSignature": "{\"id\":\"rs_049667505a9e91930169ff87cb047881a38fb884763c94bbec\",\"type\":\"reasoning\",\"encrypted_content\":\"gAAAAABp_4fMrwHYfgljno3OfRuPO0nA00ae-5BsK3QrbotfrXQ7Xv2PK7d1pVEz4x-6tlKni6hyPgFwrD7F_JYtkrn3-f49pwKwh74wAtj_EBm0sSeNHjGeYmnwJALX43Rg0Jpi2J3N4feSQclsr1MNfsvztjxv2bZ-ePvbIusGMeIXry-QxDEEaVMrhVrxXhnGN1idWoAEAx8zua3ynsm6pmS9Mi30BWiOiLeVp0WXMaozx6J8dgChdIQprwAzfm-GJvvyKg-fEsu6OG6tiz8KV6Qr9hNVTKgDlOg8mxYk4xydvBVPDJT1x-2ly47dOlWw_Lz_JuOAeNnh-wNVOWe1psUguGeQVRKH3CK1HKxLuB1ClVaBMZZsGQntN185jKdZzzep9Qi5IIxr0T2uqpOVkj6w12AHfTG7gbl50jWPsJ8KnHbM4wDcBCS_eeAauljj_LEprE_HWUy3TK3WJZ2lBSrfA0utITIol-KATf9hEmvG_yjjUbqDIEG_G4S8UncUoxsJUQhe5vlKB2ggG9sv4rDwyECQVIAJ2kxRC-unweuh1phxJt4ABBteYU6o5FpobUwIeSAcvylcyghr7qyPpVInwrzQsjhaYVP3cPn4cRlum5zti5iXf6HlOzjQz3qryclu83zCvRtSbNZs6QW_upn0JchHZCmn0v44Iy7HJT8WUQ4uXQJsDiGrkbipEIx1QxHkXLPs2EU-xaSRv3boLrXcalqg0tFvEmA1LVBfWy-jrlDdBMaezGG9VcZH7KhtjhkyYzVErzwWGXnZFlKvFNQhTIHR_M3uK7jLV7f587bULkAszIkAjbo2vJDgo02up0XEENsiv8xaoDoeseujnNGp-_1sgjnyKAHTjqMsVwwM2mvwJsipWu8k6Fdt8TeqCTQaLYvQy11e1FvdHNCMsN6Aheh0m88P4kAtWLZ4yY_N8WaQRYEycab4aEeWA0AL8DAXi5wrQokEl6HOXgOtwMGNkiOGhYK2VZbcj820hqzIRZ-V6WhDqllT9MGr1wyOwE62O0UOFUV4jWMNBQwI87JK4bApofMTxd0FGW2wBYTJmWa7bd90EzJ9tmRWaCd8uPAe8x17grbRDHJs8KEa5TACNpetyDBJjUnPKKbUsMRktg80kQY=\",\"summary\":[{\"type\":\"summary_text\",\"text\":\"**Figuring out source paths**\\n\\nI’m thinking about the source path being relative. It seems like we’re working in a specific directory structure, namely under \\\"forge/local_repositories/forge_worktrees.” I wonder if the \\\"source_context\\\" is a sibling and would need to reference it as \\\"../../source_context.” I need to confirm this to ensure I’m on the right track!\"}]}"}, {"type": "toolCall", "id": "call_Jwzj3T0EjTij1sBlwjsJIvJn|fc_049667505a9e91930169ff87ccb13881a3a6c7cc99bd5589e9", "name": "bash", "arguments": {"command": "find ../.. -path '*plexus-velocity/1.1.7/main/extracted/org/codehaus/plexus/velocity/VelocityComponent.java' -print"}}], "api": "openai-responses", "provider": "OCA", "model": "gpt-5.5", "usage": {"input": 838, "output": 86, "cacheRead": 9216, "cacheWrite": 0, "totalTokens": 10140, "cost": {"input": 0, "output": 0, "cacheRead": 0, "cacheWrite": 0, "total": 0}}, "stopReason": "toolUse", "timestamp": 1778354121760, "responseId": "resp_049667505a9e91930169ff87ca85dc81a3bbd98ab4353e1e5d"}}
[tool-exec] start id=call_Jwzj3T0EjTij1sBlwjsJIvJn|fc_049667505a9e91930169ff87ccb13881a3a6c7cc99bd5589e9 name=bash args={"command": "find ../.. -path '*plexus-velocity/1.1.7/main/extracted/org/codehaus/plexus/velocity/VelocityComponent.java' -print"}
[tool-exec] update id=call_Jwzj3T0EjTij1sBlwjsJIvJn|fc_049667505a9e91930169ff87ccb13881a3a6c7cc99bd5589e9 name=bash
[tool-exec] update id=call_Jwzj3T0EjTij1sBlwjsJIvJn|fc_049667505a9e91930169ff87ccb13881a3a6c7cc99bd5589e9 name=bash
  ../../source_context/org.codehaus.plexus/plexus-velocity/1.1.7/main/extracted/org/codehaus/plexus/velocity/VelocityComponent.java
[tool-exec] end id=call_Jwzj3T0EjTij1sBlwjsJIvJn|fc_049667505a9e91930169ff87ccb13881a3a6c7cc99bd5589e9 name=bash status=success
  ../../source_context/org.codehaus.plexus/plexus-velocity/1.1.7/main/extracted/org/codehaus/plexus/velocity/VelocityComponent.java
[recv] {"type": "message_start", "message": {"role": "toolResult", "toolCallId": "call_Jwzj3T0EjTij1sBlwjsJIvJn|fc_049667505a9e91930169ff87ccb13881a3a6c7cc99bd5589e9", "toolName": "bash", "content": [{"type": "text", "text": "../../source_context/org.codehaus.plexus/plexus-velocity/1.1.7/main/extracted/org/codehaus/plexus/velocity/VelocityComponent.java\n"}], "isError": false, "timestamp": 1778354125190}}
[recv] {"type": "message_end", "message": {"role": "toolResult", "toolCallId": "call_Jwzj3T0EjTij1sBlwjsJIvJn|fc_049667505a9e91930169ff87ccb13881a3a6c7cc99bd5589e9", "toolName": "bash", "content": [{"type": "text", "text": "../../source_context/org.codehaus.plexus/plexus-velocity/1.1.7/main/extracted/org/codehaus/plexus/velocity/VelocityComponent.java\n"}], "isError": false, "timestamp": 1778354125190}}
[recv] {"type": "turn_end", "message": {"role": "assistant", "content": [{"type": "thinking", "thinking": "**Figuring out source paths**\n\nI’m thinking about the source path being relative. It seems like we’re working in a specific directory structure, namely under \"forge/local_repositories/forge_worktrees.” I wonder if the \"source_context\" is a sibling and would need to reference it as \"../../source_context.” I need to confirm this to ensure I’m on the right track!", "thinkingSignature": "{\"id\":\"rs_049667505a9e91930169ff87cb047881a38fb884763c94bbec\",\"type\":\"reasoning\",\"encrypted_content\":\"gAAAAABp_4fMrwHYfgljno3OfRuPO0nA00ae-5BsK3QrbotfrXQ7Xv2PK7d1pVEz4x-6tlKni6hyPgFwrD7F_JYtkrn3-f49pwKwh74wAtj_EBm0sSeNHjGeYmnwJALX43Rg0Jpi2J3N4feSQclsr1MNfsvztjxv2bZ-ePvbIusGMeIXry-QxDEEaVMrhVrxXhnGN1idWoAEAx8zua3ynsm6pmS9Mi30BWiOiLeVp0WXMaozx6J8dgChdIQprwAzfm-GJvvyKg-fEsu6OG6tiz8KV6Qr9hNVTKgDlOg8mxYk4xydvBVPDJT1x-2ly47dOlWw_Lz_JuOAeNnh-wNVOWe1psUguGeQVRKH3CK1HKxLuB1ClVaBMZZsGQntN185jKdZzzep9Qi5IIxr0T2uqpOVkj6w12AHfTG7gbl50jWPsJ8KnHbM4wDcBCS_eeAauljj_LEprE_HWUy3TK3WJZ2lBSrfA0utITIol-KATf9hEmvG_yjjUbqDIEG_G4S8UncUoxsJUQhe5vlKB2ggG9sv4rDwyECQVIAJ2kxRC-unweuh1phxJt4ABBteYU6o5FpobUwIeSAcvylcyghr7qyPpVInwrzQsjhaYVP3cPn4cRlum5zti5iXf6HlOzjQz3qryclu83zCvRtSbNZs6QW_upn0JchHZCmn0v44Iy7HJT8WUQ4uXQJsDiGrkbipEIx1QxHkXLPs2EU-xaSRv3boLrXcalqg0tFvEmA1LVBfWy-jrlDdBMaezGG9VcZH7KhtjhkyYzVErzwWGXnZFlKvFNQhTIHR_M3uK7jLV7f587bULkAszIkAjbo2vJDgo02up0XEENsiv8xaoDoeseujnNGp-_1sgjnyKAHTjqMsVwwM2mvwJsipWu8k6Fdt8TeqCTQaLYvQy11e1FvdHNCMsN6Aheh0m88P4kAtWLZ4yY_N8WaQRYEycab4aEeWA0AL8DAXi5wrQokEl6HOXgOtwMGNkiOGhYK2VZbcj820hqzIRZ-V6WhDqllT9MGr1wyOwE62O0UOFUV4jWMNBQwI87JK4bApofMTxd0FGW2wBYTJmWa7bd90EzJ9tmRWaCd8uPAe8x17grbRDHJs8KEa5TACNpetyDBJjUnPKKbUsMRktg80kQY=\",\"summary\":[{\"type\":\"summary_text\",\"text\":\"**Figuring out source paths**\\n\\nI’m thinking about the source path being relative. It seems like we’re working in a specific directory structure, namely under \\\"forge/local_repositories/forge_worktrees.” I wonder if the \\\"source_context\\\" is a sibling and would need to reference it as \\\"../../source_context.” I need to confirm this to ensure I’m on the right track!\"}]}"}, {"type": "toolCall", "id": "call_Jwzj3T0EjTij1sBlwjsJIvJn|fc_049667505a9e91930169ff87ccb13881a3a6c7cc99bd5589e9", "name": "bash", "arguments": {"command": "find ../.. -path '*plexus-velocity/1.1.7/main/extracted/org/codehaus/plexus/velocity/VelocityComponent.java' -print"}}], "api": "openai-responses", "provider": "OCA", "model": "gpt-5.5", "usage": {"input": 838, "output": 86, "cacheRead": 9216, "cacheWrite": 0, "totalTokens": 10140, "cost": {"input": 0, "output": 0, "cacheRead": 0, "cacheWrite": 0, "total": 0}}, "stopReason": "toolUse", "timestamp": 1778354121760, "responseId": "resp_049667505a9e91930169ff87ca85dc81a3bbd98ab4353e1e5d"}, "toolResults": [{"role": "toolResult", "toolCallId": "call_Jwzj3T0EjTij1sBlwjsJIvJn|fc_049667505a9e91930169ff87ccb13881a3a6c7cc99bd5589e9", "toolName": "bash", "content": [{"type": "text", "text": "../../source_context/org.codehaus.plexus/plexus-velocity/1.1.7/main/extracted/org/codehaus/plexus/velocity/VelocityComponent.java\n"}], "isError": false, "timestamp": 1778354125190}]}
[recv] {"type": "turn_start"}
[recv] {"type": "message_start", "message": {"role": "assistant", "content": [], "api": "openai-responses", "provider": "OCA", "model": "gpt-5.5", "usage": {"input": 0, "output": 0, "cacheRead": 0, "cacheWrite": 0, "totalTokens": 0, "cost": {"input": 0, "output": 0, "cacheRead": 0, "cacheWrite": 0, "total": 0}}, "stopReason": "stop", "timestamp": 1778354125195}}
[tool-call] start id=unknown
[tool-call] delta {"path":"../../source_context/org.codehaus.plexus/plexus-velocity/1.1.7/main/extracted/org/codehaus/plexus/velocity/VelocityComponent.java"}
[tool-call] end id=call_2krbPkt3TeYFAJOqcVdDUmLA|fc_049667505a9e91930169ff87ce3af081a396dc334d2661ab63 name=read args={"path": "../../source_context/org.codehaus.plexus/plexus-velocity/1.1.7/main/extracted/org/codehaus/plexus/velocity/VelocityComponent.java"}
[recv] {"type": "message_end", "message": {"role": "assistant", "content": [{"type": "toolCall", "id": "call_2krbPkt3TeYFAJOqcVdDUmLA|fc_049667505a9e91930169ff87ce3af081a396dc334d2661ab63", "name": "read", "arguments": {"path": "../../source_context/org.codehaus.plexus/plexus-velocity/1.1.7/main/extracted/org/codehaus/plexus/velocity/VelocityComponent.java"}}], "api": "openai-responses", "provider": "OCA", "model": "gpt-5.5", "usage": {"input": 458, "output": 50, "cacheRead": 9728, "cacheWrite": 0, "totalTokens": 10236, "cost": {"input": 0, "output": 0, "cacheRead": 0, "cacheWrite": 0, "total": 0}}, "stopReason": "toolUse", "timestamp": 1778354125195, "responseId": "resp_049667505a9e91930169ff87cd8a6c81a3909fc8a9e206cc7e"}}
[tool-exec] start id=call_2krbPkt3TeYFAJOqcVdDUmLA|fc_049667505a9e91930169ff87ce3af081a396dc334d2661ab63 name=read args={"path": "../../source_context/org.codehaus.plexus/plexus-velocity/1.1.7/main/extracted/org/codehaus/plexus/velocity/VelocityComponent.java"}
[tool-exec] end id=call_2krbPkt3TeYFAJOqcVdDUmLA|fc_049667505a9e91930169ff87ce3af081a396dc334d2661ab63 name=read status=success
  package org.codehaus.plexus.velocity;
  
  /*
   * Copyright 2001-2006 Codehaus Foundation.
   *
   * Licensed under the Apache License, Version 2.0 (the "License");
   * you may not use this file except in compliance with the License.
   * You may obtain a copy of the License at
   *
   *      http://www.apache.org/licenses/LICENSE-2.0
   *
   * Unless required by applicable law or agreed to in writing, software
   * distributed under the License is distributed on an "AS IS" BASIS,
   * WITHOUT WARRANTIES OR CONDITIONS OF ANY KIND, either express or implied.
   * See the License for the specific language governing permissions and
   * limitations under the License.
   */
  
  import org.apache.velocity.app.VelocityEngine;
  
  public interface VelocityComponent
  {
      public final static String ROLE = VelocityComponent.class.getName();
  
      VelocityEngine getEngine();
  }
[recv] {"type": "message_start", "message": {"role": "toolResult", "toolCallId": "call_2krbPkt3TeYFAJOqcVdDUmLA|fc_049667505a9e91930169ff87ce3af081a396dc334d2661ab63", "toolName": "read", "content": [{"type": "text", "text": "package org.codehaus.plexus.velocity;\n\n/*\n * Copyright 2001-2006 Codehaus Foundation.\n *\n * Licensed under the Apache License, Version 2.0 (the \"License\");\n * you may not use this file except in compliance with the License.\n * You may obtain a copy of the License at\n *\n *      http://www.apache.org/licenses/LICENSE-2.0\n *\n * Unless required by applicable law or agreed to in writing, software\n * distributed under the License is distributed on an \"AS IS\" BASIS,\n * WITHOUT WARRANTIES OR CONDITIONS OF ANY KIND, either express or implied.\n * See the License for the specific language governing permissions and\n * limitations under the License.\n */\n\nimport org.apache.velocity.app.VelocityEngine;\n\npublic interface VelocityComponent\n{\n    public final static String ROLE = VelocityComponent.class.getName();\n\n    VelocityEngine getEngine();\n}\n"}], "isError": false, "timestamp": 1778354126727}}
[recv] {"type": "message_end", "message": {"role": "toolResult", "toolCallId": "call_2krbPkt3TeYFAJOqcVdDUmLA|fc_049667505a9e91930169ff87ce3af081a396dc334d2661ab63", "toolName": "read", "content": [{"type": "text", "text": "package org.codehaus.plexus.velocity;\n\n/*\n * Copyright 2001-2006 Codehaus Foundation.\n *\n * Licensed under the Apache License, Version 2.0 (the \"License\");\n * you may not use this file except in compliance with the License.\n * You may obtain a copy of the License at\n *\n *      http://www.apache.org/licenses/LICENSE-2.0\n *\n * Unless required by applicable law or agreed to in writing, software\n * distributed under the License is distributed on an \"AS IS\" BASIS,\n * WITHOUT WARRANTIES OR CONDITIONS OF ANY KIND, either express or implied.\n * See the License for the specific language governing permissions and\n * limitations under the License.\n */\n\nimport org.apache.velocity.app.VelocityEngine;\n\npublic interface VelocityComponent\n{\n    public final static String ROLE = VelocityComponent.class.getName();\n\n    VelocityEngine getEngine();\n}\n"}], "isError": false, "timestamp": 1778354126727}}
[recv] {"type": "turn_end", "message": {"role": "assistant", "content": [{"type": "toolCall", "id": "call_2krbPkt3TeYFAJOqcVdDUmLA|fc_049667505a9e91930169ff87ce3af081a396dc334d2661ab63", "name": "read", "arguments": {"path": "../../source_context/org.codehaus.plexus/plexus-velocity/1.1.7/main/extracted/org/codehaus/plexus/velocity/VelocityComponent.java"}}], "api": "openai-responses", "provider": "OCA", "model": "gpt-5.5", "usage": {"input": 458, "output": 50, "cacheRead": 9728, "cacheWrite": 0, "totalTokens": 10236, "cost": {"input": 0, "output": 0, "cacheRead": 0, "cacheWrite": 0, "total": 0}}, "stopReason": "toolUse", "timestamp": 1778354125195, "responseId": "resp_049667505a9e91930169ff87cd8a6c81a3909fc8a9e206cc7e"}, "toolResults": [{"role": "toolResult", "toolCallId": "call_2krbPkt3TeYFAJOqcVdDUmLA|fc_049667505a9e91930169ff87ce3af081a396dc334d2661ab63", "toolName": "read", "content": [{"type": "text", "text": "package org.codehaus.plexus.velocity;\n\n/*\n * Copyright 2001-2006 Codehaus Foundation.\n *\n * Licensed under the Apache License, Version 2.0 (the \"License\");\n * you may not use this file except in compliance with the License.\n * You may obtain a copy of the License at\n *\n *      http://www.apache.org/licenses/LICENSE-2.0\n *\n * Unless required by applicable law or agreed to in writing, software\n * distributed under the License is distributed on an \"AS IS\" BASIS,\n * WITHOUT WARRANTIES OR CONDITIONS OF ANY KIND, either express or implied.\n * See the License for the specific language governing permissions and\n * limitations under the License.\n */\n\nimport org.apache.velocity.app.VelocityEngine;\n\npublic interface VelocityComponent\n{\n    public final static String ROLE = VelocityComponent.class.getName();\n\n    VelocityEngine getEngine();\n}\n"}], "isError": false, "timestamp": 1778354126727}]}
[recv] {"type": "turn_start"}
[recv] {"type": "message_start", "message": {"role": "assistant", "content": [], "api": "openai-responses", "provider": "OCA", "model": "gpt-5.5", "usage": {"input": 0, "output": 0, "cacheRead": 0, "cacheWrite": 0, "totalTokens": 0, "cost": {"input": 0, "output": 0, "cacheRead": 0, "cacheWrite": 0, "total": 0}}, "stopReason": "stop", "timestamp": 1778354126730}}
[assistant-event] thinking_start
[assistant-event] thinking_end
[tool-call] start id=unknown
[tool-call] delta {"path":"tests/src/org.codehaus.plexus/plexus-velocity/1.1.7/build/reports/dynamic-access/dynamic-access-coverage.json","limit":200}
[tool-call] end id=call_WYCOCQLcG54RbHR9IDCqbXyK|fc_049667505a9e91930169ff87d1517081a3ab5e13e7b20a7b7a name=read args={"path": "tests/src/org.codehaus.plexus/plexus-velocity/1.1.7/build/reports/dynamic-access/dynamic-access-coverage.json", "limit": 200}
[recv] {"type": "message_end", "message": {"role": "assistant", "content": [{"type": "thinking", "thinking": "", "thinkingSignature": "{\"id\":\"rs_049667505a9e91930169ff87cfa11481a3881da192283e9e49\",\"type\":\"reasoning\",\"encrypted_content\":\"gAAAAABp_4fRewUrnXkWfosFV9h5vakSS_4RMU9D1xvF_NoxDB8WmLweoCNV1f0p8MjSARKiHo7d-RH8K93e5xAl8IYrj38jSjXURi4MKCD5oItNCoHHslUQLAtMjcu2CPg1MFgmXKjEsvVV9gkfLKNuJaN8OE4oJlk2RPxcFsjblVrxzQycjuCyuy0w1crMhuq9pzGcfWfP_cQ889albG4-JRUPOMTIIgDHf-FjhhmusSRdiyD_n7_BOGywk-3tDRUNMPGtCv2dDw9NCWgzme25dy22Lg_juB9SYbcBcUJzQqyXN6mVFORpvr5_ESlkzqxL1VYi4GKN05JUp1LCg66HX4tqkBZACe2TUIgxqmPp116i37Fwm27Yq-HliI-YonKyMp6Kl1dgde8MPTZGjhWuBdYWm9DQAQSkSup512SDz6LW1BmLNmDfolM5a9N-zaPi-yMqwmb-ac-Fdbii8atZa6uR0ejpTkJ8Ao_uXlADPq6hX2QFU_dPY0y6IDafRucrF8U_wcW0XqhpA4R8Pl0pp0gI8d2HRw-cpG86aGT7EYuhiq8q0eeW4g-JadX7isB45aWnv9vyEKo_kQQUJaGxlAian78_zwVwv-Wl_mQY8_TBaxwa1XLlQzQyZ6kqiZQdpmIbSXWi3KjG9DqfIvQ1m8OnoF8qpEMZxcyJ4Se5Bv3v708CMRudmVEaVCHtuCg-AqMyJcPhVGuvANYm-5Mr89oEUkOYWEyneae0-uPgvrsY5mWZW2C3t78Isk-lkZuzj1KZlZuQBYK4RbXBFauhoeNIchl7LoNnzDtVOdxZ6gWmKcIF24_i59VmDDIvFGikAgRYFV96peIQD7voZW1ASKas_GjXr9RlMrXJ1MIojIn4hBtYrCs7k4ciBdneNgUbesvEu3XGMcrO6h1Bru_qCoSTzym3tWzQYWigjmzVLTjJV_8T5YbS_eS4Z5F3FzUWmKleZ41Q3gCODy1rujPGCNYNMaQYafyo2veImQfj1jzDo_JQ7tKpdSPz7nS7U9Kc9DQ_teyBGDDOkPBWNht4WPF_QBMhF0rPfUMFykmgC6nGjsgjcUTlAcy7aUTy8qrdLVNG0y1jfQ9bYLxUZN957ewKmiD6-G0pb_yuyRhTRUIvYDdsC4O_s6wdggvwzENoz7y-KfkMlmckn-hC7LV2wb1UxpL9wwz6JTr0rGPgOyE2Wercs90ZUmKAqH-TiOAuhwAcT6YIjMakc1nttg7l2X8eUzYMUlQuTzU8pY65TExdntOJirF_MOwpZ-SOdhCOsaVVVYCWIvjQudajFSWYcE7lKuloj5y2CNzE6BOsq3XhR32i8-epuVVHixLJDZpkyCv6mS3J2_dNyjqbL7PXfsP7RiSY7l407_o30TiJB1dlUCaZQNtd_VcayJbE3orrW5Pqne8rTWmflnVEchC8x9InLGiz9tchyOu84yLABSZeitelGvvQHB2TnK-bzQ_hH9r0W0LkrmhCFt7aNsW6MoiVjZDhD8FMCR_veQiYRufi_VCSS7sGdS3LCWo8cDWEbAAdMGMAW60i9keNJIfYDlecamNODlytsCukKv395_y9HtAk8XtoyoURhMFbU8ySlEURWdgKQ9gCTFlaQXUHOt0r3P_YPA==\",\"summary\":[]}"}, {"type": "toolCall", "id": "call_WYCOCQLcG54RbHR9IDCqbXyK|fc_049667505a9e91930169ff87d1517081a3ab5e13e7b20a7b7a", "name": "read", "arguments": {"path": "tests/src/org.codehaus.plexus/plexus-velocity/1.1.7/build/reports/dynamic-access/dynamic-access-coverage.json", "limit": 200}}], "api": "openai-responses", "provider": "OCA", "model": "gpt-5.5", "usage": {"input": 696, "output": 160, "cacheRead": 9728, "cacheWrite": 0, "totalTokens": 10584, "cost": {"input": 0, "output": 0, "cacheRead": 0, "cacheWrite": 0, "total": 0}}, "stopReason": "toolUse", "timestamp": 1778354126730, "responseId": "resp_049667505a9e91930169ff87cf14c881a39c284f3fdd89e7bd"}}
[tool-exec] start id=call_WYCOCQLcG54RbHR9IDCqbXyK|fc_049667505a9e91930169ff87d1517081a3ab5e13e7b20a7b7a name=read args={"path": "tests/src/org.codehaus.plexus/plexus-velocity/1.1.7/build/reports/dynamic-access/dynamic-access-coverage.json", "limit": 200}
[tool-exec] end id=call_WYCOCQLcG54RbHR9IDCqbXyK|fc_049667505a9e91930169ff87d1517081a3ab5e13e7b20a7b7a name=read status=success
  {
    "classes" : [ {
      "callSites" : [ {
        "covered" : false,
        "frame" : "org.codehaus.plexus.velocity.VelocityComponent$1.class$(VelocityComponent.java:23)",
        "line" : 23,
        "metadataType" : "reflection",
        "trackedApi" : "java.lang.Class#forName(java.lang.String)"
      } ],
      "className" : "org.codehaus.plexus.velocity.VelocityComponent$1",
      "coveredCalls" : 0,
      "sourceFile" : "VelocityComponent.java",
      "totalCalls" : 1
    }, {
      "callSites" : [ {
        "covered" : true,
        "frame" : "org.codehaus.plexus.velocity.ContextClassLoaderResourceLoader.getResourceStream(ContextClassLoaderResourceLoader.java:48)",
        "line" : 48,
        "metadataType" : "resources",
        "trackedApi" : "java.lang.ClassLoader#getResourceAsStream(java.lang.String)"
      } ],
      "className" : "org.codehaus.plexus.velocity.ContextClassLoaderResourceLoader",
      "coveredCalls" : 1,
      "sourceFile" : "ContextClassLoaderResourceLoader.java",
      "totalCalls" : 1
    } ],
    "coordinate" : "org.codehaus.plexus:plexus-velocity:1.1.7",
    "hasDynamicAccess" : true,
    "totals" : {
      "coveredCalls" : 1,
      "totalCalls" : 2
    }
  }
[recv] {"type": "message_start", "message": {"role": "toolResult", "toolCallId": "call_WYCOCQLcG54RbHR9IDCqbXyK|fc_049667505a9e91930169ff87d1517081a3ab5e13e7b20a7b7a", "toolName": "read", "content": [{"type": "text", "text": "{\n  \"classes\" : [ {\n    \"callSites\" : [ {\n      \"covered\" : false,\n      \"frame\" : \"org.codehaus.plexus.velocity.VelocityComponent$1.class$(VelocityComponent.java:23)\",\n      \"line\" : 23,\n      \"metadataType\" : \"reflection\",\n      \"trackedApi\" : \"java.lang.Class#forName(java.lang.String)\"\n    } ],\n    \"className\" : \"org.codehaus.plexus.velocity.VelocityComponent$1\",\n    \"coveredCalls\" : 0,\n    \"sourceFile\" : \"VelocityComponent.java\",\n    \"totalCalls\" : 1\n  }, {\n    \"callSites\" : [ {\n      \"covered\" : true,\n      \"frame\" : \"org.codehaus.plexus.velocity.ContextClassLoaderResourceLoader.getResourceStream(ContextClassLoaderResourceLoader.java:48)\",\n      \"line\" : 48,\n      \"metadataType\" : \"resources\",\n      \"trackedApi\" : \"java.lang.ClassLoader#getResourceAsStream(java.lang.String)\"\n    } ],\n    \"className\" : \"org.codehaus.plexus.velocity.ContextClassLoaderResourceLoader\",\n    \"coveredCalls\" : 1,\n    \"sourceFile\" : \"ContextClassLoaderResourceLoader.java\",\n    \"totalCalls\" : 1\n  } ],\n  \"coordinate\" : \"org.codehaus.plexus:plexus-velocity:1.1.7\",\n  \"hasDynamicAccess\" : true,\n  \"totals\" : {\n    \"coveredCalls\" : 1,\n    \"totalCalls\" : 2\n  }\n}\n"}], "isError": false, "timestamp": 1778354129654}}
[recv] {"type": "message_end", "message": {"role": "toolResult", "toolCallId": "call_WYCOCQLcG54RbHR9IDCqbXyK|fc_049667505a9e91930169ff87d1517081a3ab5e13e7b20a7b7a", "toolName": "read", "content": [{"type": "text", "text": "{\n  \"classes\" : [ {\n    \"callSites\" : [ {\n      \"covered\" : false,\n      \"frame\" : \"org.codehaus.plexus.velocity.VelocityComponent$1.class$(VelocityComponent.java:23)\",\n      \"line\" : 23,\n      \"metadataType\" : \"reflection\",\n      \"trackedApi\" : \"java.lang.Class#forName(java.lang.String)\"\n    } ],\n    \"className\" : \"org.codehaus.plexus.velocity.VelocityComponent$1\",\n    \"coveredCalls\" : 0,\n    \"sourceFile\" : \"VelocityComponent.java\",\n    \"totalCalls\" : 1\n  }, {\n    \"callSites\" : [ {\n      \"covered\" : true,\n      \"frame\" : \"org.codehaus.plexus.velocity.ContextClassLoaderResourceLoader.getResourceStream(ContextClassLoaderResourceLoader.java:48)\",\n      \"line\" : 48,\n      \"metadataType\" : \"resources\",\n      \"trackedApi\" : \"java.lang.ClassLoader#getResourceAsStream(java.lang.String)\"\n    } ],\n    \"className\" : \"org.codehaus.plexus.velocity.ContextClassLoaderResourceLoader\",\n    \"coveredCalls\" : 1,\n    \"sourceFile\" : \"ContextClassLoaderResourceLoader.java\",\n    \"totalCalls\" : 1\n  } ],\n  \"coordinate\" : \"org.codehaus.plexus:plexus-velocity:1.1.7\",\n  \"hasDynamicAccess\" : true,\n  \"totals\" : {\n    \"coveredCalls\" : 1,\n    \"totalCalls\" : 2\n  }\n}\n"}], "isError": false, "timestamp": 1778354129654}}
[recv] {"type": "turn_end", "message": {"role": "assistant", "content": [{"type": "thinking", "thinking": "", "thinkingSignature": "{\"id\":\"rs_049667505a9e91930169ff87cfa11481a3881da192283e9e49\",\"type\":\"reasoning\",\"encrypted_content\":\"gAAAAABp_4fRewUrnXkWfosFV9h5vakSS_4RMU9D1xvF_NoxDB8WmLweoCNV1f0p8MjSARKiHo7d-RH8K93e5xAl8IYrj38jSjXURi4MKCD5oItNCoHHslUQLAtMjcu2CPg1MFgmXKjEsvVV9gkfLKNuJaN8OE4oJlk2RPxcFsjblVrxzQycjuCyuy0w1crMhuq9pzGcfWfP_cQ889albG4-JRUPOMTIIgDHf-FjhhmusSRdiyD_n7_BOGywk-3tDRUNMPGtCv2dDw9NCWgzme25dy22Lg_juB9SYbcBcUJzQqyXN6mVFORpvr5_ESlkzqxL1VYi4GKN05JUp1LCg66HX4tqkBZACe2TUIgxqmPp116i37Fwm27Yq-HliI-YonKyMp6Kl1dgde8MPTZGjhWuBdYWm9DQAQSkSup512SDz6LW1BmLNmDfolM5a9N-zaPi-yMqwmb-ac-Fdbii8atZa6uR0ejpTkJ8Ao_uXlADPq6hX2QFU_dPY0y6IDafRucrF8U_wcW0XqhpA4R8Pl0pp0gI8d2HRw-cpG86aGT7EYuhiq8q0eeW4g-JadX7isB45aWnv9vyEKo_kQQUJaGxlAian78_zwVwv-Wl_mQY8_TBaxwa1XLlQzQyZ6kqiZQdpmIbSXWi3KjG9DqfIvQ1m8OnoF8qpEMZxcyJ4Se5Bv3v708CMRudmVEaVCHtuCg-AqMyJcPhVGuvANYm-5Mr89oEUkOYWEyneae0-uPgvrsY5mWZW2C3t78Isk-lkZuzj1KZlZuQBYK4RbXBFauhoeNIchl7LoNnzDtVOdxZ6gWmKcIF24_i59VmDDIvFGikAgRYFV96peIQD7voZW1ASKas_GjXr9RlMrXJ1MIojIn4hBtYrCs7k4ciBdneNgUbesvEu3XGMcrO6h1Bru_qCoSTzym3tWzQYWigjmzVLTjJV_8T5YbS_eS4Z5F3FzUWmKleZ41Q3gCODy1rujPGCNYNMaQYafyo2veImQfj1jzDo_JQ7tKpdSPz7nS7U9Kc9DQ_teyBGDDOkPBWNht4WPF_QBMhF0rPfUMFykmgC6nGjsgjcUTlAcy7aUTy8qrdLVNG0y1jfQ9bYLxUZN957ewKmiD6-G0pb_yuyRhTRUIvYDdsC4O_s6wdggvwzENoz7y-KfkMlmckn-hC7LV2wb1UxpL9wwz6JTr0rGPgOyE2Wercs90ZUmKAqH-TiOAuhwAcT6YIjMakc1nttg7l2X8eUzYMUlQuTzU8pY65TExdntOJirF_MOwpZ-SOdhCOsaVVVYCWIvjQudajFSWYcE7lKuloj5y2CNzE6BOsq3XhR32i8-epuVVHixLJDZpkyCv6mS3J2_dNyjqbL7PXfsP7RiSY7l407_o30TiJB1dlUCaZQNtd_VcayJbE3orrW5Pqne8rTWmflnVEchC8x9InLGiz9tchyOu84yLABSZeitelGvvQHB2TnK-bzQ_hH9r0W0LkrmhCFt7aNsW6MoiVjZDhD8FMCR_veQiYRufi_VCSS7sGdS3LCWo8cDWEbAAdMGMAW60i9keNJIfYDlecamNODlytsCukKv395_y9HtAk8XtoyoURhMFbU8ySlEURWdgKQ9gCTFlaQXUHOt0r3P_YPA==\",\"summary\":[]}"}, {"type": "toolCall", "id": "call_WYCOCQLcG54RbHR9IDCqbXyK|fc_049667505a9e91930169ff87d1517081a3ab5e13e7b20a7b7a", "name": "read", "arguments": {"path": "tests/src/org.codehaus.plexus/plexus-velocity/1.1.7/build/reports/dynamic-access/dynamic-access-coverage.json", "limit": 200}}], "api": "openai-responses", "provider": "OCA", "model": "gpt-5.5", "usage": {"input": 696, "output": 160, "cacheRead": 9728, "cacheWrite": 0, "totalTokens": 10584, "cost": {"input": 0, "output": 0, "cacheRead": 0, "cacheWrite": 0, "total": 0}}, "stopReason": "toolUse", "timestamp": 1778354126730, "responseId": "resp_049667505a9e91930169ff87cf14c881a39c284f3fdd89e7bd"}, "toolResults": [{"role": "toolResult", "toolCallId": "call_WYCOCQLcG54RbHR9IDCqbXyK|fc_049667505a9e91930169ff87d1517081a3ab5e13e7b20a7b7a", "toolName": "read", "content": [{"type": "text", "text": "{\n  \"classes\" : [ {\n    \"callSites\" : [ {\n      \"covered\" : false,\n      \"frame\" : \"org.codehaus.plexus.velocity.VelocityComponent$1.class$(VelocityComponent.java:23)\",\n      \"line\" : 23,\n      \"metadataType\" : \"reflection\",\n      \"trackedApi\" : \"java.lang.Class#forName(java.lang.String)\"\n    } ],\n    \"className\" : \"org.codehaus.plexus.velocity.VelocityComponent$1\",\n    \"coveredCalls\" : 0,\n    \"sourceFile\" : \"VelocityComponent.java\",\n    \"totalCalls\" : 1\n  }, {\n    \"callSites\" : [ {\n      \"covered\" : true,\n      \"frame\" : \"org.codehaus.plexus.velocity.ContextClassLoaderResourceLoader.getResourceStream(ContextClassLoaderResourceLoader.java:48)\",\n      \"line\" : 48,\n      \"metadataType\" : \"resources\",\n      \"trackedApi\" : \"java.lang.ClassLoader#getResourceAsStream(java.lang.String)\"\n    } ],\n    \"className\" : \"org.codehaus.plexus.velocity.ContextClassLoaderResourceLoader\",\n    \"coveredCalls\" : 1,\n    \"sourceFile\" : \"ContextClassLoaderResourceLoader.java\",\n    \"totalCalls\" : 1\n  } ],\n  \"coordinate\" : \"org.codehaus.plexus:plexus-velocity:1.1.7\",\n  \"hasDynamicAccess\" : true,\n  \"totals\" : {\n    \"coveredCalls\" : 1,\n    \"totalCalls\" : 2\n  }\n}\n"}], "isError": false, "timestamp": 1778354129654}]}
[recv] {"type": "turn_start"}
[recv] {"type": "message_start", "message": {"role": "assistant", "content": [], "api": "openai-responses", "provider": "OCA", "model": "gpt-5.5", "usage": {"input": 0, "output": 0, "cacheRead": 0, "cacheWrite": 0, "totalTokens": 0, "cost": {"input": 0, "output": 0, "cacheRead": 0, "cacheWrite": 0, "total": 0}}, "stopReason": "stop", "timestamp": 1778354129660}}
[assistant-event] thinking_start
[thinking] **Investigating VelocityComponent testing**
[thinking] 
[thinking] I need to add a test file for the class named `VelocityComponent$1`, which I'll refer to as `VelocityComponentAnonymous1Test`. The rule seems to be replacing `$` followed by a number with `Anonymous1`. 
[thinking] 
[thinking] I wonder how to trigger it; maybe the static initializer of `ROLE`? It looks like the existing context doesn’t reference `VelocityComponent`, but if my test references `ROLE`, will it compile correctly? I'll need to check if it initializes interfaces and avoid direct reflection. I think I should inspect the bytecode with `javap`, too.
[thinking] 
[assistant-event] thinking_end
[tool-call] start id=unknown
[tool-call] delta {"command":"javap -classpath ~/.gradle/caches/modules-2/files-2.1/org.codehaus.plexus/plexus-velocity/1.1.7/*/plexus-velocity-1.1.7.jar -c -p 'org.codehaus.plexus.velocity.VelocityComponent$1' 'org.codehaus.plexus.velocity.VelocityComponent' 2>&1 | head -200"}
[tool-call] end id=call_izaR43vJCChgKyJdXGfWo1un|fc_049667505a9e91930169ff87d6e7b881a396cbc9bcc693c6c1 name=bash args={"command": "javap -classpath ~/.gradle/caches/modules-2/files-2.1/org.codehaus.plexus/plexus-velocity/1.1.7/*/plexus-velocity-1.1.7.jar -c -p 'org.codehaus.plexus.velocity.VelocityComponent$1' 'org.codehaus.plexus.velocity.VelocityComponent' 2>&1 | head -200"}
[recv] {"type": "message_end", "message": {"role": "assistant", "content": [{"type": "thinking", "thinking": "**Investigating VelocityComponent testing**\n\nI need to add a test file for the class named `VelocityComponent$1`, which I'll refer to as `VelocityComponentAnonymous1Test`. The rule seems to be replacing `$` followed by a number with `Anonymous1`. \n\nI wonder how to trigger it; maybe the static initializer of `ROLE`? It looks like the existing context doesn’t reference `VelocityComponent`, but if my test references `ROLE`, will it compile correctly? I'll need to check if it initializes interfaces and avoid direct reflection. I think I should inspect the bytecode with `javap`, too.", "thinkingSignature": "{\"id\":\"rs_049667505a9e91930169ff87d2b88081a39c14c32580036710\",\"type\":\"reasoning\",\"encrypted_content\":\"gAAAAABp_4fWbCi95APQYiCSsLaUdz4pL3UWBuVxGNXnTZbZlc_NMu7RMJfvXnPdZdnIkYkfS3MAXmwvxFbuURlzOvKoRqvcK4ojRO1gXtoHld6hI0pD1vmG3idWGP_yza0goAZp7RJlq6NWidlqpB_h-HnGd3R5v7BkQdoyqGvsUVpUpUGHIbihu2U_i4K3nND9E4Lbtb9jCFYIYcTRd0rD1UrnnEIxgP6gBIt8dzqf97J41RZdmszZBwW2HLTEkMq6Gg-44itIn_jlA5ngghjADTfnj88b2VaHQ5Hpuwn5vNgLDqRwUiiRu4O_Vhf7v_fW8vC5dgTXqEv9pa2jxlJniGZpY70WlKHD76iuH9_Qk4j8uwT1yrT5Ob4rMFSaCNlaSVJPAzxLmFvLQAkjo4kiToSBv8kN_7R7Zu6DpVcFoQaRpj1clhHIHXiz4MY5qWHbJBhKtS8IZLLkokHH-KZN44SO6a_0YQ4X7we--L6eTMwKmaGpFijhItffSe8cPwkeyZ5DzA4nhz5Nu55NGwEb8NY3cC8CzZjeVRtCU4e-hFq8vgKM4rhm-a9NKO2JYG4f8gmwvU5GKp_k8gXGeHdJ7rDk5AZkWf9c66ETKFQnpXECgPLzDS27Vg2_lzG9kVJ5gOMnQNNbsRzgnh3_uJ-AvZZZ1zBeFLXdeRobAe8D3MYwYw1CWCqi9UhdKHkMXtmpJED8v22YxLtBVhNnx1_LDiUvqCdw_2DZ84OniF0wAo777Rd-VQSXbKJYY9EGxC3tsAqcZsh-qep0U75Uhht7_cEE_rG39ixsBBfgQVMunGI4E2K6T_4s9sAbe6wpo3QHC_YFLGmGiaB9UCIrhT09T4mt-jhvQYY4hwAIUUr_ueim6bv5-PJJiR1Joy72Y0pw-qV6kJ4TtbtVow25Q3Neh_d5ytURBTPBe8lwyaSbFKqwKgXC8LXpQ8Lh4-Pf2-8pEArQ5qI_9WnGzU64na9rR__Pv7ycW3kwy0DX99-6Ef7jOnun99H15mHHPQvOEDfrLIcrV1fMQisfiLu2mQDS8c-bY68B2B6yW5A1K6EgH8XfaDI6AHxxhb0hrW-vze0eC_z2icJ9gBGMaNQ-lS3sN-2IkX3YbDAw6O2fDPkUQZ5aUZl4HEZghK5uMpeKyoRKgClIppvU9IwKafLqhMuUvzPqci08Fn0FRmiPfBNOtimyB-3Lw4_WnhoeWpu0n-2racS7iyrwJP8PKV8Qa-mcnWc0WvTU9jh5ckcVWc0JNSzO-tD5fAXoye_k80Yxyob-9kyTfkWpil-p-KrVc7IHS1ofxt6EOvDXorcs1Oc6UQA2uybz7xKE4KUcCBvHOkY_6VXgSH7rTqTH_k3lyDIBej3qX5Oa415Zqrqm5XeShSpyHj9JAXoPZDmFp2K5WAF8fLuzPRL263w-71bMUIc_atq4aspt3yD_fR2VBbbef_IkOKdYXB4tbZRyShcmFLzPfQ950NZxy20k4ZfVpbziek0kd3lOldC-mERVao8SZjGG1JmKivVEehlkRzALZpIv_iaCXJKYfawix6uGh4E-7ABfyFn8V6R1B7ZqxlqrGYWzjPNYoNPhvGjLRorGl64j3Mt-fJhrDZRejLpq8_lHsXiUUHjOabd3vRtk0OmbWejfk74X8a8BeSugIepPGlGeH2BZmkxRVdQ2F1K539cd09peSDkqnC5ICiKT7TAGawF7-MxDuOvssSZnGd_rYi-M65sywZSucPrpKCH3ZHr7zUschLS621FMaombHG1z17lsqoadGYqTzylu0apNDrbG0P6EftRLoUzakPu7hhDSQ4tblRha4zpHVzWHl5QDAYCoMyD5Cqe3coqcvHsp3qomBOfy9K-n92tW41jWWDjnbZ697VDyaP0WrZ6iCeVJyjEvL46JQ_0AZCr2i8EosFccwTHxiHHQhkqesUS_xvgDXCCqShqmz8NqhLw2NnWsq_BcRJtwfRNogQNyvHCRXNi7-HXSOXHHtxYKBt20UDZiVGl1V_Pa1CQ5jATnJhFQxeptheZpUkFkcmbbwm_dV1lOEIwHm4pr1Y9uEirWfAJ2tJgP7ohWsnE92LwL7n8HZdv9pwPvBLAdaLXqldUW5RL324UqfjHqmG4BE7ElNaR8qwk-9Bebdg==\",\"summary\":[{\"type\":\"summary_text\",\"text\":\"**Investigating VelocityComponent testing**\\n\\nI need to add a test file for the class named `VelocityComponent$1`, which I'll refer to as `VelocityComponentAnonymous1Test`. The rule seems to be replacing `$` followed by a number with `Anonymous1`. \\n\\nI wonder how to trigger it; maybe the static initializer of `ROLE`? It looks like the existing context doesn’t reference `VelocityComponent`, but if my test references `ROLE`, will it compile correctly? I'll need to check if it initializes interfaces and avoid direct reflection. I think I should inspect the bytecode with `javap`, too.\"}]}"}, {"type": "toolCall", "id": "call_izaR43vJCChgKyJdXGfWo1un|fc_049667505a9e91930169ff87d6e7b881a396cbc9bcc693c6c1", "name": "bash", "arguments": {"command": "javap -classpath ~/.gradle/caches/modules-2/files-2.1/org.codehaus.plexus/plexus-velocity/1.1.7/*/plexus-velocity-1.1.7.jar -c -p 'org.codehaus.plexus.velocity.VelocityComponent$1' 'org.codehaus.plexus.velocity.VelocityComponent' 2>&1 | head -200"}}], "api": "openai-responses", "provider": "OCA", "model": "gpt-5.5", "usage": {"input": 689, "output": 271, "cacheRead": 10240, "cacheWrite": 0, "totalTokens": 11200, "cost": {"input": 0, "output": 0, "cacheRead": 0, "cacheWrite": 0, "total": 0}}, "stopReason": "toolUse", "timestamp": 1778354129660, "responseId": "resp_049667505a9e91930169ff87d2227081a3a02f3cdb6122d9b0"}}
[tool-exec] start id=call_izaR43vJCChgKyJdXGfWo1un|fc_049667505a9e91930169ff87d6e7b881a396cbc9bcc693c6c1 name=bash args={"command": "javap -classpath ~/.gradle/caches/modules-2/files-2.1/org.codehaus.plexus/plexus-velocity/1.1.7/*/plexus-velocity-1.1.7.jar -c -p 'org.codehaus.plexus.velocity.VelocityComponent$1' 'org.codehaus.plexus.velocity.VelocityComponent' 2>&1 | head -200"}
[tool-exec] update id=call_izaR43vJCChgKyJdXGfWo1un|fc_049667505a9e91930169ff87d6e7b881a396cbc9bcc693c6c1 name=bash
[tool-exec] update id=call_izaR43vJCChgKyJdXGfWo1un|fc_049667505a9e91930169ff87d6e7b881a396cbc9bcc693c6c1 name=bash
  Error: class not found: org.codehaus.plexus.velocity.VelocityComponent$1
  Error: class not found: org.codehaus.plexus.velocity.VelocityComponent
[tool-exec] end id=call_izaR43vJCChgKyJdXGfWo1un|fc_049667505a9e91930169ff87d6e7b881a396cbc9bcc693c6c1 name=bash status=success
  Error: class not found: org.codehaus.plexus.velocity.VelocityComponent$1
  Error: class not found: org.codehaus.plexus.velocity.VelocityComponent
[recv] {"type": "message_start", "message": {"role": "toolResult", "toolCallId": "call_izaR43vJCChgKyJdXGfWo1un|fc_049667505a9e91930169ff87d6e7b881a396cbc9bcc693c6c1", "toolName": "bash", "content": [{"type": "text", "text": "Error: class not found: org.codehaus.plexus.velocity.VelocityComponent$1\nError: class not found: org.codehaus.plexus.velocity.VelocityComponent\n"}], "isError": false, "timestamp": 1778354135483}}
[recv] {"type": "message_end", "message": {"role": "toolResult", "toolCallId": "call_izaR43vJCChgKyJdXGfWo1un|fc_049667505a9e91930169ff87d6e7b881a396cbc9bcc693c6c1", "toolName": "bash", "content": [{"type": "text", "text": "Error: class not found: org.codehaus.plexus.velocity.VelocityComponent$1\nError: class not found: org.codehaus.plexus.velocity.VelocityComponent\n"}], "isError": false, "timestamp": 1778354135483}}
[recv] {"type": "turn_end", "message": {"role": "assistant", "content": [{"type": "thinking", "thinking": "**Investigating VelocityComponent testing**\n\nI need to add a test file for the class named `VelocityComponent$1`, which I'll refer to as `VelocityComponentAnonymous1Test`. The rule seems to be replacing `$` followed by a number with `Anonymous1`. \n\nI wonder how to trigger it; maybe the static initializer of `ROLE`? It looks like the existing context doesn’t reference `VelocityComponent`, but if my test references `ROLE`, will it compile correctly? I'll need to check if it initializes interfaces and avoid direct reflection. I think I should inspect the bytecode with `javap`, too.", "thinkingSignature": "{\"id\":\"rs_049667505a9e91930169ff87d2b88081a39c14c32580036710\",\"type\":\"reasoning\",\"encrypted_content\":\"gAAAAABp_4fWbCi95APQYiCSsLaUdz4pL3UWBuVxGNXnTZbZlc_NMu7RMJfvXnPdZdnIkYkfS3MAXmwvxFbuURlzOvKoRqvcK4ojRO1gXtoHld6hI0pD1vmG3idWGP_yza0goAZp7RJlq6NWidlqpB_h-HnGd3R5v7BkQdoyqGvsUVpUpUGHIbihu2U_i4K3nND9E4Lbtb9jCFYIYcTRd0rD1UrnnEIxgP6gBIt8dzqf97J41RZdmszZBwW2HLTEkMq6Gg-44itIn_jlA5ngghjADTfnj88b2VaHQ5Hpuwn5vNgLDqRwUiiRu4O_Vhf7v_fW8vC5dgTXqEv9pa2jxlJniGZpY70WlKHD76iuH9_Qk4j8uwT1yrT5Ob4rMFSaCNlaSVJPAzxLmFvLQAkjo4kiToSBv8kN_7R7Zu6DpVcFoQaRpj1clhHIHXiz4MY5qWHbJBhKtS8IZLLkokHH-KZN44SO6a_0YQ4X7we--L6eTMwKmaGpFijhItffSe8cPwkeyZ5DzA4nhz5Nu55NGwEb8NY3cC8CzZjeVRtCU4e-hFq8vgKM4rhm-a9NKO2JYG4f8gmwvU5GKp_k8gXGeHdJ7rDk5AZkWf9c66ETKFQnpXECgPLzDS27Vg2_lzG9kVJ5gOMnQNNbsRzgnh3_uJ-AvZZZ1zBeFLXdeRobAe8D3MYwYw1CWCqi9UhdKHkMXtmpJED8v22YxLtBVhNnx1_LDiUvqCdw_2DZ84OniF0wAo777Rd-VQSXbKJYY9EGxC3tsAqcZsh-qep0U75Uhht7_cEE_rG39ixsBBfgQVMunGI4E2K6T_4s9sAbe6wpo3QHC_YFLGmGiaB9UCIrhT09T4mt-jhvQYY4hwAIUUr_ueim6bv5-PJJiR1Joy72Y0pw-qV6kJ4TtbtVow25Q3Neh_d5ytURBTPBe8lwyaSbFKqwKgXC8LXpQ8Lh4-Pf2-8pEArQ5qI_9WnGzU64na9rR__Pv7ycW3kwy0DX99-6Ef7jOnun99H15mHHPQvOEDfrLIcrV1fMQisfiLu2mQDS8c-bY68B2B6yW5A1K6EgH8XfaDI6AHxxhb0hrW-vze0eC_z2icJ9gBGMaNQ-lS3sN-2IkX3YbDAw6O2fDPkUQZ5aUZl4HEZghK5uMpeKyoRKgClIppvU9IwKafLqhMuUvzPqci08Fn0FRmiPfBNOtimyB-3Lw4_WnhoeWpu0n-2racS7iyrwJP8PKV8Qa-mcnWc0WvTU9jh5ckcVWc0JNSzO-tD5fAXoye_k80Yxyob-9kyTfkWpil-p-KrVc7IHS1ofxt6EOvDXorcs1Oc6UQA2uybz7xKE4KUcCBvHOkY_6VXgSH7rTqTH_k3lyDIBej3qX5Oa415Zqrqm5XeShSpyHj9JAXoPZDmFp2K5WAF8fLuzPRL263w-71bMUIc_atq4aspt3yD_fR2VBbbef_IkOKdYXB4tbZRyShcmFLzPfQ950NZxy20k4ZfVpbziek0kd3lOldC-mERVao8SZjGG1JmKivVEehlkRzALZpIv_iaCXJKYfawix6uGh4E-7ABfyFn8V6R1B7ZqxlqrGYWzjPNYoNPhvGjLRorGl64j3Mt-fJhrDZRejLpq8_lHsXiUUHjOabd3vRtk0OmbWejfk74X8a8BeSugIepPGlGeH2BZmkxRVdQ2F1K539cd09peSDkqnC5ICiKT7TAGawF7-MxDuOvssSZnGd_rYi-M65sywZSucPrpKCH3ZHr7zUschLS621FMaombHG1z17lsqoadGYqTzylu0apNDrbG0P6EftRLoUzakPu7hhDSQ4tblRha4zpHVzWHl5QDAYCoMyD5Cqe3coqcvHsp3qomBOfy9K-n92tW41jWWDjnbZ697VDyaP0WrZ6iCeVJyjEvL46JQ_0AZCr2i8EosFccwTHxiHHQhkqesUS_xvgDXCCqShqmz8NqhLw2NnWsq_BcRJtwfRNogQNyvHCRXNi7-HXSOXHHtxYKBt20UDZiVGl1V_Pa1CQ5jATnJhFQxeptheZpUkFkcmbbwm_dV1lOEIwHm4pr1Y9uEirWfAJ2tJgP7ohWsnE92LwL7n8HZdv9pwPvBLAdaLXqldUW5RL324UqfjHqmG4BE7ElNaR8qwk-9Bebdg==\",\"summary\":[{\"type\":\"summary_text\",\"text\":\"**Investigating VelocityComponent testing**\\n\\nI need to add a test file for the class named `VelocityComponent$1`, which I'll refer to as `VelocityComponentAnonymous1Test`. The rule seems to be replacing `$` followed by a number with `Anonymous1`. \\n\\nI wonder how to trigger it; maybe the static initializer of `ROLE`? It looks like the existing context doesn’t reference `VelocityComponent`, but if my test references `ROLE`, will it compile correctly? I'll need to check if it initializes interfaces and avoid direct reflection. I think I should inspect the bytecode with `javap`, too.\"}]}"}, {"type": "toolCall", "id": "call_izaR43vJCChgKyJdXGfWo1un|fc_049667505a9e91930169ff87d6e7b881a396cbc9bcc693c6c1", "name": "bash", "arguments": {"command": "javap -classpath ~/.gradle/caches/modules-2/files-2.1/org.codehaus.plexus/plexus-velocity/1.1.7/*/plexus-velocity-1.1.7.jar -c -p 'org.codehaus.plexus.velocity.VelocityComponent$1' 'org.codehaus.plexus.velocity.VelocityComponent' 2>&1 | head -200"}}], "api": "openai-responses", "provider": "OCA", "model": "gpt-5.5", "usage": {"input": 689, "output": 271, "cacheRead": 10240, "cacheWrite": 0, "totalTokens": 11200, "cost": {"input": 0, "output": 0, "cacheRead": 0, "cacheWrite": 0, "total": 0}}, "stopReason": "toolUse", "timestamp": 1778354129660, "responseId": "resp_049667505a9e91930169ff87d2227081a3a02f3cdb6122d9b0"}, "toolResults": [{"role": "toolResult", "toolCallId": "call_izaR43vJCChgKyJdXGfWo1un|fc_049667505a9e91930169ff87d6e7b881a396cbc9bcc693c6c1", "toolName": "bash", "content": [{"type": "text", "text": "Error: class not found: org.codehaus.plexus.velocity.VelocityComponent$1\nError: class not found: org.codehaus.plexus.velocity.VelocityComponent\n"}], "isError": false, "timestamp": 1778354135483}]}
[recv] {"type": "turn_start"}
[recv] {"type": "message_start", "message": {"role": "assistant", "content": [], "api": "openai-responses", "provider": "OCA", "model": "gpt-5.5", "usage": {"input": 0, "output": 0, "cacheRead": 0, "cacheWrite": 0, "totalTokens": 0, "cost": {"input": 0, "output": 0, "cacheRead": 0, "cacheWrite": 0, "total": 0}}, "stopReason": "stop", "timestamp": 1778354135485}}
[assistant-event] thinking_start
[assistant-event] thinking_end
[tool-call] start id=unknown
[tool-call] delta {"command":"find ~/.gradle ~/.m2 -path '*plexus-velocity*1.1.7*.jar' -print 2>/dev/null | head -20"}
[tool-call] end id=call_7k5vpVSDszMFJyegt5NS9Zj0|fc_049667505a9e91930169ff87d9291481a387ba5546aa4ab141 name=bash args={"command": "find ~/.gradle ~/.m2 -path '*plexus-velocity*1.1.7*.jar' -print 2>/dev/null | head -20"}
[recv] {"type": "message_end", "message": {"role": "assistant", "content": [{"type": "thinking", "thinking": "", "thinkingSignature": "{\"id\":\"rs_049667505a9e91930169ff87d8a53c81a3b68de73f3b146757\",\"type\":\"reasoning\",\"encrypted_content\":\"gAAAAABp_4fZrsjAAD6wUudS0sZuRTw2r6VqjuIRCKHwdMpAmrsXEYa1fYt0JhnSPpUz6k-Yfg1XG3p8Oi2eH1zyOAD1fRXrK6LfjQpL8Tl12NpM_wNPWUmtLhJ3ClaqeFYySuGvbment6FN_lbqU1a0GIv6VYuz-Jz6qRsd6rOlVkAZJFIuGfFiIBrKohTv-xZs7gN5VFxf7ieUIlFbVGlvwtZVYLVlZgGHv1u1TwdBYVk-ZPhdcSyMCuXUXBPCJ28R4dpJkePOQcOpu6yEQgcF2-OdzPlvN6PE38bL2XlGCZB_gVblDJF1y1wCcMM5dvCDe4SXa-xZcLd82Yo7Z0hlx6iH8DshRCRzGk3AZQdPyubrdTIrynKPkfV2gm8xZY6zlGsYh3J8vghbscLaAWfS9uJC1ihv8avPmtrW1jAyF5pPvd2meB8T39LrcRATTsISTh9_XS5F_9hMEa8k0O016Ejw8FQEKXFIxX1BVc4LBTIYFzxPCEy7hVmZ3K8-e4E72bHhkM7M6FWoqHhPw3erQaZZMQrLa59X2qBmJMJeR6zOHEicH4Jjwj221V42KV5oJcv1fWMKZA6-PHzIIVUV5kEf5vTb3-GiK-0fmTYXx9XykLF88Z8FTTZIAoU_kFOJOXC49uutbZoYuz7PGf5287xrHvg7L-HuTDmGbRw4b80gjHjhIYOdkEkjmSZQ0HL3D7bFWg0iRZBdknbLG3YZRCuu__eahNgiIHfawhoe6L-ouqKJbCs-bPslnUjyI_biOzMip5wLYTfKVTE0WAcF5w81wdYygJvKRpSCxJTUc7Rep8L5VHxt9GsZ-ClsXtIcSqkp_HStTtKRs6cRbwyRXxQKoq3CFzy-8__8tLiAcX4JUTrWrZC8izx9NnDLkDbuXvDxxLRHNAhm4DCpmTJYYr2fGdHWiDNADaxGlsE3uJRwiRRHz7oarmJtrFn2F1z-tY2kNulZvi_g3zLOE7xIFJ4EDxl0Yg==\",\"summary\":[]}"}, {"type": "toolCall", "id": "call_7k5vpVSDszMFJyegt5NS9Zj0|fc_049667505a9e91930169ff87d9291481a387ba5546aa4ab141", "name": "bash", "arguments": {"command": "find ~/.gradle ~/.m2 -path '*plexus-velocity*1.1.7*.jar' -print 2>/dev/null | head -20"}}], "api": "openai-responses", "provider": "OCA", "model": "gpt-5.5", "usage": {"input": 495, "output": 64, "cacheRead": 10752, "cacheWrite": 0, "totalTokens": 11311, "cost": {"input": 0, "output": 0, "cacheRead": 0, "cacheWrite": 0, "total": 0}}, "stopReason": "toolUse", "timestamp": 1778354135485, "responseId": "resp_049667505a9e91930169ff87d7d3f481a38d8558909d0b8040"}}
[tool-exec] start id=call_7k5vpVSDszMFJyegt5NS9Zj0|fc_049667505a9e91930169ff87d9291481a387ba5546aa4ab141 name=bash args={"command": "find ~/.gradle ~/.m2 -path '*plexus-velocity*1.1.7*.jar' -print 2>/dev/null | head -20"}
[tool-exec] update id=call_7k5vpVSDszMFJyegt5NS9Zj0|fc_049667505a9e91930169ff87d9291481a387ba5546aa4ab141 name=bash
[tool-exec] update id=call_7k5vpVSDszMFJyegt5NS9Zj0|fc_049667505a9e91930169ff87d9291481a387ba5546aa4ab141 name=bash
  /home/vjovanov/.m2/repository/org/codehaus/plexus/plexus-velocity/1.1.7/plexus-velocity-1.1.7.jar
[tool-exec] end id=call_7k5vpVSDszMFJyegt5NS9Zj0|fc_049667505a9e91930169ff87d9291481a387ba5546aa4ab141 name=bash status=success
  /home/vjovanov/.m2/repository/org/codehaus/plexus/plexus-velocity/1.1.7/plexus-velocity-1.1.7.jar
[recv] {"type": "message_start", "message": {"role": "toolResult", "toolCallId": "call_7k5vpVSDszMFJyegt5NS9Zj0|fc_049667505a9e91930169ff87d9291481a387ba5546aa4ab141", "toolName": "bash", "content": [{"type": "text", "text": "/home/vjovanov/.m2/repository/org/codehaus/plexus/plexus-velocity/1.1.7/plexus-velocity-1.1.7.jar\n"}], "isError": false, "timestamp": 1778354138062}}
[recv] {"type": "message_end", "message": {"role": "toolResult", "toolCallId": "call_7k5vpVSDszMFJyegt5NS9Zj0|fc_049667505a9e91930169ff87d9291481a387ba5546aa4ab141", "toolName": "bash", "content": [{"type": "text", "text": "/home/vjovanov/.m2/repository/org/codehaus/plexus/plexus-velocity/1.1.7/plexus-velocity-1.1.7.jar\n"}], "isError": false, "timestamp": 1778354138062}}
[recv] {"type": "turn_end", "message": {"role": "assistant", "content": [{"type": "thinking", "thinking": "", "thinkingSignature": "{\"id\":\"rs_049667505a9e91930169ff87d8a53c81a3b68de73f3b146757\",\"type\":\"reasoning\",\"encrypted_content\":\"gAAAAABp_4fZrsjAAD6wUudS0sZuRTw2r6VqjuIRCKHwdMpAmrsXEYa1fYt0JhnSPpUz6k-Yfg1XG3p8Oi2eH1zyOAD1fRXrK6LfjQpL8Tl12NpM_wNPWUmtLhJ3ClaqeFYySuGvbment6FN_lbqU1a0GIv6VYuz-Jz6qRsd6rOlVkAZJFIuGfFiIBrKohTv-xZs7gN5VFxf7ieUIlFbVGlvwtZVYLVlZgGHv1u1TwdBYVk-ZPhdcSyMCuXUXBPCJ28R4dpJkePOQcOpu6yEQgcF2-OdzPlvN6PE38bL2XlGCZB_gVblDJF1y1wCcMM5dvCDe4SXa-xZcLd82Yo7Z0hlx6iH8DshRCRzGk3AZQdPyubrdTIrynKPkfV2gm8xZY6zlGsYh3J8vghbscLaAWfS9uJC1ihv8avPmtrW1jAyF5pPvd2meB8T39LrcRATTsISTh9_XS5F_9hMEa8k0O016Ejw8FQEKXFIxX1BVc4LBTIYFzxPCEy7hVmZ3K8-e4E72bHhkM7M6FWoqHhPw3erQaZZMQrLa59X2qBmJMJeR6zOHEicH4Jjwj221V42KV5oJcv1fWMKZA6-PHzIIVUV5kEf5vTb3-GiK-0fmTYXx9XykLF88Z8FTTZIAoU_kFOJOXC49uutbZoYuz7PGf5287xrHvg7L-HuTDmGbRw4b80gjHjhIYOdkEkjmSZQ0HL3D7bFWg0iRZBdknbLG3YZRCuu__eahNgiIHfawhoe6L-ouqKJbCs-bPslnUjyI_biOzMip5wLYTfKVTE0WAcF5w81wdYygJvKRpSCxJTUc7Rep8L5VHxt9GsZ-ClsXtIcSqkp_HStTtKRs6cRbwyRXxQKoq3CFzy-8__8tLiAcX4JUTrWrZC8izx9NnDLkDbuXvDxxLRHNAhm4DCpmTJYYr2fGdHWiDNADaxGlsE3uJRwiRRHz7oarmJtrFn2F1z-tY2kNulZvi_g3zLOE7xIFJ4EDxl0Yg==\",\"summary\":[]}"}, {"type": "toolCall", "id": "call_7k5vpVSDszMFJyegt5NS9Zj0|fc_049667505a9e91930169ff87d9291481a387ba5546aa4ab141", "name": "bash", "arguments": {"command": "find ~/.gradle ~/.m2 -path '*plexus-velocity*1.1.7*.jar' -print 2>/dev/null | head -20"}}], "api": "openai-responses", "provider": "OCA", "model": "gpt-5.5", "usage": {"input": 495, "output": 64, "cacheRead": 10752, "cacheWrite": 0, "totalTokens": 11311, "cost": {"input": 0, "output": 0, "cacheRead": 0, "cacheWrite": 0, "total": 0}}, "stopReason": "toolUse", "timestamp": 1778354135485, "responseId": "resp_049667505a9e91930169ff87d7d3f481a38d8558909d0b8040"}, "toolResults": [{"role": "toolResult", "toolCallId": "call_7k5vpVSDszMFJyegt5NS9Zj0|fc_049667505a9e91930169ff87d9291481a387ba5546aa4ab141", "toolName": "bash", "content": [{"type": "text", "text": "/home/vjovanov/.m2/repository/org/codehaus/plexus/plexus-velocity/1.1.7/plexus-velocity-1.1.7.jar\n"}], "isError": false, "timestamp": 1778354138062}]}
[recv] {"type": "turn_start"}
[recv] {"type": "message_start", "message": {"role": "assistant", "content": [], "api": "openai-responses", "provider": "OCA", "model": "gpt-5.5", "usage": {"input": 0, "output": 0, "cacheRead": 0, "cacheWrite": 0, "totalTokens": 0, "cost": {"input": 0, "output": 0, "cacheRead": 0, "cacheWrite": 0, "total": 0}}, "stopReason": "stop", "timestamp": 1778354138069}}
[tool-call] start id=unknown
[tool-call] delta {"command":"jar tf ~/.m2/repository/org/codehaus/plexus/plexus-velocity/1.1.7/plexus-velocity-1.1.7.jar | grep VelocityComponent && javap -classpath ~/.m2/repository/org/codehaus/plexus/plexus-velocity/1.1.7/plexus-velocity-1.1.7.jar -c -p 'org.codehaus.plexus.velocity.VelocityComponent$1' 'org.codehaus.plexus.velocity.VelocityComponent'","timeout":30}
[tool-call] end id=call_W6MhiK7K23vVPw2t5gF3NdrU|fc_049667505a9e91930169ff87dc06ec81a3bf1e1094c18b787a name=bash args={"command": "jar tf ~/.m2/repository/org/codehaus/plexus/plexus-velocity/1.1.7/plexus-velocity-1.1.7.jar | grep VelocityComponent && javap -classpath ~/.m2/repository/org/codehaus/plexus/plexus-velocity/1.1.7/plexus-velocity-1.1.7.jar -c -p 'org.codehaus.plexus.velocity.VelocityComponent$1' 'org.codehaus.plexus.velocity.VelocityComponent'", "timeout": 30}
[recv] {"type": "message_end", "message": {"role": "assistant", "content": [{"type": "toolCall", "id": "call_W6MhiK7K23vVPw2t5gF3NdrU|fc_049667505a9e91930169ff87dc06ec81a3bf1e1094c18b787a", "name": "bash", "arguments": {"command": "jar tf ~/.m2/repository/org/codehaus/plexus/plexus-velocity/1.1.7/plexus-velocity-1.1.7.jar | grep VelocityComponent && javap -classpath ~/.m2/repository/org/codehaus/plexus/plexus-velocity/1.1.7/plexus-velocity-1.1.7.jar -c -p 'org.codehaus.plexus.velocity.VelocityComponent$1' 'org.codehaus.plexus.velocity.VelocityComponent'", "timeout": 30}}], "api": "openai-responses", "provider": "OCA", "model": "gpt-5.5", "usage": {"input": 610, "output": 130, "cacheRead": 10752, "cacheWrite": 0, "totalTokens": 11492, "cost": {"input": 0, "output": 0, "cacheRead": 0, "cacheWrite": 0, "total": 0}}, "stopReason": "toolUse", "timestamp": 1778354138069, "responseId": "resp_049667505a9e91930169ff87da6aec81a3a786396148870998"}}
[tool-exec] start id=call_W6MhiK7K23vVPw2t5gF3NdrU|fc_049667505a9e91930169ff87dc06ec81a3bf1e1094c18b787a name=bash args={"command": "jar tf ~/.m2/repository/org/codehaus/plexus/plexus-velocity/1.1.7/plexus-velocity-1.1.7.jar | grep VelocityComponent && javap -classpath ~/.m2/repository/org/codehaus/plexus/plexus-velocity/1.1.7/plexus-velocity-1.1.7.jar -c -p 'org.codehaus.plexus.velocity.VelocityComponent$1' 'org.codehaus.plexus.velocity.VelocityComponent'", "timeout": 30}
[tool-exec] update id=call_W6MhiK7K23vVPw2t5gF3NdrU|fc_049667505a9e91930169ff87dc06ec81a3bf1e1094c18b787a name=bash
[tool-exec] update id=call_W6MhiK7K23vVPw2t5gF3NdrU|fc_049667505a9e91930169ff87dc06ec81a3bf1e1094c18b787a name=bash
  org/codehaus/plexus/velocity/DefaultVelocityComponent.class
  org/codehaus/plexus/velocity/VelocityComponent$1.class
  org/codehaus/plexus/velocity/VelocityComponent.class
[tool-exec] update id=call_W6MhiK7K23vVPw2t5gF3NdrU|fc_049667505a9e91930169ff87dc06ec81a3bf1e1094c18b787a name=bash
  org/codehaus/plexus/velocity/DefaultVelocityComponent.class
  org/codehaus/plexus/velocity/VelocityComponent$1.class
  org/codehaus/plexus/velocity/VelocityComponent.class
  Compiled from "VelocityComponent.java"
[tool-exec] update id=call_W6MhiK7K23vVPw2t5gF3NdrU|fc_049667505a9e91930169ff87dc06ec81a3bf1e1094c18b787a name=bash
  org/codehaus/plexus/velocity/DefaultVelocityComponent.class
  org/codehaus/plexus/velocity/VelocityComponent$1.class
  org/codehaus/plexus/velocity/VelocityComponent.class
  Compiled from "VelocityComponent.java"
  class org.codehaus.plexus.velocity.VelocityComponent$1 {
[tool-exec] update id=call_W6MhiK7K23vVPw2t5gF3NdrU|fc_049667505a9e91930169ff87dc06ec81a3bf1e1094c18b787a name=bash
  org/codehaus/plexus/velocity/DefaultVelocityComponent.class
  org/codehaus/plexus/velocity/VelocityComponent$1.class
  org/codehaus/plexus/velocity/VelocityComponent.class
  Compiled from "VelocityComponent.java"
  class org.codehaus.plexus.velocity.VelocityComponent$1 {
    static java.lang.Class class$org$codehaus$plexus$velocity$VelocityComponent;
  
[tool-exec] update id=call_W6MhiK7K23vVPw2t5gF3NdrU|fc_049667505a9e91930169ff87dc06ec81a3bf1e1094c18b787a name=bash
  org/codehaus/plexus/velocity/DefaultVelocityComponent.class
  org/codehaus/plexus/velocity/VelocityComponent$1.class
  org/codehaus/plexus/velocity/VelocityComponent.class
  Compiled from "VelocityComponent.java"
  class org.codehaus.plexus.velocity.VelocityComponent$1 {
    static java.lang.Class class$org$codehaus$plexus$velocity$VelocityComponent;
  
    static java.lang.Class class$(java.lang.String);
[tool-exec] update id=call_W6MhiK7K23vVPw2t5gF3NdrU|fc_049667505a9e91930169ff87dc06ec81a3bf1e1094c18b787a name=bash
  org/codehaus/plexus/velocity/DefaultVelocityComponent.class
  org/codehaus/plexus/velocity/VelocityComponent$1.class
  org/codehaus/plexus/velocity/VelocityComponent.class
  Compiled from "VelocityComponent.java"
  class org.codehaus.plexus.velocity.VelocityComponent$1 {
    static java.lang.Class class$org$codehaus$plexus$velocity$VelocityComponent;
  
    static java.lang.Class class$(java.lang.String);
      Code:
[tool-exec] update id=call_W6MhiK7K23vVPw2t5gF3NdrU|fc_049667505a9e91930169ff87dc06ec81a3bf1e1094c18b787a name=bash
  org/codehaus/plexus/velocity/DefaultVelocityComponent.class
  org/codehaus/plexus/velocity/VelocityComponent$1.class
  org/codehaus/plexus/velocity/VelocityComponent.class
  Compiled from "VelocityComponent.java"
  class org.codehaus.plexus.velocity.VelocityComponent$1 {
    static java.lang.Class class$org$codehaus$plexus$velocity$VelocityComponent;
  
    static java.lang.Class class$(java.lang.String);
      Code:
           0: aload_0
[tool-exec] update id=call_W6MhiK7K23vVPw2t5gF3NdrU|fc_049667505a9e91930169ff87dc06ec81a3bf1e1094c18b787a name=bash
  org/codehaus/plexus/velocity/DefaultVelocityComponent.class
  org/codehaus/plexus/velocity/VelocityComponent$1.class
  org/codehaus/plexus/velocity/VelocityComponent.class
  Compiled from "VelocityComponent.java"
  class org.codehaus.plexus.velocity.VelocityComponent$1 {
    static java.lang.Class class$org$codehaus$plexus$velocity$VelocityComponent;
  
    static java.lang.Class class$(java.lang.String);
      Code:
           0: aload_0
           1: invokestatic  #1                  // Method java/lang/Class.forName:(Ljava/lang/String;)Ljava/lang/Class;
           4: areturn
           5: astore_1
[tool-exec] update id=call_W6MhiK7K23vVPw2t5gF3NdrU|fc_049667505a9e91930169ff87dc06ec81a3bf1e1094c18b787a name=bash
  org/codehaus/plexus/velocity/DefaultVelocityComponent.class
  org/codehaus/plexus/velocity/VelocityComponent$1.class
  org/codehaus/plexus/velocity/VelocityComponent.class
  Compiled from "VelocityComponent.java"
  class org.codehaus.plexus.velocity.VelocityComponent$1 {
    static java.lang.Class class$org$codehaus$plexus$velocity$VelocityComponent;
  
    static java.lang.Class class$(java.lang.String);
      Code:
           0: aload_0
           1: invokestatic  #1                  // Method java/lang/Class.forName:(Ljava/lang/String;)Ljava/lang/Class;
           4: areturn
           5: astore_1
           6: new           #3                  // class java/lang/NoClassDefFoundError
           9: dup
[tool-exec] update id=call_W6MhiK7K23vVPw2t5gF3NdrU|fc_049667505a9e91930169ff87dc06ec81a3bf1e1094c18b787a name=bash
  org/codehaus/plexus/velocity/DefaultVelocityComponent.class
  org/codehaus/plexus/velocity/VelocityComponent$1.class
  org/codehaus/plexus/velocity/VelocityComponent.class
  Compiled from "VelocityComponent.java"
  class org.codehaus.plexus.velocity.VelocityComponent$1 {
    static java.lang.Class class$org$codehaus$plexus$velocity$VelocityComponent;
  
    static java.lang.Class class$(java.lang.String);
      Code:
           0: aload_0
           1: invokestatic  #1                  // Method java/lang/Class.forName:(Ljava/lang/String;)Ljava/lang/Class;
           4: areturn
           5: astore_1
           6: new           #3                  // class java/lang/NoClassDefFoundError
           9: dup
          10: invokespecial #4                  // Method java/lang/NoClassDefFoundError."<init>":()V
[tool-exec] update id=call_W6MhiK7K23vVPw2t5gF3NdrU|fc_049667505a9e91930169ff87dc06ec81a3bf1e1094c18b787a name=bash
  org/codehaus/plexus/velocity/DefaultVelocityComponent.class
  org/codehaus/plexus/velocity/VelocityComponent$1.class
  org/codehaus/plexus/velocity/VelocityComponent.class
  Compiled from "VelocityComponent.java"
  class org.codehaus.plexus.velocity.VelocityComponent$1 {
    static java.lang.Class class$org$codehaus$plexus$velocity$VelocityComponent;
  
    static java.lang.Class class$(java.lang.String);
      Code:
           0: aload_0
           1: invokestatic  #1                  // Method java/lang/Class.forName:(Ljava/lang/String;)Ljava/lang/Class;
           4: areturn
           5: astore_1
           6: new           #3                  // class java/lang/NoClassDefFoundError
           9: dup
          10: invokespecial #4                  // Method java/lang/NoClassDefFoundError."<init>":()V
          13: aload_1
[tool-exec] update id=call_W6MhiK7K23vVPw2t5gF3NdrU|fc_049667505a9e91930169ff87dc06ec81a3bf1e1094c18b787a name=bash
  org/codehaus/plexus/velocity/DefaultVelocityComponent.class
  org/codehaus/plexus/velocity/VelocityComponent$1.class
  org/codehaus/plexus/velocity/VelocityComponent.class
  Compiled from "VelocityComponent.java"
  class org.codehaus.plexus.velocity.VelocityComponent$1 {
    static java.lang.Class class$org$codehaus$plexus$velocity$VelocityComponent;
  
    static java.lang.Class class$(java.lang.String);
      Code:
           0: aload_0
           1: invokestatic  #1                  // Method java/lang/Class.forName:(Ljava/lang/String;)Ljava/lang/Class;
           4: areturn
           5: astore_1
           6: new           #3                  // class java/lang/NoClassDefFoundError
           9: dup
          10: invokespecial #4                  // Method java/lang/NoClassDefFoundError."<init>":()V
          13: aload_1
          14: invokevirtual #5                  // Method java/lang/NoClassDefFoundError.initCause:(Ljava/lang/Throwable;)Ljava/lang/Throwable;
          17: athrow
        Exception table:
           from    to  target type
               0     4     5   Class java/lang/ClassNotFoundException
  }
[tool-exec] update id=call_W6MhiK7K23vVPw2t5gF3NdrU|fc_049667505a9e91930169ff87dc06ec81a3bf1e1094c18b787a name=bash
  org/codehaus/plexus/velocity/DefaultVelocityComponent.class
  org/codehaus/plexus/velocity/VelocityComponent$1.class
  org/codehaus/plexus/velocity/VelocityComponent.class
  Compiled from "VelocityComponent.java"
  class org.codehaus.plexus.velocity.VelocityComponent$1 {
    static java.lang.Class class$org$codehaus$plexus$velocity$VelocityComponent;
  
    static java.lang.Class class$(java.lang.String);
      Code:
           0: aload_0
           1: invokestatic  #1                  // Method java/lang/Class.forName:(Ljava/lang/String;)Ljava/lang/Class;
           4: areturn
           5: astore_1
           6: new           #3                  // class java/lang/NoClassDefFoundError
           9: dup
          10: invokespecial #4                  // Method java/lang/NoClassDefFoundError."<init>":()V
          13: aload_1
          14: invokevirtual #5                  // Method java/lang/NoClassDefFoundError.initCause:(Ljava/lang/Throwable;)Ljava/lang/Throwable;
          17: athrow
        Exception table:
           from    to  target type
               0     4     5   Class java/lang/ClassNotFoundException
  }
  Compiled from "VelocityComponent.java"
[tool-exec] update id=call_W6MhiK7K23vVPw2t5gF3NdrU|fc_049667505a9e91930169ff87dc06ec81a3bf1e1094c18b787a name=bash
  org/codehaus/plexus/velocity/DefaultVelocityComponent.class
  org/codehaus/plexus/velocity/VelocityComponent$1.class
  org/codehaus/plexus/velocity/VelocityComponent.class
  Compiled from "VelocityComponent.java"
  class org.codehaus.plexus.velocity.VelocityComponent$1 {
    static java.lang.Class class$org$codehaus$plexus$velocity$VelocityComponent;
  
    static java.lang.Class class$(java.lang.String);
      Code:
           0: aload_0
           1: invokestatic  #1                  // Method java/lang/Class.forName:(Ljava/lang/String;)Ljava/lang/Class;
           4: areturn
           5: astore_1
           6: new           #3                  // class java/lang/NoClassDefFoundError
           9: dup
          10: invokespecial #4                  // Method java/lang/NoClassDefFoundError."<init>":()V
          13: aload_1
          14: invokevirtual #5                  // Method java/lang/NoClassDefFoundError.initCause:(Ljava/lang/Throwable;)Ljava/lang/Throwable;
          17: athrow
        Exception table:
           from    to  target type
               0     4     5   Class java/lang/ClassNotFoundException
  }
  Compiled from "VelocityComponent.java"
  public interface org.codehaus.plexus.velocity.VelocityComponent {
    public static final java.lang.String ROLE;
  
[tool-exec] update id=call_W6MhiK7K23vVPw2t5gF3NdrU|fc_049667505a9e91930169ff87dc06ec81a3bf1e1094c18b787a name=bash
  org/codehaus/plexus/velocity/DefaultVelocityComponent.class
  org/codehaus/plexus/velocity/VelocityComponent$1.class
  org/codehaus/plexus/velocity/VelocityComponent.class
  Compiled from "VelocityComponent.java"
  class org.codehaus.plexus.velocity.VelocityComponent$1 {
    static java.lang.Class class$org$codehaus$plexus$velocity$VelocityComponent;
  
    static java.lang.Class class$(java.lang.String);
      Code:
           0: aload_0
           1: invokestatic  #1                  // Method java/lang/Class.forName:(Ljava/lang/String;)Ljava/lang/Class;
           4: areturn
           5: astore_1
           6: new           #3                  // class java/lang/NoClassDefFoundError
           9: dup
          10: invokespecial #4                  // Method java/lang/NoClassDefFoundError."<init>":()V
          13: aload_1
          14: invokevirtual #5                  // Method java/lang/NoClassDefFoundError.initCause:(Ljava/lang/Throwable;)Ljava/lang/Throwable;
          17: athrow
        Exception table:
           from    to  target type
               0     4     5   Class java/lang/ClassNotFoundException
  }
  Compiled from "VelocityComponent.java"
  public interface org.codehaus.plexus.velocity.VelocityComponent {
    public static final java.lang.String ROLE;
  
    public abstract org.apache.velocity.app.VelocityEngine getEngine();
[tool-exec] update id=call_W6MhiK7K23vVPw2t5gF3NdrU|fc_049667505a9e91930169ff87dc06ec81a3bf1e1094c18b787a name=bash
  org/codehaus/plexus/velocity/DefaultVelocityComponent.class
  org/codehaus/plexus/velocity/VelocityComponent$1.class
  org/codehaus/plexus/velocity/VelocityComponent.class
  Compiled from "VelocityComponent.java"
  class org.codehaus.plexus.velocity.VelocityComponent$1 {
    static java.lang.Class class$org$codehaus$plexus$velocity$VelocityComponent;
  
    static java.lang.Class class$(java.lang.String);
      Code:
           0: aload_0
           1: invokestatic  #1                  // Method java/lang/Class.forName:(Ljava/lang/String;)Ljava/lang/Class;
           4: areturn
           5: astore_1
           6: new           #3                  // class java/lang/NoClassDefFoundError
           9: dup
          10: invokespecial #4                  // Method java/lang/NoClassDefFoundError."<init>":()V
          13: aload_1
          14: invokevirtual #5                  // Method java/lang/NoClassDefFoundError.initCause:(Ljava/lang/Throwable;)Ljava/lang/Throwable;
          17: athrow
        Exception table:
           from    to  target type
               0     4     5   Class java/lang/ClassNotFoundException
  }
  Compiled from "VelocityComponent.java"
  public interface org.codehaus.plexus.velocity.VelocityComponent {
    public static final java.lang.String ROLE;
  
    public abstract org.apache.velocity.app.VelocityEngine getEngine();
  
[tool-exec] update id=call_W6MhiK7K23vVPw2t5gF3NdrU|fc_049667505a9e91930169ff87dc06ec81a3bf1e1094c18b787a name=bash
  org/codehaus/plexus/velocity/DefaultVelocityComponent.class
  org/codehaus/plexus/velocity/VelocityComponent$1.class
  org/codehaus/plexus/velocity/VelocityComponent.class
  Compiled from "VelocityComponent.java"
  class org.codehaus.plexus.velocity.VelocityComponent$1 {
    static java.lang.Class class$org$codehaus$plexus$velocity$VelocityComponent;
  
    static java.lang.Class class$(java.lang.String);
      Code:
           0: aload_0
           1: invokestatic  #1                  // Method java/lang/Class.forName:(Ljava/lang/String;)Ljava/lang/Class;
           4: areturn
           5: astore_1
           6: new           #3                  // class java/lang/NoClassDefFoundError
           9: dup
          10: invokespecial #4                  // Method java/lang/NoClassDefFoundError."<init>":()V
          13: aload_1
          14: invokevirtual #5                  // Method java/lang/NoClassDefFoundError.initCause:(Ljava/lang/Throwable;)Ljava/lang/Throwable;
          17: athrow
        Exception table:
           from    to  target type
               0     4     5   Class java/lang/ClassNotFoundException
  }
  Compiled from "VelocityComponent.java"
  public interface org.codehaus.plexus.velocity.VelocityComponent {
    public static final java.lang.String ROLE;
  
    public abstract org.apache.velocity.app.VelocityEngine getEngine();
  
    static {};
      Code:
[tool-exec] update id=call_W6MhiK7K23vVPw2t5gF3NdrU|fc_049667505a9e91930169ff87dc06ec81a3bf1e1094c18b787a name=bash
  org/codehaus/plexus/velocity/DefaultVelocityComponent.class
  org/codehaus/plexus/velocity/VelocityComponent$1.class
  org/codehaus/plexus/velocity/VelocityComponent.class
  Compiled from "VelocityComponent.java"
  class org.codehaus.plexus.velocity.VelocityComponent$1 {
    static java.lang.Class class$org$codehaus$plexus$velocity$VelocityComponent;
  
    static java.lang.Class class$(java.lang.String);
      Code:
           0: aload_0
           1: invokestatic  #1                  // Method java/lang/Class.forName:(Ljava/lang/String;)Ljava/lang/Class;
           4: areturn
           5: astore_1
           6: new           #3                  // class java/lang/NoClassDefFoundError
           9: dup
          10: invokespecial #4                  // Method java/lang/NoClassDefFoundError."<init>":()V
          13: aload_1
          14: invokevirtual #5                  // Method java/lang/NoClassDefFoundError.initCause:(Ljava/lang/Throwable;)Ljava/lang/Throwable;
          17: athrow
        Exception table:
           from    to  target type
               0     4     5   Class java/lang/ClassNotFoundException
  }
  Compiled from "VelocityComponent.java"
  public interface org.codehaus.plexus.velocity.VelocityComponent {
    public static final java.lang.String ROLE;
  
    public abstract org.apache.velocity.app.VelocityEngine getEngine();
  
    static {};
      Code:
           0: getstatic     #1                  // Field org/codehaus/plexus/velocity/VelocityComponent$1.class$org$codehaus$plexus$velocity$VelocityComponent:Ljava/lang/Class;
           3: ifnonnull     18
[tool-exec] update id=call_W6MhiK7K23vVPw2t5gF3NdrU|fc_049667505a9e91930169ff87dc06ec81a3bf1e1094c18b787a name=bash
  org/codehaus/plexus/velocity/DefaultVelocityComponent.class
  org/codehaus/plexus/velocity/VelocityComponent$1.class
  org/codehaus/plexus/velocity/VelocityComponent.class
  Compiled from "VelocityComponent.java"
  class org.codehaus.plexus.velocity.VelocityComponent$1 {
    static java.lang.Class class$org$codehaus$plexus$velocity$VelocityComponent;
  
    static java.lang.Class class$(java.lang.String);
      Code:
           0: aload_0
           1: invokestatic  #1                  // Method java/lang/Class.forName:(Ljava/lang/String;)Ljava/lang/Class;
           4: areturn
           5: astore_1
           6: new           #3                  // class java/lang/NoClassDefFoundError
           9: dup
          10: invokespecial #4                  // Method java/lang/NoClassDefFoundError."<init>":()V
          13: aload_1
          14: invokevirtual #5                  // Method java/lang/NoClassDefFoundError.initCause:(Ljava/lang/Throwable;)Ljava/lang/Throwable;
          17: athrow
        Exception table:
           from    to  target type
               0     4     5   Class java/lang/ClassNotFoundException
  }
  Compiled from "VelocityComponent.java"
  public interface org.codehaus.plexus.velocity.VelocityComponent {
    public static final java.lang.String ROLE;
  
    public abstract org.apache.velocity.app.VelocityEngine getEngine();
  
    static {};
      Code:
           0: getstatic     #1                  // Field org/codehaus/plexus/velocity/VelocityComponent$1.class$org$codehaus$plexus$velocity$VelocityComponent:Ljava/lang/Class;
           3: ifnonnull     18
           6: ldc           #2                  // String org.codehaus.plexus.velocity.VelocityComponent
[tool-exec] update id=call_W6MhiK7K23vVPw2t5gF3NdrU|fc_049667505a9e91930169ff87dc06ec81a3bf1e1094c18b787a name=bash
  org/codehaus/plexus/velocity/DefaultVelocityComponent.class
  org/codehaus/plexus/velocity/VelocityComponent$1.class
  org/codehaus/plexus/velocity/VelocityComponent.class
  Compiled from "VelocityComponent.java"
  class org.codehaus.plexus.velocity.VelocityComponent$1 {
    static java.lang.Class class$org$codehaus$plexus$velocity$VelocityComponent;
  
    static java.lang.Class class$(java.lang.String);
      Code:
           0: aload_0
           1: invokestatic  #1                  // Method java/lang/Class.forName:(Ljava/lang/String;)Ljava/lang/Class;
           4: areturn
           5: astore_1
           6: new           #3                  // class java/lang/NoClassDefFoundError
           9: dup
          10: invokespecial #4                  // Method java/lang/NoClassDefFoundError."<init>":()V
          13: aload_1
          14: invokevirtual #5                  // Method java/lang/NoClassDefFoundError.initCause:(Ljava/lang/Throwable;)Ljava/lang/Throwable;
          17: athrow
        Exception table:
           from    to  target type
               0     4     5   Class java/lang/ClassNotFoundException
  }
  Compiled from "VelocityComponent.java"
  public interface org.codehaus.plexus.velocity.VelocityComponent {
    public static final java.lang.String ROLE;
  
    public abstract org.apache.velocity.app.VelocityEngine getEngine();
  
    static {};
      Code:
           0: getstatic     #1                  // Field org/codehaus/plexus/velocity/VelocityComponent$1.class$org$codehaus$plexus$velocity$VelocityComponent:Ljava/lang/Class;
           3: ifnonnull     18
           6: ldc           #2                  // String org.codehaus.plexus.velocity.VelocityComponent
           8: invokestatic  #3                  // Method org/codehaus/plexus/velocity/VelocityComponent$1.class$:(Ljava/lang/String;)Ljava/lang/Class;
[tool-exec] update id=call_W6MhiK7K23vVPw2t5gF3NdrU|fc_049667505a9e91930169ff87dc06ec81a3bf1e1094c18b787a name=bash
  org/codehaus/plexus/velocity/DefaultVelocityComponent.class
  org/codehaus/plexus/velocity/VelocityComponent$1.class
  org/codehaus/plexus/velocity/VelocityComponent.class
  Compiled from "VelocityComponent.java"
  class org.codehaus.plexus.velocity.VelocityComponent$1 {
    static java.lang.Class class$org$codehaus$plexus$velocity$VelocityComponent;
  
    static java.lang.Class class$(java.lang.String);
      Code:
           0: aload_0
           1: invokestatic  #1                  // Method java/lang/Class.forName:(Ljava/lang/String;)Ljava/lang/Class;
           4: areturn
           5: astore_1
           6: new           #3                  // class java/lang/NoClassDefFoundError
           9: dup
          10: invokespecial #4                  // Method java/lang/NoClassDefFoundError."<init>":()V
          13: aload_1
          14: invokevirtual #5                  // Method java/lang/NoClassDefFoundError.initCause:(Ljava/lang/Throwable;)Ljava/lang/Throwable;
          17: athrow
        Exception table:
           from    to  target type
               0     4     5   Class java/lang/ClassNotFoundException
  }
  Compiled from "VelocityComponent.java"
  public interface org.codehaus.plexus.velocity.VelocityComponent {
    public static final java.lang.String ROLE;
  
    public abstract org.apache.velocity.app.VelocityEngine getEngine();
  
    static {};
      Code:
           0: getstatic     #1                  // Field org/codehaus/plexus/velocity/VelocityComponent$1.class$org$codehaus$plexus$velocity$VelocityComponent:Ljava/lang/Class;
           3: ifnonnull     18
           6: ldc           #2                  // String org.codehaus.plexus.velocity.VelocityComponent
           8: invokestatic  #3                  // Method org/codehaus/plexus/velocity/VelocityComponent$1.class$:(Ljava/lang/String;)Ljava/lang/Class;
          11: dup
[tool-exec] update id=call_W6MhiK7K23vVPw2t5gF3NdrU|fc_049667505a9e91930169ff87dc06ec81a3bf1e1094c18b787a name=bash
  org/codehaus/plexus/velocity/DefaultVelocityComponent.class
  org/codehaus/plexus/velocity/VelocityComponent$1.class
  org/codehaus/plexus/velocity/VelocityComponent.class
  Compiled from "VelocityComponent.java"
  class org.codehaus.plexus.velocity.VelocityComponent$1 {
    static java.lang.Class class$org$codehaus$plexus$velocity$VelocityComponent;
  
    static java.lang.Class class$(java.lang.String);
      Code:
           0: aload_0
           1: invokestatic  #1                  // Method java/lang/Class.forName:(Ljava/lang/String;)Ljava/lang/Class;
           4: areturn
           5: astore_1
           6: new           #3                  // class java/lang/NoClassDefFoundError
           9: dup
          10: invokespecial #4                  // Method java/lang/NoClassDefFoundError."<init>":()V
          13: aload_1
          14: invokevirtual #5                  // Method java/lang/NoClassDefFoundError.initCause:(Ljava/lang/Throwable;)Ljava/lang/Throwable;
          17: athrow
        Exception table:
           from    to  target type
               0     4     5   Class java/lang/ClassNotFoundException
  }
  Compiled from "VelocityComponent.java"
  public interface org.codehaus.plexus.velocity.VelocityComponent {
    public static final java.lang.String ROLE;
  
    public abstract org.apache.velocity.app.VelocityEngine getEngine();
  
    static {};
      Code:
           0: getstatic     #1                  // Field org/codehaus/plexus/velocity/VelocityComponent$1.class$org$codehaus$plexus$velocity$VelocityComponent:Ljava/lang/Class;
           3: ifnonnull     18
           6: ldc           #2                  // String org.codehaus.plexus.velocity.VelocityComponent
           8: invokestatic  #3                  // Method org/codehaus/plexus/velocity/VelocityComponent$1.class$:(Ljava/lang/String;)Ljava/lang/Class;
          11: dup
          12: putstatic     #1                  // Field org/codehaus/plexus/velocity/VelocityComponent$1.class$org$codehaus$plexus$velocity$VelocityComponent:Ljava/lang/Class;
[tool-exec] update id=call_W6MhiK7K23vVPw2t5gF3NdrU|fc_049667505a9e91930169ff87dc06ec81a3bf1e1094c18b787a name=bash
  org/codehaus/plexus/velocity/DefaultVelocityComponent.class
  org/codehaus/plexus/velocity/VelocityComponent$1.class
  org/codehaus/plexus/velocity/VelocityComponent.class
  Compiled from "VelocityComponent.java"
  class org.codehaus.plexus.velocity.VelocityComponent$1 {
    static java.lang.Class class$org$codehaus$plexus$velocity$VelocityComponent;
  
    static java.lang.Class class$(java.lang.String);
      Code:
           0: aload_0
           1: invokestatic  #1                  // Method java/lang/Class.forName:(Ljava/lang/String;)Ljava/lang/Class;
           4: areturn
           5: astore_1
           6: new           #3                  // class java/lang/NoClassDefFoundError
           9: dup
          10: invokespecial #4                  // Method java/lang/NoClassDefFoundError."<init>":()V
          13: aload_1
          14: invokevirtual #5                  // Method java/lang/NoClassDefFoundError.initCause:(Ljava/lang/Throwable;)Ljava/lang/Throwable;
          17: athrow
        Exception table:
           from    to  target type
               0     4     5   Class java/lang/ClassNotFoundException
  }
  Compiled from "VelocityComponent.java"
  public interface org.codehaus.plexus.velocity.VelocityComponent {
    public static final java.lang.String ROLE;
  
    public abstract org.apache.velocity.app.VelocityEngine getEngine();
  
    static {};
      Code:
           0: getstatic     #1                  // Field org/codehaus/plexus/velocity/VelocityComponent$1.class$org$codehaus$plexus$velocity$VelocityComponent:Ljava/lang/Class;
           3: ifnonnull     18
           6: ldc           #2                  // String org.codehaus.plexus.velocity.VelocityComponent
           8: invokestatic  #3                  // Method org/codehaus/plexus/velocity/VelocityComponent$1.class$:(Ljava/lang/String;)Ljava/lang/Class;
          11: dup
          12: putstatic     #1                  // Field org/codehaus/plexus/velocity/VelocityComponent$1.class$org$codehaus$plexus$velocity$VelocityComponent:Ljava/lang/Class;
          15: goto          21
[tool-exec] update id=call_W6MhiK7K23vVPw2t5gF3NdrU|fc_049667505a9e91930169ff87dc06ec81a3bf1e1094c18b787a name=bash
  org/codehaus/plexus/velocity/DefaultVelocityComponent.class
  org/codehaus/plexus/velocity/VelocityComponent$1.class
  org/codehaus/plexus/velocity/VelocityComponent.class
  Compiled from "VelocityComponent.java"
  class org.codehaus.plexus.velocity.VelocityComponent$1 {
    static java.lang.Class class$org$codehaus$plexus$velocity$VelocityComponent;
  
    static java.lang.Class class$(java.lang.String);
      Code:
           0: aload_0
           1: invokestatic  #1                  // Method java/lang/Class.forName:(Ljava/lang/String;)Ljava/lang/Class;
           4: areturn
           5: astore_1
           6: new           #3                  // class java/lang/NoClassDefFoundError
           9: dup
          10: invokespecial #4                  // Method java/lang/NoClassDefFoundError."<init>":()V
          13: aload_1
          14: invokevirtual #5                  // Method java/lang/NoClassDefFoundError.initCause:(Ljava/lang/Throwable;)Ljava/lang/Throwable;
          17: athrow
        Exception table:
           from    to  target type
               0     4     5   Class java/lang/ClassNotFoundException
  }
  Compiled from "VelocityComponent.java"
  public interface org.codehaus.plexus.velocity.VelocityComponent {
    public static final java.lang.String ROLE;
  
    public abstract org.apache.velocity.app.VelocityEngine getEngine();
  
    static {};
      Code:
           0: getstatic     #1                  // Field org/codehaus/plexus/velocity/VelocityComponent$1.class$org$codehaus$plexus$velocity$VelocityComponent:Ljava/lang/Class;
           3: ifnonnull     18
           6: ldc           #2                  // String org.codehaus.plexus.velocity.VelocityComponent
           8: invokestatic  #3                  // Method org/codehaus/plexus/velocity/VelocityComponent$1.class$:(Ljava/lang/String;)Ljava/lang/Class;
          11: dup
          12: putstatic     #1                  // Field org/codehaus/plexus/velocity/VelocityComponent$1.class$org$codehaus$plexus$velocity$VelocityComponent:Ljava/lang/Class;
          15: goto          21
          18: getstatic     #1                  // Field org/codehaus/plexus/velocity/VelocityComponent$1.class$org$codehaus$plexus$velocity$VelocityComponent:Ljava/lang/Class;
          21: invokevirtual #4                  // Method java/lang/Class.getName:()Ljava/lang/String;
          24: putstatic     #5                  // Field ROLE:Ljava/lang/String;
          27: return
  }
[tool-exec] end id=call_W6MhiK7K23vVPw2t5gF3NdrU|fc_049667505a9e91930169ff87dc06ec81a3bf1e1094c18b787a name=bash status=success
  org/codehaus/plexus/velocity/DefaultVelocityComponent.class
  org/codehaus/plexus/velocity/VelocityComponent$1.class
  org/codehaus/plexus/velocity/VelocityComponent.class
  Compiled from "VelocityComponent.java"
  class org.codehaus.plexus.velocity.VelocityComponent$1 {
    static java.lang.Class class$org$codehaus$plexus$velocity$VelocityComponent;
  
    static java.lang.Class class$(java.lang.String);
      Code:
           0: aload_0
           1: invokestatic  #1                  // Method java/lang/Class.forName:(Ljava/lang/String;)Ljava/lang/Class;
           4: areturn
           5: astore_1
           6: new           #3                  // class java/lang/NoClassDefFoundError
           9: dup
          10: invokespecial #4                  // Method java/lang/NoClassDefFoundError."<init>":()V
          13: aload_1
          14: invokevirtual #5                  // Method java/lang/NoClassDefFoundError.initCause:(Ljava/lang/Throwable;)Ljava/lang/Throwable;
          17: athrow
        Exception table:
           from    to  target type
               0     4     5   Class java/lang/ClassNotFoundException
  }
  Compiled from "VelocityComponent.java"
  public interface org.codehaus.plexus.velocity.VelocityComponent {
    public static final java.lang.String ROLE;
  
    public abstract org.apache.velocity.app.VelocityEngine getEngine();
  
    static {};
      Code:
           0: getstatic     #1                  // Field org/codehaus/plexus/velocity/VelocityComponent$1.class$org$codehaus$plexus$velocity$VelocityComponent:Ljava/lang/Class;
           3: ifnonnull     18
           6: ldc           #2                  // String org.codehaus.plexus.velocity.VelocityComponent
           8: invokestatic  #3                  // Method org/codehaus/plexus/velocity/VelocityComponent$1.class$:(Ljava/lang/String;)Ljava/lang/Class;
          11: dup
          12: putstatic     #1                  // Field org/codehaus/plexus/velocity/VelocityComponent$1.class$org$codehaus$plexus$velocity$VelocityComponent:Ljava/lang/Class;
          15: goto          21
          18: getstatic     #1                  // Field org/codehaus/plexus/velocity/VelocityComponent$1.class$org$codehaus$plexus$velocity$VelocityComponent:Ljava/lang/Class;
          21: invokevirtual #4                  // Method java/lang/Class.getName:()Ljava/lang/String;
          24: putstatic     #5                  // Field ROLE:Ljava/lang/String;
          27: return
  }
[recv] {"type": "message_start", "message": {"role": "toolResult", "toolCallId": "call_W6MhiK7K23vVPw2t5gF3NdrU|fc_049667505a9e91930169ff87dc06ec81a3bf1e1094c18b787a", "toolName": "bash", "content": [{"type": "text", "text": "org/codehaus/plexus/velocity/DefaultVelocityComponent.class\norg/codehaus/plexus/velocity/VelocityComponent$1.class\norg/codehaus/plexus/velocity/VelocityComponent.class\nCompiled from \"VelocityComponent.java\"\nclass org.codehaus.plexus.velocity.VelocityComponent$1 {\n  static java.lang.Class class$org$codehaus$plexus$velocity$VelocityComponent;\n\n  static java.lang.Class class$(java.lang.String);\n    Code:\n         0: aload_0\n         1: invokestatic  #1                  // Method java/lang/Class.forName:(Ljava/lang/String;)Ljava/lang/Class;\n         4: areturn\n         5: astore_1\n         6: new           #3                  // class java/lang/NoClassDefFoundError\n         9: dup\n        10: invokespecial #4                  // Method java/lang/NoClassDefFoundError.\"<init>\":()V\n        13: aload_1\n        14: invokevirtual #5                  // Method java/lang/NoClassDefFoundError.initCause:(Ljava/lang/Throwable;)Ljava/lang/Throwable;\n        17: athrow\n      Exception table:\n         from    to  target type\n             0     4     5   Class java/lang/ClassNotFoundException\n}\nCompiled from \"VelocityComponent.java\"\npublic interface org.codehaus.plexus.velocity.VelocityComponent {\n  public static final java.lang.String ROLE;\n\n  public abstract org.apache.velocity.app.VelocityEngine getEngine();\n\n  static {};\n    Code:\n         0: getstatic     #1                  // Field org/codehaus/plexus/velocity/VelocityComponent$1.class$org$codehaus$plexus$velocity$VelocityComponent:Ljava/lang/Class;\n         3: ifnonnull     18\n         6: ldc           #2                  // String org.codehaus.plexus.velocity.VelocityComponent\n         8: invokestatic  #3                  // Method org/codehaus/plexus/velocity/VelocityComponent$1.class$:(Ljava/lang/String;)Ljava/lang/Class;\n        11: dup\n        12: putstatic     #1                  // Field org/codehaus/plexus/velocity/VelocityComponent$1.class$org$codehaus$plexus$velocity$VelocityComponent:Ljava/lang/Class;\n        15: goto          21\n        18: getstatic     #1                  // Field org/codehaus/plexus/velocity/VelocityComponent$1.class$org$codehaus$plexus$velocity$VelocityComponent:Ljava/lang/Class;\n        21: invokevirtual #4                  // Method java/lang/Class.getName:()Ljava/lang/String;\n        24: putstatic     #5                  // Field ROLE:Ljava/lang/String;\n        27: return\n}\n"}], "isError": false, "timestamp": 1778354141029}}
[recv] {"type": "message_end", "message": {"role": "toolResult", "toolCallId": "call_W6MhiK7K23vVPw2t5gF3NdrU|fc_049667505a9e91930169ff87dc06ec81a3bf1e1094c18b787a", "toolName": "bash", "content": [{"type": "text", "text": "org/codehaus/plexus/velocity/DefaultVelocityComponent.class\norg/codehaus/plexus/velocity/VelocityComponent$1.class\norg/codehaus/plexus/velocity/VelocityComponent.class\nCompiled from \"VelocityComponent.java\"\nclass org.codehaus.plexus.velocity.VelocityComponent$1 {\n  static java.lang.Class class$org$codehaus$plexus$velocity$VelocityComponent;\n\n  static java.lang.Class class$(java.lang.String);\n    Code:\n         0: aload_0\n         1: invokestatic  #1                  // Method java/lang/Class.forName:(Ljava/lang/String;)Ljava/lang/Class;\n         4: areturn\n         5: astore_1\n         6: new           #3                  // class java/lang/NoClassDefFoundError\n         9: dup\n        10: invokespecial #4                  // Method java/lang/NoClassDefFoundError.\"<init>\":()V\n        13: aload_1\n        14: invokevirtual #5                  // Method java/lang/NoClassDefFoundError.initCause:(Ljava/lang/Throwable;)Ljava/lang/Throwable;\n        17: athrow\n      Exception table:\n         from    to  target type\n             0     4     5   Class java/lang/ClassNotFoundException\n}\nCompiled from \"VelocityComponent.java\"\npublic interface org.codehaus.plexus.velocity.VelocityComponent {\n  public static final java.lang.String ROLE;\n\n  public abstract org.apache.velocity.app.VelocityEngine getEngine();\n\n  static {};\n    Code:\n         0: getstatic     #1                  // Field org/codehaus/plexus/velocity/VelocityComponent$1.class$org$codehaus$plexus$velocity$VelocityComponent:Ljava/lang/Class;\n         3: ifnonnull     18\n         6: ldc           #2                  // String org.codehaus.plexus.velocity.VelocityComponent\n         8: invokestatic  #3                  // Method org/codehaus/plexus/velocity/VelocityComponent$1.class$:(Ljava/lang/String;)Ljava/lang/Class;\n        11: dup\n        12: putstatic     #1                  // Field org/codehaus/plexus/velocity/VelocityComponent$1.class$org$codehaus$plexus$velocity$VelocityComponent:Ljava/lang/Class;\n        15: goto          21\n        18: getstatic     #1                  // Field org/codehaus/plexus/velocity/VelocityComponent$1.class$org$codehaus$plexus$velocity$VelocityComponent:Ljava/lang/Class;\n        21: invokevirtual #4                  // Method java/lang/Class.getName:()Ljava/lang/String;\n        24: putstatic     #5                  // Field ROLE:Ljava/lang/String;\n        27: return\n}\n"}], "isError": false, "timestamp": 1778354141029}}
[recv] {"type": "turn_end", "message": {"role": "assistant", "content": [{"type": "toolCall", "id": "call_W6MhiK7K23vVPw2t5gF3NdrU|fc_049667505a9e91930169ff87dc06ec81a3bf1e1094c18b787a", "name": "bash", "arguments": {"command": "jar tf ~/.m2/repository/org/codehaus/plexus/plexus-velocity/1.1.7/plexus-velocity-1.1.7.jar | grep VelocityComponent && javap -classpath ~/.m2/repository/org/codehaus/plexus/plexus-velocity/1.1.7/plexus-velocity-1.1.7.jar -c -p 'org.codehaus.plexus.velocity.VelocityComponent$1' 'org.codehaus.plexus.velocity.VelocityComponent'", "timeout": 30}}], "api": "openai-responses", "provider": "OCA", "model": "gpt-5.5", "usage": {"input": 610, "output": 130, "cacheRead": 10752, "cacheWrite": 0, "totalTokens": 11492, "cost": {"input": 0, "output": 0, "cacheRead": 0, "cacheWrite": 0, "total": 0}}, "stopReason": "toolUse", "timestamp": 1778354138069, "responseId": "resp_049667505a9e91930169ff87da6aec81a3a786396148870998"}, "toolResults": [{"role": "toolResult", "toolCallId": "call_W6MhiK7K23vVPw2t5gF3NdrU|fc_049667505a9e91930169ff87dc06ec81a3bf1e1094c18b787a", "toolName": "bash", "content": [{"type": "text", "text": "org/codehaus/plexus/velocity/DefaultVelocityComponent.class\norg/codehaus/plexus/velocity/VelocityComponent$1.class\norg/codehaus/plexus/velocity/VelocityComponent.class\nCompiled from \"VelocityComponent.java\"\nclass org.codehaus.plexus.velocity.VelocityComponent$1 {\n  static java.lang.Class class$org$codehaus$plexus$velocity$VelocityComponent;\n\n  static java.lang.Class class$(java.lang.String);\n    Code:\n         0: aload_0\n         1: invokestatic  #1                  // Method java/lang/Class.forName:(Ljava/lang/String;)Ljava/lang/Class;\n         4: areturn\n         5: astore_1\n         6: new           #3                  // class java/lang/NoClassDefFoundError\n         9: dup\n        10: invokespecial #4                  // Method java/lang/NoClassDefFoundError.\"<init>\":()V\n        13: aload_1\n        14: invokevirtual #5                  // Method java/lang/NoClassDefFoundError.initCause:(Ljava/lang/Throwable;)Ljava/lang/Throwable;\n        17: athrow\n      Exception table:\n         from    to  target type\n             0     4     5   Class java/lang/ClassNotFoundException\n}\nCompiled from \"VelocityComponent.java\"\npublic interface org.codehaus.plexus.velocity.VelocityComponent {\n  public static final java.lang.String ROLE;\n\n  public abstract org.apache.velocity.app.VelocityEngine getEngine();\n\n  static {};\n    Code:\n         0: getstatic     #1                  // Field org/codehaus/plexus/velocity/VelocityComponent$1.class$org$codehaus$plexus$velocity$VelocityComponent:Ljava/lang/Class;\n         3: ifnonnull     18\n         6: ldc           #2                  // String org.codehaus.plexus.velocity.VelocityComponent\n         8: invokestatic  #3                  // Method org/codehaus/plexus/velocity/VelocityComponent$1.class$:(Ljava/lang/String;)Ljava/lang/Class;\n        11: dup\n        12: putstatic     #1                  // Field org/codehaus/plexus/velocity/VelocityComponent$1.class$org$codehaus$plexus$velocity$VelocityComponent:Ljava/lang/Class;\n        15: goto          21\n        18: getstatic     #1                  // Field org/codehaus/plexus/velocity/VelocityComponent$1.class$org$codehaus$plexus$velocity$VelocityComponent:Ljava/lang/Class;\n        21: invokevirtual #4                  // Method java/lang/Class.getName:()Ljava/lang/String;\n        24: putstatic     #5                  // Field ROLE:Ljava/lang/String;\n        27: return\n}\n"}], "isError": false, "timestamp": 1778354141029}]}
[recv] {"type": "turn_start"}
[recv] {"type": "message_start", "message": {"role": "assistant", "content": [], "api": "openai-responses", "provider": "OCA", "model": "gpt-5.5", "usage": {"input": 0, "output": 0, "cacheRead": 0, "cacheWrite": 0, "totalTokens": 0, "cost": {"input": 0, "output": 0, "cacheRead": 0, "cacheWrite": 0, "total": 0}}, "stopReason": "stop", "timestamp": 1778354141032}}
[assistant-event] thinking_start
[thinking] **Accessing file and tests**
[thinking] 
[thinking] I need to access the ROLE and add a file. It’s crucial to ensure tests are external to the lib packages, and the current package is org_codehaus_... I might be working with an existing build that utilizes JUnit Jupiter. I should make the test class public and name it VelocityComponentAnonymous1Test.java. I wonder if it maps the active class correctly? It probably shouldn’t be included in the package library, so I’ll write it accordingly.
[thinking] 
[assistant-event] thinking_end
[tool-call] start id=unknown
[tool-call] delta {"path":"tests/src/org.codehaus.plexus/plexus-velocity/1.1.7/src/test/java/org_codehaus_plexus/plexus_velocity/VelocityComponentAnonymous1Test.java","content":"/*\n * Copyright and related rights waived via CC0\n *\n * You should have received a copy of the CC0 legalcode along with this\n * work. If not, see <http://creativecommons.org/publicdomain/zero/1.0/>.\n */\npackage org_codehaus_plexus.plexus_velocity;\n\nimport static org.assertj.core.api.Assertions.assertThat;\n\nimport org.codehaus.plexus.velocity.VelocityComponent;\nimport org.junit.jupiter.api.Test;\n\npublic class VelocityComponentAnonymous1Test {\n    @Test\n    void roleInitializesVelocityComponentClassLiteral() {\n        assertThat(VelocityComponent.ROLE).isEqualTo(VelocityComponent.class.getName());\n    }\n}\n"}
[tool-call] end id=call_DupWrJQD62vZw2RdnTHt6fNX|fc_049667505a9e91930169ff87e08d9881a3b78b87822f2a4352 name=write args={"path": "tests/src/org.codehaus.plexus/plexus-velocity/1.1.7/src/test/java/org_codehaus_plexus/plexus_velocity/VelocityComponentAnonymous1Test.java", "content": "/*\n * Copyright and related rights waived via CC0\n *\n * You should have received a copy of the CC0 legalcode along with this\n * work. If not, see <http://creativecommons.org/publicdomain/zero/1.0/>.\n */\npackage org_codehaus_plexus.plexus_velocity;\n\nimport static org.assertj.core.api.Assertions.assertThat;\n\nimport org.codehaus.plexus.velocity.VelocityComponent;\nimport org.junit.jupiter.api.Test;\n\npublic class VelocityComponentAnonymous1Test {\n    @Test\n    void roleInitializesVelocityComponentClassLiteral() {\n        assertThat(VelocityComponent.ROLE).isEqualTo(VelocityComponent.class.getName());\n    }\n}\n"}
[recv] {"type": "message_end", "message": {"role": "assistant", "content": [{"type": "thinking", "thinking": "**Accessing file and tests**\n\nI need to access the ROLE and add a file. It’s crucial to ensure tests are external to the lib packages, and the current package is org_codehaus_... I might be working with an existing build that utilizes JUnit Jupiter. I should make the test class public and name it VelocityComponentAnonymous1Test.java. I wonder if it maps the active class correctly? It probably shouldn’t be included in the package library, so I’ll write it accordingly.", "thinkingSignature": "{\"id\":\"rs_049667505a9e91930169ff87de01fc81a3b5853b19736260f8\",\"type\":\"reasoning\",\"encrypted_content\":\"gAAAAABp_4fgMG3sLlidFw_rdEqCXM_KThHuc-_Hp4bTvcckCN5Y0TTKtFaLk0U8GPY1C52r7EIPZ2xpWrgEd-1xa_85j6kQFMdCbyXdCHFEksWSXIkJwFw1T0dnwZXuFvXGQoA0F8gnZlOG1lctHO7SYNCSTzxB3jaXPvZ19lfT0Z8niUmiIRgE05XJ5korC1G5l43e8HF-M3yHBNlGwDVl10QYoLMGaQ2dWB9vfm0cJ0Tod97usZlZJziRrVIb4_4XVOYZD4BgPjHWgDHowBCXOW7k17XH8mRdbmUFrgyiRJwgLhrcxYddGhw5DIPpCed8K-KaPsEWv7LZ6m8O_wk99ST0afWtkwKg-gkIkFFvMVjwVuOOjmRyByJWgs3O-QRxqkt1B1Zj9iJ1S7EZ081XT_RfkfzlHuwOLcfB7QSm-jt1XHIsyNmZhZOLOz9FbiC1IY7ozcX2xPQ3F8tDBoGiFuDOaVp4VurUWPqD0faANzfnjkeI5OryeIMMnJIs6tlyWvdB_tdCMFL0somevri9noaHFYLFpblXeEC3-eycZlDL9o0z1O6mk79uponZeHcg1O3Q2iToEnk4kKPwvs_3MBXLbx54ihrDQUdX15kSVRqsI69GyALLMbPTS9Rog-RiQrbJb7Ezv5V7wefJegdw0dzt4uc2Pd35tvdtpc8lhY9Hr_0KLOglI4pRzKvp0hBCyWJmgU5l8grGq9DTxLywC-SjVS1FPwqrFQyq-cZ9uLkIUqe9wULxEQPscqy_1kAkQ2oyTbhy7g7qYclrP7HQmBavtqzPJhYy4z3QxI_wTsAp_QruxUX87wnKhKjG4fYKnhROe7z4mlMhOKNRwhAtfODmcE9Qaz05zWAyKV4Ubayr0CH-R-tflxPATwWrARWoM1ETlcVMnbrKSd5VmpxxxV1iYSl8OL3O3BbfUoGTjNEB1BrbaJAacAxr3sB5LoxzCbMO_mFu55HlQ9WvKfgqfFAUD3jxjRnGYFHUkXf7oHqp5jOpQyXg_FvSGthzqokJfInfJ0Fw1B-G6GinAUGww3ibCFvhI3xIMuh525vUeJ7ZIAeBsKul4bro8ON5ikppTvbYFS-wYJmxFRq6eTFlfWyJg_GaAMeZtZ3CSxaFHS4kU_JonFlA9iiMXBjGnk3XcsjTFrArHe-3TppluqILzXnhaF1B67mr0bV-rFpKTBXlcKHpZKaDs9XqTldUz0n3peqsWto6GtsJ7Kmwn4BgOZYbGxdVDDRootwd4KLnStocgkQ_EnIBh7RF6gkBNWaY292HU1exb3NXtmYQEk4uaNwJhplo_HQNRpTi2ut0PEFl2gnTVjgv7Yb0u3tzf1tvHhP8bN9V\",\"summary\":[{\"type\":\"summary_text\",\"text\":\"**Accessing file and tests**\\n\\nI need to access the ROLE and add a file. It’s crucial to ensure tests are external to the lib packages, and the current package is org_codehaus_... I might be working with an existing build that utilizes JUnit Jupiter. I should make the test class public and name it VelocityComponentAnonymous1Test.java. I wonder if it maps the active class correctly? It probably shouldn’t be included in the package library, so I’ll write it accordingly.\"}]}"}, {"type": "toolCall", "id": "call_DupWrJQD62vZw2RdnTHt6fNX|fc_049667505a9e91930169ff87e08d9881a3b78b87822f2a4352", "name": "write", "arguments": {"path": "tests/src/org.codehaus.plexus/plexus-velocity/1.1.7/src/test/java/org_codehaus_plexus/plexus_velocity/VelocityComponentAnonymous1Test.java", "content": "/*\n * Copyright and related rights waived via CC0\n *\n * You should have received a copy of the CC0 legalcode along with this\n * work. If not, see <http://creativecommons.org/publicdomain/zero/1.0/>.\n */\npackage org_codehaus_plexus.plexus_velocity;\n\nimport static org.assertj.core.api.Assertions.assertThat;\n\nimport org.codehaus.plexus.velocity.VelocityComponent;\nimport org.junit.jupiter.api.Test;\n\npublic class VelocityComponentAnonymous1Test {\n    @Test\n    void roleInitializesVelocityComponentClassLiteral() {\n        assertThat(VelocityComponent.ROLE).isEqualTo(VelocityComponent.class.getName());\n    }\n}\n"}}], "api": "openai-responses", "provider": "OCA", "model": "gpt-5.5", "usage": {"input": 824, "output": 286, "cacheRead": 11264, "cacheWrite": 0, "totalTokens": 12374, "cost": {"input": 0, "output": 0, "cacheRead": 0, "cacheWrite": 0, "total": 0}}, "stopReason": "toolUse", "timestamp": 1778354141032, "responseId": "resp_049667505a9e91930169ff87dd718081a39f5b8b231f2c9797"}}
[tool-exec] start id=call_DupWrJQD62vZw2RdnTHt6fNX|fc_049667505a9e91930169ff87e08d9881a3b78b87822f2a4352 name=write args={"path": "tests/src/org.codehaus.plexus/plexus-velocity/1.1.7/src/test/java/org_codehaus_plexus/plexus_velocity/VelocityComponentAnonymous1Test.java", "content": "/*\n * Copyright and related rights waived via CC0\n *\n * You should have received a copy of the CC0 legalcode along with this\n * work. If not, see <http://creativecommons.org/publicdomain/zero/1.0/>.\n */\npackage org_codehaus_plexus.plexus_velocity;\n\nimport static org.assertj.core.api.Assertions.assertThat;\n\nimport org.codehaus.plexus.velocity.VelocityComponent;\nimport org.junit.jupiter.api.Test;\n\npublic class VelocityComponentAnonymous1Test {\n    @Test\n    void roleInitializesVelocityComponentClassLiteral() {\n        assertThat(VelocityComponent.ROLE).isEqualTo(VelocityComponent.class.getName());\n    }\n}\n"}
[tool-exec] end id=call_DupWrJQD62vZw2RdnTHt6fNX|fc_049667505a9e91930169ff87e08d9881a3b78b87822f2a4352 name=write status=success
  Successfully wrote 611 bytes to tests/src/org.codehaus.plexus/plexus-velocity/1.1.7/src/test/java/org_codehaus_plexus/plexus_velocity/VelocityComponentAnonymous1Test.java
[recv] {"type": "message_start", "message": {"role": "toolResult", "toolCallId": "call_DupWrJQD62vZw2RdnTHt6fNX|fc_049667505a9e91930169ff87e08d9881a3b78b87822f2a4352", "toolName": "write", "content": [{"type": "text", "text": "Successfully wrote 611 bytes to tests/src/org.codehaus.plexus/plexus-velocity/1.1.7/src/test/java/org_codehaus_plexus/plexus_velocity/VelocityComponentAnonymous1Test.java"}], "isError": false, "timestamp": 1778354145526}}
[recv] {"type": "message_end", "message": {"role": "toolResult", "toolCallId": "call_DupWrJQD62vZw2RdnTHt6fNX|fc_049667505a9e91930169ff87e08d9881a3b78b87822f2a4352", "toolName": "write", "content": [{"type": "text", "text": "Successfully wrote 611 bytes to tests/src/org.codehaus.plexus/plexus-velocity/1.1.7/src/test/java/org_codehaus_plexus/plexus_velocity/VelocityComponentAnonymous1Test.java"}], "isError": false, "timestamp": 1778354145526}}
[recv] {"type": "turn_end", "message": {"role": "assistant", "content": [{"type": "thinking", "thinking": "**Accessing file and tests**\n\nI need to access the ROLE and add a file. It’s crucial to ensure tests are external to the lib packages, and the current package is org_codehaus_... I might be working with an existing build that utilizes JUnit Jupiter. I should make the test class public and name it VelocityComponentAnonymous1Test.java. I wonder if it maps the active class correctly? It probably shouldn’t be included in the package library, so I’ll write it accordingly.", "thinkingSignature": "{\"id\":\"rs_049667505a9e91930169ff87de01fc81a3b5853b19736260f8\",\"type\":\"reasoning\",\"encrypted_content\":\"gAAAAABp_4fgMG3sLlidFw_rdEqCXM_KThHuc-_Hp4bTvcckCN5Y0TTKtFaLk0U8GPY1C52r7EIPZ2xpWrgEd-1xa_85j6kQFMdCbyXdCHFEksWSXIkJwFw1T0dnwZXuFvXGQoA0F8gnZlOG1lctHO7SYNCSTzxB3jaXPvZ19lfT0Z8niUmiIRgE05XJ5korC1G5l43e8HF-M3yHBNlGwDVl10QYoLMGaQ2dWB9vfm0cJ0Tod97usZlZJziRrVIb4_4XVOYZD4BgPjHWgDHowBCXOW7k17XH8mRdbmUFrgyiRJwgLhrcxYddGhw5DIPpCed8K-KaPsEWv7LZ6m8O_wk99ST0afWtkwKg-gkIkFFvMVjwVuOOjmRyByJWgs3O-QRxqkt1B1Zj9iJ1S7EZ081XT_RfkfzlHuwOLcfB7QSm-jt1XHIsyNmZhZOLOz9FbiC1IY7ozcX2xPQ3F8tDBoGiFuDOaVp4VurUWPqD0faANzfnjkeI5OryeIMMnJIs6tlyWvdB_tdCMFL0somevri9noaHFYLFpblXeEC3-eycZlDL9o0z1O6mk79uponZeHcg1O3Q2iToEnk4kKPwvs_3MBXLbx54ihrDQUdX15kSVRqsI69GyALLMbPTS9Rog-RiQrbJb7Ezv5V7wefJegdw0dzt4uc2Pd35tvdtpc8lhY9Hr_0KLOglI4pRzKvp0hBCyWJmgU5l8grGq9DTxLywC-SjVS1FPwqrFQyq-cZ9uLkIUqe9wULxEQPscqy_1kAkQ2oyTbhy7g7qYclrP7HQmBavtqzPJhYy4z3QxI_wTsAp_QruxUX87wnKhKjG4fYKnhROe7z4mlMhOKNRwhAtfODmcE9Qaz05zWAyKV4Ubayr0CH-R-tflxPATwWrARWoM1ETlcVMnbrKSd5VmpxxxV1iYSl8OL3O3BbfUoGTjNEB1BrbaJAacAxr3sB5LoxzCbMO_mFu55HlQ9WvKfgqfFAUD3jxjRnGYFHUkXf7oHqp5jOpQyXg_FvSGthzqokJfInfJ0Fw1B-G6GinAUGww3ibCFvhI3xIMuh525vUeJ7ZIAeBsKul4bro8ON5ikppTvbYFS-wYJmxFRq6eTFlfWyJg_GaAMeZtZ3CSxaFHS4kU_JonFlA9iiMXBjGnk3XcsjTFrArHe-3TppluqILzXnhaF1B67mr0bV-rFpKTBXlcKHpZKaDs9XqTldUz0n3peqsWto6GtsJ7Kmwn4BgOZYbGxdVDDRootwd4KLnStocgkQ_EnIBh7RF6gkBNWaY292HU1exb3NXtmYQEk4uaNwJhplo_HQNRpTi2ut0PEFl2gnTVjgv7Yb0u3tzf1tvHhP8bN9V\",\"summary\":[{\"type\":\"summary_text\",\"text\":\"**Accessing file and tests**\\n\\nI need to access the ROLE and add a file. It’s crucial to ensure tests are external to the lib packages, and the current package is org_codehaus_... I might be working with an existing build that utilizes JUnit Jupiter. I should make the test class public and name it VelocityComponentAnonymous1Test.java. I wonder if it maps the active class correctly? It probably shouldn’t be included in the package library, so I’ll write it accordingly.\"}]}"}, {"type": "toolCall", "id": "call_DupWrJQD62vZw2RdnTHt6fNX|fc_049667505a9e91930169ff87e08d9881a3b78b87822f2a4352", "name": "write", "arguments": {"path": "tests/src/org.codehaus.plexus/plexus-velocity/1.1.7/src/test/java/org_codehaus_plexus/plexus_velocity/VelocityComponentAnonymous1Test.java", "content": "/*\n * Copyright and related rights waived via CC0\n *\n * You should have received a copy of the CC0 legalcode along with this\n * work. If not, see <http://creativecommons.org/publicdomain/zero/1.0/>.\n */\npackage org_codehaus_plexus.plexus_velocity;\n\nimport static org.assertj.core.api.Assertions.assertThat;\n\nimport org.codehaus.plexus.velocity.VelocityComponent;\nimport org.junit.jupiter.api.Test;\n\npublic class VelocityComponentAnonymous1Test {\n    @Test\n    void roleInitializesVelocityComponentClassLiteral() {\n        assertThat(VelocityComponent.ROLE).isEqualTo(VelocityComponent.class.getName());\n    }\n}\n"}}], "api": "openai-responses", "provider": "OCA", "model": "gpt-5.5", "usage": {"input": 824, "output": 286, "cacheRead": 11264, "cacheWrite": 0, "totalTokens": 12374, "cost": {"input": 0, "output": 0, "cacheRead": 0, "cacheWrite": 0, "total": 0}}, "stopReason": "toolUse", "timestamp": 1778354141032, "responseId": "resp_049667505a9e91930169ff87dd718081a39f5b8b231f2c9797"}, "toolResults": [{"role": "toolResult", "toolCallId": "call_DupWrJQD62vZw2RdnTHt6fNX|fc_049667505a9e91930169ff87e08d9881a3b78b87822f2a4352", "toolName": "write", "content": [{"type": "text", "text": "Successfully wrote 611 bytes to tests/src/org.codehaus.plexus/plexus-velocity/1.1.7/src/test/java/org_codehaus_plexus/plexus_velocity/VelocityComponentAnonymous1Test.java"}], "isError": false, "timestamp": 1778354145526}]}
[recv] {"type": "turn_start"}
[recv] {"type": "message_start", "message": {"role": "assistant", "content": [], "api": "openai-responses", "provider": "OCA", "model": "gpt-5.5", "usage": {"input": 0, "output": 0, "cacheRead": 0, "cacheWrite": 0, "totalTokens": 0, "cost": {"input": 0, "output": 0, "cacheRead": 0, "cacheWrite": 0, "total": 0}}, "stopReason": "stop", "timestamp": 1778354145534}}
[assistant-event] thinking_start
[assistant-event] thinking_end
[tool-call] start id=unknown
[tool-call] delta {"command":"git status --short"}
[tool-call] end id=call_Kmh0bitlkSXUgo5JHbNxlRZL|fc_049667505a9e91930169ff87e4636881a38ff1db0f74459c63 name=bash args={"command": "git status --short"}
[recv] {"type": "message_end", "message": {"role": "assistant", "content": [{"type": "thinking", "thinking": "", "thinkingSignature": "{\"id\":\"rs_049667505a9e91930169ff87e288c481a39363ce27e3be9f90\",\"type\":\"reasoning\",\"encrypted_content\":\"gAAAAABp_4fkc1y-CMrKLp3cUrVji8busWHbe5v5spD7h3wdLOup8I9-GCdIC-LkPKbaSQtjb19Yd07Hyq8oiBZ2qFkyTkL3r9B_1Wd-8i0-ugOOdHB6FNC8Y5SU3lHxNCUbPY4nx9Irs4JNENRrPJewhI0hRqd-1TwS79MVlXG6uZ4nzVloYvcrceixkuH0IbQUiQUj1L6v3GB1sQ7JCMphZI32Jsb2zURTdYT6dDVPJf3zqbm8CW30GcVEMerziQHsaynbE5GoA5YTrSUhn_RWKIbjDqYMQjvINQ6OsZ61ggIU5emBGi7-2uWRMb8UiMcRx3NYbvQ8ST-1qdFDEUkEa6wIQDRTNr07gfoQDoc1kKibAG6L35J-xl-EgkXuF6YqUtRLW7hW2tAr2WIg51vMaMkLDn1Y58kT3kkj5I9h7cvgk1MVwKs5DEiUPF23CQ-Zwso5nHb8z7CZ6Il4jfLzwIIhugkfx97cMSlH8KmhHywKUFYEfgYMFmiWxyBf-ADncmqmWy8bG1t5RdkzyN_jG1LptAveVLYBk8R63Vkw_ZxUWde_3V4YFGZsaMY7Kp0i67OgKJExEnFYX6aFhnodjH0hW5ssjg_SjRGw112mP6qJ_HsPT-xATBdNILH-sAYEZTyhtbVBRd2mWMVgPyAWjNd5dZ0WrYCc_Ws6yMicYQsdznZ1nvI4WHCtDnJgfTBE4mFD0JkGhGN44QYPiGjHfG2v4i9w3EEN01gNjTX4SDlW-FpifxZ8jvaCKv-in1bbakbcL8flaepbXZKukEKH4HCScJzs22zQcOx1inbfvkthFM5RVZaQbAKuOhcWKWKKdR9LB37TkUFmW7oXRJFyaXhdVS4BnAaDxbdk4jMnvM2HyjkAlSbH8mGabxNJ8uYZV4WjVc_ay6UmeR5EylT-43KlZ7b5KiZu-9lcgddG9k6ApKTVSpi4UX_ycrb3Kxk7bb8sYiRwk2qqPBWUhICX0qan019y4Y2P7qQ-McSsW6-RTfuQ2cWAsemR0xqGjqmS2EOKcmcyp8tA8_UmgiD4_Gzn94vjJ_Ar1LTLKPZpv39LTefHRa0mwB0cebjsqZcPme12__6T3w2IG4wn-MuuyBUNyvmtSxD1Go7f7nsUYfBpQAsO6_L0M7M4WT276SiDnENHL1O5B2mzM_3SANFcQULndCOoWFivnroYq28ewO8V_YFv2ffoXCqE3RNJ8tLDXwCyTPY6WtuociV0V4-cqgccTrGmvl3SB5uVGCALm3RzDCnDTySdgDynJzT9trccI2dit1Uub2DrJKtVTsk0wAzhfVFCYvI-G5bXbaJUbSRMjcontX381iByLFwCVYVSrCJsYdGcG8o9ci8en7lgFDCa78ufUOR_S4vMwhWqSef6LV8F87-2GWAWpCkMj-FJy6v1bIfTJdyf7EBaFP2bauOOnz1_2IdNgNCqjoRBfwb39Y61fiv8LU-DVd4cWSaINaLNxoohgqb1QiGuiZyAnbtICq7QtFGKVZjulCrs20lK9RMPWEs=\",\"summary\":[]}"}, {"type": "toolCall", "id": "call_Kmh0bitlkSXUgo5JHbNxlRZL|fc_049667505a9e91930169ff87e4636881a38ff1db0f74459c63", "name": "bash", "arguments": {"command": "git status --short"}}], "api": "openai-responses", "provider": "OCA", "model": "gpt-5.5", "usage": {"input": 652, "output": 114, "cacheRead": 11776, "cacheWrite": 0, "totalTokens": 12542, "cost": {"input": 0, "output": 0, "cacheRead": 0, "cacheWrite": 0, "total": 0}}, "stopReason": "toolUse", "timestamp": 1778354145534, "responseId": "resp_049667505a9e91930169ff87e1f04c81a3b9e1355a2b1946a7"}}
[tool-exec] start id=call_Kmh0bitlkSXUgo5JHbNxlRZL|fc_049667505a9e91930169ff87e4636881a38ff1db0f74459c63 name=bash args={"command": "git status --short"}
[tool-exec] update id=call_Kmh0bitlkSXUgo5JHbNxlRZL|fc_049667505a9e91930169ff87e4636881a38ff1db0f74459c63 name=bash
[tool-exec] update id=call_Kmh0bitlkSXUgo5JHbNxlRZL|fc_049667505a9e91930169ff87e4636881a38ff1db0f74459c63 name=bash
  ?? metadata/org.codehaus.plexus/plexus-velocity/1.1.7/
  ?? tests/src/org.codehaus.plexus/plexus-velocity/1.1.7/src/test/java/org_codehaus_plexus/plexus_velocity/VelocityComponentAnonymous1Test.java
[tool-exec] end id=call_Kmh0bitlkSXUgo5JHbNxlRZL|fc_049667505a9e91930169ff87e4636881a38ff1db0f74459c63 name=bash status=success
  ?? metadata/org.codehaus.plexus/plexus-velocity/1.1.7/
  ?? tests/src/org.codehaus.plexus/plexus-velocity/1.1.7/src/test/java/org_codehaus_plexus/plexus_velocity/VelocityComponentAnonymous1Test.java
[recv] {"type": "message_start", "message": {"role": "toolResult", "toolCallId": "call_Kmh0bitlkSXUgo5JHbNxlRZL|fc_049667505a9e91930169ff87e4636881a38ff1db0f74459c63", "toolName": "bash", "content": [{"type": "text", "text": "?? metadata/org.codehaus.plexus/plexus-velocity/1.1.7/\n?? tests/src/org.codehaus.plexus/plexus-velocity/1.1.7/src/test/java/org_codehaus_plexus/plexus_velocity/VelocityComponentAnonymous1Test.java\n"}], "isError": false, "timestamp": 1778354148783}}
[recv] {"type": "message_end", "message": {"role": "toolResult", "toolCallId": "call_Kmh0bitlkSXUgo5JHbNxlRZL|fc_049667505a9e91930169ff87e4636881a38ff1db0f74459c63", "toolName": "bash", "content": [{"type": "text", "text": "?? metadata/org.codehaus.plexus/plexus-velocity/1.1.7/\n?? tests/src/org.codehaus.plexus/plexus-velocity/1.1.7/src/test/java/org_codehaus_plexus/plexus_velocity/VelocityComponentAnonymous1Test.java\n"}], "isError": false, "timestamp": 1778354148783}}
[recv] {"type": "turn_end", "message": {"role": "assistant", "content": [{"type": "thinking", "thinking": "", "thinkingSignature": "{\"id\":\"rs_049667505a9e91930169ff87e288c481a39363ce27e3be9f90\",\"type\":\"reasoning\",\"encrypted_content\":\"gAAAAABp_4fkc1y-CMrKLp3cUrVji8busWHbe5v5spD7h3wdLOup8I9-GCdIC-LkPKbaSQtjb19Yd07Hyq8oiBZ2qFkyTkL3r9B_1Wd-8i0-ugOOdHB6FNC8Y5SU3lHxNCUbPY4nx9Irs4JNENRrPJewhI0hRqd-1TwS79MVlXG6uZ4nzVloYvcrceixkuH0IbQUiQUj1L6v3GB1sQ7JCMphZI32Jsb2zURTdYT6dDVPJf3zqbm8CW30GcVEMerziQHsaynbE5GoA5YTrSUhn_RWKIbjDqYMQjvINQ6OsZ61ggIU5emBGi7-2uWRMb8UiMcRx3NYbvQ8ST-1qdFDEUkEa6wIQDRTNr07gfoQDoc1kKibAG6L35J-xl-EgkXuF6YqUtRLW7hW2tAr2WIg51vMaMkLDn1Y58kT3kkj5I9h7cvgk1MVwKs5DEiUPF23CQ-Zwso5nHb8z7CZ6Il4jfLzwIIhugkfx97cMSlH8KmhHywKUFYEfgYMFmiWxyBf-ADncmqmWy8bG1t5RdkzyN_jG1LptAveVLYBk8R63Vkw_ZxUWde_3V4YFGZsaMY7Kp0i67OgKJExEnFYX6aFhnodjH0hW5ssjg_SjRGw112mP6qJ_HsPT-xATBdNILH-sAYEZTyhtbVBRd2mWMVgPyAWjNd5dZ0WrYCc_Ws6yMicYQsdznZ1nvI4WHCtDnJgfTBE4mFD0JkGhGN44QYPiGjHfG2v4i9w3EEN01gNjTX4SDlW-FpifxZ8jvaCKv-in1bbakbcL8flaepbXZKukEKH4HCScJzs22zQcOx1inbfvkthFM5RVZaQbAKuOhcWKWKKdR9LB37TkUFmW7oXRJFyaXhdVS4BnAaDxbdk4jMnvM2HyjkAlSbH8mGabxNJ8uYZV4WjVc_ay6UmeR5EylT-43KlZ7b5KiZu-9lcgddG9k6ApKTVSpi4UX_ycrb3Kxk7bb8sYiRwk2qqPBWUhICX0qan019y4Y2P7qQ-McSsW6-RTfuQ2cWAsemR0xqGjqmS2EOKcmcyp8tA8_UmgiD4_Gzn94vjJ_Ar1LTLKPZpv39LTefHRa0mwB0cebjsqZcPme12__6T3w2IG4wn-MuuyBUNyvmtSxD1Go7f7nsUYfBpQAsO6_L0M7M4WT276SiDnENHL1O5B2mzM_3SANFcQULndCOoWFivnroYq28ewO8V_YFv2ffoXCqE3RNJ8tLDXwCyTPY6WtuociV0V4-cqgccTrGmvl3SB5uVGCALm3RzDCnDTySdgDynJzT9trccI2dit1Uub2DrJKtVTsk0wAzhfVFCYvI-G5bXbaJUbSRMjcontX381iByLFwCVYVSrCJsYdGcG8o9ci8en7lgFDCa78ufUOR_S4vMwhWqSef6LV8F87-2GWAWpCkMj-FJy6v1bIfTJdyf7EBaFP2bauOOnz1_2IdNgNCqjoRBfwb39Y61fiv8LU-DVd4cWSaINaLNxoohgqb1QiGuiZyAnbtICq7QtFGKVZjulCrs20lK9RMPWEs=\",\"summary\":[]}"}, {"type": "toolCall", "id": "call_Kmh0bitlkSXUgo5JHbNxlRZL|fc_049667505a9e91930169ff87e4636881a38ff1db0f74459c63", "name": "bash", "arguments": {"command": "git status --short"}}], "api": "openai-responses", "provider": "OCA", "model": "gpt-5.5", "usage": {"input": 652, "output": 114, "cacheRead": 11776, "cacheWrite": 0, "totalTokens": 12542, "cost": {"input": 0, "output": 0, "cacheRead": 0, "cacheWrite": 0, "total": 0}}, "stopReason": "toolUse", "timestamp": 1778354145534, "responseId": "resp_049667505a9e91930169ff87e1f04c81a3b9e1355a2b1946a7"}, "toolResults": [{"role": "toolResult", "toolCallId": "call_Kmh0bitlkSXUgo5JHbNxlRZL|fc_049667505a9e91930169ff87e4636881a38ff1db0f74459c63", "toolName": "bash", "content": [{"type": "text", "text": "?? metadata/org.codehaus.plexus/plexus-velocity/1.1.7/\n?? tests/src/org.codehaus.plexus/plexus-velocity/1.1.7/src/test/java/org_codehaus_plexus/plexus_velocity/VelocityComponentAnonymous1Test.java\n"}], "isError": false, "timestamp": 1778354148783}]}
[recv] {"type": "turn_start"}
[recv] {"type": "message_start", "message": {"role": "assistant", "content": [], "api": "openai-responses", "provider": "OCA", "model": "gpt-5.5", "usage": {"input": 0, "output": 0, "cacheRead": 0, "cacheWrite": 0, "totalTokens": 0, "cost": {"input": 0, "output": 0, "cacheRead": 0, "cacheWrite": 0, "total": 0}}, "stopReason": "stop", "timestamp": 1778354148791}}
[assistant-event] thinking_start
[thinking] **Clarifying metadata issues**
[thinking] 
[thinking] I need to consider whether there's untracked metadata already present, and I probably don't need to touch it unless necessary. Maybe there’s an untracked directory created by the environment, but I must ensure we didn't accidentally create it. It's important to keep my final message concise while making sure I'm accurately representing the situation. I want to communicate clearly without introducing unnecessary confusion.
[thinking] 
[assistant-event] thinking_end
[assistant-event] text_start
[assistant] Added a dedicated test for the active dynamic-access class:
[assistant] 
[assistant] - `tests/src/org.codehaus.plexus/plexus-velocity/1.1.7/src/test/java/org_codehaus_plexus/plexus_velocity/VelocityComponentAnonymous1Test.java`
[assistant] 
[assistant] The test accesses `VelocityComponent.ROLE`, which initializes `VelocityComponent` and reaches the synthetic `VelocityComponent$1.class$` call site containing `Class.forName(...)`.
[assistant] 
[assistant] I did not run tests, per instructions.
[assistant-event] text_end
[recv] {"type": "message_end", "message": {"role": "assistant", "content": [{"type": "thinking", "thinking": "**Clarifying metadata issues**\n\nI need to consider whether there's untracked metadata already present, and I probably don't need to touch it unless necessary. Maybe there’s an untracked directory created by the environment, but I must ensure we didn't accidentally create it. It's important to keep my final message concise while making sure I'm accurately representing the situation. I want to communicate clearly without introducing unnecessary confusion.", "thinkingSignature": "{\"id\":\"rs_049667505a9e91930169ff87e5fb2881a395984ec3c4cec68d\",\"type\":\"reasoning\",\"encrypted_content\":\"gAAAAABp_4fn9qh0LwHxF2pHr_rjKFfs2Mia4nsPV_LzL38x9v2pzWHOsL8f3CH4Absah36ZjI7D_q5f3BL8WIfshNAIS_XW2i4SkoBSxr2d59FfUnTuncOxBBHmMTxieKWMIS8d-QcqLFByLPeoOAjPeAU5Wovm05AjMZCRKdhTdNVwEEXDkqV5r1AdQo3IRM_0mDUpi4CGneyXtncSiwGN0ttUB_PsZAkhltwF6Ovsz01o2ESj5gtFU1R3bNTL62yHEMYMr8O8obpkda2rNNiMEVX4yXQN44H1gO17NwDcteHZQ1Q_SGSIUI3mmjpW1JNRLVTdao456pDrHefZlrckB0Yd4TGHbhxAivAK2aWuKv2lDS47p-KSNrdRJQCj2j_Quifs53cO6ZIEzQGUQZJ7b9w3zvGS2j_HyE07T8g8QNFwr9jguE_2T4bTEiLoAnQuo4ant9u8qCBIvcaMW499BS4lo8aJM6hhDZ2eCWXi0AVEaaOcsE4WfuXfX3qt-8TESpQ4pFqparUWBJRWWhkZqP5ak6ib6EnkGLutroNAmNOh-UWxSFNMbc5LjbMQkQKSYCE_O_r4DsKY0BGSgvLe_SYHDDOLh2Uhn-ke7uDHby1UZ_DRCQV_PWgjM8ULjpLynSNwr02H4TfPbYZ4trmd-wABzGbcaAbDu9snyfzERtQ5Nvtw3Mv6hkEqsHXtA9_TUiCA_jQ5LPgHC1V81S_F_ZYe6EgIsT4tYjH9Wq-j7iTHgOVX2VdWUmEAXpR6CkGf8mzSMov3wLttMmfnf4eONFH6g4ybNJwYMqToHXsWop5Pa0Vxpjq8o1yU_f8yYgjiO6p-Tusdm3MAAW6c4k0id_VNARhCtYzAQ4mnGYuRFJBQKT11NeDSi5KNjRASt6RLzYEdTgrZ4gHDv7shUgfbQ6ZYNut-enJpHmTiDixLl-4ZcK80BHWOg0z4er2g1IZJ8_xwF888B49VMFyJqEGl0ODKK3qrx0kGObqrHRGte4htsaLuaVQG7Iy2_frxhfJ-0H6ncq4ALXovruPeduQ1HQEtZAvMIvFFENOpbb2HsPj_13VAUsLkQ7HrQtiozbdWaEnBGvk968Vw_NgeA8PX_cje8S22j2QYB7Vp4ontKa9XcCS9jtKJlHhS6Qd6BRgODY1df4DfNlukPmw8AUPE6nJz4CTsBMcduGxMZyhKjLPg_FZe5AyJAofmJAjX4Rfk_1Nai_k8\",\"summary\":[{\"type\":\"summary_text\",\"text\":\"**Clarifying metadata issues**\\n\\nI need to consider whether there's untracked metadata already present, and I probably don't need to touch it unless necessary. Maybe there’s an untracked directory created by the environment, but I must ensure we didn't accidentally create it. It's important to keep my final message concise while making sure I'm accurately representing the situation. I want to communicate clearly without introducing unnecessary confusion.\"}]}"}, {"type": "text", "text": "Added a dedicated test for the active dynamic-access class:\n\n- `tests/src/org.codehaus.plexus/plexus-velocity/1.1.7/src/test/java/org_codehaus_plexus/plexus_velocity/VelocityComponentAnonymous1Test.java`\n\nThe test accesses `VelocityComponent.ROLE`, which initializes `VelocityComponent` and reaches the synthetic `VelocityComponent$1.class$` call site containing `Class.forName(...)`.\n\nI did not run tests, per instructions.", "textSignature": "{\"v\":1,\"id\":\"msg_049667505a9e91930169ff87e78dd481a3a26d080fdd1725e2\",\"phase\":\"final_answer\"}"}], "api": "openai-responses", "provider": "OCA", "model": "gpt-5.5", "usage": {"input": 324, "output": 147, "cacheRead": 12288, "cacheWrite": 0, "totalTokens": 12759, "cost": {"input": 0, "output": 0, "cacheRead": 0, "cacheWrite": 0, "total": 0}}, "stopReason": "stop", "timestamp": 1778354148791, "responseId": "resp_049667505a9e91930169ff87e5568c81a39e4894125eef2eeb"}}
[recv] {"type": "turn_end", "message": {"role": "assistant", "content": [{"type": "thinking", "thinking": "**Clarifying metadata issues**\n\nI need to consider whether there's untracked metadata already present, and I probably don't need to touch it unless necessary. Maybe there’s an untracked directory created by the environment, but I must ensure we didn't accidentally create it. It's important to keep my final message concise while making sure I'm accurately representing the situation. I want to communicate clearly without introducing unnecessary confusion.", "thinkingSignature": "{\"id\":\"rs_049667505a9e91930169ff87e5fb2881a395984ec3c4cec68d\",\"type\":\"reasoning\",\"encrypted_content\":\"gAAAAABp_4fn9qh0LwHxF2pHr_rjKFfs2Mia4nsPV_LzL38x9v2pzWHOsL8f3CH4Absah36ZjI7D_q5f3BL8WIfshNAIS_XW2i4SkoBSxr2d59FfUnTuncOxBBHmMTxieKWMIS8d-QcqLFByLPeoOAjPeAU5Wovm05AjMZCRKdhTdNVwEEXDkqV5r1AdQo3IRM_0mDUpi4CGneyXtncSiwGN0ttUB_PsZAkhltwF6Ovsz01o2ESj5gtFU1R3bNTL62yHEMYMr8O8obpkda2rNNiMEVX4yXQN44H1gO17NwDcteHZQ1Q_SGSIUI3mmjpW1JNRLVTdao456pDrHefZlrckB0Yd4TGHbhxAivAK2aWuKv2lDS47p-KSNrdRJQCj2j_Quifs53cO6ZIEzQGUQZJ7b9w3zvGS2j_HyE07T8g8QNFwr9jguE_2T4bTEiLoAnQuo4ant9u8qCBIvcaMW499BS4lo8aJM6hhDZ2eCWXi0AVEaaOcsE4WfuXfX3qt-8TESpQ4pFqparUWBJRWWhkZqP5ak6ib6EnkGLutroNAmNOh-UWxSFNMbc5LjbMQkQKSYCE_O_r4DsKY0BGSgvLe_SYHDDOLh2Uhn-ke7uDHby1UZ_DRCQV_PWgjM8ULjpLynSNwr02H4TfPbYZ4trmd-wABzGbcaAbDu9snyfzERtQ5Nvtw3Mv6hkEqsHXtA9_TUiCA_jQ5LPgHC1V81S_F_ZYe6EgIsT4tYjH9Wq-j7iTHgOVX2VdWUmEAXpR6CkGf8mzSMov3wLttMmfnf4eONFH6g4ybNJwYMqToHXsWop5Pa0Vxpjq8o1yU_f8yYgjiO6p-Tusdm3MAAW6c4k0id_VNARhCtYzAQ4mnGYuRFJBQKT11NeDSi5KNjRASt6RLzYEdTgrZ4gHDv7shUgfbQ6ZYNut-enJpHmTiDixLl-4ZcK80BHWOg0z4er2g1IZJ8_xwF888B49VMFyJqEGl0ODKK3qrx0kGObqrHRGte4htsaLuaVQG7Iy2_frxhfJ-0H6ncq4ALXovruPeduQ1HQEtZAvMIvFFENOpbb2HsPj_13VAUsLkQ7HrQtiozbdWaEnBGvk968Vw_NgeA8PX_cje8S22j2QYB7Vp4ontKa9XcCS9jtKJlHhS6Qd6BRgODY1df4DfNlukPmw8AUPE6nJz4CTsBMcduGxMZyhKjLPg_FZe5AyJAofmJAjX4Rfk_1Nai_k8\",\"summary\":[{\"type\":\"summary_text\",\"text\":\"**Clarifying metadata issues**\\n\\nI need to consider whether there's untracked metadata already present, and I probably don't need to touch it unless necessary. Maybe there’s an untracked directory created by the environment, but I must ensure we didn't accidentally create it. It's important to keep my final message concise while making sure I'm accurately representing the situation. I want to communicate clearly without introducing unnecessary confusion.\"}]}"}, {"type": "text", "text": "Added a dedicated test for the active dynamic-access class:\n\n- `tests/src/org.codehaus.plexus/plexus-velocity/1.1.7/src/test/java/org_codehaus_plexus/plexus_velocity/VelocityComponentAnonymous1Test.java`\n\nThe test accesses `VelocityComponent.ROLE`, which initializes `VelocityComponent` and reaches the synthetic `VelocityComponent$1.class$` call site containing `Class.forName(...)`.\n\nI did not run tests, per instructions.", "textSignature": "{\"v\":1,\"id\":\"msg_049667505a9e91930169ff87e78dd481a3a26d080fdd1725e2\",\"phase\":\"final_answer\"}"}], "api": "openai-responses", "provider": "OCA", "model": "gpt-5.5", "usage": {"input": 324, "output": 147, "cacheRead": 12288, "cacheWrite": 0, "totalTokens": 12759, "cost": {"input": 0, "output": 0, "cacheRead": 0, "cacheWrite": 0, "total": 0}}, "stopReason": "stop", "timestamp": 1778354148791, "responseId": "resp_049667505a9e91930169ff87e5568c81a39e4894125eef2eeb"}, "toolResults": []}
[recv] agent_end
[send] get_state
[recv] get_state success
  sessionFile: ../../../../../../../../.pi/agent/sessions/--home-vjovanov-c-forge-forge8-graalvm-reachability-metadata-forge-local_repositories-forge_worktrees-2428-8b9c7e6e--/2026-05-09T19-15-12-466Z_019e0e2a-47d2-70d5-af15-96f11a75e417.jsonl
  sessionId: 019e0e2a-47d2-70d5-af15-96f11a75e417
[send] get_session_stats
[recv] get_session_stats success
  tokens: input=13991 output=1573 cacheRead=111616 cacheWrite=0 total=127180

